Workbook
Name billion_kw_to_MW: About!$B$39
Name gigwatt_to_megawatt: About!$B$40
Name Percent_rural: About!$A$37
Name Percent_Urban: About!$A$36

Sheet About
A1: BDEQ BAU Electricity Output from Distributed Sources | B1: Nebraska | C1: 46260 | F1: State | G1: State
A2: BDEQ BAU Distributed Electricity Source Capacity | B2: =LOOKUP(B1,F2:G51,G2:G51) -> NE | F2: Alabama | G2: AL
F3: Alaska | G3: AK
A4: Sources: | B4: res v commercial breakdown | F4: Arizona | G4: AZ
B5: Energy Information Administration | F5: Arkansas | G5: AR
B6: 2023 | F6: California | G6: CA
B7: Annual Electric Power Industry Report, Form EIA-861 detailed data files | F7: Colorado | G7: CO
B8: https://www.eia.gov/electricity/data/eia861/ | F8: Connecticut | G8: CT
B9: Net_metering_2022 | F9: Delaware | G9: DE
F10: Florida | G10: FL
B11: Urban vs. Rural Residential Households | F11: Georgia | G11: GA
B12: Energy Information Administration | F12: Hawaii | G12: HI
B13: 2018 | F13: Idaho | G13: ID
B14: Residential Energy Consumption Survey (RECS) | F14: Illinois | G14: IL
B15: https://www.eia.gov/consumption/residential/data/2015/hc/hc2.1.xlsx | F15: Indiana | G15: IN
B16: Table HC2.1 | F16: Iowa | G16: IA
F17: Kansas | G17: KS
B18: Solar for All awards | F18: Kentucky | G18: KY
B19: US Environmental Protection Agency, Greenhouse Gas Reduction Fund - Solar for All | F19: Louisiana | G19: LA
B20: Selected applicants announced 22 April 2024; program terminated 7 August 2025 | F20: Maine | G20: ME
B21: https://19january2025snapshot.epa.gov/greenhouse-gas-reduction-fund/solar-all | F21: Maryland | G21: MD
B22: Award table reproduced on the 'SFA Awards' tab of this workbook | F22: Massachusetts | G22: MA
B23: 2026 | F23: Michigan | G23: MI
F24: Minnesota | G24: MN
B25: State population weights | F25: Mississippi | G25: MS
B26: US Census Bureau, 2020 Census resident population | F26: Missouri | G26: MO
B27: Reproduced on the 'SFA Multistate Split' tab of this workbook | F27: Montana | G27: MT
F28: Nebraska | G28: NE
A29: Notes | F29: Nevada | G29: NV
A30: The variable "BCEU BAU Components Energy Use" includes only "purchased electricity" | F30: New Hampshire | G30: NH
A31: (i.e. that which buildings get from the grid, not generate on-site), so the quantities | F31: New Jersey | G31: NJ
A32: of generation in this variable are additional. Electricity Output is reported in MWh and | F32: New Mexico | G32: NM
A33: Capacity is reported in MW | F33: New York | G33: NY
F34: North Carolina | G34: NC
A35: Urban Rural Split | F35: North Dakota | G35: ND
A36: 0.80118443 | B36: Urban | F36: Ohio | G36: OH
A37: 0.19881557 | B37: Rural | F37: Oklahoma | G37: OK
F38: Oregon | G38: OR
A39: Conversion from billion kilowatthours to megawatthours | B39: 1000000 | F39: Pennsylvania | G39: PA
A40: Conversion from gigawatts to megawatts | B40: 1000 | F40: Rhode Island | G40: RI
F41: South Carolina | G41: SC
A42: Notes for state downscaling | F42: South Dakota | G42: SD
F43: Tennessee | G43: TN
A44: EIA publishes small-scale production by state for residential, commercial, and independent | F44: Texas | G44: TX
A45: producers (e.g. residential PV generation located at https://www.eia.gov/opendata/qb.php?category=1737602) | F45: Utah | G45: UT
A46: Divide the state’s net electricity generation for a given technology (e.g. solar PV, including utility-scale) by the national total | F46: Vermont | G46: VT
A47: Where the given sector’s generation is not available (e.g. onshore wind for residential), proxy using the state’s independent power producers. | F47: Virginia | G47: VA
A48: Get national level distributed generation figures from the AEO, using the API | F48: Washington | G48: WA
F49: West Virginia | G49: WV
F50: Wisconsin | G50: WI
F51: Wyoming | G51: WY
A54: Description
A55: CiDESCTY - Change in Distributed Electricity Source Capacities This Year - for the state
A56: selected in cell B1 above, in MW per year by building type. It is the residential distributed
A57: solar the EPA Solar for All grants would have added had the program not been cancelled.
A59: Calculations
A60: SFA Awards -> SFA Multistate Split -> Solar for All -> calcs -> the three output tabs.
A61: Tan cells are pasted source data, blue cells are editable assumptions, everything else is a formula.
A63: 1. SFA Awards EPA's 60 awards plus the program totals (4,000 MW unlocked, $7.0B awarded).
A64: Their ratio is one national factor of 5.714e-07 MW per dollar, i.e. $1.75 of
A65: grant per watt. Each award's MW = award dollars x that factor.
A66: 2. SFA Multistate Split The 9 multistate, tribal and nationwide awards ($1.384B) are apportioned to
A67: the jurisdictions each one serves, by 2020 Census population.
... A72: capacity added. Nothing is assigned to commercial.

Sheet States
A1: Utility Characteristics | F1: Photovoltaic | AP1: Wind | BE1: Other | BT1: All Technologies
F2: Capacity MW | L2: Installations | Q2: Storage Capacity (MW) | V2: Storage Installations | AA2: Virtual Capacity (MW) | AF2: Virtual Customers | AK2: Energy Sold Back MWh | AP2: Capacity MW | AU2: Installations | AZ2: Energy Sold Back MWh | BE2: Capacity MW | BJ2: Installations | BO2: Energy Sold Back MWh | BT2: Capacity MW | BY2: Installations | CD2: Energy Sold Back MWh
A3: Year | B3: State | C3: Utility Number | D3: Utility Name | E3: BA Code | F3: Type | G3: Residential | H3: Commercial | I3: Industrial | J3: Transportation | K3: Total | L3: Residential | M3: Commercial | N3: Industrial | O3: Transportation | P3: Total | Q3: Residential | R3: Commercial | S3: Industrial | T3: Transportation | U3: Total | V3: Residential | W3: Commercial | X3: Industrial | Y3: Transportation | Z3: Total | AA3: Residential | AB3: Commercial | AC3: Industrial | AD3: Transportation | AE3: Total | AF3: Residential | AG3: Commercial | AH3: Industrial | AI3: Transportation | AJ3: Total | AK3: Residential | AL3: Commercial | AM3: Industrial | AN3: Transportation | AO3: Total | AP3: Residential | AQ3: Commercial | AR3: Industrial | AS3: Transportation | AT3: Total | AU3: Residential | AV3: Commercial | AW3: Industrial | AX3: Transportation | AY3: Total | AZ3: Residential | BA3: Commercial | BB3: Industrial | BC3: Transportation | BD3: Total | BE3: Residential | BF3: Commercial | BG3: Industrial | BH3: Transportation | BI3: Total | BJ3: Residential | BK3: Commercial | BL3: Industrial | BM3: Transportation | BN3: Total | BO3: Residential | BP3: Commercial | BQ3: Industrial | BR3: Transportation | BS3: Total | BT3: Residential | BU3: Commercial | BV3: Industrial | BW3: Transportation | BX3: Total | BY3: Residential | BZ3: Commercial | CA3: Industrial | CB3: Transportation | CC3: Total | CD3: Residential | CE3: Commercial | CF3: Industrial | CG3: Transportation | CH3: Total
A4: 2022 | B4: AK | C4: 219 | D4: Alaska Power and Telephone Co | E4: NA | F4: AC | G4: 0.012 | H4: 0.021 | I4: . | J4: . | K4: 0.033 | L4: 3 | M4: 2 | N4: . | O4: . | P4: 5 | Q4: . | R4: . | S4: . | T4: . | U4: . | V4: . | W4: . | X4: . | Y4: . | Z4: . | AA4: . | AB4: . | AC4: . | AD4: . | AE4: . | AF4: . | AG4: . | AH4: . | AI4: . | AJ4: . | AK4: 1.919 | AL4: 4.06 | AM4: . | AN4: . | AO4: 5.979 | AP4: . | AQ4: . | AR4: . | AS4: . | AT4: 0 | AU4: . | AV4: . | AW4: . | AX4: . | AY4: 0 | AZ4: . | BA4: . | BB4: . | BC4: . | BD4: 0 | BE4: 0.005 | BF4: . | BG4: . | BH4: . | BI4: 0.005 | BJ4: 1 | BK4: . | BL4: . | BM4: . | BN4: 1 | BO4: 0 | BP4: . | BQ4: . | BR4: . | BS4: 0 | BT4: 0.017 | BU4: 0.021 | BV4: 0 | BW4: 0 | BX4: 0.038 | BY4: 4 | BZ4: 2 | CA4: 0 | CB4: 0 | CC4: 6 | CD4: 1.919 | CE4: 4.06 | CF4: 0 | CG4: 0 | CH4: 5.979
A5: 2022 | B5: AK | C5: 3522 | D5: Chugach Electric Assn Inc | E5: CEA | F5: AC | G5: 3.373 | H5: 0.639 | I5: . | J5: . | K5: 4.012 | L5: 716 | M5: 61 | N5: . | O5: . | P5: 777 | Q5: . | R5: . | S5: . | T5: . | U5: . | V5: . | W5: . | X5: . | Y5: . | Z5: . | AA5: . | AB5: . | AC5: . | AD5: . | AE5: . | AF5: . | AG5: . | AH5: . | AI5: . | AJ5: . | AK5: . | AL5: . | AM5: . | AN5: . | AO5: 0 | AP5: . | AQ5: 0.01 | AR5: . | AS5: . | AT5: 0.01 | AU5: . | AV5: 4 | AW5: . | AX5: . | AY5: 4 | AZ5: . | BA5: . | BB5: . | BC5: . | BD5: 0 | BE5: . | BF5: . | BG5: . | BH5: . | BI5: 0 | BJ5: . | BK5: . | BL5: . | BM5: . | BN5: 0 | BO5: . | BP5: . | BQ5: . | BR5: . | BS5: 0 | BT5: 3.373 | BU5: 0.649 | BV5: 0 | BW5: 0 | BX5: 4.022 | BY5: 716 | BZ5: 65 | CA5: 0 | CB5: 0 | CC5: 781 | CD5: 0 | CE5: 0 | CF5: 0 | CG5: 0 | CH5: 0
A6: 2022 | B6: AK | C6: 7353 | D6: Golden Valley Elec Assn Inc | E6: NA | F6: AC | G6: 2.876 | H6: 0.422 | I6: 0.067 | J6: 0 | K6: 3.365 | L6: 556 | M6: 42 | N6: 5 | O6: 0 | P6: 603 | Q6: . | R6: . | S6: . | T6: . | U6: . | V6: . | W6: . | X6: . | Y6: . | Z6: . | AA6: . | AB6: . | AC6: . | AD6: . | AE6: . | AF6: . | AG6: . | AH6: . | AI6: . | AJ6: . | AK6: 404.969 | AL6: 44.365 | AM6: 0 | AN6: 0 | AO6: 449.334 | AP6: 0.013 | AQ6: 0.012 | AR6: 0 | AS6: 0 | AT6: 0.025 | AU6: 4 | AV6: 2 | AW6: 0 | AX6: 0 | AY6: 6 | AZ6: . | BA6: . | BB6: . | BC6: . | BD6: 0 | BE6: . | BF6: . | BG6: . | BH6: . | BI6: 0 | BJ6: . | BK6: . | BL6: . | BM6: . | BN6: 0 | BO6: . | BP6: . | BQ6: . | BR6: . | BS6: 0 | BT6: 2.889 | BU6: 0.434 | BV6: 0.067 | BW6: 0 | BX6: 3.39 | BY6: 560 | BZ6: 44 | CA6: 5 | CB6: 0 | CC6: 609 | CD6: 404.969 | CE6: 44.365 | CF6: 0 | CG6: 0 | CH6: 449.334
A7: 2022 | B7: AK | C7: 11824 | D7: Matanuska Electric Assn Inc | E7: NA | F7: AC | G7: 2.206 | H7: 0.284 | I7: . | J7: . | K7: 2.49 | L7: 347 | M7: 23 | N7: . | O7: . | P7: 370 | Q7: . | R7: . | S7: . | T7: . | U7: . | V7: . | W7: . | X7: . | Y7: . | Z7: . | AA7: . | AB7: . | AC7: . | AD7: . | AE7: . | AF7: . | AG7: . | AH7: . | AI7: . | AJ7: . | AK7: . | AL7: . | AM7: . | AN7: . | AO7: 0 | AP7: 0.064 | AQ7: 0.016 | AR7: . | AS7: . | AT7: 0.08 | AU7: 20 | AV7: 3 | AW7: . | AX7: . | AY7: 23 | AZ7: . | BA7: . | BB7: . | BC7: . | BD7: 0 | BE7: 0.048 | BF7: 0.004 | BG7: . | BH7: . | BI7: 0.052 | BJ7: 7 | BK7: 1 | BL7: . | BM7: . | BN7: 8 | BO7: . | BP7: . | BQ7: . | BR7: . | BS7: 0 | BT7: 2.318 | BU7: 0.304 | BV7: 0 | BW7: 0 | BX7: 2.622 | BY7: 374 | BZ7: 27 | CA7: 0 | CB7: 0 | CC7: 401 | CD7: 0 | CE7: 0 | CF7: 0 | CG7: 0 | CH7: 0
A8: 2022 | B8: AK | C8: 19558 | D8: Homer Electric Assn Inc | E8: NA | F8: DC | G8: 2.511 | H8: 0.782 | I8: 0 | J8: 0 | K8: 3.293 | L8: 451 | M8: 47 | N8: 0 | O8: 0 | P8: 498 | Q8: . | R8: . | S8: . | T8: . | U8: . | V8: . | W8: . | X8: . | Y8: . | Z8: . | AA8: . | AB8: . | AC8: . | AD8: . | AE8: . | AF8: . | AG8: . | AH8: . | AI8: . | AJ8: . | AK8: 1268.392 | AL8: 61.066 | AM8: . | AN8: . | AO8: 1329.458 | AP8: 0.109 | AQ8: 0.008 | AR8: . | AS8: . | AT8: 0.117 | AU8: 32 | AV8: 2 | AW8: . | AX8: . | AY8: 34 | AZ8: 18.174 | BA8: 1.586 | BB8: . | BC8: . | BD8: 19.76 | BE8: . | BF8: . | BG8: . | BH8: . | BI8: 0 | BJ8: . | BK8: . | BL8: . | BM8: . | BN8: 0 | BO8: . | BP8: . | BQ8: . | BR8: . | BS8: 0 | BT8: 2.62 | BU8: 0.79 | BV8: 0 | BW8: 0 | BX8: 3.41 | BY8: 483 | BZ8: 49 | CA8: 0 | CB8: 0 | CC8: 532 | CD8: 1286.566 | CE8: 62.652 | CF8: 0 | CG8: 0 | CH8: 1349.218
A9: 2022 | B9: AK | C9: 99999 | D9: Adjustment 2022 | E9: NA | G9: -0.438 | H9: -0.136 | I9: 0 | J9: 0 | K9: -0.574 | L9: . | M9: . | N9: . | O9: . | P9: . | Q9: . | R9: . | S9: . | T9: . | U9: . | V9: . | W9: . | X9: . | Y9: . | Z9: . | AA9: . | AB9: . | AC9: . | AD9: . | AE9: . | AF9: . | AG9: . | AH9: . | AI9: . | AJ9: . | AK9: . | AL9: . | AM9: . | AN9: . | AO9: . | AP9: . | AQ9: . | AR9: . | AS9: . | AT9: . | AU9: . | AV9: . | AW9: . | AX9: . | AY9: . | AZ9: . | BA9: . | BB9: . | BC9: . | BD9: . | BE9: . | BF9: . | BG9: . | BH9: . | BI9: . | BJ9: . | BK9: . | BL9: . | BM9: . | BN9: . | BO9: . | BP9: . | BQ9: . | BR9: . | BS9: . | BT9: -0.438 | BU9: -0.136 | BV9: 0 | BW9: 0 | BX9: -0.574 | BY9: . | BZ9: . | CA9: . | CB9: . | CC9: . | CD9: . | CE9: . | CF9: . | CG9: . | CH9: .
A10: 2022 | B10: AL | C10: 3222 | D10: Central Alabama Electric Coop | E10: SOCO | F10: DC | G10: 0.157 | H10: . | I10: . | J10: . | K10: 0.157 | L10: 23 | M10: . | N10: . | O10: . | P10: 23 | Q10: . | R10: . | S10: . | T10: . | U10: . | V10: . | W10: . | X10: . | Y10: . | Z10: . | AA10: . | AB10: . | AC10: . | AD10: . | AE10: . | AF10: . | AG10: . | AH10: . | AI10: . | AJ10: . | AK10: 1.78 | AL10: . | AM10: . | AN10: . | AO10: 1.78 | AP10: . | AQ10: . | AR10: . | AS10: . | AT10: 0 | AU10: . | AV10: . | AW10: . | AX10: . | AY10: 0 | AZ10: . | BA10: . | BB10: . | BC10: . | BD10: 0 | BE10: . | BF10: . | BG10: . | BH10: . | BI10: 0 | BJ10: . | BK10: . | BL10: . | BM10: . | BN10: 0 | BO10: . | BP10: . | BQ10: . | BR10: . | BS10: 0 | BT10: 0.157 | BU10: 0 | BV10: 0 | BW10: 0 | BX10: 0.157 | BY10: 23 | BZ10: 0 | CA10: 0 | CB10: 0 | CC10: 23 | CD10: 1.78 | CE10: 0 | CF10: 0 | CG10: 0 | CH10: 1.78
A11: 2022 | B11: AL | C11: 4327 | D11: Coosa Valley Electric Coop Inc | E11: SOCO | F11: AC | G11: 0.01 | H11: . | I11: . | J11: . | K11: 0.01 | L11: 1 | M11: . | N11: . | O11: . | P11: 1 | Q11: . | R11: . | S11: . | T11: . | U11: 0 | V11: . | W11: . | X11: . | Y11: . | Z11: 0 | AA11: . | AB11: . | AC11: . | AD11: . | AE11: 0 | AF11: . | AG11: . | AH11: . | AI11: . | AJ11: 0 | AK11: . | AL11: . | AM11: . | AN11: . | AO11: 0 | AP11: . | AQ11: . | AR11: . | AS11: . | AT11: 0 | AU11: . | AV11: . | AW11: . | AX11: . | AY11: 0 | AZ11: . | BA11: . | BB11: . | BC11: . | BD11: 0 | BE11: . | BF11: . | BG11: . | BH11: . | BI11: 0 | BJ11: . | BK11: . | BL11: . | BM11: . | BN11: 0 | BO11: . | BP11: . | BQ11: . | BR11: . | BS11: 0 | BT11: 0.01 | BU11: 0 | BV11: 0 | BW11: 0 | BX11: 0.01 | BY11: 1 | BZ11: 0 | CA11: 0 | CB11: 0 | CC11: 1 | CD11: 0 | CE11: 0 | CF11: 0 | CG11: 0 | CH11: 0
A12: 2022 | B12: AL | C12: 4430 | D12: Covington Electric Coop, Inc | E12: SOCO | F12: AC | G12: 0.058 | H12: . | I12: . | J12: . | K12: 0.058 | L12: 8 | M12: . | N12: . | O12: . | P12: 8 | Q12: . | R12: . | S12: . | T12: . | U12: . | V12: . | W12: . | X12: . | Y12: . | Z12: . | AA12: . | AB12: . | AC12: . | AD12: . | AE12: . | AF12: . | AG12: . | AH12: . | AI12: . | AJ12: . | AK12: 23.312 | AL12: . | AM12: . | AN12: . | AO12: 23.312 | AP12: . | AQ12: . | AR12: . | AS12: . | AT12: 0 | AU12: . | AV12: . | AW12: . | AX12: . | AY12: 0 | AZ12: . | BA12: . | BB12: . | BC12: . | BD12: 0 | BE12: . | BF12: . | BG12: . | BH12: . | BI12: 0 | BJ12: . | BK12: . | BL12: . | BM12: . | BN12: 0 | BO12: . | BP12: . | BQ12: . | BR12: . | BS12: 0 | BT12: 0.058 | BU12: 0 | BV12: 0 | BW12: 0 | BX12: 0.058 | BY12: 8 | BZ12: 0 | CA12: 0 | CB12: 0 | CC12: 8 | CD12: 23.312 | CE12: 0 | CF12: 0 | CG12: 0 | CH12: 23.312
A13: 2022 | B13: AL | C13: 6491 | D13: Foley Board of Utilities | E13: SOCO | F13: AC | G13: 0.19 | H13: 0.5 | I13: . | J13: . | K13: 0.69 | L13: 19 | M13: 5 | N13: . | O13: . | P13: 24 | Q13: . | R13: . | S13: . | T13: . | U13: . | V13: . | W13: . | X13: . | Y13: . | Z13: . | AA13: . | AB13: . | AC13: . | AD13: . | AE13: . | AF13: . | AG13: . | AH13: . | AI13: . | AJ13: . | AK13: . | AL13: . | AM13: . | AN13: . | AO13: 0 | AP13: . | AQ13: . | AR13: . | AS13: . | AT13: 0 | AU13: . | AV13: . | AW13: . | AX13: . | AY13: 0 | AZ13: . | BA13: . | BB13: . | BC13: . | BD13: 0 | BE13: . | BF13: . | BG13: . | BH13: . | BI13: 0 | BJ13: . | BK13: . | BL13: . | BM13: . | BN13: 0 | BO13: . | BP13: . | BQ13: . | BR13: . | BS13: 0 | BT13: 0.19 | BU13: 0.5 | BV13: 0 | BW13: 0 | BX13: 0.69 | BY13: 19 | BZ13: 5 | CA13: 0 | CB13: 0 | CC13: 24 | CD13: 0 | CE13: 0 | CF13: 0 | CG13: 0 | CH13: 0
A14: 2022 | B14: AL | C14: 17646 | D14: Southern Pine Elec Coop, Inc | E14: SOCO | F14: AC | G14: 0.001 | H14: . | I14: . | J14: . | K14: 0.001 | L14: 2 | M14: . | N14: . | O14: . | P14: 2 | Q14: . | R14: . | S14: . | T14: . | U14: . | V14: . | W14: . | X14: . | Y14: . | Z14: . | AA14: . | AB14: . | AC14: . | AD14: . | AE14: . | AF14: . | AG14: . | AH14: . | AI14: . | AJ14: . | AK14: . | AL14: . | AM14: . | AN14: . | AO14: 0 | AP14: 0.001 | AQ14: . | AR14: . | AS14: . | AT14: 0.001 | AU14: 1 | AV14: . | AW14: . | AX14: . | AY14: 1 | AZ14: . | BA14: . | BB14: . | BC14: . | BD14: 0 | BE14: . | BF14: . | BG14: . | BH14: . | BI14: 0 | BJ14: . | BK14: . | BL14: . | BM14: . | BN14: 0 | BO14: . | BP14: . | BQ14: . | BR14: . | BS14: 0 | BT14: 0.002 | BU14: 0 | BV14: 0 | BW14: 0 | BX14: 0.002 | BY14: 3 | BZ14: 0 | CA14: 0 | CB14: 0 | CC14: 3 | CD14: 0 | CE14: 0 | CF14: 0 | CG14: 0 | CH14: 0
A15: 2022 | B15: AL | C15: 99999 | D15: Adjustment 2022 | E15: SOCO | G15: -0.027 | H15: . | I15: . | J15: . | K15: -0.027 | L15: . | M15: . | N15: . | O15: . | P15: . | Q15: . | R15: . | S15: . | T15: . | U15: . | V15: . | W15: . | X15: . | Y15: . | Z15: . | AA15: . | AB15: . | AC15: . | AD15: . | AE15: . | AF15: . | AG15: . | AH15: . | AI15: . | AJ15: . | AK15: . | AL15: . | AM15: . | AN15: . | AO15: . | AP15: . | AQ15: . | AR15: . | AS15: . | AT15: . | AU15: . | AV15: . | AW15: . | AX15: . | AY15: . | AZ15: . | BA15: . | BB15: . | BC15: . | BD15: . | BE15: . | BF15: . | BG15: . | BH15: . | BI15: . | BJ15: . | BK15: . | BL15: . | BM15: . | BN15: . | BO15: . | BP15: . | BQ15: . | BR15: . | BS15: . | BT15: -0.027 | BU15: . | BV15: . | BW15: . | BX15: -0.027 | BY15: . | BZ15: . | CA15: . | CB15: . | CC15: . | CD15: . | CE15: . | CF15: . | CG15: . | CH15: .
A16: 2022 | B16: AR | C16: 814 | D16: Entergy Arkansas LLC | E16: MISO | F16: DC | G16: 46.03 | H16: 34.92 | I16: 3.449 | J16: . | K16: 84.399 | L16: 4253 | M16: 189 | N16: 26 | O16: . | P16: 4468 | Q16: . | R16: . | S16: . | T16: . | U16: . | V16: . | W16: . | X16: . | Y16: . | Z16: . | AA16: . | AB16: . | AC16: . | AD16: . | AE16: . | AF16: . | AG16: . | AH16: . | AI16: . | AJ16: . | AK16: . | AL16: . | AM16: . | AN16: . | AO16: 0 | AP16: 0.007 | AQ16: 0.002 | AR16: 0.006 | AS16: . | AT16: 0.015 | AU16: 1 | AV16: 1 | AW16: 2 | AX16: . | AY16: 4 | AZ16: . | BA16: . | BB16: . | BC16: . | BD16: 0 | BE16: . | BF16: . | BG16: . | BH16: . | BI16: 0 | BJ16: . | BK16: . | BL16: . | BM16: . | BN16: 0 | BO16: . | BP16: . | BQ16: . | BR16: . | BS16: 0 | BT16: 46.037 | BU16: 34.922 | BV16: 3.455 | BW16: 0 | BX16: 84.414 | BY16: 4254 | BZ16: 190 | CA16: 28 | CB16: 0 | CC16: 4472 | CD16: 0 | CE16: 0 | CF16: 0 | CG16: 0 | CH16: 0
A17: 2022 | B17: AR | C17: 817 | D17: Arkansas Valley Elec Coop Corp | E17: SWPP | F17: DC | G17: 7.318 | H17: 1.822 | I17: . | J17: . | K17: 9.14 | L17: 699 | M17: 12 | N17: . | O17: . | P17: 711 | Q17: . | R17: . | S17: . | T17: . | U17: . | V17: . | W17: . | X17: . | Y17: . | Z17: . | AA17: . | AB17: . | AC17: . | AD17: . | AE17: . | AF17: . | AG17: . | AH17: . | AI17: . | AJ17: . | AK17: 4094.546 | AL17: 2272.106 | AM17: . | AN17: . | AO17: 6366.652 | AP17: 0.007 | AQ17: . | AR17: . | AS17: . | AT17: 0.007 | AU17: 2 | AV17: . | AW17: . | AX17: . | AY17: 2 | AZ17: 0 | BA17: . | BB17: . | BC17: . | BD17: 0 | BE17: . | BF17: . | BG17: . | BH17: . | BI17: 0 | BJ17: . | BK17: . | BL17: . | BM17: . | BN17: 0 | BO17: . | BP17: . | BQ17: . | BR17: . | BS17: 0 | BT17: 7.325 | BU17: 1.822 | BV17: 0 | BW17: 0 | BX17: 9.147 | BY17: 701 | BZ17: 12 | CA17: 0 | CB17: 0 | CC17: 713 | CD17: 4094.546 | CE17: 2272.106 | CF17: 0 | CG17: 0 | CH17: 6366.652
A18: 2022 | B18: AR | C18: 1586 | D18: City of Bentonville - (AR) | E18: SWPP | F18: DC | G18: 6.3 | H18: 3.6 | I18: . | J18: . | K18: 9.9 | L18: 252 | M18: 12 | N18: . | O18: . | P18: 264 | Q18: . | R18: . | S18: . | T18: . | U18: . | V18: . | W18: . | X18: . | Y18: . | Z18: . | AA18: . | AB18: . | AC18: . | AD18: . | AE18: . | AF18: . | AG18: . | AH18: . | AI18: . | AJ18: . | AK18: . | AL18: . | AM18: . | AN18: . | AO18: 0 | AP18: . | AQ18: . | AR18: . | AS18: . | AT18: 0 | AU18: . | AV18: . | AW18: . | AX18: . | AY18: 0 | AZ18: . | BA18: . | BB18: . | BC18: . | BD18: 0 | BE18: . | BF18: . | BG18: . | BH18: . | BI18: 0 | BJ18: . | BK18: . | BL18: . | BM18: . | BN18: 0 | BO18: . | BP18: . | BQ18: . | BR18: . | BS18: 0 | BT18: 6.3 | BU18: 3.6 | BV18: 0 | BW18: 0 | BX18: 9.9 | BY18: 252 | BZ18: 12 | CA18: 0 | CB18: 0 | CC18: 264 | CD18: 0 | CE18: 0 | CF18: 0 | CG18: 0 | CH18: 0
A19: 2022 | B19: AR | C19: 2678 | D19: C & L Electric Coop Corp | E19: MISO | F19: DC | G19: 1.971 | H19: 3.576 | I19: . | J19: . | K19: 5.547 | L19: 169 | M19: 16 | N19: . | O19: . | P19: 185 | Q19: . | R19: . | S19: . | T19: . | U19: . | V19: . | W19: . | X19: . | Y19: . | Z19: . | AA19: . | AB19: . | AC19: . | AD19: . | AE19: . | AF19: . | AG19: . | AH19: . | AI19: . | AJ19: . | AK19: . | AL19: . | AM19: . | AN19: . | AO19: 0 | AP19: . | AQ19: . | AR19: . | AS19: . | AT19: 0 | AU19: . | AV19: . | AW19: . | AX19: . | AY19: 0 | AZ19: . | BA19: . | BB19: . | BC19: . | BD19: 0 | BE19: . | BF19: . | BG19: . | BH19: . | BI19: 0 | BJ19: . | BK19: . | BL19: . | BM19: . | BN19: 0 | BO19: . | BP19: . | BQ19: . | BR19: . | BS19: 0 | BT19: 1.971 | BU19: 3.576 | BV19: 0 | BW19: 0 | BX19: 5.547 | BY19: 169 | BZ19: 16 | CA19: 0 | CB19: 0 | CC19: 185 | CD19: 0 | CE19: 0 | CF19: 0 | CG19: 0 | CH19: 0
A20: 2022 | B20: AR | C20: 3093 | D20: Carroll Electric Coop Corp - (AR) | E20: SWPP | F20: DC | G20: 12.77 | H20: . | I20: . | J20: . | K20: 12.77 | L20: 1564 | M20: . | N20: . | O20: . | P20: 1564 | Q20: . | R20: . | S20: . | T20: . | U20: . | V20: . | W20: . | X20: . | Y20: . | Z20: . | AA20: . | AB20: . | AC20: . | AD20: . | AE20: . | AF20: . | AG20: . | AH20: . | AI20: . | AJ20: . | AK20: . | AL20: . | AM20: . | AN20: . | AO20: 0 | AP20: 0.019 | AQ20: . | AR20: . | AS20: . | AT20: 0.019 | AU20: 3 | AV20: . | AW20: . | AX20: . | AY20: 3 | AZ20: . | BA20: . | BB20: . | BC20: . | BD20: 0 | BE20: . | BF20: . | BG20: . | BH20: . | BI20: 0 | BJ20: . | BK20: . | BL20: . | BM20: . | BN20: 0 | BO20: . | BP20: . | BQ20: . | BR20: . | BS20: 0 | BT20: 12.789 | BU20: 0 | BV20: 0 | BW20: 0 | BX20: 12.789 | BY20: 1567 | BZ20: 0 | CA20: 0 | CB20: 0 | CC20: 1567 | CD20: 0 | CE20: 0 | CF20: 0 | CG20: 0 | CH20: 0
A21: 2022 | B21: AR | C21: 3712 | D21: Clay County Electric Coop Corp | E21: MISO | F21: AC | G21: 0.165 | H21: 0.463 | I21: . | J21: . | K21: 0.628 | L21: 23 | M21: 4 | N21: . | O21: . | P21: 27 | Q21: . | R21: . | S21: . | T21: . | U21: . | V21: . | W21: . | X21: . | Y21: . | Z21: . | AA21: . | AB21: . | AC21: . | AD21: . | AE21: . | AF21: . | AG21: . | AH21: . | AI21: . | AJ21: . | AK21: . | AL21: . | AM21: . | AN21: . | AO21: 0 | AP21: . | AQ21: . | AR21: . | AS21: . | AT21: 0 | AU21: . | AV21: . | AW21: . | AX21: . | AY21: 0 | AZ21: . | BA21: . | BB21: . | BC21: . | BD21: 0 | BE21: . | BF21: . | BG21: . | BH21: . | BI21: 0 | BJ21: . | BK21: . | BL21: . | BM21: . | BN21: 0 | BO21: . | BP21: . | BQ21: . | BR21: . | BS21: 0 | BT21: 0.165 | BU21: 0.463 | BV21: 0 | BW21: 0 | BX21: 0.628 | BY21: 23 | BZ21: 4 | CA21: 0 | CB21: 0 | CC21: 27 | CD21: 0 | CE21: 0 | CF21: 0 | CG21: 0 | CH21: 0
A22: 2022 | B22: AR | C22: 4280 | D22: Conway Corporation | E22: MISO | F22: AC | G22: 0.361 | H22: . | I22: . | J22: . | K22: 0.361 | L22: 56 | M22: . | N22: . | O22: . | P22: 56 | Q22: . | R22: . | S22: . | T22: . | U22: . | V22: . | W22: . | X22: . | Y22: . | Z22: . | AA22: . | AB22: . | AC22: . | AD22: . | AE22: . | AF22: . | AG22: . | AH22: . | AI22: . | AJ22: . | AK22: . | AL22: . | AM22: . | AN22: . | AO22: 0 | AP22: . | AQ22: . | AR22: . | AS22: . | AT22: 0 | AU22: . | AV22: . | AW22: . | AX22: . | AY22: 0 | AZ22: . | BA22: . | BB22: . | BC22: . | BD22: 0 | BE22: . | BF22: . | BG22: . | BH22: . | BI22: 0 | BJ22: . | BK22: . | BL22: . | BM22: . | BN22: 0 | BO22: . | BP22: . | BQ22: . | BR22: . | BS22: 0 | BT22: 0.361 | BU22: 0 | BV22: 0 | BW22: 0 | BX22: 0.361 | BY22: 56 | BZ22: 0 | CA22: 0 | CB22: 0 | CC22: 56 | CD22: 0 | CE22: 0 | CF22: 0 | CG22: 0 | CH22: 0
A23: 2022 | B23: AR | C23: 4509 | D23: Craighead Electric Coop Corp | E23: MISO | F23: AC | G23: 0.848 | H23: 3.2 | I23: . | J23: . | K23: 4.048 | L23: 87 | M23: 8 | N23: . | O23: . | P23: 95 | Q23: 0.012 | R23: 3 | S23: . | T23: . | U23: 3.012 | V23: 3 | W23: 6 | X23: . | Y23: . | Z23: 9 | AA23: . | AB23: . | AC23: . | AD23: . | AE23: 0 | AF23: . | AG23: . | AH23: . | AI23: . | AJ23: 0 | AK23: . | AL23: . | AM23: . | AN23: . | AO23: 0 | AP23: . | AQ23: . | AR23: . | AS23: . | AT23: 0 | AU23: . | AV23: . | AW23: . | AX23: . | AY23: 0 | AZ23: . | BA23: . | BB23: . | BC23: . | BD23: 0 | BE23: . | BF23: . | BG23: . | BH23: . | BI23: 0 | BJ23: . | BK23: . | BL23: . | BM23: . | BN23: 0 | BO23: . | BP23: . | BQ23: . | BR23: . | BS23: 0 | BT23: 0.848 | BU23: 3.2 | BV23: 0 | BW23: 0 | BX23: 4.048 | BY23: 87 | BZ23: 8 | CA23: 0 | CB23: 0 | CC23: 95 | CD23: 0 | CE23: 0 | CF23: 0 | CG23: 0 | CH23: 0
A24: 2022 | B24: AR | C24: 5860 | D24: Empire District Electric Co | E24: SWPP | F24: DC | G24: 0.688 | H24: . | I24: . | J24: . | K24: 0.688 | L24: 89 | M24: . | N24: . | O24: . | P24: 89 | Q24: . | R24: . | S24: . | T24: . | U24: . | V24: . | W24: . | X24: . | Y24: . | Z24: . | AA24: . | AB24: . | AC24: . | AD24: . | AE24: . | AF24: . | AG24: . | AH24: . | AI24: . | AJ24: . | AK24: . | AL24: . | AM24: . | AN24: . | AO24: 0 | AP24: . | AQ24: . | AR24: . | AS24: . | AT24: 0 | AU24: . | AV24: . | AW24: . | AX24: . | AY24: 0 | AZ24: . | BA24: . | BB24: . | BC24: . | BD24: 0 | BE24: . | BF24: . | BG24: . | BH24: . | BI24: 0 | BJ24: . | BK24: . | BL24: . | BM24: . | BN24: 0 | BO24: . | BP24: . | BQ24: . | BR24: . | BS24: 0 | BT24: 0.688 | BU24: 0 | BV24: 0 | BW24: 0 | BX24: 0.688 | BY24: 89 | BZ24: 0 | CA24: 0 | CB24: 0 | CC24: 89 | CD24: 0 | CE24: 0 | CF24: 0 | CG24: 0 | CH24: 0
A25: 2022 | B25: AR | C25: 6342 | D25: First Electric Coop Corp | E25: MISO | F25: AC | G25: 12.462 | H25: 0.446 | I25: 0.791 | J25: . | K25: 13.699 | L25: 1329 | M25: 8 | N25: 7 | O25: . | P25: 1344 | Q25: . | R25: . | S25: . | T25: . | U25: . | V25: . | W25: . | X25: . | Y25: . | Z25: . | AA25: . | AB25: . | AC25: . | AD25: . | AE25: . | AF25: . | AG25: . | AH25: . | AI25: . | AJ25: . | AK25: . | AL25: . | AM25: . | AN25: . | AO25: 0 | AP25: . | AQ25: . | AR25: . | AS25: . | AT25: 0 | AU25: . | AV25: . | AW25: . | AX25: . | AY25: 0 | AZ25: . | BA25: . | BB25: . | BC25: . | BD25: 0 | BE25: . | BF25: . | BG25: . | BH25: . | BI25: 0 | BJ25: . | BK25: . | BL25: . | BM25: . | BN25: 0 | BO25: . | BP25: . | BQ25: . | BR25: . | BS25: 0 | BT25: 12.462 | BU25: 0.446 | BV25: 0.791 | BW25: 0 | BX25: 13.699 | BY25: 1329 | BZ25: 8 | CA25: 7 | CB25: 0 | CC25: 1344 | CD25: 0 | CE25: 0 | CF25: 0 | CG25: 0 | CH25: 0
A26: 2022 | B26: AR | C26: 8840 | D26: City of Hope | E26: MISO | F26: AC | G26: 0.141 | H26: 1.23 | I26: . | J26: . | K26: 1.371 | L26: 16 | M26: 23 | N26: . | O26: . | P26: 39 | Q26: . | R26: . | S26: . | T26: . | U26: . | V26: . | W26: . | X26: . | Y26: . | Z26: . | AA26: . | AB26: . | AC26: . | AD26: . | AE26: . | AF26: . | AG26: . | AH26: . | AI26: . | AJ26: . | AK26: . | AL26: . | AM26: . | AN26: . | AO26: 0 | AP26: . | AQ26: . | AR26: . | AS26: . | AT26: 0 | AU26: . | AV26: . | AW26: . | AX26: . | AY26: 0 | AZ26: . | BA26: . | BB26: . | BC26: . | BD26: 0 | BE26: . | BF26: . | BG26: . | BH26: . | BI26: 0 | BJ26: . | BK26: . | BL26: . | BM26: . | BN26: 0 | BO26: . | BP26: . | BQ26: . | BR26: . | BS26: 0 | BT26: 0.141 | BU26: 1.23 | BV26: 0 | BW26: 0 | BX26: 1.371 | BY26: 16 | BZ26: 23 | CA26: 0 | CB26: 0 | CC26: 39 | CD26: 0 | CE26: 0 | CF26: 0 | CG26: 0 | CH26: 0
A27: 2022 | B27: AR | C27: 9879 | D27: City Water and Light Plant | E27: MISO | F27: AC | G27: 0.215 | H27: 0.042 | I27: 0.133 | J27: . | K27: 0.39 | L27: 28 | M27: 2 | N27: 1 | O27: . | P27: 31 | Q27: . | R27: . | S27: . | T27: . | U27: . | V27: . | W27: . | X27: . | Y27: . | Z27: . | AA27: . | AB27: . | AC27: . | AD27: . | AE27: . | AF27: . | AG27: . | AH27: . | AI27: . | AJ27: . | AK27: . | AL27: . | AM27: . | AN27: . | AO27: 0 | AP27: . | AQ27: . | AR27: . | AS27: . | AT27: 0 | AU27: . | AV27: . | AW27: . | AX27: . | AY27: 0 | AZ27: . | BA27: . | BB27: . | BC27: . | BD27: 0 | BE27: . | BF27: . | BG27: . | BH27: . | BI27: 0 | BJ27: . | BK27: . | BL27: . | BM27: . | BN27: 0 | BO27: . | BP27: . | BQ27: . | BR27: . | BS27: 0 | BT27: 0.215 | BU27: 0.042 | BV27: 0.133 | BW27: 0 | BX27: 0.39 | BY27: 28 | BZ27: 2 | CA27: 1 | CB27: 0 | CC27: 31 | CD27: 0 | CE27: 0 | CF27: 0 | CG27: 0 | CH27: 0
A28: 2022 | B28: AR | C28: 12681 | D28: Mississippi County Electric Co | E28: MISO | F28: AC | G28: 0.053 | H28: 1 | I28: . | J28: . | K28: 1.053 | L28: 5 | M28: 4 | N28: . | O28: . | P28: 9 | Q28: . | R28: . | S28: . | T28: . | U28: 0 | V28: . | W28: . | X28: . | Y28: . | Z28: 0 | AA28: . | AB28: . | AC28: . | AD28: . | AE28: 0 | AF28: . | AG28: . | AH28: . | AI28: . | AJ28: 0 | AK28: . | AL28: . | AM28: . | AN28: . | AO28: 0 | AP28: . | AQ28: . | AR28: . | AS28: . | AT28: 0 | AU28: . | AV28: . | AW28: . | AX28: . | AY28: 0 | AZ28: . | BA28: . | BB28: . | BC28: . | BD28: 0 | BE28: . | BF28: . | BG28: . | BH28: . | BI28: 0 | BJ28: . | BK28: . | BL28: . | BM28: . | BN28: 0 | BO28: . | BP28: . | BQ28: . | BR28: . | BS28: 0 | BT28: 0.053 | BU28: 1 | BV28: 0 | BW28: 0 | BX28: 1.053 | BY28: 5 | BZ28: 4 | CA28: 0 | CB28: 0 | CC28: 9 | CD28: 0 | CE28: 0 | CF28: 0 | CG28: 0 | CH28: 0
A29: 2022 | B29: AR | C29: 13676 | D29: North Arkansas Elec Coop, Inc | E29: MISO | F29: DC | G29: 2.979 | H29: . | I29: . | J29: . | K29: 2.979 | L29: 234 | M29: . | N29: . | O29: . | P29: 234 | Q29: . | R29: . | S29: . | T29: . | U29: . | V29: . | W29: . | X29: . | Y29: . | Z29: . | AA29: . | AB29: . | AC29: . | AD29: . | AE29: . | AF29: . | AG29: . | AH29: . | AI29: . | AJ29: . | AK29: . | AL29: . | AM29: . | AN29: . | AO29: 0 | AP29: 0.013 | AQ29: . | AR29: . | AS29: . | AT29: 0.013 | AU29: 5 | AV29: . | AW29: . | AX29: . | AY29: 5 | AZ29: . | BA29: . | BB29: . | BC29: . | BD29: 0 | BE29: . | BF29: . | BG29: . | BH29: . | BI29: 0 | BJ29: . | BK29: . | BL29: . | BM29: . | BN29: 0 | BO29: . | BP29: . | BQ29: . | BR29: . | BS29: 0 | BT29: 2.992 | BU29: 0 | BV29: 0 | BW29: 0 | BX29: 2.992 | BY29: 239 | BZ29: 0 | CA29: 0 | CB29: 0 | CC29: 239 | CD29: 0 | CE29: 0 | CF29: 0 | CG29: 0 | CH29: 0
A30: 2022 | B30: AR | C30: 13718 | D30: City of North Little Rock - (AR) | E30: MISO | F30: AC | G30: 1.85 | H30: 0.28 | I30: 2.45 | J30: 0 | K30: 4.58 | L30: 241 | M30: 5 | N30: 2 | O30: 0 | P30: 248 | Q30: . | R30: . | S30: . | T30: . | U30: . | V30: . | W30: . | X30: . | Y30: . | Z30: . | AA30: . | AB30: . | AC30: . | AD30: . | AE30: . | AF30: . | AG30: . | AH30: . | AI30: . | AJ30: . | AK30: . | AL30: . | AM30: . | AN30: . | AO30: 0 | AP30: . | AQ30: . | AR30: . | AS30: . | AT30: 0 | AU30: . | AV30: . | AW30: . | AX30: . | AY30: 0 | AZ30: . | BA30: . | BB30: . | BC30: . | BD30: 0 | BE30: . | BF30: . | BG30: . | BH30: . | BI30: 0 | BJ30: . | BK30: . | BL30: . | BM30: . | BN30: 0 | BO30: . | BP30: . | BQ30: . | BR30: . | BS30: 0 | BT30: 1.85 | BU30: 0.28 | BV30: 2.45 | BW30: 0 | BX30: 4.58 | BY30: 241 | BZ30: 5 | CA30: 2 | CB30: 0 | CC30: 248 | CD30: 0 | CE30: 0 | CF30: 0 | CG30: 0 | CH30: 0
A31: 2022 | B31: AR | C31: 14063 | D31: Oklahoma Gas & Electric Co | E31: SWPP | F31: AC | G31: 2.657 | H31: 1.19 | I31: 0 | J31: 0 | K31: 3.847 | L31: 349 | M31: 16 | N31: 0 | O31: 0 | P31: 365 | Q31: 0 | R31: 0 | S31: 0 | T31: 0 | U31: 0 | V31: 0 | W31: 0 | X31: 0 | Y31: 0 | Z31: 0 | AA31: 1.551 | AB31: 1.444 | AC31: 0.023 | AD31: 0 | AE31: 3.018 | AF31: 420 | AG31: 397 | AH31: 2 | AI31: 0 | AJ31: 819 | AK31: 0 | AL31: 0 | AM31: 0 | AN31: 0 | AO31: 0 | AP31: 0.007 | AQ31: 0.001 | AR31: 0 | AS31: 0 | AT31: 0.008 | AU31: 2 | AV31: 1 | AW31: 0 | AX31: 0 | AY31: 3 | AZ31: 0 | BA31: 0 | BB31: 0 | BC31: 0 | BD31: 0 | BE31: 0 | BF31: 0 | BG31: 0 | BH31: 0 | BI31: 0 | BJ31: 0 | BK31: 0 | BL31: 0 | BM31: 0 | BN31: 0 | BO31: 0 | BP31: 0 | BQ31: 0 | BR31: 0 | BS31: 0 | BT31: 4.215 | BU31: 2.635 | BV31: 0.023 | BW31: 0 | BX31: 6.873 | BY31: 771 | BZ31: 414 | CA31: 2 | CB31: 0 | CC31: 1187 | CD31: 0 | CE31: 0 | CF31: 0 | CG31: 0 | CH31: 0
A32: 2022 | B32: AR | C32: 14289 | D32: Ozarks Electric Coop Corp - (AR) | E32: SWPP | F32: AC | G32: 8.129 | H32: 0.955 | I32: 15.314 | J32: . | K32: 24.398 | L32: 1119 | M32: 15 | N32: 11 | O32: . | P32: 1145 | Q32: . | R32: . | S32: . | T32: . | U32: . | V32: . | W32: . | X32: . | Y32: . | Z32: . | AA32: . | AB32: . | AC32: . | AD32: . | AE32: . | AF32: . | AG32: . | AH32: . | AI32: . | AJ32: . | AK32: . | AL32: . | AM32: . | AN32: . | AO32: 0 | AP32: . | AQ32: 0.009 | AR32: . | AS32: . | AT32: 0.009 | AU32: . | AV32: 1 | AW32: . | AX32: . | AY32: 1 | AZ32: . | BA32: . | BB32: . | BC32: . | BD32: 0 | BE32: . | BF32: . | BG32: . | BH32: . | BI32: 0 | BJ32: . | BK32: . | BL32: . | BM32: . | BN32: 0 | BO32: . | BP32: . | BQ32: . | BR32: . | BS32: 0 | BT32: 8.129 | BU32: 0.964 | BV32: 15.314 | BW32: 0 | BX32: 24.407 | BY32: 1119 | BZ32: 16 | CA32: 11 | CB32: 0 | CC32: 1146 | CD32: 0 | CE32: 0 | CF32: 0 | CG32: 0 | CH32: 0
A33: 2022 | B33: AR | C33: 14446 | D33: Paragould Light & Water Comm | E33: SPA | F33: AC | G33: 0.164 | H33: . | I33: . | J33: . | K33: 0.164 | L33: 13 | M33: . | N33: . | O33: . | P33: 13 | Q33: . | R33: . | S33: . | T33: . | U33: 0 | V33: . | W33: . | X33: . | Y33: . | Z33: 0 | AA33: . | AB33: . | AC33: . | AD33: . | AE33: 0 | AF33: . | AG33: . | AH33: . | AI33: . | AJ33: 0 | AK33: . | AL33: . | AM33: . | AN33: . | AO33: 0 | AP33: . | AQ33: . | AR33: . | AS33: . | AT33: 0 | AU33: . | AV33: . | AW33: . | AX33: . | AY33: 0 | AZ33: . | BA33: . | BB33: . | BC33: . | BD33: 0 | BE33: . | BF33: . | BG33: . | BH33: . | BI33: 0 | BJ33: . | BK33: . | BL33: . | BM33: . | BN33: 0 | BO33: . | BP33: . | BQ33: . | BR33: . | BS33: 0 | BT33: 0.164 | BU33: 0 | BV33: 0 | BW33: 0 | BX33: 0.164 | BY33: 13 | BZ33: 0 | CA33: 0 | CB33: 0 | CC33: 13 | CD33: 0 | CE33: 0 | CF33: 0 | CG33: 0 | CH33: 0
A34: 2022 | B34: AR | C34: 14864 | D34: Petit Jean Electric Coop Corp | E34: MISO | F34: AC | G34: 0.684 | H34: 0.45 | I34: . | J34: . | K34: 1.134 | L34: 68 | M34: 1 | N34: . | O34: . | P34: 69 | Q34: . | R34: . | S34: . | T34: . | U34: . | V34: . | W34: . | X34: . | Y34: . | Z34: . | AA34: . | AB34: . | AC34: . | AD34: . | AE34: . | AF34: . | AG34: . | AH34: . | AI34: . | AJ34: . | AK34: . | AL34: . | AM34: . | AN34: . | AO34: 0 | AP34: . | AQ34: . | AR34: . | AS34: . | AT34: 0 | AU34: . | AV34: . | AW34: . | AX34: . | AY34: 0 | AZ34: . | BA34: . | BB34: . | BC34: . | BD34: 0 | BE34: . | BF34: . | BG34: . | BH34: . | BI34: 0 | BJ34: . | BK34: . | BL34: . | BM34: . | BN34: 0 | BO34: . | BP34: . | BQ34: . | BR34: . | BS34: 0 | BT34: 0.684 | BU34: 0.45 | BV34: 0 | BW34: 0 | BX34: 1.134 | BY34: 68 | BZ34: 1 | CA34: 0 | CB34: 0 | CC34: 69 | CD34: 0 | CE34: 0 | CF34: 0 | CG34: 0 | CH34: 0
A35: 2022 | B35: AR | C35: 17184 | D35: City of Siloam Springs - (AR) | E35: SWPP | F35: AC | G35: 0.35 | H35: . | I35: . | J35: . | K35: 0.35 | L35: 51 | M35: . | N35: . | O35: . | P35: 51 | Q35: 0 | R35: . | S35: . | T35: . | U35: 0 | V35: 0 | W35: . | X35: . | Y35: . | Z35: 0 | AA35: 0 | AB35: . | AC35: . | AD35: . | AE35: 0 | AF35: 0 | AG35: . | AH35: . | AI35: . | AJ35: 0 | AK35: . | AL35: . | AM35: . | AN35: . | AO35: 0 | AP35: 0 | AQ35: . | AR35: . | AS35: . | AT35: 0 | AU35: 0 | AV35: . | AW35: . | AX35: . | AY35: 0 | AZ35: 0 | BA35: . | BB35: . | BC35: . | BD35: 0 | BE35: 0 | BF35: . | BG35: . | BH35: . | BI35: 0 | BJ35: 0 | BK35: . | BL35: . | BM35: . | BN35: 0 | BO35: 0 | BP35: . | BQ35: . | BR35: . | BS35: 0 | BT35: 0.35 | BU35: 0 | BV35: 0 | BW35: 0 | BX35: 0.35 | BY35: 51 | BZ35: 0 | CA35: 0 | CB35: 0 | CC35: 51 | CD35: 0 | CE35: 0 | CF35: 0 | CG35: 0 | CH35: 0
A36: 2022 | B36: AR | C36: 17671 | D36: Southwest Arkansas E C C | E36: MISO | F36: AC | G36: 0.763 | H36: 0.067 | I36: . | J36: . | K36: 0.83 | L36: 77 | M36: 3 | N36: . | O36: . | P36: 80 | Q36: . | R36: . | S36: . | T36: . | U36: . | V36: . | W36: . | X36: . | Y36: . | Z36: . | AA36: . | AB36: . | AC36: . | AD36: . | AE36: . | AF36: . | AG36: . | AH36: . | AI36: . | AJ36: . | AK36: . | AL36: . | AM36: . | AN36: . | AO36: 0 | AP36: . | AQ36: . | AR36: . | AS36: . | AT36: 0 | AU36: . | AV36: . | AW36: . | AX36: . | AY36: 0 | AZ36: . | BA36: . | BB36: . | BC36: . | BD36: 0 | BE36: . | BF36: . | BG36: . | BH36: . | BI36: 0 | BJ36: . | BK36: . | BL36: . | BM36: . | BN36: 0 | BO36: . | BP36: . | BQ36: . | BR36: . | BS36: 0 | BT36: 0.763 | BU36: 0.067 | BV36: 0 | BW36: 0 | BX36: 0.83 | BY36: 77 | BZ36: 3 | CA36: 0 | CB36: 0 | CC36: 80 | CD36: 0 | CE36: 0 | CF36: 0 | CG36: 0 | CH36: 0
A37: 2022 | B37: AR | C37: 17698 | D37: Southwestern Electric Power Co | E37: SWPP | F37: AC | G37: 6.504 | H37: 3.91 | I37: 0.7 | J37: . | K37: 11.114 | L37: 988 | M37: 45 | N37: 1 | O37: . | P37: 1034 | Q37: 0.427 | R37: . | S37: . | T37: . | U37: 0.427 | V37: 4 | W37: . | X37: . | Y37: . | Z37: 4 | AA37: 0.052 | AB37: 0.463 | AC37: . | AD37: . | AE37: 0.515 | AF37: 6 | AG37: 5 | AH37: . | AI37: . | AJ37: 11 | AK37: 3892.35 | AL37: 4251.13 | AM37: 307.9 | AN37: . | AO37: 8451.38 | AP37: . | AQ37: 0.005 | AR37: . | AS37: . | AT37: 0.005 | AU37: . | AV37: 2 | AW37: . | AX37: . | AY37: 2 | AZ37: . | BA37: 0.249 | BB37: . | BC37: . | BD37: 0.249 | BE37: . | BF37: . | BG37: . | BH37: . | BI37: 0 | BJ37: . | BK37: . | BL37: . | BM37: . | BN37: 0 | BO37: . | BP37: . | BQ37: . | BR37: . | BS37: 0 | BT37: 6.556 | BU37: 4.378 | BV37: 0.7 | BW37: 0 | BX37: 11.634 | BY37: 994 | BZ37: 52 | CA37: 1 | CB37: 0 | CC37: 1047 | CD37: 3892.35 | CE37: 4251.379 | CF37: 307.9 | CG37: 0 | CH37: 8451.629
A38: 2022 | B38: AR | C38: 20963 | D38: Woodruff Electric Coop Corp | E38: MISO | F38: AC | G38: 0.288 | H38: 2.213 | I38: . | J38: . | K38: 2.501 | L38: 25 | M38: 7 | N38: . | O38: . | P38: 32 | Q38: . | R38: . | S38: . | T38: . | U38: . | V38: . | W38: . | X38: . | Y38: . | Z38: . | AA38: . | AB38: . | AC38: . | AD38: . | AE38: . | AF38: . | AG38: . | AH38: . | AI38: . | AJ38: . | AK38: . | AL38: . | AM38: . | AN38: . | AO38: 0 | AP38: 0.003 | AQ38: . | AR38: . | AS38: . | AT38: 0.003 | AU38: 1 | AV38: . | AW38: . | AX38: . | AY38: 1 | AZ38: . | BA38: . | BB38: . | BC38: . | BD38: 0 | BE38: . | BF38: . | BG38: . | BH38: . | BI38: 0 | BJ38: . | BK38: . | BL38: . | BM38: . | BN38: 0 | BO38: . | BP38: . | BQ38: . | BR38: . | BS38: 0 | BT38: 0.291 | BU38: 2.213 | BV38: 0 | BW38: 0 | BX38: 2.504 | BY38: 26 | BZ38: 7 | CA38: 0 | CB38: 0 | CC38: 33 | CD38: 0 | CE38: 0 | CF38: 0 | CG38: 0 | CH38: 0
A39: 2022 | B39: AR | C39: 99999 | D39: Adjustment 2022 | E39: MISO | G39: -8.891 | H39: -6.714 | I39: -0.602 | J39: . | K39: -16.206 | L39: . | M39: . | N39: . | O39: . | P39: . | Q39: . | R39: . | S39: . | T39: . | U39: . | V39: . | W39: . | X39: . | Y39: . | Z39: . | AA39: . | AB39: . | AC39: . | AD39: . | AE39: . | AF39: . | AG39: . | AH39: . | AI39: . | AJ39: . | AK39: . | AL39: . | AM39: . | AN39: . | AO39: . | AP39: . | AQ39: . | AR39: . | AS39: . | AT39: . | AU39: . | AV39: . | AW39: . | AX39: . | AY39: . | AZ39: . | BA39: . | BB39: . | BC39: . | BD39: . | BE39: . | BF39: . | BG39: . | BH39: . | BI39: . | BJ39: . | BK39: . | BL39: . | BM39: . | BN39: . | BO39: . | BP39: . | BQ39: . | BR39: . | BS39: . | BT39: -8.891 | BU39: -6.714 | BV39: -0.602 | BW39: . | BX39: -16.206 | BY39: . | BZ39: . | CA39: . | CB39: . | CC39: . | CD39: . | CE39: . | CF39: . | CG39: . | CH39: .
A40: 2022 | B40: AR | C40: 99999 | D40: Adjustment 2022 | E40: SWPP | G40: -4.722 | H40: -0.946 | I40: . | J40: . | K40: -5.668 | L40: . | M40: . | N40: . | O40: . | P40: . | Q40: . | R40: . | S40: . | T40: . | U40: . | V40: . | W40: . | X40: . | Y40: . | Z40: . | AA40: . | AB40: . | AC40: . | AD40: . | AE40: . | AF40: . | AG40: . | AH40: . | AI40: . | AJ40: . | AK40: . | AL40: . | AM40: . | AN40: . | AO40: . | AP40: . | AQ40: . | AR40: . | AS40: . | AT40: . | AU40: . | AV40: . | AW40: . | AX40: . | AY40: . | AZ40: . | BA40: . | BB40: . | BC40: . | BD40: . | BE40: . | BF40: . | BG40: . | BH40: . | BI40: . | BJ40: . | BK40: . | BL40: . | BM40: . | BN40: . | BO40: . | BP40: . | BQ40: . | BR40: . | BS40: . | BT40: -4.722 | BU40: -0.946 | BV40: . | BW40: . | BX40: -5.668 | BY40: . | BZ40: . | CA40: . | CB40: . | CC40: . | CD40: . | CE40: . | CF40: . | CG40: . | CH40: .
A41: 2022 | B41: AZ | C41: 176 | D41: Ajo Improvement Co | E41: AZPS | F41: AC | G41: 0.028 | H41: 0.4 | I41: . | J41: . | K41: 0.428 | L41: 8 | M41: 3 | N41: . | O41: . | P41: 11 | Q41: . | R41: . | S41: . | T41: . | U41: . | V41: . | W41: . | X41: . | Y41: . | Z41: . | AA41: . | AB41: . | AC41: . | AD41: . | AE41: . | AF41: . | AG41: . | AH41: . | AI41: . | AJ41: . | AK41: 2.833 | AL41: 0.184 | AM41: . | AN41: . | AO41: 3.017 | AP41: . | AQ41: . | AR41: . | AS41: . | AT41: 0 | AU41: . | AV41: . | AW41: . | AX41: . | AY41: 0 | AZ41: . | BA41: . | BB41: . | BC41: . | BD41: 0 | BE41: . | BF41: . | BG41: . | BH41: . | BI41: 0 | BJ41: . | BK41: . | BL41: . | BM41: . | BN41: 0 | BO41: . | BP41: . | BQ41: . | BR41: . | BS41: 0 | BT41: 0.028 | BU41: 0.4 | BV41: 0 | BW41: 0 | BX41: 0.428 | BY41: 8 | BZ41: 3 | CA41: 0 | CB41: 0 | CC41: 11 | CD41: 2.833 | CE41: 0.184 | CF41: 0 | CG41: 0 | CH41: 3.017
A42: 2022 | B42: AZ | C42: 803 | D42: Arizona Public Service Co | E42: AZPS | F42: DC | G42: 1324.821 | H42: 321.766 | I42: 0 | J42: 0 | K42: 1646.587 | L42: 152366 | M42: 1992 | N42: 0 | O42: 0 | P42: 154358 | Q42: . | R42: . | S42: . | T42: . | U42: . | V42: . | W42: . | X42: . | Y42: . | Z42: . | AA42: . | AB42: . | AC42: . | AD42: . | AE42: . | AF42: . | AG42: . | AH42: . | AI42: . | AJ42: . | AK42: . | AL42: . | AM42: . | AN42: . | AO42: 0 | AP42: 0.057 | AQ42: 0.125 | AR42: 0 | AS42: 0 | AT42: 0.182 | AU42: 24 | AV42: 12 | AW42: 0 | AX42: 0 | AY42: 36 | AZ42: . | BA42: . | BB42: . | BC42: . | BD42: 0 | BE42: . | BF42: . | BG42: . | BH42: . | BI42: 0 | BJ42: . | BK42: . | BL42: . | BM42: . | BN42: 0 | BO42: . | BP42: . | BQ42: . | BR42: . | BS42: 0 | BT42: 1324.878 | BU42: 321.891 | BV42: 0 | BW42: 0 | BX42: 1646.769 | BY42: 152390 | BZ42: 2004 | CA42: 0 | CB42: 0 | CC42: 154394 | CD42: 0 | CE42: 0 | CF42: 0 | CG42: 0 | CH42: 0
A43: 2022 | B43: AZ | C43: 6957 | D43: Garkane Energy Coop, Inc | E43: WALC | F43: DC | G43: 0.421 | H43: 0.063 | I43: . | J43: . | K43: 0.484 | L43: 23 | M43: 2 | N43: . | O43: . | P43: 25 | Q43: . | R43: . | S43: . | T43: . | U43: . | V43: . | W43: . | X43: . | Y43: . | Z43: . | AA43: . | AB43: . | AC43: . | AD43: . | AE43: . | AF43: . | AG43: . | AH43: . | AI43: . | AJ43: . | AK43: . | AL43: . | AM43: . | AN43: . | AO43: 0 | AP43: . | AQ43: . | AR43: . | AS43: . | AT43: 0 | AU43: . | AV43: . | AW43: . | AX43: . | AY43: 0 | AZ43: . | BA43: . | BB43: . | BC43: . | BD43: 0 | BE43: . | BF43: . | BG43: . | BH43: . | BI43: 0 | BJ43: . | BK43: . | BL43: . | BM43: . | BN43: 0 | BO43: . | BP43: . | BQ43: . | BR43: . | BS43: 0 | BT43: 0.421 | BU43: 0.063 | BV43: 0 | BW43: 0 | BX43: 0.484 | BY43: 23 | BZ43: 2 | CA43: 0 | CB43: 0 | CC43: 25 | CD43: 0 | CE43: 0 | CF43: 0 | CG43: 0 | CH43: 0
A44: 2022 | B44: AZ | C44: 12351 | D44: City of Mesa - (AZ) | E44: WALC | F44: DC | G44: 0.446 | H44: 0.999 | I44: . | J44: . | K44: 1.445 | L44: 111 | M44: 30 | N44: . | O44: . | P44: 141 | Q44: . | R44: . | S44: . | T44: . | U44: . | V44: . | W44: . | X44: . | Y44: . | Z44: . | AA44: . | AB44: . | AC44: . | AD44: . | AE44: . | AF44: . | AG44: . | AH44: . | AI44: . | AJ44: . | AK44: . | AL44: . | AM44: . | AN44: . | AO44: 0 | AP44: . | AQ44: . | AR44: . | AS44: . | AT44: 0 | AU44: . | AV44: . | AW44: . | AX44: . | AY44: 0 | AZ44: . | BA44: . | BB44: . | BC44: . | BD44: 0 | BE44: . | BF44: . | BG44: . | BH44: . | BI44: 0 | BJ44: . | BK44: . | BL44: . | BM44: . | BN44: 0 | BO44: . | BP44: . | BQ44: . | BR44: . | BS44: 0 | BT44: 0.446 | BU44: 0.999 | BV44: 0 | BW44: 0 | BX44: 1.445 | BY44: 111 | BZ44: 30 | CA44: 0 | CB44: 0 | CC44: 141 | CD44: 0 | CE44: 0 | CF44: 0 | CG44: 0 | CH44: 0
A45: 2022 | B45: AZ | C45: 12919 | D45: Morenci Water and Electric | E45: WALC | F45: AC | G45: 0.008 | H45: 0.028 | I45: . | J45: . | K45: 0.036 | L45: 1 | M45: 3 | N45: . | O45: . | P45: 4 | Q45: . | R45: . | S45: . | T45: . | U45: . | V45: . | W45: . | X45: . | Y45: . | Z45: . | AA45: . | AB45: . | AC45: . | AD45: . | AE45: . | AF45: . | AG45: . | AH45: . | AI45: . | AJ45: . | AK45: 0.891 | AL45: 0.981 | AM45: . | AN45: . | AO45: 1.872 | AP45: . | AQ45: . | AR45: . | AS45: . | AT45: 0 | AU45: . | AV45: . | AW45: . | AX45: . | AY45: 0 | AZ45: . | BA45: . | BB45: . | BC45: . | BD45: 0 | BE45: . | BF45: . | BG45: . | BH45: . | BI45: 0 | BJ45: . | BK45: . | BL45: . | BM45: . | BN45: 0 | BO45: . | BP45: . | BQ45: . | BR45: . | BS45: 0 | BT45: 0.008 | BU45: 0.028 | BV45: 0 | BW45: 0 | BX45: 0.036 | BY45: 1 | BZ45: 3 | CA45: 0 | CB45: 0 | CC45: 4 | CD45: 0.891 | CE45: 0.981 | CF45: 0 | CG45: 0 | CH45: 1.872
A46: 2022 | B46: AZ | C46: 13318 | D46: Navopache Electric Coop, Inc | E46: TEPC | F46: AC | G46: 3.344 | H46: 0.454 | I46: . | J46: . | K46: 3.798 | L46: 427 | M46: 31 | N46: . | O46: . | P46: 458 | Q46: . | R46: . | S46: . | T46: . | U46: . | V46: . | W46: . | X46: . | Y46: . | Z46: . | AA46: . | AB46: . | AC46: . | AD46: . | AE46: . | AF46: . | AG46: . | AH46: . | AI46: . | AJ46: . | AK46: 2928.101 | AL46: 293.462 | AM46: . | AN46: . | AO46: 3221.563 | AP46: 0.006 | AQ46: . | AR46: . | AS46: . | AT46: 0.006 | AU46: 5 | AV46: . | AW46: . | AX46: . | AY46: 5 | AZ46: . | BA46: . | BB46: . | BC46: . | BD46: 0 | BE46: . | BF46: . | BG46: . | BH46: . | BI46: 0 | BJ46: . | BK46: . | BL46: . | BM46: . | BN46: 0 | BO46: . | BP46: . | BQ46: . | BR46: . | BS46: 0 | BT46: 3.35 | BU46: 0.454 | BV46: 0 | BW46: 0 | BX46: 3.804 | BY46: 432 | BZ46: 31 | CA46: 0 | CB46: 0 | CC46: 463 | CD46: 2928.101 | CE46: 293.462 | CF46: 0 | CG46: 0 | CH46: 3221.563
A47: 2022 | B47: AZ | C47: 16572 | D47: Salt River Project | E47: SRP | F47: AC | G47: 310.86 | H47: 108.621 | I47: 6.63 | J47: . | K47: 426.111 | L47: 46617 | M47: 826 | N47: 3 | O47: . | P47: 47446 | Q47: 13.939 | R47: 0.38 | S47: 0 | T47: . | U47: 14.319 | V47: 2966 | W47: 8 | X47: 0 | Y47: . | Z47: 2974 | AA47: 0 | AB47: 0 | AC47: 0 | AD47: . | AE47: 0 | AF47: 0 | AG47: 0 | AH47: 0 | AI47: . | AJ47: 0 | AK47: 48552 | AL47: 44249 | AM47: . | AN47: . | AO47: 92801 | AP47: . | AQ47: . | AR47: . | AS47: . | AT47: 0 | AU47: . | AV47: . | AW47: . | AX47: . | AY47: 0 | AZ47: . | BA47: . | BB47: . | BC47: . | BD47: 0 | BE47: . | BF47: . | BG47: . | BH47: . | BI47: 0 | BJ47: . | BK47: . | BL47: . | BM47: . | BN47: 0 | BO47: . | BP47: . | BQ47: . | BR47: . | BS47: 0 | BT47: 310.86 | BU47: 108.621 | BV47: 6.63 | BW47: 0 | BX47: 426.111 | BY47: 46617 | BZ47: 826 | CA47: 3 | CB47: 0 | CC47: 47446 | CD47: 48552 | CE47: 44249 | CF47: 0 | CG47: 0 | CH47: 92801
A48: 2022 | B48: AZ | C48: 18280 | D48: Sulphur Springs Valley E C Inc | E48: WALC | F48: AC | G48: 8.5 | H48: 4 | I48: . | J48: . | K48: 12.5 | L48: 1137 | M48: 307 | N48: . | O48: . | P48: 1444 | Q48: . | R48: . | S48: . | T48: . | U48: . | V48: . | W48: . | X48: . | Y48: . | Z48: . | AA48: . | AB48: . | AC48: . | AD48: . | AE48: . | AF48: . | AG48: . | AH48: . | AI48: . | AJ48: . | AK48: . | AL48: . | AM48: . | AN48: . | AO48: 0 | AP48: 0.1 | AQ48: . | AR48: . | AS48: . | AT48: 0.1 | AU48: 37 | AV48: . | AW48: . | AX48: . | AY48: 37 | AZ48: . | BA48: . | BB48: . | BC48: . | BD48: 0 | BE48: . | BF48: . | BG48: . | BH48: . | BI48: 0 | BJ48: . | BK48: . | BL48: . | BM48: . | BN48: 0 | BO48: . | BP48: . | BQ48: . | BR48: . | BS48: 0 | BT48: 8.6 | BU48: 4 | BV48: 0 | BW48: 0 | BX48: 12.6 | BY48: 1174 | BZ48: 307 | CA48: 0 | CB48: 0 | CC48: 1481 | CD48: 0 | CE48: 0 | CF48: 0 | CG48: 0 | CH48: 0
A49: 2022 | B49: AZ | C49: 19189 | D49: Trico Electric Cooperative Inc | E49: WALC | F49: DC | G49: 34.045 | H49: 15.11 | I49: . | J49: . | K49: 49.155 | L49: 4423 | M49: 71 | N49: . | O49: . | P49: 4494 | Q49: . | R49: . | S49: . | T49: . | U49: 0 | V49: . | W49: . | X49: . | Y49: . | Z49: 0 | AA49: 0.044 | AB49: 0.183 | AC49: . | AD49: . | AE49: 0.227 | AF49: 48 | AG49: 1 | AH49: . | AI49: . | AJ49: 49 | AK49: 28273.999 | AL49: 7203.092 | AM49: . | AN49: . | AO49: 35477.091 | AP49: 0.002 | AQ49: . | AR49: . | AS49: . | AT49: 0.002 | AU49: 1 | AV49: . | AW49: . | AX49: . | AY49: 1 | AZ49: 0.137 | BA49: . | BB49: . | BC49: . | BD49: 0.137 | BE49: . | BF49: . | BG49: . | BH49: . | BI49: 0 | BJ49: . | BK49: . | BL49: . | BM49: . | BN49: 0 | BO49: . | BP49: . | BQ49: . | BR49: . | BS49: 0 | BT49: 34.091 | BU49: 15.293 | BV49: 0 | BW49: 0 | BX49: 49.384 | BY49: 4472 | BZ49: 72 | CA49: 0 | CB49: 0 | CC49: 4544 | CD49: 28274.136 | CE49: 7203.092 | CF49: 0 | CG49: 0 | CH49: 35477.228
A50: 2022 | B50: AZ | C50: 19728 | D50: UNS Electric, Inc | E50: TEPC | F50: AC | G50: 50.83 | H50: 15.08 | I50: . | J50: . | K50: 65.91 | L50: 6538 | M50: 219 | N50: . | O50: . | P50: 6757 | Q50: 0.39 | R50: . | S50: . | T50: . | U50: 0.39 | V50: 66 | W50: . | X50: . | Y50: . | Z50: 66 | AA50: . | AB50: . | AC50: . | AD50: . | AE50: 0 | AF50: . | AG50: . | AH50: . | AI50: . | AJ50: 0 | AK50: 3653.189 | AL50: 519.334 | AM50: . | AN50: . | AO50: 4172.523 | AP50: 0.3 | AQ50: 0.01 | AR50: . | AS50: . | AT50: 0.31 | AU50: 117 | AV50: 1 | AW50: . | AX50: . | AY50: 118 | AZ50: 5.531 | BA50: 0.039 | BB50: . | BC50: . | BD50: 5.57 | BE50: . | BF50: . | BG50: . | BH50: . | BI50: 0 | BJ50: . | BK50: . | BL50: . | BM50: . | BN50: 0 | BO50: . | BP50: . | BQ50: . | BR50: . | BS50: 0 | BT50: 51.13 | BU50: 15.09 | BV50: 0 | BW50: 0 | BX50: 66.22 | BY50: 6655 | BZ50: 220 | CA50: 0 | CB50: 0 | CC50: 6875 | CD50: 3658.72 | CE50: 519.373 | CF50: 0 | CG50: 0 | CH50: 4178.093
A51: 2022 | B51: AZ | C51: 21538 | D51: Mohave Electric Cooperative, Inc. | E51: WALC | F51: AC | G51: 14.849 | H51: 3.537 | I51: 0 | J51: 0 | K51: 18.386 | L51: 1500 | M51: 89 | N51: 0 | O51: 0 | P51: 1589 | Q51: 0 | R51: 0 | S51: 0 | T51: 0 | U51: 0 | V51: 0 | W51: 0 | X51: 0 | Y51: 0 | Z51: 0 | AA51: 0 | AB51: 0 | AC51: 0 | AD51: 0 | AE51: 0 | AF51: 0 | AG51: 0 | AH51: 0 | AI51: 0 | AJ51: 0 | AK51: 489.252 | AL51: 65.237 | AM51: 0 | AN51: 0 | AO51: 554.489 | AP51: 0.055 | AQ51: 0 | AR51: 0 | AS51: 0 | AT51: 0.055 | AU51: 25 | AV51: 0 | AW51: 0 | AX51: 0 | AY51: 25 | AZ51: 0 | BA51: 0 | BB51: 0 | BC51: 0 | BD51: 0 | BE51: 0 | BF51: 0 | BG51: 0 | BH51: 0 | BI51: 0 | BJ51: 0 | BK51: 0 | BL51: 0 | BM51: 0 | BN51: 0 | BO51: . | BP51: . | BQ51: . | BR51: . | BS51: 0 | BT51: 14.904 | BU51: 3.537 | BV51: 0 | BW51: 0 | BX51: 18.441 | BY51: 1525 | BZ51: 89 | CA51: 0 | CB51: 0 | CC51: 1614 | CD51: 489.252 | CE51: 65.237 | CF51: 0 | CG51: 0 | CH51: 554.489
A52: 2022 | B52: AZ | C52: 24211 | D52: Tucson Electric Power Co | E52: TEPC | F52: AC | G52: 259.512 | H52: 149.504 | I52: . | J52: . | K52: 409.016 | L52: 40473 | M52: 1021 | N52: . | O52: . | P52: 41494 | Q52: 5.73 | R52: 0.337 | S52: . | T52: . | U52: 6.067 | V52: 640 | W52: 7 | X52: . | Y52: . | Z52: 647 | AA52: . | AB52: . | AC52: . | AD52: . | AE52: 0 | AF52: . | AG52: . | AH52: . | AI52: . | AJ52: 0 | AK52: 3995.63 | AL52: 2237.318 | AM52: . | AN52: . | AO52: 6232.948 | AP52: . | AQ52: 0.012 | AR52: . | AS52: . | AT52: 0.012 | AU52: . | AV52: 1 | AW52: . | AX52: . | AY52: 1 | AZ52: . | BA52: 0.002 | BB52: . | BC52: . | BD52: 0.002 | BE52: . | BF52: . | BG52: . | BH52: . | BI52: 0 | BJ52: . | BK52: . | BL52: . | BM52: . | BN52: 0 | BO52: . | BP52: . | BQ52: . | BR52: . | BS52: 0 | BT52: 259.512 | BU52: 149.516 | BV52: 0 | BW52: 0 | BX52: 409.028 | BY52: 40473 | BZ52: 1022 | CA52: 0 | CB52: 0 | CC52: 41495 | CD52: 3995.63 | CE52: 2237.32 | CF52: 0 | CG52: 0 | CH52: 6232.95
A53: 2022 | B53: AZ | C53: 30518 | D53: Electrical Dist No3 Pinal County | E53: AZPS | F53: AC | G53: 21.213 | H53: . | I53: . | J53: . | K53: 21.213 | L53: 2794 | M53: . | N53: . | O53: . | P53: 2794 | Q53: . | R53: . | S53: . | T53: . | U53: . | V53: . | W53: . | X53: . | Y53: . | Z53: . | AA53: . | AB53: . | AC53: . | AD53: . | AE53: . | AF53: . | AG53: . | AH53: . | AI53: . | AJ53: . | AK53: . | AL53: . | AM53: . | AN53: . | AO53: 0 | AP53: . | AQ53: . | AR53: . | AS53: . | AT53: 0 | AU53: . | AV53: . | AW53: . | AX53: . | AY53: 0 | AZ53: . | BA53: . | BB53: . | BC53: . | BD53: 0 | BE53: . | BF53: . | BG53: . | BH53: . | BI53: 0 | BJ53: . | BK53: . | BL53: . | BM53: . | BN53: 0 | BO53: . | BP53: . | BQ53: . | BR53: . | BS53: 0 | BT53: 21.213 | BU53: 0 | BV53: 0 | BW53: 0 | BX53: 21.213 | BY53: 2794 | BZ53: 0 | CA53: 0 | CB53: 0 | CC53: 2794 | CD53: 0 | CE53: 0 | CF53: 0 | CG53: 0 | CH53: 0
A54: 2022 | B54: AZ | C54: 40165 | D54: Dixie Escalante R E A, Inc | E54: PACE | F54: DC | G54: 0.06 | H54: 0.02 | I54: . | J54: . | K54: 0.08 | L54: 6 | M54: 1 | N54: . | O54: . | P54: 7 | Q54: . | R54: . | S54: . | T54: . | U54: . | V54: . | W54: . | X54: . | Y54: . | Z54: . | AA54: . | AB54: . | AC54: . | AD54: . | AE54: . | AF54: . | AG54: . | AH54: . | AI54: . | AJ54: . | AK54: 16.62 | AL54: . | AM54: . | AN54: . | AO54: 16.62 | AP54: . | AQ54: . | AR54: . | AS54: . | AT54: 0 | AU54: . | AV54: . | AW54: . | AX54: . | AY54: 0 | AZ54: . | BA54: . | BB54: . | BC54: . | BD54: 0 | BE54: . | BF54: . | BG54: . | BH54: . | BI54: 0 | BJ54: . | BK54: . | BL54: . | BM54: . | BN54: 0 | BO54: . | BP54: . | BQ54: . | BR54: . | BS54: 0 | BT54: 0.06 | BU54: 0.02 | BV54: 0 | BW54: 0 | BX54: 0.08 | BY54: 6 | BZ54: 1 | CA54: 0 | CB54: 0 | CC54: 7 | CD54: 16.62 | CE54: 0 | CF54: 0 | CG54: 0 | CH54: 16.62
A55: 2022 | B55: AZ | C55: 65261 | D55: Gila River Indian Utility Authority (GRICUA) | E55: WALC | F55: AC | G55: . | H55: . | I55: . | J55: . | K55: 0 | L55: . | M55: . | N55: . | O55: . | P55: 0 | Q55: . | R55: . | S55: . | T55: . | U55: 0 | V55: . | W55: . | X55: . | Y55: . | Z55: 0 | AA55: . | AB55: . | AC55: . | AD55: . | AE55: 0 | AF55: . | AG55: . | AH55: . | AI55: . | AJ55: 0 | AK55: . | AL55: . | AM55: . | AN55: . | AO55: 0 | AP55: . | AQ55: . | AR55: . | AS55: . | AT55: 0 | AU55: . | AV55: . | AW55: . | AX55: . | AY55: 0 | AZ55: . | BA55: . | BB55: . | BC55: . | BD55: 0 | BE55: . | BF55: 1 | BG55: . | BH55: . | BI55: 1 | BJ55: . | BK55: 3 | BL55: . | BM55: . | BN55: 3 | BO55: . | BP55: . | BQ55: . | BR55: . | BS55: 0 | BT55: 0 | BU55: 1 | BV55: 0 | BW55: 0 | BX55: 1 | BY55: 0 | BZ55: 3 | CA55: 0 | CB55: 0 | CC55: 3 | CD55: 0 | CE55: 0 | CF55: 0 | CG55: 0 | CH55: 0
A56: 2022 | B56: AZ | C56: 99999 | D56: Adjustment 2022 | E56: AZPS | G56: -231.049 | H56: -56.116 | I56: 0 | J56: 0 | K56: -287.165 | L56: . | M56: . | N56: . | O56: . | P56: . | Q56: . | R56: . | S56: . | T56: . | U56: . | V56: . | W56: . | X56: . | Y56: . | Z56: . | AA56: . | AB56: . | AC56: . | AD56: . | AE56: . | AF56: . | AG56: . | AH56: . | AI56: . | AJ56: . | AK56: . | AL56: . | AM56: . | AN56: . | AO56: . | AP56: . | AQ56: . | AR56: . | AS56: . | AT56: . | AU56: . | AV56: . | AW56: . | AX56: . | AY56: . | AZ56: . | BA56: . | BB56: . | BC56: . | BD56: . | BE56: . | BF56: . | BG56: . | BH56: . | BI56: . | BJ56: . | BK56: . | BL56: . | BM56: . | BN56: . | BO56: . | BP56: . | BQ56: . | BR56: . | BS56: . | BT56: -231.049 | BU56: -56.116 | BV56: 0 | BW56: 0 | BX56: -287.165 | BY56: . | BZ56: . | CA56: . | CB56: . | CC56: . | CD56: . | CE56: . | CF56: . | CG56: . | CH56: .
A57: 2022 | B57: AZ | C57: 99999 | D57: Adjustment 2022 | E57: PACE | G57: -0.01 | H57: -0.003 | I57: . | J57: . | K57: -0.014 | L57: . | M57: . | N57: . | O57: . | P57: . | Q57: . | R57: . | S57: . | T57: . | U57: . | V57: . | W57: . | X57: . | Y57: . | Z57: . | AA57: . | AB57: . | AC57: . | AD57: . | AE57: . | AF57: . | AG57: . | AH57: . | AI57: . | AJ57: . | AK57: . | AL57: . | AM57: . | AN57: . | AO57: . | AP57: . | AQ57: . | AR57: . | AS57: . | AT57: . | AU57: . | AV57: . | AW57: . | AX57: . | AY57: . | AZ57: . | BA57: . | BB57: . | BC57: . | BD57: . | BE57: . | BF57: . | BG57: . | BH57: . | BI57: . | BJ57: . | BK57: . | BL57: . | BM57: . | BN57: . | BO57: . | BP57: . | BQ57: . | BR57: . | BS57: . | BT57: -0.01 | BU57: -0.003 | BV57: . | BW57: . | BX57: -0.014 | BY57: . | BZ57: . | CA57: . | CB57: . | CC57: . | CD57: . | CE57: . | CF57: . | CG57: . | CH57: .
A58: 2022 | B58: AZ | C58: 99999 | D58: Adjustment 2022 | E58: WALC | G58: -6.089 | H58: -2.82 | I58: . | J58: . | K58: -8.909 | L58: . | M58: . | N58: . | O58: . | P58: . | Q58: . | R58: . | S58: . | T58: . | U58: . | V58: . | W58: . | X58: . | Y58: . | Z58: . | AA58: -0.008 | AB58: -0.032 | AC58: . | AD58: . | AE58: -0.04 | AF58: . | AG58: . | AH58: . | AI58: . | AJ58: . | AK58: . | AL58: . | AM58: . | AN58: . | AO58: . | AP58: . | AQ58: . | AR58: . | AS58: . | AT58: . | AU58: . | AV58: . | AW58: . | AX58: . | AY58: . | AZ58: . | BA58: . | BB58: . | BC58: . | BD58: . | BE58: . | BF58: . | BG58: . | BH58: . | BI58: . | BJ58: . | BK58: . | BL58: . | BM58: . | BN58: . | BO58: . | BP58: . | BQ58: . | BR58: . | BS58: . | BT58: -6.096 | BU58: -2.852 | BV58: . | BW58: . | BX58: -8.949 | BY58: . | BZ58: . | CA58: . | CB58: . | CC58: . | CD58: . | CE58: . | CF58: . | CG58: . | CH58: .
A59: 2022 | B59: CA | C59: 207 | D59: Alameda Municipal Power | E59: CISO | F59: AC | G59: 3.67 | H59: 3.734 | I59: . | J59: . | K59: 7.404 | L59: 856 | M59: 42 | N59: . | O59: . | P59: 898 | Q59: . | R59: . | S59: . | T59: . | U59: . | V59: . | W59: . | X59: . | Y59: . | Z59: . | AA59: . | AB59: . | AC59: . | AD59: . | AE59: . | AF59: . | AG59: . | AH59: . | AI59: . | AJ59: . | AK59: 41.862 | AL59: 160.354 | AM59: . | AN59: . | AO59: 202.216 | AP59: . | AQ59: . | AR59: . | AS59: . | AT59: 0 | AU59: . | AV59: . | AW59: . | AX59: . | AY59: 0 | AZ59: . | BA59: . | BB59: . | BC59: . | BD59: 0 | BE59: . | BF59: . | BG59: . | BH59: . | BI59: 0 | BJ59: . | BK59: . | BL59: . | BM59: . | BN59: 0 | BO59: . | BP59: . | BQ59: . | BR59: . | BS59: 0 | BT59: 3.67 | BU59: 3.734 | BV59: 0 | BW59: 0 | BX59: 7.404 | BY59: 856 | BZ59: 42 | CA59: 0 | CB59: 0 | CC59: 898 | CD59: 41.862 | CE59: 160.354 | CF59: 0 | CG59: 0 | CH59: 202.216
A60: 2022 | B60: CA | C60: 590 | D60: City of Anaheim - (CA) | E60: CISO | F60: DC | G60: 26.986 | H60: 20.157 | I60: . | J60: . | K60: 47.143 | L60: 4789 | M60: 209 | N60: . | O60: . | P60: 4998 | Q60: . | R60: . | S60: . | T60: . | U60: . | V60: . | W60: . | X60: . | Y60: . | Z60: . | AA60: . | AB60: . | AC60: . | AD60: . | AE60: . | AF60: . | AG60: . | AH60: . | AI60: . | AJ60: . | AK60: . | AL60: . | AM60: . | AN60: . | AO60: 0 | AP60: . | AQ60: . | AR60: . | AS60: . | AT60: 0 | AU60: . | AV60: . | AW60: . | AX60: . | AY60: 0 | AZ60: . | BA60: . | BB60: . | BC60: . | BD60: 0 | BE60: . | BF60: . | BG60: . | BH60: . | BI60: 0 | BJ60: . | BK60: . | BL60: . | BM60: . | BN60: 0 | BO60: . | BP60: . | BQ60: . | BR60: . | BS60: 0 | BT60: 26.986 | BU60: 20.157 | BV60: 0 | BW60: 0 | BX60: 47.143 | BY60: 4789 | BZ60: 209 | CA60: 0 | CB60: 0 | CC60: 4998 | CD60: 0 | CE60: 0 | CF60: 0 | CG60: 0 | CH60: 0
A61: 2022 | B61: CA | C61: 1050 | D61: City of Azusa | E61: CISO | F61: DC | G61: 1.607 | H61: 0.467 | I61: 0.405 | J61: . | K61: 2.479 | L61: 324 | M61: 7 | N61: 5 | O61: . | P61: 336 | Q61: . | R61: . | S61: . | T61: . | U61: . | V61: . | W61: . | X61: . | Y61: . | Z61: . | AA61: . | AB61: . | AC61: . | AD61: . | AE61: . | AF61: . | AG61: . | AH61: . | AI61: . | AJ61: . | AK61: . | AL61: . | AM61: . | AN61: . | AO61: 0 | AP61: . | AQ61: . | AR61: . | AS61: . | AT61: 0 | AU61: . | AV61: . | AW61: . | AX61: . | AY61: 0 | AZ61: . | BA61: . | BB61: . | BC61: . | BD61: 0 | BE61: . | BF61: . | BG61: . | BH61: . | BI61: 0 | BJ61: . | BK61: . | BL61: . | BM61: . | BN61: 0 | BO61: . | BP61: . | BQ61: . | BR61: . | BS61: 0 | BT61: 1.607 | BU61: 0.467 | BV61: 0.405 | BW61: 0 | BX61: 2.479 | BY61: 324 | BZ61: 7 | CA61: 5 | CB61: 0 | CC61: 336 | CD61: 0 | CE61: 0 | CF61: 0 | CG61: 0 | CH61: 0
A62: 2022 | B62: CA | C62: 2507 | D62: City of Burbank Water and Power | E62: LDWP | F62: AC | G62: 5.913 | H62: 5.8 | I62: . | J62: . | K62: 11.713 | L62: 1017 | M62: 54 | N62: . | O62: . | P62: 1071 | Q62: 0.145 | R62: . | S62: . | T62: . | U62: 0.145 | V62: 20 | W62: . | X62: . | Y62: . | Z62: 20 | AA62: . | AB62: . | AC62: . | AD62: . | AE62: 0 | AF62: . | AG62: . | AH62: . | AI62: . | AJ62: 0 | AK62: . | AL62: . | AM62: . | AN62: . | AO62: 0 | AP62: . | AQ62: . | AR62: . | AS62: . | AT62: 0 | AU62: . | AV62: . | AW62: . | AX62: . | AY62: 0 | AZ62: . | BA62: . | BB62: . | BC62: . | BD62: 0 | BE62: . | BF62: . | BG62: . | BH62: . | BI62: 0 | BJ62: . | BK62: . | BL62: . | BM62: . | BN62: 0 | BO62: . | BP62: . | BQ62: . | BR62: . | BS62: 0 | BT62: 5.913 | BU62: 5.8 | BV62: 0 | BW62: 0 | BX62: 11.713 | BY62: 1017 | BZ62: 54 | CA62: 0 | CB62: 0 | CC62: 1071 | CD62: 0 | CE62: 0 | CF62: 0 | CG62: 0 | CH62: 0
A63: 2022 | B63: CA | C63: 4003 | D63: City of Colton - (CA) | E63: CISO | F63: AC | G63: 8.311 | H63: 1.189 | I63: 7.325 | J63: . | K63: 16.825 | L63: 909 | M63: 7 | N63: 10 | O63: . | P63: 926 | Q63: . | R63: . | S63: . | T63: . | U63: . | V63: . | W63: . | X63: . | Y63: . | Z63: . | AA63: . | AB63: . | AC63: . | AD63: . | AE63: . | AF63: . | AG63: . | AH63: . | AI63: . | AJ63: . | AK63: . | AL63: . | AM63: . | AN63: . | AO63: 0 | AP63: . | AQ63: . | AR63: . | AS63: . | AT63: 0 | AU63: . | AV63: . | AW63: . | AX63: . | AY63: 0 | AZ63: . | BA63: . | BB63: . | BC63: . | BD63: 0 | BE63: . | BF63: . | BG63: . | BH63: . | BI63: 0 | BJ63: . | BK63: . | BL63: . | BM63: . | BN63: 0 | BO63: . | BP63: . | BQ63: . | BR63: . | BS63: 0 | BT63: 8.311 | BU63: 1.189 | BV63: 7.325 | BW63: 0 | BX63: 16.825 | BY63: 909 | BZ63: 7 | CA63: 10 | CB63: 0 | CC63: 926 | CD63: 0 | CE63: 0 | CF63: 0 | CG63: 0 | CH63: 0
A64: 2022 | B64: CA | C64: 4390 | D64: City of Corona - (CA) | E64: CISO | F64: AC | G64: 0.103 | H64: 0.362 | I64: 0 | J64: 0 | K64: 0.465 | L64: 14 | M64: 2 | N64: 0 | O64: 0 | P64: 16 | Q64: . | R64: . | S64: . | T64: . | U64: . | V64: . | W64: . | X64: . | Y64: . | Z64: . | AA64: . | AB64: . | AC64: . | AD64: . | AE64: . | AF64: . | AG64: . | AH64: . | AI64: . | AJ64: . | AK64: . | AL64: . | AM64: . | AN64: . | AO64: 0 | AP64: . | AQ64: . | AR64: . | AS64: . | AT64: 0 | AU64: . | AV64: . | AW64: . | AX64: . | AY64: 0 | AZ64: . | BA64: . | BB64: . | BC64: . | BD64: 0 | BE64: . | BF64: . | BG64: . | BH64: . | BI64: 0 | BJ64: . | BK64: . | BL64: . | BM64: . | BN64: 0 | BO64: . | BP64: . | BQ64: . | BR64: . | BS64: 0 | BT64: 0.103 | BU64: 0.362 | BV64: 0 | BW64: 0 | BX64: 0.465 | BY64: 14 | BZ64: 2 | CA64: 0 | CB64: 0 | CC64: 16 | CD64: 0 | CE64: 0 | CF64: 0 | CG64: 0 | CH64: 0
A65: 2022 | B65: CA | C65: 7294 | D65: City of Glendale - (CA) | E65: LDWP | F65: AC | G65: 14.019 | H65: 10.975 | I65: . | J65: . | K65: 24.994 | L65: 2332 | M65: 119 | N65: . | O65: . | P65: 2451 | Q65: 0.682 | R65: 0.01 | S65: . | T65: . | U65: 0.692 | V65: 142 | W65: 2 | X65: . | Y65: . | Z65: 144 | AA65: . | AB65: . | AC65: . | AD65: . | AE65: 0 | AF65: . | AG65: . | AH65: . | AI65: . | AJ65: 0 | AK65: 408.483 | AL65: . | AM65: . | AN65: . | AO65: 408.483 | AP65: . | AQ65: . | AR65: . | AS65: . | AT65: 0 | AU65: . | AV65: . | AW65: . | AX65: . | AY65: 0 | AZ65: . | BA65: . | BB65: . | BC65: . | BD65: 0 | BE65: . | BF65: . | BG65: . | BH65: . | BI65: 0 | BJ65: . | BK65: . | BL65: . | BM65: . | BN65: 0 | BO65: . | BP65: . | BQ65: . | BR65: . | BS65: 0 | BT65: 14.019 | BU65: 10.975 | BV65: 0 | BW65: 0 | BX65: 24.994 | BY65: 2332 | BZ65: 119 | CA65: 0 | CB65: 0 | CC65: 2451 | CD65: 408.483 | CE65: 0 | CF65: 0 | CG65: 0 | CH65: 408.483
A66: 2022 | B66: CA | C66: 9216 | D66: Imperial Irrigation District | E66: IID | F66: AC | G66: 53.961 | H66: 55.403 | I66: . | J66: . | K66: 109.364 | L66: 6855 | M66: 252 | N66: . | O66: . | P66: 7107 | Q66: . | R66: . | S66: . | T66: . | U66: 0 | V66: . | W66: . | X66: . | Y66: . | Z66: 0 | AA66: 2.824 | AB66: 0.283 | AC66: . | AD66: . | AE66: 3.107 | AF66: 971 | AG66: 90 | AH66: . | AI66: . | AJ66: 1061 | AK66: . | AL66: . | AM66: . | AN66: . | AO66: 0 | AP66: 0.002 | AQ66: . | AR66: . | AS66: . | AT66: 0.002 | AU66: 1 | AV66: . | AW66: . | AX66: . | AY66: 1 | AZ66: . | BA66: . | BB66: . | BC66: . | BD66: 0 | BE66: . | BF66: 2.13 | BG66: . | BH66: . | BI66: 2.13 | BJ66: . | BK66: 5 | BL66: . | BM66: . | BN66: 5 | BO66: . | BP66: . | BQ66: . | BR66: . | BS66: 0 | BT66: 56.787 | BU66: 57.816 | BV66: 0 | BW66: 0 | BX66: 114.603 | BY66: 7827 | BZ66: 347 | CA66: 0 | CB66: 0 | CC66: 8174 | CD66: 0 | CE66: 0 | CF66: 0 | CG66: 0 | CH66: 0
A67: 2022 | B67: CA | C67: 11124 | D67: City of Lodi - (CA) | E67: CISO | F67: AC | G67: 3.27 | H67: 3.661 | I67: . | J67: . | K67: 6.931 | L67: 648 | M67: 61 | N67: . | O67: . | P67: 709 | Q67: . | R67: . | S67: . | T67: . | U67: . | V67: . | W67: . | X67: . | Y67: . | Z67: . | AA67: . | AB67: . | AC67: . | AD67: . | AE67: . | AF67: . | AG67: . | AH67: . | AI67: . | AJ67: . | AK67: . | AL67: . | AM67: . | AN67: . | AO67: 0 | AP67: . | AQ67: . | AR67: . | AS67: . | AT67: 0 | AU67: . | AV67: . | AW67: . | AX67: . | AY67: 0 | AZ67: . | BA67: . | BB67: . | BC67: . | BD67: 0 | BE67: . | BF67: . | BG67: . | BH67: . | BI67: 0 | BJ67: . | BK67: . | BL67: . | BM67: . | BN67: 0 | BO67: . | BP67: . | BQ67: . | BR67: . | BS67: 0 | BT67: 3.27 | BU67: 3.661 | BV67: 0 | BW67: 0 | BX67: 6.931 | BY67: 648 | BZ67: 61 | CA67: 0 | CB67: 0 | CC67: 709 | CD67: 0 | CE67: 0 | CF67: 0 | CG67: 0 | CH67: 0
A68: 2022 | B68: CA | C68: 11208 | D68: Los Angeles Department of Water & Power | E68: LDWP | F68: AC | G68: 408.943 | H68: 128.438 | I68: . | J68: . | K68: 537.381 | L68: 68832 | M68: 1626 | N68: . | O68: . | P68: 70458 | Q68: 24.96 | R68: 0.538 | S68: . | T68: . | U68: 25.498 | V68: 3159 | W68: 7 | X68: . | Y68: . | Z68: 3166 | AA68: . | AB68: . | AC68: . | AD68: . | AE68: 0 | AF68: . | AG68: . | AH68: . | AI68: . | AJ68: 0 | AK68: 15687.604 | AL68: 2000.422 | AM68: . | AN68: . | AO68: 17688.026 | AP68: . | AQ68: . | AR68: . | AS68: . | AT68: 0 | AU68: . | AV68: . | AW68: . | AX68: . | AY68: 0 | AZ68: . | BA68: . | BB68: . | BC68: . | BD68: 0 | BE68: . | BF68: . | BG68: . | BH68: . | BI68: 0 | BJ68: . | BK68: . | BL68: . | BM68: . | BN68: 0 | BO68: . | BP68: . | BQ68: . | BR68: . | BS68: 0 | BT68: 408.943 | BU68: 128.438 | BV68: 0 | BW68: 0 | BX68: 537.381 | BY68: 68832 | BZ68: 1626 | CA68: 0 | CB68: 0 | CC68: 70458 | CD68: 15687.604 | CE68: 2000.422 | CF68: 0 | CG68: 0 | CH68: 17688.026
A69: 2022 | B69: CA | C69: 12312 | D69: Merced Irrigation District | E69: CISO | F69: AC | G69: 10.599 | H69: 8.807 | I69: 0.114 | J69: . | K69: 19.52 | L69: 2622 | M69: 55 | N69: 2 | O69: . | P69: 2679 | Q69: . | R69: . | S69: . | T69: . | U69: . | V69: . | W69: . | X69: . | Y69: . | Z69: . | AA69: . | AB69: . | AC69: . | AD69: . | AE69: . | AF69: . | AG69: . | AH69: . | AI69: . | AJ69: . | AK69: . | AL69: . | AM69: . | AN69: . | AO69: 0 | AP69: . | AQ69: . | AR69: . | AS69: . | AT69: 0 | AU69: . | AV69: . | AW69: . | AX69: . | AY69: 0 | AZ69: . | BA69: . | BB69: . | BC69: . | BD69: 0 | BE69: . | BF69: . | BG69: . | BH69: . | BI69: 0 | BJ69: . | BK69: . | BL69: . | BM69: . | BN69: 0 | BO69: . | BP69: . | BQ69: . | BR69: . | BS69: 0 | BT69: 10.599 | BU69: 8.807 | BV69: 0.114 | BW69: 0 | BX69: 19.52 | BY69: 2622 | BZ69: 55 | CA69: 2 | CB69: 0 | CC69: 2679 | CD69: 0 | CE69: 0 | CF69: 0 | CG69: 0 | CH69: 0
A70: 2022 | B70: CA | C70: 12745 | D70: Modesto Irrigation District | E70: BANC | F70: AC | G70: 44.822 | H70: 14.813 | I70: 9.906 | J70: . | K70: 69.541 | L70: 9243 | M70: 159 | N70: 54 | O70: . | P70: 9456 | Q70: 2.199 | R70: 0 | S70: 1.512 | T70: . | U70: 3.711 | V70: 289 | W70: 0 | X70: 2 | Y70: . | Z70: 291 | AA70: . | AB70: . | AC70: . | AD70: . | AE70: 0 | AF70: . | AG70: . | AH70: . | AI70: . | AJ70: 0 | AK70: . | AL70: . | AM70: . | AN70: . | AO70: 0 | AP70: . | AQ70: . | AR70: . | AS70: . | AT70: 0 | AU70: . | AV70: . | AW70: . | AX70: . | AY70: 0 | AZ70: . | BA70: . | BB70: . | BC70: . | BD70: 0 | BE70: . | BF70: . | BG70: . | BH70: . | BI70: 0 | BJ70: . | BK70: . | BL70: . | BM70: . | BN70: 0 | BO70: . | BP70: . | BQ70: . | BR70: . | BS70: 0 | BT70: 44.822 | BU70: 14.813 | BV70: 9.906 | BW70: 0 | BX70: 69.541 | BY70: 9243 | BZ70: 159 | CA70: 54 | CB70: 0 | CC70: 9456 | CD70: 0 | CE70: 0 | CF70: 0 | CG70: 0 | CH70: 0
A71: 2022 | B71: CA | C71: 14328 | D71: Pacific Gas & Electric Co. | E71: CISO | F71: AC | G71: 4133.834 | H71: 1332.639 | I71: 1186.608 | J71: 0 | K71: 6653.081 | L71: 683640 | M71: 14331 | N71: 4909 | O71: 0 | P71: 702880 | Q71: 355.492 | R71: 20.899 | S71: 53.402 | T71: 0 | U71: 429.793 | V71: 49824 | W71: 243 | X71: 144 | Y71: 0 | Z71: 50211 | AA71: 21.428 | AB71: 33.711 | AC71: 0.138 | AD71: 0 | AE71: 55.277 | AF71: 5657 | AG71: 2384 | AH71: 4 | AI71: 0 | AJ71: 8045 | AK71: 0 | AL71: 0 | AM71: 0 | AN71: 0 | AO71: 0 | AP71: 0.92 | AQ71: 0.623 | AR71: 24.048 | AS71: 0 | AT71: 25.591 | AU71: 167 | AV71: 36 | AW71: 43 | AX71: 0 | AY71: 246 | AZ71: 0 | BA71: 0 | BB71: 0 | BC71: 0 | BD71: 0 | BE71: 0.528 | BF71: 37.16 | BG71: 191.831 | BH71: 0 | BI71: 229.519 | BJ71: 26 | BK71: 69 | BL71: 254 | BM71: 0 | BN71: 349 | BO71: 0 | BP71: 0 | BQ71: 0 | BR71: 0 | BS71: 0 | BT71: 4156.71 | BU71: 1404.133 | BV71: 1402.625 | BW71: 0 | BX71: 6963.468 | BY71: 689490 | BZ71: 16820 | CA71: 5210 | CB71: 0 | CC71: 711520 | CD71: 0 | CE71: 0 | CF71: 0 | CG71: 0 | CH71: 0
A72: 2022 | B72: CA | C72: 14354 | D72: PacifiCorp | E72: PACW | F72: DC | G72: 4.9 | H72: 3.844 | I72: 2.964 | J72: 0 | K72: 11.708 | L72: 608 | M72: 63 | N72: 21 | O72: 0 | P72: 692 | Q72: 0.127 | R72: 0.03 | S72: 0 | T72: 0 | U72: 0.157 | V72: 18 | W72: 1 | X72: 0 | Y72: 0 | Z72: 19 | AA72: . | AB72: . | AC72: . | AD72: . | AE72: 0 | AF72: . | AG72: . | AH72: . | AI72: . | AJ72: 0 | AK72: . | AL72: . | AM72: . | AN72: . | AO72: 0 | AP72: 0.001 | AQ72: 0.005 | AR72: 0 | AS72: 0 | AT72: 0.006 | AU72: 1 | AV72: 2 | AW72: 0 | AX72: 0 | AY72: 3 | AZ72: . | BA72: . | BB72: . | BC72: . | BD72: 0 | BE72: 0.011 | BF72: 0.066 | BG72: 0 | BH72: 0 | BI72: 0.077 | BJ72: 2 | BK72: 1 | BL72: 0 | BM72: 0 | BN72: 3 | BO72: . | BP72: . | BQ72: . | BR72: . | BS72: 0 | BT72: 4.912 | BU72: 3.915 | BV72: 2.964 | BW72: 0 | BX72: 11.791 | BY72: 611 | BZ72: 66 | CA72: 21 | CB72: 0 | CC72: 698 | CD72: 0 | CE72: 0 | CF72: 0 | CG72: 0 | CH72: 0
A73: 2022 | B73: CA | C73: 14401 | D73: City of Palo Alto - (CA) | E73: CISO | F73: AC | G73: 5.4 | H73: 10.7 | I73: . | J73: . | K73: 16.1 | L73: 1173 | M73: 100 | N73: . | O73: . | P73: 1273 | Q73: 0.941 | R73: . | S73: . | T73: . | U73: 0.941 | V73: 88 | W73: . | X73: . | Y73: . | Z73: 88 | AA73: . | AB73: . | AC73: . | AD73: . | AE73: 0 | AF73: . | AG73: . | AH73: . | AI73: . | AJ73: 0 | AK73: 85 | AL73: 4292 | AM73: . | AN73: . | AO73: 4377 | AP73: . | AQ73: 0.004 | AR73: . | AS73: . | AT73: 0.004 | AU73: . | AV73: 1 | AW73: . | AX73: . | AY73: 1 | AZ73: . | BA73: . | BB73: . | BC73: . | BD73: 0 | BE73: . | BF73: . | BG73: . | BH73: . | BI73: 0 | BJ73: . | BK73: . | BL73: . | BM73: . | BN73: 0 | BO73: . | BP73: . | BQ73: . | BR73: . | BS73: 0 | BT73: 5.4 | BU73: 10.704 | BV73: 0 | BW73: 0 | BX73: 16.104 | BY73: 1173 | BZ73: 101 | CA73: 0 | CB73: 0 | CC73: 1274 | CD73: 85 | CE73: 4292 | CF73: 0 | CG73: 0 | CH73: 4377
A74: 2022 | B74: CA | C74: 14534 | D74: City of Pasadena - (CA) | E74: CISO | F74: AC | G74: 12.862 | H74: 8.95 | I74: . | J74: . | K74: 21.812 | L74: 2270 | M74: 100 | N74: . | O74: . | P74: 2370 | Q74: . | R74: . | S74: . | T74: . | U74: . | V74: . | W74: . | X74: . | Y74: . | Z74: . | AA74: . | AB74: . | AC74: . | AD74: . | AE74: . | AF74: . | AG74: . | AH74: . | AI74: . | AJ74: . | AK74: . | AL74: . | AM74: . | AN74: . | AO74: 0 | AP74: . | AQ74: . | AR74: . | AS74: . | AT74: 0 | AU74: . | AV74: . | AW74: . | AX74: . | AY74: 0 | AZ74: . | BA74: . | BB74: . | BC74: . | BD74: 0 | BE74: . | BF74: . | BG74: . | BH74: . | BI74: 0 | BJ74: . | BK74: . | BL74: . | BM74: . | BN74: 0 | BO74: . | BP74: . | BQ74: . | BR74: . | BS74: 0 | BT74: 12.862 | BU74: 8.95 | BV74: 0 | BW74: 0 | BX74: 21.812 | BY74: 2270 | BZ74: 100 | CA74: 0 | CB74: 0 | CC74: 2370 | CD74: 0 | CE74: 0 | CF74: 0 | CG74: 0 | CH74: 0
A75: 2022 | B75: CA | C75: 15783 | D75: City of Redding - (CA) | E75: BANC | F75: DC | G75: 12.96 | H75: 6.459 | I75: . | J75: . | K75: 19.419 | L75: 1745 | M75: 98 | N75: . | O75: . | P75: 1843 | Q75: . | R75: . | S75: . | T75: . | U75: . | V75: . | W75: . | X75: . | Y75: . | Z75: . | AA75: . | AB75: . | AC75: . | AD75: . | AE75: . | AF75: . | AG75: . | AH75: . | AI75: . | AJ75: . | AK75: . | AL75: . | AM75: . | AN75: . | AO75: 0 | AP75: . | AQ75: . | AR75: . | AS75: . | AT75: 0 | AU75: . | AV75: . | AW75: . | AX75: . | AY75: 0 | AZ75: . | BA75: . | BB75: . | BC75: . | BD75: 0 | BE75: . | BF75: . | BG75: . | BH75: . | BI75: 0 | BJ75: . | BK75: . | BL75: . | BM75: . | BN75: 0 | BO75: . | BP75: . | BQ75: . | BR75: . | BS75: 0 | BT75: 12.96 | BU75: 6.459 | BV75: 0 | BW75: 0 | BX75: 19.419 | BY75: 1745 | BZ75: 98 | CA75: 0 | CB75: 0 | CC75: 1843 | CD75: 0 | CE75: 0 | CF75: 0 | CG75: 0 | CH75: 0
A76: 2022 | B76: CA | C76: 16088 | D76: City of Riverside - (CA) | E76: CISO | F76: DC | G76: 35.12 | H76: 22.08 | I76: . | J76: . | K76: 57.2 | L76: 5801 | M76: 218 | N76: . | O76: . | P76: 6019 | Q76: . | R76: . | S76: . | T76: . | U76: . | V76: . | W76: . | X76: . | Y76: . | Z76: . | AA76: . | AB76: . | AC76: . | AD76: . | AE76: . | AF76: . | AG76: . | AH76: . | AI76: . | AJ76: . | AK76: 1420 | AL76: . | AM76: . | AN76: . | AO76: 1420 | AP76: . | AQ76: . | AR76: . | AS76: . | AT76: 0 | AU76: . | AV76: . | AW76: . | AX76: . | AY76: 0 | AZ76: . | BA76: . | BB76: . | BC76: . | BD76: 0 | BE76: . | BF76: . | BG76: . | BH76: . | BI76: 0 | BJ76: . | BK76: . | BL76: . | BM76: . | BN76: 0 | BO76: . | BP76: . | BQ76: . | BR76: . | BS76: 0 | BT76: 35.12 | BU76: 22.08 | BV76: 0 | BW76: 0 | BX76: 57.2 | BY76: 5801 | BZ76: 218 | CA76: 0 | CB76: 0 | CC76: 6019 | CD76: 1420 | CE76: 0 | CF76: 0 | CG76: 0 | CH76: 1420
A77: 2022 | B77: CA | C77: 16295 | D77: City of Roseville - (CA) | E77: BANC | F77: AC | G77: 32.702 | H77: 8.001 | I77: 0.415 | J77: . | K77: 41.118 | L77: 8937 | M77: 76 | N77: 1 | O77: . | P77: 9014 | Q77: 0.49 | R77: . | S77: . | T77: . | U77: 0.49 | V77: 62 | W77: . | X77: . | Y77: . | Z77: 62 | AA77: 0.96 | AB77: . | AC77: . | AD77: . | AE77: 0.96 | AF77: 183 | AG77: . | AH77: . | AI77: . | AJ77: 183 | AK77: . | AL77: . | AM77: . | AN77: . | AO77: 0 | AP77: . | AQ77: . | AR77: . | AS77: . | AT77: 0 | AU77: . | AV77: . | AW77: . | AX77: . | AY77: 0 | AZ77: . | BA77: . | BB77: . | BC77: . | BD77: 0 | BE77: . | BF77: . | BG77: . | BH77: . | BI77: 0 | BJ77: . | BK77: . | BL77: . | BM77: . | BN77: 0 | BO77: . | BP77: . | BQ77: . | BR77: . | BS77: 0 | BT77: 33.662 | BU77: 8.001 | BV77: 0.415 | BW77: 0 | BX77: 42.078 | BY77: 9120 | BZ77: 76 | CA77: 1 | CB77: 0 | CC77: 9197 | CD77: 0 | CE77: 0 | CF77: 0 | CG77: 0 | CH77: 0
A78: 2022 | B78: CA | C78: 16534 | D78: Sacramento Municipal Util Dist | E78: BANC | F78: AC | G78: 207.22 | H78: 75.137 | I78: 35.879 | J78: 0 | K78: 318.236 | L78: 45957 | M78: 1067 | N78: 50 | O78: 0 | P78: 47074 | Q78: 7.273 | R78: 0.036 | S78: 0.5 | T78: 0 | U78: 7.809 | V78: 1125 | W78: 1 | X78: 1 | Y78: 0 | Z78: 1127 | AA78: 0.671 | AB78: 0.348 | AC78: 0 | AD78: 0 | AE78: 1.019 | AF78: 560 | AG78: 43 | AH78: 0 | AI78: 0 | AJ78: 603 | AK78: . | AL78: . | AM78: . | AN78: . | AO78: 0 | AP78: 0.002 | AQ78: . | AR78: 0.005 | AS78: . | AT78: 0.007 | AU78: 1 | AV78: . | AW78: 1 | AX78: . | AY78: 2 | AZ78: . | BA78: . | BB78: . | BC78: . | BD78: 0 | BE78: . | BF78: . | BG78: . | BH78: . | BI78: 0 | BJ78: . | BK78: . | BL78: . | BM78: . | BN78: 0 | BO78: . | BP78: . | BQ78: . | BR78: . | BS78: 0 | BT78: 207.893 | BU78: 75.485 | BV78: 35.884 | BW78: 0 | BX78: 319.262 | BY78: 46518 | BZ78: 1110 | CA78: 51 | CB78: 0 | CC78: 47679 | CD78: 0 | CE78: 0 | CF78: 0 | CG78: 0 | CH78: 0
A79: 2022 | B79: CA | C79: 16609 | D79: San Diego Gas & Electric Co | E79: CISO | F79: AC | G79: 1445.29 | H79: 272.95 | I79: 98.91 | J79: 0 | K79: 1817.15 | L79: 263910 | M79: 4991 | N79: 132 | O79: 0 | P79: 269033 | Q79: 67.93 | R79: 13.76 | S79: 3.48 | T79: 0 | U79: 85.17 | V79: 10149 | W79: 138 | X79: 5 | Y79: 0 | Z79: 10292 | AA79: 19.12 | AB79: 5.59 | AC79: 3.26 | AD79: 0 | AE79: 27.97 | AF79: 539 | AG79: 68 | AH79: 5 | AI79: 0 | AJ79: 612 | AK79: 0 | AL79: 0 | AM79: 0 | AN79: 0 | AO79: 0 | AP79: 0.12 | AQ79: 0.01 | AR79: 1 | AS79: 0 | AT79: 1.13 | AU79: 37 | AV79: 3 | AW79: 1 | AX79: 0 | AY79: 41 | AZ79: 0 | BA79: 0 | BB79: 0 | BC79: 0 | BD79: 0 | BE79: 0.03 | BF79: 13.58 | BG79: 15.3 | BH79: 0 | BI79: 28.91 | BJ79: 3 | BK79: 49 | BL79: 21 | BM79: 0 | BN79: 73 | BO79: 0 | BP79: 0 | BQ79: 0 | BR79: 0 | BS79: 0 | BT79: 1464.56 | BU79: 292.13 | BV79: 118.47 | BW79: 0 | BX79: 1875.16 | BY79: 264489 | BZ79: 5111 | CA79: 159 | CB79: 0 | CC79: 269759 | CD79: 0 | CE79: 0 | CF79: 0 | CG79: 0 | CH79: 0
A80: 2022 | B80: CA | C80: 16612 | D80: City & County of San Francisco | E80: CISO | F80: AC | G80: . | H80: . | I80: . | J80: . | K80: 0 | L80: . | M80: . | N80: . | O80: . | P80: 0 | Q80: . | R80: . | S80: . | T80: . | U80: 0 | V80: . | W80: . | X80: . | Y80: . | Z80: 0 | AA80: . | AB80: 0.458 | AC80: . | AD80: . | AE80: 0.458 | AF80: . | AG80: 2 | AH80: . | AI80: . | AJ80: 2 | AK80: . | AL80: . | AM80: . | AN80: . | AO80: 0 | AP80: . | AQ80: . | AR80: . | AS80: . | AT80: 0 | AU80: . | AV80: . | AW80: . | AX80: . | AY80: 0 | AZ80: . | BA80: . | BB80: . | BC80: . | BD80: 0 | BE80: . | BF80: . | BG80: . | BH80: . | BI80: 0 | BJ80: . | BK80: . | BL80: . | BM80: . | BN80: 0 | BO80: . | BP80: . | BQ80: . | BR80: . | BS80: 0 | BT80: 0 | BU80: 0.458 | BV80: 0 | BW80: 0 | BX80: 0.458 | BY80: 0 | BZ80: 2 | CA80: 0 | CB80: 0 | CC80: 2 | CD80: 0 | CE80: 0 | CF80: 0 | CG80: 0 | CH80: 0
A81: 2022 | B81: CA | C81: 16655 | D81: City of Santa Clara - (CA) | E81: CISO | F81: AC | G81: 3.207 | H81: 16.313 | I81: . | J81: . | K81: 19.52 | L81: 826 | M81: 99 | N81: . | O81: . | P81: 925 | Q81: . | R81: . | S81: . | T81: . | U81: . | V81: . | W81: . | X81: . | Y81: . | Z81: . | AA81: . | AB81: . | AC81: . | AD81: . | AE81: . | AF81: . | AG81: . | AH81: . | AI81: . | AJ81: . | AK81: . | AL81: . | AM81: . | AN81: . | AO81: 0 | AP81: . | AQ81: . | AR81: . | AS81: . | AT81: 0 | AU81: . | AV81: . | AW81: . | AX81: . | AY81: 0 | AZ81: . | BA81: . | BB81: . | BC81: . | BD81: 0 | BE81: . | BF81: . | BG81: . | BH81: . | BI81: 0 | BJ81: . | BK81: . | BL81: . | BM81: . | BN81: 0 | BO81: . | BP81: . | BQ81: . | BR81: . | BS81: 0 | BT81: 3.207 | BU81: 16.313 | BV81: 0 | BW81: 0 | BX81: 19.52 | BY81: 826 | BZ81: 99 | CA81: 0 | CB81: 0 | CC81: 925 | CD81: 0 | CE81: 0 | CF81: 0 | CG81: 0 | CH81: 0
A82: 2022 | B82: CA | C82: 17609 | D82: Southern California Edison Co | E82: CISO | F82: AC | G82: 3130.229 | H82: 942.127 | I82: 221.241 | J82: . | K82: 4293.597 | L82: 527676 | M82: 8111 | N82: 477 | O82: . | P82: 536264 | Q82: 201.413 | R82: 54.811 | S82: 3.154 | T82: . | U82: 259.378 | V82: 30080 | W82: 350 | X82: 11 | Y82: . | Z82: 30441 | AA82: 7.572 | AB82: 41.255 | AC82: . | AD82: . | AE82: 48.827 | AF82: 99 | AG82: 1055 | AH82: . | AI82: . | AJ82: 1154 | AK82: . | AL82: . | AM82: . | AN82: . | AO82: 0 | AP82: 1.908 | AQ82: 4.955 | AR82: 8.1 | AS82: . | AT82: 14.963 | AU82: 225 | AV82: 15 | AW82: 7 | AX82: . | AY82: 247 | AZ82: . | BA82: . | BB82: . | BC82: . | BD82: 0 | BE82: 0.694 | BF82: 49.285 | BG82: 33.703 | BH82: . | BI82: 83.682 | BJ82: 75 | BK82: 129 | BL82: 46 | BM82: . | BN82: 250 | BO82: . | BP82: . | BQ82: . | BR82: . | BS82: 0 | BT82: 3140.403 | BU82: 1037.622 | BV82: 263.044 | BW82: 0 | BX82: 4441.069 | BY82: 528075 | BZ82: 9310 | CA82: 530 | CB82: 0 | CC82: 537915 | CD82: 0 | CE82: 0 | CF82: 0 | CG82: 0 | CH82: 0
A83: 2022 | B83: CA | C83: 17612 | D83: Bear Valley Electric Service | E83: CISO | F83: AC | G83: 2.4 | H83: 3.112 | I83: . | J83: . | K83: 5.512 | L83: 516 | M83: 25 | N83: . | O83: . | P83: 541 | Q83: . | R83: . | S83: . | T83: . | U83: . | V83: . | W83: . | X83: . | Y83: . | Z83: . | AA83: . | AB83: . | AC83: . | AD83: . | AE83: . | AF83: . | AG83: . | AH83: . | AI83: . | AJ83: . | AK83: . | AL83: . | AM83: . | AN83: . | AO83: 0 | AP83: 0.069 | AQ83: 0.01 | AR83: . | AS83: . | AT83: 0.079 | AU83: 6 | AV83: 1 | AW83: . | AX83: . | AY83: 7 | AZ83: . | BA83: . | BB83: . | BC83: . | BD83: 0 | BE83: . | BF83: . | BG83: . | BH83: . | BI83: 0 | BJ83: . | BK83: . | BL83: . | BM83: . | BN83: 0 | BO83: . | BP83: . | BQ83: . | BR83: . | BS83: 0 | BT83: 2.469 | BU83: 3.122 | BV83: 0 | BW83: 0 | BX83: 5.591 | BY83: 522 | BZ83: 26 | CA83: 0 | CB83: 0 | CC83: 548 | CD83: 0 | CE83: 0 | CF83: 0 | CG83: 0 | CH83: 0
A84: 2022 | B84: CA | C84: 18260 | D84: Surprise Valley Electrification | E84: PACW | F84: AC | G84: 0.095 | H84: 0.025 | I84: 0 | J84: 0 | K84: 0.12 | L84: 10 | M84: 2 | N84: 0 | O84: 0 | P84: 12 | Q84: . | R84: . | S84: . | T84: . | U84: . | V84: . | W84: . | X84: . | Y84: . | Z84: . | AA84: . | AB84: . | AC84: . | AD84: . | AE84: . | AF84: . | AG84: . | AH84: . | AI84: . | AJ84: . | AK84: . | AL84: . | AM84: . | AN84: . | AO84: 0 | AP84: . | AQ84: . | AR84: . | AS84: . | AT84: 0 | AU84: . | AV84: . | AW84: . | AX84: . | AY84: 0 | AZ84: . | BA84: . | BB84: . | BC84: . | BD84: 0 | BE84: . | BF84: . | BG84: . | BH84: . | BI84: 0 | BJ84: . | BK84: . | BL84: . | BM84: . | BN84: 0 | BO84: . | BP84: . | BQ84: . | BR84: . | BS84: 0 | BT84: 0.095 | BU84: 0.025 | BV84: 0 | BW84: 0 | BX84: 0.12 | BY84: 10 | BZ84: 2 | CA84: 0 | CB84: 0 | CC84: 12 | CD84: 0 | CE84: 0 | CF84: 0 | CG84: 0 | CH84: 0
A85: 2022 | B85: CA | C85: 19281 | D85: Turlock Irrigation District | E85: TIDC | F85: AC | G85: 19.705 | H85: 12.82 | I85: 18.984 | J85: . | K85: 51.509 | L85: 4342 | M85: 89 | N85: 126 | O85: . | P85: 4557 | Q85: . | R85: . | S85: . | T85: . | U85: 0 | V85: . | W85: . | X85: . | Y85: . | Z85: 0 | AA85: 0.063 | AB85: . | AC85: 3.623 | AD85: . | AE85: 3.686 | AF85: 3 | AG85: . | AH85: 10 | AI85: . | AJ85: 13 | AK85: . | AL85: . | AM85: . | AN85: . | AO85: 0 | AP85: . | AQ85: . | AR85: . | AS85: . | AT85: 0 | AU85: . | AV85: . | AW85: . | AX85: . | AY85: 0 | AZ85: . | BA85: . | BB85: . | BC85: . | BD85: 0 | BE85: . | BF85: . | BG85: . | BH85: . | BI85: 0 | BJ85: . | BK85: . | BL85: . | BM85: . | BN85: 0 | BO85: . | BP85: . | BQ85: . | BR85: . | BS85: 0 | BT85: 19.768 | BU85: 12.82 | BV85: 22.607 | BW85: 0 | BX85: 55.195 | BY85: 4345 | BZ85: 89 | CA85: 136 | CB85: 0 | CC85: 4570 | CD85: 0 | CE85: 0 | CF85: 0 | CG85: 0 | CH85: 0
A86: 2022 | B86: CA | C86: 19798 | D86: City of Vernon | E86: CISO | F86: AC | G86: . | H86: 4.463 | I86: . | J86: . | K86: 4.463 | L86: . | M86: 28 | N86: . | O86: . | P86: 28 | Q86: . | R86: . | S86: . | T86: . | U86: . | V86: . | W86: . | X86: . | Y86: . | Z86: . | AA86: . | AB86: . | AC86: . | AD86: . | AE86: . | AF86: . | AG86: . | AH86: . | AI86: . | AJ86: . | AK86: . | AL86: . | AM86: . | AN86: . | AO86: 0 | AP86: . | AQ86: . | AR86: . | AS86: . | AT86: 0 | AU86: . | AV86: . | AW86: . | AX86: . | AY86: 0 | AZ86: . | BA86: . | BB86: . | BC86: . | BD86: 0 | BE86: . | BF86: . | BG86: . | BH86: . | BI86: 0 | BJ86: . | BK86: . | BL86: . | BM86: . | BN86: 0 | BO86: . | BP86: . | BQ86: . | BR86: . | BS86: 0 | BT86: 0 | BU86: 4.463 | BV86: 0 | BW86: 0 | BX86: 4.463 | BY86: 0 | BZ86: 28 | CA86: 0 | CB86: 0 | CC86: 28 | CD86: 0 | CE86: 0 | CF86: 0 | CG86: 0 | CH86: 0
A87: 2022 | B87: CA | C87: 55787 | D87: City of Moreno Valley - (CA) | E87: CISO | F87: DC | G87: 9.376 | H87: 5.018 | I87: 0 | J87: 0 | K87: 14.394 | L87: 2078 | M87: 21 | N87: 0 | O87: 0 | P87: 2099 | Q87: 0.175 | R87: 0 | S87: 0 | T87: 0 | U87: 0.175 | V87: 22 | W87: 0 | X87: 0 | Y87: 0 | Z87: 22 | AA87: 0 | AB87: 0 | AC87: 0 | AD87: 0 | AE87: 0 | AF87: 0 | AG87: 0 | AH87: 0 | AI87: 0 | AJ87: 0 | AK87: 0 | AL87: 0 | AM87: 0 | AN87: 0 | AO87: 0 | AP87: 0 | AQ87: 0 | AR87: 0 | AS87: 0 | AT87: 0 | AU87: 0 | AV87: 0 | AW87: 0 | AX87: 0 | AY87: 0 | AZ87: 0 | BA87: 0 | BB87: 0 | BC87: 0 | BD87: 0 | BE87: 0 | BF87: 0 | BG87: 0 | BH87: 0 | BI87: 0 | BJ87: 0 | BK87: 0 | BL87: 0 | BM87: 0 | BN87: 0 | BO87: 0 | BP87: 0 | BQ87: 0 | BR87: 0 | BS87: 0 | BT87: 9.376 | BU87: 5.018 | BV87: 0 | BW87: 0 | BX87: 14.394 | BY87: 2078 | BZ87: 21 | CA87: 0 | CB87: 0 | CC87: 2099 | CD87: 0 | CE87: 0 | CF87: 0 | CG87: 0 | CH87: 0
A88: 2022 | B88: CA | C88: 57483 | D88: Liberty Utilities | E88: CISO | F88: AC | G88: 3.499 | H88: 0.902 | I88: . | J88: . | K88: 4.401 | L88: 461 | M88: 24 | N88: . | O88: . | P88: 485 | Q88: . | R88: . | S88: . | T88: . | U88: 0 | V88: . | W88: . | X88: . | Y88: . | Z88: 0 | AA88: 0.063 | AB88: 0.014 | AC88: . | AD88: . | AE88: 0.077 | AF88: 54 | AG88: 7 | AH88: . | AI88: . | AJ88: 61 | AK88: . | AL88: . | AM88: . | AN88: . | AO88: 0 | AP88: 0.001 | AQ88: . | AR88: . | AS88: . | AT88: 0.001 | AU88: 1 | AV88: . | AW88: . | AX88: . | AY88: 1 | AZ88: . | BA88: . | BB88: . | BC88: . | BD88: 0 | BE88: . | BF88: . | BG88: . | BH88: . | BI88: 0 | BJ88: . | BK88: . | BL88: . | BM88: . | BN88: 0 | BO88: . | BP88: . | BQ88: . | BR88: . | BS88: 0 | BT88: 3.563 | BU88: 0.916 | BV88: 0 | BW88: 0 | BX88: 4.479 | BY88: 516 | BZ88: 31 | CA88: 0 | CB88: 0 | CC88: 547 | CD88: 0 | CE88: 0 | CF88: 0 | CG88: 0 | CH88: 0
A89: 2022 | B89: CA | C89: 99999 | D89: Adjustment 2022 | E89: BANC | G89: -2.26 | H89: -1.126 | I89: . | J89: . | K89: -3.387 | L89: . | M89: . | N89: . | O89: . | P89: . | Q89: . | R89: . | S89: . | T89: . | U89: . | V89: . | W89: . | X89: . | Y89: . | Z89: . | AA89: . | AB89: . | AC89: . | AD89: . | AE89: . | AF89: . | AG89: . | AH89: . | AI89: . | AJ89: . | AK89: . | AL89: . | AM89: . | AN89: . | AO89: . | AP89: . | AQ89: . | AR89: . | AS89: . | AT89: . | AU89: . | AV89: . | AW89: . | AX89: . | AY89: . | AZ89: . | BA89: . | BB89: . | BC89: . | BD89: . | BE89: . | BF89: . | BG89: . | BH89: . | BI89: . | BJ89: . | BK89: . | BL89: . | BM89: . | BN89: . | BO89: . | BP89: . | BQ89: . | BR89: . | BS89: . | BT89: -2.26 | BU89: -1.126 | BV89: . | BW89: . | BX89: -3.387 | BY89: . | BZ89: . | CA89: . | CB89: . | CC89: . | CD89: . | CE89: . | CF89: . | CG89: . | CH89: .
A90: 2022 | B90: CA | C90: 99999 | D90: Adjustment 2022 | E90: CISO | G90: -12.747 | H90: -8.323 | I90: -0.071 | J90: 0 | K90: -21.14 | L90: . | M90: . | N90: . | O90: . | P90: . | Q90: . | R90: . | S90: . | T90: . | U90: . | V90: . | W90: . | X90: . | Y90: . | Z90: . | AA90: 0 | AB90: 0 | AC90: 0 | AD90: 0 | AE90: 0 | AF90: . | AG90: . | AH90: . | AI90: . | AJ90: . | AK90: . | AL90: . | AM90: . | AN90: . | AO90: . | AP90: . | AQ90: . | AR90: . | AS90: . | AT90: . | AU90: . | AV90: . | AW90: . | AX90: . | AY90: . | AZ90: . | BA90: . | BB90: . | BC90: . | BD90: . | BE90: . | BF90: . | BG90: . | BH90: . | BI90: . | BJ90: . | BK90: . | BL90: . | BM90: . | BN90: . | BO90: . | BP90: . | BQ90: . | BR90: . | BS90: . | BT90: -12.747 | BU90: -8.323 | BV90: -0.071 | BW90: 0 | BX90: -21.14 | BY90: . | BZ90: . | CA90: . | CB90: . | CC90: . | CD90: . | CE90: . | CF90: . | CG90: . | CH90: .
A91: 2022 | B91: CA | C91: 99999 | D91: Adjustment 2022 | E91: PACW | G91: -0.855 | H91: -0.67 | I91: -0.517 | J91: 0 | K91: -2.042 | L91: . | M91: . | N91: . | O91: . | P91: . | Q91: . | R91: . | S91: . | T91: . | U91: . | V91: . | W91: . | X91: . | Y91: . | Z91: . | AA91: . | AB91: . | AC91: . | AD91: . | AE91: 0 | AF91: . | AG91: . | AH91: . | AI91: . | AJ91: . | AK91: . | AL91: . | AM91: . | AN91: . | AO91: . | AP91: . | AQ91: . | AR91: . | AS91: . | AT91: . | AU91: . | AV91: . | AW91: . | AX91: . | AY91: . | AZ91: . | BA91: . | BB91: . | BC91: . | BD91: . | BE91: . | BF91: . | BG91: . | BH91: . | BI91: . | BJ91: . | BK91: . | BL91: . | BM91: . | BN91: . | BO91: . | BP91: . | BQ91: . | BR91: . | BS91: . | BT91: -0.855 | BU91: -0.67 | BV91: -0.517 | BW91: 0 | BX91: -2.042 | BY91: . | BZ91: . | CA91: . | CB91: . | CC91: . | CD91: . | CE91: . | CF91: . | CG91: . | CH91: .
A92: 2022 | B92: CO | C92: 3989 | D92: City of Colorado Springs - (CO) | E92: WACM | F92: AC | G92: 30.735 | H92: 5.301 | I92: . | J92: . | K92: 36.036 | L92: 6704 | M92: 689 | N92: . | O92: . | P92: 7393 | Q92: 1.263 | R92: 0.035 | S92: . | T92: . | U92: 1.298 | V92: 171 | W92: 2 | X92: . | Y92: . | Z92: 173 | AA92: 0.74 | AB92: 3.181 | AC92: . | AD92: . | AE92: 3.921 | AF92: 411 | AG92: 63 | AH92: . | AI92: . | AJ92: 474 | AK92: 0 | AL92: 0 | AM92: . | AN92: . | AO92: 0 | AP92: . | AQ92: 0.006 | AR92: . | AS92: . | AT92: 0.006 | AU92: . | AV92: 1 | AW92: . | AX92: . | AY92: 1 | AZ92: . | BA92: . | BB92: . | BC92: . | BD92: 0 | BE92: . | BF92: . | BG92: . | BH92: . | BI92: 0 | BJ92: . | BK92: . | BL92: . | BM92: . | BN92: 0 | BO92: . | BP92: . | BQ92: . | BR92: . | BS92: 0 | BT92: 31.475 | BU92: 8.488 | BV92: 0 | BW92: 0 | BX92: 39.963 | BY92: 7115 | BZ92: 753 | CA92: 0 | CB92: 0 | CC92: 7868 | CD92: 0 | CE92: 0 | CF92: 0 | CG92: 0 | CH92: 0
A93: 2022 | B93: CO | C93: 5086 | D93: Delta Montrose Electric Assn | E93: WACM | F93: DC | G93: 9.092 | H93: 1.015 | I93: . | J93: . | K93: 10.107 | L93: 1392 | M93: 48 | N93: . | O93: . | P93: 1440 | Q93: . | R93: . | S93: . | T93: . | U93: . | V93: . | W93: . | X93: . | Y93: . | Z93: . | AA93: . | AB93: . | AC93: . | AD93: . | AE93: . | AF93: . | AG93: . | AH93: . | AI93: . | AJ93: . | AK93: . | AL93: . | AM93: . | AN93: . | AO93: 0 | AP93: 0.012 | AQ93: . | AR93: . | AS93: . | AT93: 0.012 | AU93: 2 | AV93: . | AW93: . | AX93: . | AY93: 2 | AZ93: . | BA93: . | BB93: . | BC93: . | BD93: 0 | BE93: 0.015 | BF93: 0.158 | BG93: . | BH93: . | BI93: 0.173 | BJ93: 3 | BK93: 2 | BL93: . | BM93: . | BN93: 5 | BO93: . | BP93: . | BQ93: . | BR93: . | BS93: 0 | BT93: 9.119 | BU93: 1.173 | BV93: 0 | BW93: 0 | BX93: 10.292 | BY93: 1397 | BZ93: 50 | CA93: 0 | CB93: 0 | CC93: 1447 | CD93: 0 | CE93: 0 | CF93: 0 | CG93: 0 | CH93: 0
A94: 2022 | B94: CO | C94: 5862 | D94: Empire Electric Assn, Inc | E94: WACM | F94: AC | G94: 2.444 | H94: 2.622 | I94: 0.047 | J94: 0 | K94: 5.113 | L94: 387 | M94: 91 | N94: 2 | O94: 0 | P94: 480 | Q94: . | R94: . | S94: . | T94: . | U94: 0 | V94: . | W94: . | X94: . | Y94: . | Z94: 0 | AA94: 0.021 | AB94: 0 | AC94: 0 | AD94: 0 | AE94: 0.021 | AF94: 6 | AG94: 0 | AH94: 0 | AI94: 0 | AJ94: 6 | AK94: . | AL94: . | AM94: . | AN94: . | AO94: 0 | AP94: 0 | AQ94: 0 | AR94: 0 | AS94: 0 | AT94: 0 | AU94: 0 | AV94: 0 | AW94: 0 | AX94: 0 | AY94: 0 | AZ94: . | BA94: . | BB94: . | BC94: . | BD94: 0 | BE94: 0 | BF94: 0 | BG94: 0 | BH94: 0 | BI94: 0 | BJ94: 0 | BK94: 0 | BL94: 0 | BM94: 0 | BN94: 0 | BO94: . | BP94: . | BQ94: . | BR94: . | BS94: 0 | BT94: 2.465 | BU94: 2.622 | BV94: 0.047 | BW94: 0 | BX94: 5.134 | BY94: 393 | BZ94: 91 | CA94: 2 | CB94: 0 | CC94: 486 | CD94: 0 | CE94: 0 | CF94: 0 | CG94: 0 | CH94: 0
A95: 2022 | B95: CO | C95: 6604 | D95: City of Fort Collins - (CO) | E95: PSCO | F95: DC | G95: 19.029 | H95: 2.149 | I95: 3.058 | J95: . | K95: 24.236 | L95: 3022 | M95: 72 | N95: 21 | O95: . | P95: 3115 | Q95: 0.887 | R95: 0.065 | S95: . | T95: . | U95: 0.952 | V95: 122 | W95: 2 | X95: . | Y95: . | Z95: 124 | AA95: 0.62 | AB95: . | AC95: . | AD95: . | AE95: 0.62 | AF95: 200 | AG95: . | AH95: . | AI95: . | AJ95: 200 | AK95: . | AL95: . | AM95: . | AN95: . | AO95: 0 | AP95: 0.001 | AQ95: . | AR95: . | AS95: . | AT95: 0.001 | AU95: 1 | AV95: . | AW95: . | AX95: . | AY95: 1 | AZ95: . | BA95: . | BB95: . | BC95: . | BD95: 0 | BE95: . | BF95: . | BG95: 1.976 | BH95: . | BI95: 1.976 | BJ95: . | BK95: . | BL95: 6 | BM95: . | BN95: 6 | BO95: . | BP95: . | BQ95: . | BR95: . | BS95: 0 | BT95: 19.65 | BU95: 2.149 | BV95: 5.034 | BW95: 0 | BX95: 26.833 | BY95: 3223 | BZ95: 72 | CA95: 27 | CB95: 0 | CC95: 3322 | CD95: 0 | CE95: 0 | CF95: 0 | CG95: 0 | CH95: 0
A96: 2022 | B96: CO | C96: 6638 | D96: City of Fountain | E96: PSCO | F96: AC | G96: 4.09 | H96: . | I96: . | J96: . | K96: 4.09 | L96: 645 | M96: . | N96: . | O96: . | P96: 645 | Q96: . | R96: . | S96: . | T96: . | U96: . | V96: . | W96: . | X96: . | Y96: . | Z96: . | AA96: . | AB96: . | AC96: . | AD96: . | AE96: . | AF96: . | AG96: . | AH96: . | AI96: . | AJ96: . | AK96: 2637 | AL96: . | AM96: . | AN96: . | AO96: 2637 | AP96: . | AQ96: . | AR96: . | AS96: . | AT96: 0 | AU96: . | AV96: . | AW96: . | AX96: . | AY96: 0 | AZ96: . | BA96: . | BB96: . | BC96: . | BD96: 0 | BE96: . | BF96: . | BG96: . | BH96: . | BI96: 0 | BJ96: . | BK96: . | BL96: . | BM96: . | BN96: 0 | BO96: . | BP96: . | BQ96: . | BR96: . | BS96: 0 | BT96: 4.09 | BU96: 0 | BV96: 0 | BW96: 0 | BX96: 4.09 | BY96: 645 | BZ96: 0 | CA96: 0 | CB96: 0 | CC96: 645 | CD96: 2637 | CE96: 0 | CF96: 0 | CG96: 0 | CH96: 2637
A97: 2022 | B97: CO | C97: 7563 | D97: Grand Valley Power | E97: PSCO | F97: DC | G97: 5.299 | H97: 1.1 | I97: . | J97: . | K97: 6.399 | L97: 918 | M97: 14 | N97: . | O97: . | P97: 932 | Q97: . | R97: . | S97: . | T97: . | U97: . | V97: . | W97: . | X97: . | Y97: . | Z97: . | AA97: . | AB97: . | AC97: . | AD97: . | AE97: . | AF97: . | AG97: . | AH97: . | AI97: . | AJ97: . | AK97: . | AL97: . | AM97: . | AN97: . | AO97: 0 | AP97: 0.003 | AQ97: . | AR97: . | AS97: . | AT97: 0.003 | AU97: 1 | AV97: . | AW97: . | AX97: . | AY97: 1 | AZ97: . | BA97: . | BB97: . | BC97: . | BD97: 0 | BE97: 0.005 | BF97: . | BG97: . | BH97: . | BI97: 0.005 | BJ97: 2 | BK97: . | BL97: . | BM97: . | BN97: 2 | BO97: . | BP97: . | BQ97: . | BR97: . | BS97: 0 | BT97: 5.307 | BU97: 1.1 | BV97: 0 | BW97: 0 | BX97: 6.407 | BY97: 921 | BZ97: 14 | CA97: 0 | CB97: 0 | CC97: 935 | CD97: 0 | CE97: 0 | CF97: 0 | CG97: 0 | CH97: 0
A98: 2022 | B98: CO | C98: 8570 | D98: Highline Electric Assn | E98: WACM | F98: DC | G98: 0.444 | H98: 0.024 | I98: 0.037 | J98: . | K98: 0.505 | L98: 47 | M98: 1 | N98: 3 | O98: . | P98: 51 | Q98: . | R98: . | S98: . | T98: . | U98: . | V98: . | W98: . | X98: . | Y98: . | Z98: . | AA98: . | AB98: . | AC98: . | AD98: . | AE98: . | AF98: . | AG98: . | AH98: . | AI98: . | AJ98: . | AK98: 329.53 | AL98: 25.8 | AM98: 20.809 | AN98: . | AO98: 376.139 | AP98: 0.026 | AQ98: . | AR98: . | AS98: . | AT98: 0.026 | AU98: 3 | AV98: . | AW98: . | AX98: . | AY98: 3 | AZ98: 4.666 | BA98: . | BB98: . | BC98: . | BD98: 4.666 | BE98: . | BF98: . | BG98: . | BH98: . | BI98: 0 | BJ98: . | BK98: . | BL98: . | BM98: . | BN98: 0 | BO98: . | BP98: . | BQ98: . | BR98: . | BS98: 0 | BT98: 0.47 | BU98: 0.024 | BV98: 0.037 | BW98: 0 | BX98: 0.531 | BY98: 50 | BZ98: 1 | CA98: 3 | CB98: 0 | CC98: 54 | CD98: 334.196 | CE98: 25.8 | CF98: 20.809 | CG98: 0 | CH98: 380.805
A99: 2022 | B99: CO | C99: 8773 | D99: Holy Cross Electric Assn, Inc | E99: PSCO | F99: DC | G99: 18.862 | H99: 3.1 | I99: 0.016 | J99: 0 | K99: 21.978 | L99: 2317 | M99: 167 | N99: 2 | O99: 0 | P99: 2486 | Q99: 1.785 | R99: 0 | S99: 0 | T99: 0 | U99: 1.785 | V99: 86 | W99: 0 | X99: 0 | Y99: 0 | Z99: 86 | AA99: 0 | AB99: 0 | AC99: 0 | AD99: 0 | AE99: 0 | AF99: 0 | AG99: 0 | AH99: 0 | AI99: 0 | AJ99: 0 | AK99: 640 | AL99: 202 | AM99: 0 | AN99: 0 | AO99: 842 | AP99: 0 | AQ99: 0.002 | AR99: 0 | AS99: 0 | AT99: 0.002 | AU99: 0 | AV99: 1 | AW99: 0 | AX99: 0 | AY99: 1 | AZ99: . | BA99: . | BB99: . | BC99: . | BD99: 0 | BE99: 0.032 | BF99: 0.009 | BG99: 0 | BH99: 0 | BI99: 0.041 | BJ99: 6 | BK99: 3 | BL99: 0 | BM99: 0 | BN99: 9 | BO99: 0 | BP99: 0 | BQ99: 0 | BR99: 0 | BS99: 0 | BT99: 18.894 | BU99: 3.111 | BV99: 0.016 | BW99: 0 | BX99: 22.021 | BY99: 2323 | BZ99: 171 | CA99: 2 | CB99: 0 | CC99: 2496 | CD99: 640 | CE99: 202 | CF99: 0 | CG99: 0 | CH99: 842
A100: 2022 | B100: CO | C100: 9336 | D100: CORE Electric Cooperative | E100: PSCO | F100: AC | G100: 41.46 | H100: 0.83 | I100: 0.43 | J100: . | K100: 42.72 | L100: 7308 | M100: 25 | N100: 3 | O100: . | P100: 7336 | Q100: . | R100: . | S100: . | T100: . | U100: . | V100: . | W100: . | X100: . | Y100: . | Z100: . | AA100: . | AB100: . | AC100: . | AD100: . | AE100: . | AF100: . | AG100: . | AH100: . | AI100: . | AJ100: . | AK100: . | AL100: . | AM100: . | AN100: . | AO100: 0 | AP100: 0.03 | AQ100: . | AR100: . | AS100: . | AT100: 0.03 | AU100: 14 | AV100: . | AW100: . | AX100: . | AY100: 14 | AZ100: . | BA100: . | BB100: . | BC100: . | BD100: 0 | BE100: 0.011 | BF100: . | BG100: . | BH100: . | BI100: 0.011 | BJ100: 2 | BK100: . | BL100: . | BM100: . | BN100: 2 | BO100: . | BP100: . | BQ100: . | BR100: . | BS100: 0 | BT100: 41.501 | BU100: 0.83 | BV100: 0.43 | BW100: 0 | BX100: 42.761 | BY100: 7324 | BZ100: 25 | CA100: 3 | CB100: 0 | CC100: 7352 | CD100: 0 | CE100: 0 | CF100: 0 | CG100: 0 | CH100: 0
...

Sheet SFA Awards
A1: Solar for All - EPA award table and program assumptions
A2: STEP 1 of 3. Raw EPA record (tan). Everything downstream is derived from it: SFA Awards -> SFA Multistate Split -> Solar for All -> calcs -> output tabs.
A3: Source: EPA 19 January 2025 snapshot of the Solar for All recipients table (the live page was removed after the program was terminated).
A4: https://19january2025snapshot.epa.gov/greenhouse-gas-reduction-fund/solar-all
A6: PROGRAM ASSUMPTIONS (blue = editable input)
A7: Program capacity deployed or unlocked (MW) | B7: 4000 | C7: EPA press release, 22 April 2024: 'over 4 GW'
A8: Total program grant ($) | B8: 7000000000 | C8: EPA press release, 22 April 2024
A9: National factor (MW per $) | B9: =B7/B8 -> 5.7142857e-07 | C9: 4,000 MW / $7.0B, applied uniformly to every award
A10: Implied grant cost ($/W) | B10: =B8/(B7*1000000) -> 1.75 | C10: grant $ per watt unlocked - NOT the installed cost of solar
A12: EPA Region | B12: Grantee Type | C12: Grantee Name | D12: Geography Served | E12: State | F12: Split key | G12: Category | H12: Award Amount ($) | I12: Allocated capacity (MW)
A13: 1 | B13: State | C13: Executive Office of the State of New Hampshire | D13: NH | E13: NH | G13: Single-state | H13: 43510000 | I13: =H13*$B$9 -> 24.862857
A14: 1 | B14: State | C14: Massachusetts Department of Energy Resources | D14: MA | E14: MA | G14: Single-state | H14: 156120000 | I14: =H14*$B$9 -> 89.211429
A15: 1 | B15: State | C15: Rhode Island Office of Energy Resources | D15: RI | E15: RI | G15: Single-state | H15: 49330000 | I15: =H15*$B$9 -> 28.188571
A16: 1 | B16: State | C16: Connecticut Department of Energy and Environmental Protection | D16: CT | E16: CT | G16: Single-state | H16: 62450000 | I16: =H16*$B$9 -> 35.685714
A17: 1 | B17: State | C17: Maine Governor's Energy Office | D17: ME | E17: ME | G17: Single-state | H17: 62120000 | I17: =H17*$B$9 -> 35.497143
A18: 1 | B18: State | C18: Vermont Department of Public Service | D18: VT | E18: VT | G18: Single-state | H18: 62450000 | I18: =H18*$B$9 -> 35.685714
A19: Multi | B19: Multistate Nonprofit | C19: Inclusive Prosperity Capital, Inc. (Community Power Coalition) | D19: Multistate (~44 states) | F19: Inclusive Prosperity Capital | G19: Multistate/National | H19: 249300000 | I19: =H19*$B$9 -> 142.45714
A20: 2 | B20: State | C20: New Jersey Board of Public Utilities | D20: NJ | E20: NJ | G20: Single-state | H20: 156120000 | I20: =H20*$B$9 -> 89.211429
A21: 2 | B21: State | C21: New York State Energy Research and Development Authority (NYSERDA) | D21: NY | E21: NY | G21: Single-state | H21: 249800000 | I21: =H21*$B$9 -> 142.74286
A22: 2 | B22: State | C22: Puerto Rico Office of Management and Budget | D22: PR | E22: PR | G22: Single-state | H22: 156120000 | I22: =H22*$B$9 -> 89.211429
A23: 2 | B23: State | C23: U.S. Virgin Islands Energy Office | D23: VI | E23: VI | G23: Single-state | H23: 62450000 | I23: =H23*$B$9 -> 35.685714
A24: 3 | B24: State | C24: District of Columbia Government | D24: DC | E24: DC | G24: Single-state | H24: 62450000 | I24: =H24*$B$9 -> 35.685714
A25: 3 | B25: State | C25: Maryland Clean Energy Center | D25: MD | E25: MD | G25: Single-state | H25: 62450000 | I25: =H25*$B$9 -> 35.685714
A26: 3 | B26: State | C26: Pennsylvania Energy Development Authority | D26: PA | E26: PA | G26: Single-state | H26: 156120000 | I26: =H26*$B$9 -> 89.211429
A27: 3 | B27: State | C27: Virginia Department of Energy | D27: VA | E27: VA | G27: Single-state | H27: 156120000 | I27: =H27*$B$9 -> 89.211429
A28: 3 | B28: State | C28: West Virginia Office of Energy | D28: WV | E28: WV | G28: Single-state | H28: 106180000 | I28: =H28*$B$9 -> 60.674286
A29: Multi | B29: Multistate Nonprofit | C29: Groundswell Inc. | D29: Multistate (AL,AR,FL,GA,MS,NC,SC,VA) | F29: Groundswell | G29: Multistate/National | H29: 156120000 | I29: =H29*$B$9 -> 89.211429
A30: 4 | B30: State | C30: Department of Environment & Conservation, Tennessee | D30: TN | E30: TN | G30: Single-state | H30: 156120000 | I30: =H30*$B$9 -> 89.211429
A31: 4 | B31: State | C31: Kentucky Energy and Environment Cabinet | D31: KY | E31: KY | G31: Single-state | H31: 62450000 | I31: =H31*$B$9 -> 35.685714
A32: 4 | B32: State | C32: North Carolina Department of Environmental Quality | D32: NC | E32: NC | G32: Single-state | H32: 156120000 | I32: =H32*$B$9 -> 89.211429
A33: 4 | B33: State | C33: South Carolina Office of Resilience | D33: SC | E33: SC | G33: Single-state | H33: 124440000 | I33: =H33*$B$9 -> 71.108571
A34: 4 | B34: Nonprofit | C34: Hope Enterprise Corporation | D34: MS | E34: MS | G34: Single-state | H34: 62450000 | I34: =H34*$B$9 -> 35.685714
A35: 4 | B35: Nonprofit | C35: Solar and Energy Loan Fund of St. Lucie County (SELF) | D35: FL | E35: FL | G35: Single-state | H35: 156120000 | I35: =H35*$B$9 -> 89.211429
A36: 4 | B36: Nonprofit | C36: The Capital Good Fund | D36: GA | E36: GA | G36: Single-state | H36: 156010000 | I36: =H36*$B$9 -> 89.148571
A37: 5 | B37: State | C37: Illinois Finance Authority | D37: IL | E37: IL | G37: Single-state | H37: 156120000 | I37: =H37*$B$9 -> 89.211429
A38: 5 | B38: State | C38: Minnesota Department of Commerce | D38: MN | E38: MN | G38: Single-state | H38: 62450000 | I38: =H38*$B$9 -> 35.685714
A39: 5 | B39: State | C39: State of Michigan, Dept. of Environment, Great Lakes, and Energy | D39: MI | E39: MI | G39: Single-state | H39: 156120000 | I39: =H39*$B$9 -> 89.211429
A40: 5 | B40: State | C40: State of Ohio Office of Budget and Management | D40: OH | E40: OH | G40: Single-state | H40: 156120000 | I40: =H40*$B$9 -> 89.211429
A41: 5 | B41: State | C41: Wisconsin Economic Development Corporation | D41: WI | E41: WI | G41: Single-state | H41: 62450000 | I41: =H41*$B$9 -> 35.685714
A42: 5 | B42: Nonprofit | C42: Indiana Community Action Association (IN-CAA) | D42: IN | E42: IN | G42: Single-state | H42: 117470000 | I42: =H42*$B$9 -> 67.125714
A43: Multi | B43: Tribal Consortium | C43: Midwest Tribal Energy Resources Association Inc. | D43: Tribal (MN,WI,MI) | F43: MTERA | G43: Multistate/National | H43: 62330000 | I43: =H43*$B$9 -> 35.617143
A44: Multi | B44: Multistate Nonprofit | C44: Growth Opportunity Partners | D44: Multistate (IN,KS,MI,MO,PA,NY,OH,WV) | F44: Growth Opportunity Partners | G44: Multistate/National | H44: 156120000 | I44: =H44*$B$9 -> 89.211429
A45: 6 | B45: State | C45: New Mexico Energy, Minerals & Natural Resources Department | D45: NM | E45: NM | G45: Single-state | H45: 156120000 | I45: =H45*$B$9 -> 89.211429
A46: 6 | B46: State | C46: State of Louisiana, Department of Natural Resources | D46: LA | E46: LA | G46: Single-state | H46: 156120000 | I46: =H46*$B$9 -> 89.211429
A47: 6 | B47: Municipality | C47: Harris County (Texas SFA Coalition) | D47: TX (Statewide) | E47: TX | G47: Single-state | H47: 249700000 | I47: =H47*$B$9 -> 142.68571
A48: 6 | B48: Nonprofit | C48: Hope Enterprise Corporation | D48: AR | E48: AR | G48: Single-state | H48: 93670000 | I48: =H48*$B$9 -> 53.525714
A49: Multi | B49: Multistate Nonprofit | C49: Clean Energy Fund of Texas | D49: Multistate (19 states) | F49: Clean Energy Fund of Texas | G49: Multistate/National | H49: 156120000 | I49: =H49*$B$9 -> 89.211429
A50: 7 | B50: State | C50: Missouri Environmental Improvement and Energy Resources Authority | D50: MO | E50: MO | G50: Single-state | H50: 156120000 | I50: =H50*$B$9 -> 89.211429
A51: 7 | B51: Nonprofit | C51: Center for Rural Affairs | D51: NE | E51: NE | G51: Single-state | H51: 62450000 | I51: =H51*$B$9 -> 35.685714
A52: 8 | B52: State | C52: Colorado Energy Office | D52: CO | E52: CO | G52: Single-state | H52: 156120000 | I52: =H52*$B$9 -> 89.211429
A53: 8 | B53: State | C53: Utah Office of Energy Development | D53: UT | E53: UT | G53: Single-state | H53: 62450000 | I53: =H53*$B$9 -> 35.685714
A54: 8 | B54: Nonprofit | C54: Bonneville Environmental Foundation | D54: MT | E54: MT | G54: Single-state | H54: 43700000 | I54: =H54*$B$9 -> 24.971429
A55: 8 | B55: Nonprofit | C55: Bonneville Environmental Foundation | D55: WY | E55: WY | G55: Single-state | H55: 30260000 | I55: =H55*$B$9 -> 17.291429
A56: 8 | B56: Nonprofit | C56: Coalition for Green Capital | D56: ND | E56: ND | G56: Single-state | H56: 62450000 | I56: =H56*$B$9 -> 35.685714
A57: 8 | B57: Nonprofit | C57: Coalition for Green Capital | D57: SD | E57: SD | G57: Single-state | H57: 62450000 | I57: =H57*$B$9 -> 35.685714
A58: Multi | B58: Tribal Nonprofit | C58: Oweesta Corporation | D58: Tribal Lands Nationwide | F58: Oweesta | G58: Multistate/National | H58: 156120000 | I58: =H58*$B$9 -> 89.211429
A59: Multi | B59: Tribe | C59: Three Affiliated Tribes (MHA Nation) | D59: Tribal (ND,SD,MT,WY,WI) | F59: Three Affiliated Tribes (MHA) | G59: Multistate/National | H59: 135580000 | I59: =H59*$B$9 -> 77.474286
A60: 9 | B60: State | C60: Executive Office of the State of Arizona | D60: AZ | E60: AZ | G60: Single-state | H60: 156120000 | I60: =H60*$B$9 -> 89.211429
A61: 9 | B61: State | C61: Government of Guam - Department of Administration | D61: GU | E61: GU | G61: Single-state | H61: 62450000 | I61: =H61*$B$9 -> 35.685714
A62: 9 | B62: State | C62: Hawai'i Green Infrastructure Authority | D62: HI | E62: HI | G62: Single-state | H62: 62450000 | I62: =H62*$B$9 -> 35.685714
A63: 9 | B63: State | C63: California Infrastructure Economic Development Bank (IBank) | D63: CA | E63: CA | G63: Single-state | H63: 249800000 | I63: =H63*$B$9 -> 142.74286
A64: 9 | B64: Nonprofit | C64: Nevada Clean Energy Fund | D64: NV | E64: NV | G64: Single-state | H64: 156120000 | I64: =H64*$B$9 -> 89.211429
A65: 9 | B65: Tribe | C65: Hopi Utilities Corporation | D65: Hopi Reservation (AZ) | E65: AZ | G65: Tribal (in-state) | H65: 25120000 | I65: =H65*$B$9 -> 14.354286
A66: Multi | B66: Tribal Nonprofit | C66: GRID Alternatives (WIN-SFA) | D66: Tribal Nationwide (AZ,CO,NV,NM,UT priority) | F66: GRID WIN-SFA | G66: Multistate/National | H66: 62450000 | I66: =H66*$B$9 -> 35.685714
A67: Multi | B67: Multistate Nonprofit | C67: GRID Alternatives (SANAH) | D67: Nationwide | F67: GRID SANAH | G67: Multistate/National | H67: 249800000 | I67: =H67*$B$9 -> 142.74286
A68: 10 | B68: State | C68: Alaska Energy Authority | D68: AK | E68: AK | G68: Single-state | H68: 62450000 | I68: =H68*$B$9 -> 35.685714
A69: 10 | B69: State | C69: Oregon Department of Energy | D69: OR | E69: OR | G69: Single-state | H69: 86600000 | I69: =H69*$B$9 -> 49.485714
A70: 10 | B70: State | C70: Washington State Department of Commerce | D70: WA | E70: WA | G70: Single-state | H70: 156120000 | I70: =H70*$B$9 -> 89.211429
A71: 10 | B71: Nonprofit | C71: Bonneville Environmental Foundation | D71: ID | E71: ID | G71: Single-state | H71: 56540000 | I71: =H71*$B$9 -> 32.308571
A72: 10 | B72: Tribal Consortium | C72: Tanana Chiefs Conference | D72: Tribal Lands in AK | E72: AK | G72: Tribal (in-state) | H72: 62450000 | I72: =H72*$B$9 -> 35.685714
G73: TOTAL | H73: =SUM(H13:H72) -> 7000000000 | I73: =SUM(I13:I72) -> 4000
G74: Check | H74: =IF(ROUND(H73,2)=$B$8,"OK","MISMATCH") -> OK | I74: =IF(ROUND(I73,6)=$B$7,"OK","MISMATCH") -> OK
A76: Note: one transcription fix vs. the EPA table - North Carolina appeared as '$156,120,00' (missing a trailing zero); corrected to $156,120,000, after which all 60 awards sum to exactly $7.0B.
A77: 'State' is filled for single-state awards and for the two in-state tribal awards (Hopi Utilities in AZ, Tanana Chiefs in AK). It is blank for the 9 multistate / tribal-nationwide awards, which are apportioned on the next tab via 'Split key'.

Sheet SFA Multistate Split
A1: Solar for All - apportioning the 9 multistate, tribal and nationwide awards
A2: STEP 2 of 3. These awards serve more than one state, so each is split across the jurisdictions it serves in proportion to 2020 Census resident population.
A3: Member-state lists (column A/B of the lower table) and populations (right-hand table) are the only raw entries here; every dollar and MW figure is a formula.
H4: Source: U.S. Census Bureau, 2020 Census resident population.
A5: THE NINE AWARDS | H5: STATE POPULATION WEIGHTS
A6: Grantee (split key) | B6: Award ($) | C6: # jurisdictions | D6: Geography basis | H6: State | I6: Name | J6: Population (2020 Census)
A7: Inclusive Prosperity Capital | B7: =SUMIFS('SFA Awards'!$H$13:$H$72,'SFA Awards'!$F$13:$F$72,$A7) -> 249300000 | C7: =COUNTIFS($A$25:$A$225,$A7) -> 52 | D7: Nationwide proxy: 50 states + DC + PR | H7: AK | I7: Alaska | J7: 733391
A8: Groundswell | B8: =SUMIFS('SFA Awards'!$H$13:$H$72,'SFA Awards'!$F$13:$F$72,$A8) -> 156120000 | C8: =COUNTIFS($A$25:$A$225,$A8) -> 8 | D8: AL, AR, FL, GA, MS, NC, SC, VA (per EPA award summary, Allocation tab) | H8: AL | I8: Alabama | J8: 5024279
A9: MTERA | B9: =SUMIFS('SFA Awards'!$H$13:$H$72,'SFA Awards'!$F$13:$F$72,$A9) -> 62330000 | C9: =COUNTIFS($A$25:$A$225,$A9) -> 3 | D9: Tribal: MN, WI, MI (per EPA award summary, Allocation tab) | H9: AR | I9: Arkansas | J9: 3011524
A10: Growth Opportunity Partners | B10: =SUMIFS('SFA Awards'!$H$13:$H$72,'SFA Awards'!$F$13:$F$72,$A10) -> 156120000 | C10: =COUNTIFS($A$25:$A$225,$A10) -> 8 | D10: IN, KS, MI, MO, PA, NY, OH, WV (per EPA award summary, Allocation tab) | H10: AZ | I10: Arizona | J10: 7151502
A11: Clean Energy Fund of Texas | B11: =SUMIFS('SFA Awards'!$H$13:$H$72,'SFA Awards'!$F$13:$F$72,$A11) -> 156120000 | C11: =COUNTIFS($A$25:$A$225,$A11) -> 19 | D11: CHARGE program: 18 states + DC (AL, AR, DE, FL, GA, KY, LA, MD, MS, NM, NC, OK, PA, SC, TN, TX, VA, WV, DC) | H11: CA | I11: California | J11: 39538223
A12: Oweesta | B12: =SUMIFS('SFA Awards'!$H$13:$H$72,'SFA Awards'!$F$13:$F$72,$A12) -> 156120000 | C12: =COUNTIFS($A$25:$A$225,$A12) -> 50 | D12: Tribal lands nationwide: all 50 states | H12: CO | I12: Colorado | J12: 5773714
A13: Three Affiliated Tribes (MHA) | B13: =SUMIFS('SFA Awards'!$H$13:$H$72,'SFA Awards'!$F$13:$F$72,$A13) -> 135580000 | C13: =COUNTIFS($A$25:$A$225,$A13) -> 5 | D13: Tribal: ND, SD, MT, WY, WI (per EPA award summary, Allocation tab) | H13: CT | I13: Connecticut | J13: 3605944
A14: GRID WIN-SFA | B14: =SUMIFS('SFA Awards'!$H$13:$H$72,'SFA Awards'!$F$13:$F$72,$A14) -> 62450000 | C14: =COUNTIFS($A$25:$A$225,$A14) -> 5 | D14: Tribal, priority states: AZ, CO, NV, NM, UT (per EPA award summary, Allocation tab) | H14: DC | I14: District of Columbia | J14: 689545
A15: GRID SANAH | B15: =SUMIFS('SFA Awards'!$H$13:$H$72,'SFA Awards'!$F$13:$F$72,$A15) -> 249800000 | C15: =COUNTIFS($A$25:$A$225,$A15) -> 51 | D15: Nationwide affordable housing: 50 states + DC | H15: DE | I15: Delaware | J15: 989948
A16: TOTAL | B16: =SUM(B7:B15) -> 1383940000 | C16: =SUM(C7:C15) -> 201 | H16: FL | I16: Florida | J16: 21538187
H17: GA | I17: Georgia | J17: 10711908
H18: HI | I18: Hawaii | J18: 1455271
H19: IA | I19: Iowa | J19: 3190369
H20: ID | I20: Idaho | J20: 1839106
H21: IL | I21: Illinois | J21: 12812508
H22: IN | I22: Indiana | J22: 6785528
A23: AWARD x JURISDICTION SPLIT | H23: KS | I23: Kansas | J23: 2937880
A24: Grantee (split key) | B24: State | C24: Population | D24: Share of award | E24: Allocated ($) | F24: Allocated (MW) | H24: KY | I24: Kentucky | J24: 4505836
A25: Inclusive Prosperity Capital | B25: AK | C25: =SUMIFS($J$7:$J$58,$H$7:$H$58,$B25) -> 733391 | D25: =C25/SUMIFS($C$25:$C$225,$A$25:$A$225,$A25) -> 0.002190959 | E25: =D25*SUMIFS($B$7:$B$15,$A$7:$A$15,$A25) -> 546206.08 | F25: =E25*'SFA Awards'!$B$9 -> 0.31211776 | H25: LA | I25: Louisiana | J25: 4657757
A26: Inclusive Prosperity Capital | B26: AL | C26: =SUMIFS($J$7:$J$58,$H$7:$H$58,$B26) -> 5024279 | D26: =C26/SUMIFS($C$25:$C$225,$A$25:$A$225,$A26) -> 0.015009714 | E26: =D26*SUMIFS($B$7:$B$15,$A$7:$A$15,$A26) -> 3741921.7 | F26: =E26*'SFA Awards'!$B$9 -> 2.138241 | H26: MA | I26: Massachusetts | J26: 7029917
A27: Inclusive Prosperity Capital | B27: AR | C27: =SUMIFS($J$7:$J$58,$H$7:$H$58,$B27) -> 3011524 | D27: =C27/SUMIFS($C$25:$C$225,$A$25:$A$225,$A27) -> 0.0089967365 | E27: =D27*SUMIFS($B$7:$B$15,$A$7:$A$15,$A27) -> 2242886.4 | F27: =E27*'SFA Awards'!$B$9 -> 1.2816494 | H27: MD | I27: Maryland | J27: 6177224
A28: Inclusive Prosperity Capital | B28: AZ | C28: =SUMIFS($J$7:$J$58,$H$7:$H$58,$B28) -> 7151502 | D28: =C28/SUMIFS($C$25:$C$225,$A$25:$A$225,$A28) -> 0.021364658 | E28: =D28*SUMIFS($B$7:$B$15,$A$7:$A$15,$A28) -> 5326209.2 | F28: =E28*'SFA Awards'!$B$9 -> 3.0435481 | H28: ME | I28: Maine | J28: 1362359
A29: Inclusive Prosperity Capital | B29: CA | C29: =SUMIFS($J$7:$J$58,$H$7:$H$58,$B29) -> 39538223 | D29: =C29/SUMIFS($C$25:$C$225,$A$25:$A$225,$A29) -> 0.11811793 | E29: =D29*SUMIFS($B$7:$B$15,$A$7:$A$15,$A29) -> 29446799 | F29: =E29*'SFA Awards'!$B$9 -> 16.826743 | H29: MI | I29: Michigan | J29: 10077331
A30: Inclusive Prosperity Capital | B30: CO | C30: =SUMIFS($J$7:$J$58,$H$7:$H$58,$B30) -> 5773714 | D30: =C30/SUMIFS($C$25:$C$225,$A$25:$A$225,$A30) -> 0.017248604 | E30: =D30*SUMIFS($B$7:$B$15,$A$7:$A$15,$A30) -> 4300076.9 | F30: =E30*'SFA Awards'!$B$9 -> 2.4571868 | H30: MN | I30: Minnesota | J30: 5706494
A31: Inclusive Prosperity Capital | B31: CT | C31: =SUMIFS($J$7:$J$58,$H$7:$H$58,$B31) -> 3605944 | D31: =C31/SUMIFS($C$25:$C$225,$A$25:$A$225,$A31) -> 0.010772529 | E31: =D31*SUMIFS($B$7:$B$15,$A$7:$A$15,$A31) -> 2685591.4 | F31: =E31*'SFA Awards'!$B$9 -> 1.5346236 | H31: MO | I31: Missouri | J31: 6154913
A32: Inclusive Prosperity Capital | B32: DC | C32: =SUMIFS($J$7:$J$58,$H$7:$H$58,$B32) -> 689545 | D32: =C32/SUMIFS($C$25:$C$225,$A$25:$A$225,$A32) -> 0.0020599719 | E32: =D32*SUMIFS($B$7:$B$15,$A$7:$A$15,$A32) -> 513550.98 | F32: =E32*'SFA Awards'!$B$9 -> 0.29345771 | H32: MS | I32: Mississippi | J32: 2961279
A33: Inclusive Prosperity Capital | B33: DE | C33: =SUMIFS($J$7:$J$58,$H$7:$H$58,$B33) -> 989948 | D33: =C33/SUMIFS($C$25:$C$225,$A$25:$A$225,$A33) -> 0.0029574067 | E33: =D33*SUMIFS($B$7:$B$15,$A$7:$A$15,$A33) -> 737281.5 | F33: =E33*'SFA Awards'!$B$9 -> 0.42130371 | H33: MT | I33: Montana | J33: 1084225
A34: Inclusive Prosperity Capital | B34: FL | C34: =SUMIFS($J$7:$J$58,$H$7:$H$58,$B34) -> 21538187 | D34: =C34/SUMIFS($C$25:$C$225,$A$25:$A$225,$A34) -> 0.064343965 | E34: =D34*SUMIFS($B$7:$B$15,$A$7:$A$15,$A34) -> 16040950 | F34: =E34*'SFA Awards'!$B$9 -> 9.1662574 | H34: NC | I34: North Carolina | J34: 10439388
A35: Inclusive Prosperity Capital | B35: GA | C35: =SUMIFS($J$7:$J$58,$H$7:$H$58,$B35) -> 10711908 | D35: =C35/SUMIFS($C$25:$C$225,$A$25:$A$225,$A35) -> 0.032001144 | E35: =D35*SUMIFS($B$7:$B$15,$A$7:$A$15,$A35) -> 7977885.3 | F35: =E35*'SFA Awards'!$B$9 -> 4.5587916 | H35: ND | I35: North Dakota | J35: 779094
A36: Inclusive Prosperity Capital | B36: HI | C36: =SUMIFS($J$7:$J$58,$H$7:$H$58,$B36) -> 1455271 | D36: =C36/SUMIFS($C$25:$C$225,$A$25:$A$225,$A36) -> 0.0043475296 | E36: =D36*SUMIFS($B$7:$B$15,$A$7:$A$15,$A36) -> 1083839.1 | F36: =E36*'SFA Awards'!$B$9 -> 0.61933665 | H36: NE | I36: Nebraska | J36: 1961504
... A58: Inclusive Prosperity Capital | B58: NV | C58: =SUMIFS($J$7:$J$58,$H$7:$H$58,$B58) -> 3104614 | D58: =C58/SUMIFS($C$25:$C$225,$A$25:$A$225,$A58) -> 0.009274837 | E58: =D58*SUMIFS($B$7:$B$15,$A$7:$A$15,$A58) -> 2312216.9 | F58: =E58*'SFA Awards'!$B$9 -> 1.3212668 | H58: WY | I58: Wyoming | J58: 576851
A59: Inclusive Prosperity Capital | B59: NY | C59: =SUMIFS($J$7:$J$58,$H$7:$H$58,$B59) -> 20201249 | D59: =C59/SUMIFS($C$25:$C$225,$A$25:$A$225,$A59) -> 0.060349947 | E59: =D59*SUMIFS($B$7:$B$15,$A$7:$A$15,$A59) -> 15045242 | F59: =E59*'SFA Awards'!$B$9 -> 8.5972811 | H59: TOTAL | J59: =SUM(J7:J58) -> 334735155
A60: Inclusive Prosperity Capital | B60: OH | C60: =SUMIFS($J$7:$J$58,$H$7:$H$58,$B60) -> 11799448 | D60: =C60/SUMIFS($C$25:$C$225,$A$25:$A$225,$A60) -> 0.035250101 | E60: =D60*SUMIFS($B$7:$B$15,$A$7:$A$15,$A60) -> 8787850.2 | F60: =E60*'SFA Awards'!$B$9 -> 5.0216287
A61: Inclusive Prosperity Capital | B61: OK | C61: =SUMIFS($J$7:$J$58,$H$7:$H$58,$B61) -> 3959353 | D61: =C61/SUMIFS($C$25:$C$225,$A$25:$A$225,$A61) -> 0.011828315 | E61: =D61*SUMIFS($B$7:$B$15,$A$7:$A$15,$A61) -> 2948799 | F61: =E61*'SFA Awards'!$B$9 -> 1.685028
A62: Inclusive Prosperity Capital | B62: OR | C62: =SUMIFS($J$7:$J$58,$H$7:$H$58,$B62) -> 4237256 | D62: =C62/SUMIFS($C$25:$C$225,$A$25:$A$225,$A62) -> 0.012658533 | E62: =D62*SUMIFS($B$7:$B$15,$A$7:$A$15,$A62) -> 3155772.3 | F62: =E62*'SFA Awards'!$B$9 -> 1.8032984
A63: Inclusive Prosperity Capital | B63: PA | C63: =SUMIFS($J$7:$J$58,$H$7:$H$58,$B63) -> 13002700 | D63: =C63/SUMIFS($C$25:$C$225,$A$25:$A$225,$A63) -> 0.03884474 | E63: =D63*SUMIFS($B$7:$B$15,$A$7:$A$15,$A63) -> 9683993.6 | F63: =E63*'SFA Awards'!$B$9 -> 5.5337106
A64: Inclusive Prosperity Capital | B64: PR | C64: =SUMIFS($J$7:$J$58,$H$7:$H$58,$B64) -> 3285874 | D64: =C64/SUMIFS($C$25:$C$225,$A$25:$A$225,$A64) -> 0.0098163397 | E64: =D64*SUMIFS($B$7:$B$15,$A$7:$A$15,$A64) -> 2447213.5 | F64: =E64*'SFA Awards'!$B$9 -> 1.3984077
A65: Inclusive Prosperity Capital | B65: RI | C65: =SUMIFS($J$7:$J$58,$H$7:$H$58,$B65) -> 1097379 | D65: =C65/SUMIFS($C$25:$C$225,$A$25:$A$225,$A65) -> 0.00327835 | E65: =D65*SUMIFS($B$7:$B$15,$A$7:$A$15,$A65) -> 817292.66 | F65: =E65*'SFA Awards'!$B$9 -> 0.46702438
A66: Inclusive Prosperity Capital | B66: SC | C66: =SUMIFS($J$7:$J$58,$H$7:$H$58,$B66) -> 5118425 | D66: =C66/SUMIFS($C$25:$C$225,$A$25:$A$225,$A66) -> 0.015290969 | E66: =D66*SUMIFS($B$7:$B$15,$A$7:$A$15,$A66) -> 3812038.7 | F66: =E66*'SFA Awards'!$B$9 -> 2.1783078
A67: Inclusive Prosperity Capital | B67: SD | C67: =SUMIFS($J$7:$J$58,$H$7:$H$58,$B67) -> 886667 | D67: =C67/SUMIFS($C$25:$C$225,$A$25:$A$225,$A67) -> 0.0026488613 | E67: =D67*SUMIFS($B$7:$B$15,$A$7:$A$15,$A67) -> 660361.12 | F67: =E67*'SFA Awards'!$B$9 -> 0.37734921
A68: Inclusive Prosperity Capital | B68: TN | C68: =SUMIFS($J$7:$J$58,$H$7:$H$58,$B68) -> 6910840 | D68: =C68/SUMIFS($C$25:$C$225,$A$25:$A$225,$A68) -> 0.020645695 | E68: =D68*SUMIFS($B$7:$B$15,$A$7:$A$15,$A68) -> 5146971.8 | F68: =E68*'SFA Awards'!$B$9 -> 2.9411268
A69: Inclusive Prosperity Capital | B69: TX | C69: =SUMIFS($J$7:$J$58,$H$7:$H$58,$B69) -> 29145505 | D69: =C69/SUMIFS($C$25:$C$225,$A$25:$A$225,$A69) -> 0.087070344 | E69: =D69*SUMIFS($B$7:$B$15,$A$7:$A$15,$A69) -> 21706637 | F69: =E69*'SFA Awards'!$B$9 -> 12.403792
A70: Inclusive Prosperity Capital | B70: UT | C70: =SUMIFS($J$7:$J$58,$H$7:$H$58,$B70) -> 3271616 | D70: =C70/SUMIFS($C$25:$C$225,$A$25:$A$225,$A70) -> 0.0097737449 | E70: =D70*SUMIFS($B$7:$B$15,$A$7:$A$15,$A70) -> 2436594.6 | F70: =E70*'SFA Awards'!$B$9 -> 1.3923398
A71: Inclusive Prosperity Capital | B71: VA | C71: =SUMIFS($J$7:$J$58,$H$7:$H$58,$B71) -> 8631393 | D71: =C71/SUMIFS($C$25:$C$225,$A$25:$A$225,$A71) -> 0.025785738 | E71: =D71*SUMIFS($B$7:$B$15,$A$7:$A$15,$A71) -> 6428384.5 | F71: =E71*'SFA Awards'!$B$9 -> 3.6733626
... A225: GRID SANAH | B225: WY | C225: =SUMIFS($J$7:$J$58,$H$7:$H$58,$B225) -> 576851 | D225: =C225/SUMIFS($C$25:$C$225,$A$25:$A$225,$A225) -> 0.00174039 | E225: =D225*SUMIFS($B$7:$B$15,$A$7:$A$15,$A225) -> 434749.41 | F225: =E225*'SFA Awards'!$B$9 -> 0.24842824
A226: TOTAL | E226: =SUM(E25:E225) -> 1.38394e+09 | F226: =SUM(F25:F225) -> 790.82286
A227: Check: splits sum back to the nine awards | E227: =IF(ROUND(E226-B16,2)=0,"OK","MISMATCH") -> OK

Sheet Solar for All
A1: Solar for All - capacity by state
A2: STEP 3 of 3. Direct awards (from 'SFA Awards') plus each state's share of the multistate awards (from 'SFA Multistate Split'), converted to MW at the national factor.
A3: These are the PLANNED figures from the awards as made. The program was cancelled, so this file models the counterfactual in which it proceeded. (EPA announced on 7 August 2025 it would not implement it; the 4 July 2025 law rescinded the funds.)
A4: Column F is what the 'calcs' tab reads. Nothing on this tab is typed in by hand.
A6: State | B6: Name (uppercase) | C6: Direct + in-state tribal awards ($) | D6: Multistate / tribal share ($) | E6: Total ($) | F6: Total (MW) | G6: % of program
A7: AK | B7: ALASKA | C7: =SUMIFS('SFA Awards'!$H$13:$H$72,'SFA Awards'!$E$13:$E$72,$A7) -> 124900000 | D7: =SUMIFS('SFA Multistate Split'!$E$25:$E$225,'SFA Multistate Split'!$B$25:$B$225,$A7) -> 1445097.1 | E7: =C7+D7 -> 1.263451e+08 | F7: =E7*'SFA Awards'!$B$9 -> 72.197198 | G7: =E7/'SFA Awards'!$B$8 -> 0.0180493
A8: AL | B8: ALABAMA | C8: =SUMIFS('SFA Awards'!$H$13:$H$72,'SFA Awards'!$E$13:$E$72,$A8) -> 0 | D8: =SUMIFS('SFA Multistate Split'!$E$25:$E$225,'SFA Multistate Split'!$B$25:$B$225,$A8) -> 27079413 | E8: =C8+D8 -> 27079413 | F8: =E8*'SFA Awards'!$B$9 -> 15.473951 | G8: =E8/'SFA Awards'!$B$8 -> 0.0038684876
A9: AR | B9: ARKANSAS | C9: =SUMIFS('SFA Awards'!$H$13:$H$72,'SFA Awards'!$E$13:$E$72,$A9) -> 93670000 | D9: =SUMIFS('SFA Multistate Split'!$E$25:$E$225,'SFA Multistate Split'!$B$25:$B$225,$A9) -> 16231245 | E9: =C9+D9 -> 1.0990125e+08 | F9: =E9*'SFA Awards'!$B$9 -> 62.800711 | G9: =E9/'SFA Awards'!$B$8 -> 0.015700178
A10: AZ | B10: ARIZONA | C10: =SUMIFS('SFA Awards'!$H$13:$H$72,'SFA Awards'!$E$13:$E$72,$A10) -> 181240000 | D10: =SUMIFS('SFA Multistate Split'!$E$25:$E$225,'SFA Multistate Split'!$B$25:$B$225,$A10) -> 34942753 | E10: =C10+D10 -> 2.1618275e+08 | F10: =E10*'SFA Awards'!$B$9 -> 123.533 | G10: =E10/'SFA Awards'!$B$8 -> 0.03088325
A11: CA | B11: CALIFORNIA | C11: =SUMIFS('SFA Awards'!$H$13:$H$72,'SFA Awards'!$E$13:$E$72,$A11) -> 249800000 | D11: =SUMIFS('SFA Multistate Split'!$E$25:$E$225,'SFA Multistate Split'!$B$25:$B$225,$A11) -> 77907378 | E11: =C11+D11 -> 3.2770738e+08 | F11: =E11*'SFA Awards'!$B$9 -> 187.26136 | G11: =E11/'SFA Awards'!$B$8 -> 0.04681534
A12: CO | B12: COLORADO | C12: =SUMIFS('SFA Awards'!$H$13:$H$72,'SFA Awards'!$E$13:$E$72,$A12) -> 156120000 | D12: =SUMIFS('SFA Multistate Split'!$E$25:$E$225,'SFA Multistate Split'!$B$25:$B$225,$A12) -> 28210782 | E12: =C12+D12 -> 1.8433078e+08 | F12: =E12*'SFA Awards'!$B$9 -> 105.33188 | G12: =E12/'SFA Awards'!$B$8 -> 0.026332969
A13: CT | B13: CONNECTICUT | C13: =SUMIFS('SFA Awards'!$H$13:$H$72,'SFA Awards'!$E$13:$E$72,$A13) -> 62450000 | D13: =SUMIFS('SFA Multistate Split'!$E$25:$E$225,'SFA Multistate Split'!$B$25:$B$225,$A13) -> 7105267.3 | E13: =C13+D13 -> 69555267 | F13: =E13*'SFA Awards'!$B$9 -> 39.745867 | G13: =E13/'SFA Awards'!$B$8 -> 0.0099364668
A14: DC | B14: DISTRICT OF COLUMBIA | C14: =SUMIFS('SFA Awards'!$H$13:$H$72,'SFA Awards'!$E$13:$E$72,$A14) -> 62450000 | D14: =SUMIFS('SFA Multistate Split'!$E$25:$E$225,'SFA Multistate Split'!$B$25:$B$225,$A14) -> 1794634.9 | E14: =C14+D14 -> 64244635 | F14: =E14*'SFA Awards'!$B$9 -> 36.71122 | G14: =E14/'SFA Awards'!$B$8 -> 0.009177805
A15: DE | B15: DELAWARE | C15: =SUMIFS('SFA Awards'!$H$13:$H$72,'SFA Awards'!$E$13:$E$72,$A15) -> 0 | D15: =SUMIFS('SFA Multistate Split'!$E$25:$E$225,'SFA Multistate Split'!$B$25:$B$225,$A15) -> 3043734.3 | E15: =C15+D15 -> 3043734.3 | F15: =E15*'SFA Awards'!$B$9 -> 1.7392767 | G15: =E15/'SFA Awards'!$B$8 -> 0.00043481918
A16: FL | B16: FLORIDA | C16: =SUMIFS('SFA Awards'!$H$13:$H$72,'SFA Awards'!$E$13:$E$72,$A16) -> 156120000 | D16: =SUMIFS('SFA Multistate Split'!$E$25:$E$225,'SFA Multistate Split'!$B$25:$B$225,$A16) -> 1.1608461e+08 | E16: =C16+D16 -> 2.7220461e+08 | F16: =E16*'SFA Awards'!$B$9 -> 155.54549 | G16: =E16/'SFA Awards'!$B$8 -> 0.038886373
A17: GA | B17: GEORGIA | C17: =SUMIFS('SFA Awards'!$H$13:$H$72,'SFA Awards'!$E$13:$E$72,$A17) -> 156010000 | D17: =SUMIFS('SFA Multistate Split'!$E$25:$E$225,'SFA Multistate Split'!$B$25:$B$225,$A17) -> 57734092 | E17: =C17+D17 -> 2.1374409e+08 | F17: =E17*'SFA Awards'!$B$9 -> 122.13948 | G17: =E17/'SFA Awards'!$B$8 -> 0.03053487
A18: GU | B18: GUAM | C18: =SUMIFS('SFA Awards'!$H$13:$H$72,'SFA Awards'!$E$13:$E$72,$A18) -> 62450000 | D18: =SUMIFS('SFA Multistate Split'!$E$25:$E$225,'SFA Multistate Split'!$B$25:$B$225,$A18) -> 0 | E18: =C18+D18 -> 62450000 | F18: =E18*'SFA Awards'!$B$9 -> 35.685714 | G18: =E18/'SFA Awards'!$B$8 -> 0.0089214286
... A60: WY | B60: WYOMING | C60: =SUMIFS('SFA Awards'!$H$13:$H$72,'SFA Awards'!$E$13:$E$72,$A60) -> 30260000 | D60: =SUMIFS('SFA Multistate Split'!$E$25:$E$225,'SFA Multistate Split'!$B$25:$B$225,$A60) -> 9618722.8 | E60: =C60+D60 -> 39878723 | F60: =E60*'SFA Awards'!$B$9 -> 22.787842 | G60: =E60/'SFA Awards'!$B$8 -> 0.0056969604
A61: TOTAL | C61: =SUM(C7:C60) -> 5616060000 | D61: =SUM(D7:D60) -> 1383940000 | E61: =SUM(E7:E60) -> 7e+09 | F61: =SUM(F7:F60) -> 4000 | G61: =SUM(G7:G60) -> 1
A62: Check vs. program totals | E62: =IF(ROUND(E61,2)='SFA Awards'!$B$8,"OK","MISMATCH") -> OK | F62: =IF(ROUND(F61,6)='SFA Awards'!$B$7,"OK","MISMATCH") -> OK
A64: DC, GU, PR and VI appear here for completeness but have no EPS state model; the 48 modelled states cover about 95% of program MW.

Sheet calcs
A1: CiDESCTY - Change in Distributed Electricity Source Capacities This Year
A2: Counterfactual: the residential distributed solar the EPA Solar for All grants would have added
A4: State (from About tab) | B4: =About!$B$1 -> Nebraska
A5: State abbreviation | B5: =About!$B$2 -> NE
A6: State name (uppercase, for lookups) | B6: =UPPER($B$4) -> NEBRASKA
A8: Solar for All capacity, all sectors (MW) | B8: =SUMIFS('Solar for All'!$F$7:$F$60,'Solar for All'!$A$7:$A$60,$B$5) -> 37.894292 | C8: from the 'Solar for All' tab, which is built up from the two SFA source tabs
A9: Urban residential share of households | B9: =SUMIFS('res v com'!$J:$J,'res v com'!$I:$I,$B$6) -> 0.731
A10: Rural residential share of households | B10: =SUMIFS('res v com'!$K:$K,'res v com'!$I:$I,$B$6) -> 0.269
A11: Check: urban + rural = 1 | B11: =IF(ROUND(B9+B10,6)=1,"OK","CHECK") -> OK
A13: Deployment window (blue = editable input)
A14: First year capacity is added | B14: 2025
A15: Last year capacity is added | B15: 2029
A16: Capacity is spread evenly across the window; Solar for All awards were made in April 2024 with five-year performance periods.
A18: Annual profile
A19: year | B19: 2021 | C19: 2022 | D19: 2023 | E19: 2024 | F19: 2025 | G19: 2026 | H19: 2027 | I19: 2028 | J19: 2029 | K19: 2030 | L19: 2031 | M19: 2032 | N19: 2033 | O19: 2034 | P19: 2035 | Q19: 2036 | R19: 2037 | S19: 2038 | T19: 2039 | U19: 2040 | V19: 2041 | W19: 2042 | X19: 2043 | Y19: 2044 | Z19: 2045 | AA19: 2046 | AB19: 2047 | AC19: 2048 | AD19: 2049 | AE19: 2050
A20: share of capacity deployed | B20: =IF(AND(B$19>=$B$14,B$19<=$B$15),1/($B$15-$B$14+1),0) -> 0 | C20: =IF(AND(C$19>=$B$14,C$19<=$B$15),1/($B$15-$B$14+1),0) -> 0 | D20: =IF(AND(D$19>=$B$14,D$19<=$B$15),1/($B$15-$B$14+1),0) -> 0 | E20: =IF(AND(E$19>=$B$14,E$19<=$B$15),1/($B$15-$B$14+1),0) -> 0 | F20: =IF(AND(F$19>=$B$14,F$19<=$B$15),1/($B$15-$B$14+1),0) -> 0.2 | G20: =IF(AND(G$19>=$B$14,G$19<=$B$15),1/($B$15-$B$14+1),0) -> 0.2 | H20: =IF(AND(H$19>=$B$14,H$19<=$B$15),1/($B$15-$B$14+1),0) -> 0.2 | I20: =IF(AND(I$19>=$B$14,I$19<=$B$15),1/($B$15-$B$14+1),0) -> 0.2 | ... AE20: =IF(AND(AE$19>=$B$14,AE$19<=$B$15),1/($B$15-$B$14+1),0) -> 0
A21: Check: shares sum to 1 | B21: =IF(ROUND(SUM(B20:AE20),6)=1,"OK","CHECK") -> OK
A23: Change in distributed solar PV capacity this year (MW added per year)
A24: urban residential | B24: =$B$8*$B$9*B$20 -> 0 | C24: =$B$8*$B$9*C$20 -> 0 | D24: =$B$8*$B$9*D$20 -> 0 | E24: =$B$8*$B$9*E$20 -> 0 | F24: =$B$8*$B$9*F$20 -> 5.5401454 | G24: =$B$8*$B$9*G$20 -> 5.5401454 | H24: =$B$8*$B$9*H$20 -> 5.5401454 | I24: =$B$8*$B$9*I$20 -> 5.5401454 | ... AE24: =$B$8*$B$9*AE$20 -> 0
A25: rural residential | B25: =$B$8*$B$10*B$20 -> 0 | C25: =$B$8*$B$10*C$20 -> 0 | D25: =$B$8*$B$10*D$20 -> 0 | E25: =$B$8*$B$10*E$20 -> 0 | F25: =$B$8*$B$10*F$20 -> 2.0387129 | G25: =$B$8*$B$10*G$20 -> 2.0387129 | H25: =$B$8*$B$10*H$20 -> 2.0387129 | I25: =$B$8*$B$10*I$20 -> 2.0387129 | ... AE25: =$B$8*$B$10*AE$20 -> 0
A26: commercial | B26: 0 | C26: 0 | D26: 0 | E26: 0 | F26: 0 | G26: 0 | H26: 0 | I26: 0 | J26: 0 | K26: 0 | L26: 0 | M26: 0 | N26: 0 | O26: 0 | P26: 0 | Q26: 0 | R26: 0 | S26: 0 | T26: 0 | U26: 0 | V26: 0 | W26: 0 | X26: 0 | Y26: 0 | Z26: 0 | AA26: 0 | AB26: 0 | AC26: 0 | AD26: 0 | AE26: 0
A27: total | B27: =SUM(B24:B26) -> 0 | C27: =SUM(C24:C26) -> 0 | D27: =SUM(D24:D26) -> 0 | E27: =SUM(E24:E26) -> 0 | F27: =SUM(F24:F26) -> 7.5788583 | G27: =SUM(G24:G26) -> 7.5788583 | H27: =SUM(H24:H26) -> 7.5788583 | I27: =SUM(I24:I26) -> 7.5788583 | ... AE27: =SUM(AE24:AE26) -> 0
A28: cumulative total | B28: =SUM($B$27:B27) -> 0 | C28: =SUM($B$27:C27) -> 0 | D28: =SUM($B$27:D27) -> 0 | E28: =SUM($B$27:E27) -> 0 | F28: =SUM($B$27:F27) -> 7.5788583 | G28: =SUM($B$27:G27) -> 15.157717 | H28: =SUM($B$27:H27) -> 22.736575 | I28: =SUM($B$27:I27) -> 30.315433 | ... AE28: =SUM($B$27:AE27) -> 37.894292
A29: Check: 2050 cumulative = Solar for All capacity | B29: =IF(ROUND(AE28-$B$8,6)=0,"OK","CHECK") -> OK

Sheet res v com
I1: state | J1: urban_share | K1: rural_share
A2: State | B2: State | C2: Residential | D2: Commercial | E2: percent residential | F2: percent commercial | I2: UNITED STATES | J2: 0.807 | K2: 0.193 | O2: =UPPER(About!B1) -> NEBRASKA
A3: Alabama | B3: AL | C3: =SUMIFS(States!G:G,States!$B:$B,$B3) -> 0.389 | D3: =SUMIFS(States!H:H,States!$B:$B,$B3) -> 0.5 | E3: =C3/SUM($C3:$D3) -> 0.4375703 | F3: =D3/SUM($C3:$D3) -> 0.5624297 | H3: =I3=A3 -> TRUE | I3: ALABAMA | J3: 0.59 | K3: 0.41 | N3: Urban | O3: =SUMIFS(J:J,I:I,O2) -> 0.731
A4: Alaska | B4: AK | C4: =SUMIFS(States!G:G,States!$B:$B,$B4) -> 10.54 | D4: =SUMIFS(States!H:H,States!$B:$B,$B4) -> 2.012 | E4: =C4/SUM($C4:$D4) -> 0.83970682 | F4: =D4/SUM($C4:$D4) -> 0.16029318 | H4: =I4=A4 -> TRUE | I4: ALASKA | J4: 0.66 | K4: 0.34 | N4: Rural | O4: =SUMIFS(K:K,I:I,O2) -> 0.269
A5: Arizona | B5: AZ | C5: =SUMIFS(States!G:G,States!$B:$B,$B5) -> 1791.789 | D5: =SUMIFS(States!H:H,States!$B:$B,$B5) -> 560.643 | E5: =C5/SUM($C5:$D5) -> 0.76167515 | F5: =D5/SUM($C5:$D5) -> 0.23832485 | H5: =I5=A5 -> TRUE | I5: ARIZONA | J5: 0.898 | K5: 0.102
A6: Arkansas | B6: AR | C6: =SUMIFS(States!G:G,States!$B:$B,$B6) -> 100.077 | D6: =SUMIFS(States!H:H,States!$B:$B,$B6) -> 51.704 | E6: =C6/SUM($C6:$D6) -> 0.6593513 | F6: =D6/SUM($C6:$D6) -> 0.3406487 | H6: =I6=A6 -> TRUE | I6: ARKANSAS | J6: 0.562 | K6: 0.438
A7: California | B7: CA | C7: =SUMIFS(States!G:G,States!$B:$B,$B7) -> 9625.141 | D7: =SUMIFS(States!H:H,States!$B:$B,$B7) -> 2969.227 | E7: =C7/SUM($C7:$D7) -> 0.76424168 | F7: =D7/SUM($C7:$D7) -> 0.23575832 | H7: =I7=A7 -> TRUE | I7: CALIFORNIA | J7: 0.95 | K7: 0.05
A8: Colorado | B8: CO | C8: =SUMIFS(States!G:G,States!$B:$B,$B8) -> 640.728 | D8: =SUMIFS(States!H:H,States!$B:$B,$B8) -> 194.549 | E8: =C8/SUM($C8:$D8) -> 0.76708445 | F8: =D8/SUM($C8:$D8) -> 0.23291555 | H8: =I8=A8 -> TRUE | I8: COLORADO | J8: 0.862 | K8: 0.138
A9: Connecticut | B9: CT | C9: =SUMIFS(States!G:G,States!$B:$B,$B9) -> 511.698 | D9: =SUMIFS(States!H:H,States!$B:$B,$B9) -> 236.848 | E9: =C9/SUM($C9:$D9) -> 0.68358925 | F9: =D9/SUM($C9:$D9) -> 0.31641075 | H9: =I9=A9 -> TRUE | I9: CONNECTICUT | J9: 0.88 | K9: 0.12
A10: Delaware | B10: DE | C10: =SUMIFS(States!G:G,States!$B:$B,$B10) -> 84.058 | D10: =SUMIFS(States!H:H,States!$B:$B,$B10) -> 25.116 | E10: =C10/SUM($C10:$D10) -> 0.76994523 | F10: =D10/SUM($C10:$D10) -> 0.23005477 | H10: =I10=A10 -> TRUE | I10: DELAWARE | J10: 0.833 | K10: 0.167
A11: Florida | B11: FL | C11: =SUMIFS(States!G:G,States!$B:$B,$B11) -> 1581.563 | D11: =SUMIFS(States!H:H,States!$B:$B,$B11) -> 141.59 | E11: =C11/SUM($C11:$D11) -> 0.91783086 | F11: =D11/SUM($C11:$D11) -> 0.08216914 | H11: =I11=A11 -> TRUE | I11: FLORIDA | J11: 0.912 | K11: 0.088
A12: Georgia | B12: GA | C12: =SUMIFS(States!G:G,States!$B:$B,$B12) -> 35.742 | D12: =SUMIFS(States!H:H,States!$B:$B,$B12) -> 13.142 | E12: =C12/SUM($C12:$D12) -> 0.73115948 | F12: =D12/SUM($C12:$D12) -> 0.26884052 | H12: =I12=A12 -> TRUE | I12: GEORGIA | J12: 0.751 | K12: 0.249
A13: Hawaii | B13: HI | C13: =SUMIFS(States!G:G,States!$B:$B,$B13) -> 458.578 | D13: =SUMIFS(States!H:H,States!$B:$B,$B13) -> 125.331 | E13: =C13/SUM($C13:$D13) -> 0.78535868 | F13: =D13/SUM($C13:$D13) -> 0.21464132 | H13: =I13=A13 -> TRUE | I13: HAWAII | J13: 0.919 | K13: 0.081
A14: Idaho | B14: ID | C14: =SUMIFS(States!G:G,States!$B:$B,$B14) -> 100.23 | D14: =SUMIFS(States!H:H,States!$B:$B,$B14) -> 7.57 | E14: =C14/SUM($C14:$D14) -> 0.92977737 | F14: =D14/SUM($C14:$D14) -> 0.070222635 | H14: =I14=A14 -> TRUE | I14: IDAHO | J14: 0.706 | K14: 0.294
A15: Illinois | B15: IL | C15: =SUMIFS(States!G:G,States!$B:$B,$B15) -> 342.517 | D15: =SUMIFS(States!H:H,States!$B:$B,$B15) -> 283.795 | E15: =C15/SUM($C15:$D15) -> 0.54687919 | F15: =D15/SUM($C15:$D15) -> 0.45312081 | H15: =I15=A15 -> TRUE | I15: ILLINOIS | J15: 0.885 | K15: 0.115
A16: Indiana | B16: IN | C16: =SUMIFS(States!G:G,States!$B:$B,$B16) -> 82.194 | D16: =SUMIFS(States!H:H,States!$B:$B,$B16) -> 118.413 | E16: =C16/SUM($C16:$D16) -> 0.40972648 | F16: =D16/SUM($C16:$D16) -> 0.59027352 | H16: =I16=A16 -> TRUE | I16: INDIANA | J16: 0.724 | K16: 0.276
... A52: Wyoming | B52: WY | C52: =SUMIFS(States!G:G,States!$B:$B,$B52) -> 12.791 | D52: =SUMIFS(States!H:H,States!$B:$B,$B52) -> 1.63 | E52: =C52/SUM($C52:$D52) -> 0.88697039 | F52: =D52/SUM($C52:$D52) -> 0.11302961 | H52: =I52=A52 -> TRUE | I52: WYOMING | J52: 0.648 | K52: 0.352

Sheet CiDESCTY-urban-residential
A1: MW | B1: 2021 | C1: 2022 | D1: 2023 | E1: 2024 | F1: 2025 | G1: 2026 | H1: 2027 | I1: 2028 | J1: 2029 | K1: 2030 | L1: 2031 | M1: 2032 | N1: 2033 | O1: 2034 | P1: 2035 | Q1: 2036 | R1: 2037 | S1: 2038 | T1: 2039 | U1: 2040 | V1: 2041 | W1: 2042 | X1: 2043 | Y1: 2044 | Z1: 2045 | AA1: 2046 | AB1: 2047 | AC1: 2048 | AD1: 2049 | AE1: 2050
A2: hard coal | B2: 0 | C2: 0 | D2: 0 | E2: 0 | F2: 0 | G2: 0 | H2: 0 | I2: 0 | J2: 0 | K2: 0 | L2: 0 | M2: 0 | N2: 0 | O2: 0 | P2: 0 | Q2: 0 | R2: 0 | S2: 0 | T2: 0 | U2: 0 | V2: 0 | W2: 0 | X2: 0 | Y2: 0 | Z2: 0 | AA2: 0 | AB2: 0 | AC2: 0 | AD2: 0 | AE2: 0
A3: natural gas steam turbine | B3: 0 | C3: 0 | D3: 0 | E3: 0 | F3: 0 | G3: 0 | H3: 0 | I3: 0 | J3: 0 | K3: 0 | L3: 0 | M3: 0 | N3: 0 | O3: 0 | P3: 0 | Q3: 0 | R3: 0 | S3: 0 | T3: 0 | U3: 0 | V3: 0 | W3: 0 | X3: 0 | Y3: 0 | Z3: 0 | AA3: 0 | AB3: 0 | AC3: 0 | AD3: 0 | AE3: 0
A4: natural gas combined cycle | B4: 0 | C4: 0 | D4: 0 | E4: 0 | F4: 0 | G4: 0 | H4: 0 | I4: 0 | J4: 0 | K4: 0 | L4: 0 | M4: 0 | N4: 0 | O4: 0 | P4: 0 | Q4: 0 | R4: 0 | S4: 0 | T4: 0 | U4: 0 | V4: 0 | W4: 0 | X4: 0 | Y4: 0 | Z4: 0 | AA4: 0 | AB4: 0 | AC4: 0 | AD4: 0 | AE4: 0
A5: nuclear | B5: 0 | C5: 0 | D5: 0 | E5: 0 | F5: 0 | G5: 0 | H5: 0 | I5: 0 | J5: 0 | K5: 0 | L5: 0 | M5: 0 | N5: 0 | O5: 0 | P5: 0 | Q5: 0 | R5: 0 | S5: 0 | T5: 0 | U5: 0 | V5: 0 | W5: 0 | X5: 0 | Y5: 0 | Z5: 0 | AA5: 0 | AB5: 0 | AC5: 0 | AD5: 0 | AE5: 0
A6: hydro | B6: 0 | C6: 0 | D6: 0 | E6: 0 | F6: 0 | G6: 0 | H6: 0 | I6: 0 | J6: 0 | K6: 0 | L6: 0 | M6: 0 | N6: 0 | O6: 0 | P6: 0 | Q6: 0 | R6: 0 | S6: 0 | T6: 0 | U6: 0 | V6: 0 | W6: 0 | X6: 0 | Y6: 0 | Z6: 0 | AA6: 0 | AB6: 0 | AC6: 0 | AD6: 0 | AE6: 0
A7: onshore wind | B7: 0 | C7: 0 | D7: 0 | E7: 0 | F7: 0 | G7: 0 | H7: 0 | I7: 0 | J7: 0 | K7: 0 | L7: 0 | M7: 0 | N7: 0 | O7: 0 | P7: 0 | Q7: 0 | R7: 0 | S7: 0 | T7: 0 | U7: 0 | V7: 0 | W7: 0 | X7: 0 | Y7: 0 | Z7: 0 | AA7: 0 | AB7: 0 | AC7: 0 | AD7: 0 | AE7: 0
A8: solar PV | B8: =calcs!B24 -> 0 | C8: =calcs!C24 -> 0 | D8: =calcs!D24 -> 0 | E8: =calcs!E24 -> 0 | F8: =calcs!F24 -> 5.5401454 | G8: =calcs!G24 -> 5.5401454 | H8: =calcs!H24 -> 5.5401454 | I8: =calcs!I24 -> 5.5401454 | ... AE8: =calcs!AE24 -> 0
A9: solar thermal | B9: 0 | C9: 0 | D9: 0 | E9: 0 | F9: 0 | G9: 0 | H9: 0 | I9: 0 | J9: 0 | K9: 0 | L9: 0 | M9: 0 | N9: 0 | O9: 0 | P9: 0 | Q9: 0 | R9: 0 | S9: 0 | T9: 0 | U9: 0 | V9: 0 | W9: 0 | X9: 0 | Y9: 0 | Z9: 0 | AA9: 0 | AB9: 0 | AC9: 0 | AD9: 0 | AE9: 0
A10: biomass | B10: 0 | C10: 0 | D10: 0 | E10: 0 | F10: 0 | G10: 0 | H10: 0 | I10: 0 | J10: 0 | K10: 0 | L10: 0 | M10: 0 | N10: 0 | O10: 0 | P10: 0 | Q10: 0 | R10: 0 | S10: 0 | T10: 0 | U10: 0 | V10: 0 | W10: 0 | X10: 0 | Y10: 0 | Z10: 0 | AA10: 0 | AB10: 0 | AC10: 0 | AD10: 0 | AE10: 0
A11: geothermal | B11: 0 | C11: 0 | D11: 0 | E11: 0 | F11: 0 | G11: 0 | H11: 0 | I11: 0 | J11: 0 | K11: 0 | L11: 0 | M11: 0 | N11: 0 | O11: 0 | P11: 0 | Q11: 0 | R11: 0 | S11: 0 | T11: 0 | U11: 0 | V11: 0 | W11: 0 | X11: 0 | Y11: 0 | Z11: 0 | AA11: 0 | AB11: 0 | AC11: 0 | AD11: 0 | AE11: 0
A12: petroleum | B12: 0 | C12: 0 | D12: 0 | E12: 0 | F12: 0 | G12: 0 | H12: 0 | I12: 0 | J12: 0 | K12: 0 | L12: 0 | M12: 0 | N12: 0 | O12: 0 | P12: 0 | Q12: 0 | R12: 0 | S12: 0 | T12: 0 | U12: 0 | V12: 0 | W12: 0 | X12: 0 | Y12: 0 | Z12: 0 | AA12: 0 | AB12: 0 | AC12: 0 | AD12: 0 | AE12: 0
A13: natural gas peaker | B13: 0 | C13: 0 | D13: 0 | E13: 0 | F13: 0 | G13: 0 | H13: 0 | I13: 0 | J13: 0 | K13: 0 | L13: 0 | M13: 0 | N13: 0 | O13: 0 | P13: 0 | Q13: 0 | R13: 0 | S13: 0 | T13: 0 | U13: 0 | V13: 0 | W13: 0 | X13: 0 | Y13: 0 | Z13: 0 | AA13: 0 | AB13: 0 | AC13: 0 | AD13: 0 | AE13: 0
A14: lignite | B14: 0 | C14: 0 | D14: 0 | E14: 0 | F14: 0 | G14: 0 | H14: 0 | I14: 0 | J14: 0 | K14: 0 | L14: 0 | M14: 0 | N14: 0 | O14: 0 | P14: 0 | Q14: 0 | R14: 0 | S14: 0 | T14: 0 | U14: 0 | V14: 0 | W14: 0 | X14: 0 | Y14: 0 | Z14: 0 | AA14: 0 | AB14: 0 | AC14: 0 | AD14: 0 | AE14: 0
A15: offshore wind | B15: 0 | C15: 0 | D15: 0 | E15: 0 | F15: 0 | G15: 0 | H15: 0 | I15: 0 | J15: 0 | K15: 0 | L15: 0 | M15: 0 | N15: 0 | O15: 0 | P15: 0 | Q15: 0 | R15: 0 | S15: 0 | T15: 0 | U15: 0 | V15: 0 | W15: 0 | X15: 0 | Y15: 0 | Z15: 0 | AA15: 0 | AB15: 0 | AC15: 0 | AD15: 0 | AE15: 0
A16: crude oil | B16: 0 | C16: 0 | D16: 0 | E16: 0 | F16: 0 | G16: 0 | H16: 0 | I16: 0 | J16: 0 | K16: 0 | L16: 0 | M16: 0 | N16: 0 | O16: 0 | P16: 0 | Q16: 0 | R16: 0 | S16: 0 | T16: 0 | U16: 0 | V16: 0 | W16: 0 | X16: 0 | Y16: 0 | Z16: 0 | AA16: 0 | AB16: 0 | AC16: 0 | AD16: 0 | AE16: 0
A17: heavy or residual fuel oil | B17: 0 | C17: 0 | D17: 0 | E17: 0 | F17: 0 | G17: 0 | H17: 0 | I17: 0 | J17: 0 | K17: 0 | L17: 0 | M17: 0 | N17: 0 | O17: 0 | P17: 0 | Q17: 0 | R17: 0 | S17: 0 | T17: 0 | U17: 0 | V17: 0 | W17: 0 | X17: 0 | Y17: 0 | Z17: 0 | AA17: 0 | AB17: 0 | AC17: 0 | AD17: 0 | AE17: 0
A18: municipal solid waste | B18: 0 | C18: 0 | D18: 0 | E18: 0 | F18: 0 | G18: 0 | H18: 0 | I18: 0 | J18: 0 | K18: 0 | L18: 0 | M18: 0 | N18: 0 | O18: 0 | P18: 0 | Q18: 0 | R18: 0 | S18: 0 | T18: 0 | U18: 0 | V18: 0 | W18: 0 | X18: 0 | Y18: 0 | Z18: 0 | AA18: 0 | AB18: 0 | AC18: 0 | AD18: 0 | AE18: 0
A19: hard coal w CCS | B19: 0 | C19: 0 | D19: 0 | E19: 0 | F19: 0 | G19: 0 | H19: 0 | I19: 0 | J19: 0 | K19: 0 | L19: 0 | M19: 0 | N19: 0 | O19: 0 | P19: 0 | Q19: 0 | R19: 0 | S19: 0 | T19: 0 | U19: 0 | V19: 0 | W19: 0 | X19: 0 | Y19: 0 | Z19: 0 | AA19: 0 | AB19: 0 | AC19: 0 | AD19: 0 | AE19: 0
A20: natural gas combined cycle w CCS | B20: 0 | C20: 0 | D20: 0 | E20: 0 | F20: 0 | G20: 0 | H20: 0 | I20: 0 | J20: 0 | K20: 0 | L20: 0 | M20: 0 | N20: 0 | O20: 0 | P20: 0 | Q20: 0 | R20: 0 | S20: 0 | T20: 0 | U20: 0 | V20: 0 | W20: 0 | X20: 0 | Y20: 0 | Z20: 0 | AA20: 0 | AB20: 0 | AC20: 0 | AD20: 0 | AE20: 0
... A25: hydrogen combined cycle | B25: 0 | C25: 0 | D25: 0 | E25: 0 | F25: 0 | G25: 0 | H25: 0 | I25: 0 | J25: 0 | K25: 0 | L25: 0 | M25: 0 | N25: 0 | O25: 0 | P25: 0 | Q25: 0 | R25: 0 | S25: 0 | T25: 0 | U25: 0 | V25: 0 | W25: 0 | X25: 0 | Y25: 0 | Z25: 0 | AA25: 0 | AB25: 0 | AC25: 0 | AD25: 0 | AE25: 0

Sheet CiDESCTY-rural-residential
A1: MW | B1: 2021 | C1: 2022 | D1: 2023 | E1: 2024 | F1: 2025 | G1: 2026 | H1: 2027 | I1: 2028 | J1: 2029 | K1: 2030 | L1: 2031 | M1: 2032 | N1: 2033 | O1: 2034 | P1: 2035 | Q1: 2036 | R1: 2037 | S1: 2038 | T1: 2039 | U1: 2040 | V1: 2041 | W1: 2042 | X1: 2043 | Y1: 2044 | Z1: 2045 | AA1: 2046 | AB1: 2047 | AC1: 2048 | AD1: 2049 | AE1: 2050
A2: hard coal | B2: 0 | C2: 0 | D2: 0 | E2: 0 | F2: 0 | G2: 0 | H2: 0 | I2: 0 | J2: 0 | K2: 0 | L2: 0 | M2: 0 | N2: 0 | O2: 0 | P2: 0 | Q2: 0 | R2: 0 | S2: 0 | T2: 0 | U2: 0 | V2: 0 | W2: 0 | X2: 0 | Y2: 0 | Z2: 0 | AA2: 0 | AB2: 0 | AC2: 0 | AD2: 0 | AE2: 0
A3: natural gas steam turbine | B3: 0 | C3: 0 | D3: 0 | E3: 0 | F3: 0 | G3: 0 | H3: 0 | I3: 0 | J3: 0 | K3: 0 | L3: 0 | M3: 0 | N3: 0 | O3: 0 | P3: 0 | Q3: 0 | R3: 0 | S3: 0 | T3: 0 | U3: 0 | V3: 0 | W3: 0 | X3: 0 | Y3: 0 | Z3: 0 | AA3: 0 | AB3: 0 | AC3: 0 | AD3: 0 | AE3: 0
A4: natural gas combined cycle | B4: 0 | C4: 0 | D4: 0 | E4: 0 | F4: 0 | G4: 0 | H4: 0 | I4: 0 | J4: 0 | K4: 0 | L4: 0 | M4: 0 | N4: 0 | O4: 0 | P4: 0 | Q4: 0 | R4: 0 | S4: 0 | T4: 0 | U4: 0 | V4: 0 | W4: 0 | X4: 0 | Y4: 0 | Z4: 0 | AA4: 0 | AB4: 0 | AC4: 0 | AD4: 0 | AE4: 0
A5: nuclear | B5: 0 | C5: 0 | D5: 0 | E5: 0 | F5: 0 | G5: 0 | H5: 0 | I5: 0 | J5: 0 | K5: 0 | L5: 0 | M5: 0 | N5: 0 | O5: 0 | P5: 0 | Q5: 0 | R5: 0 | S5: 0 | T5: 0 | U5: 0 | V5: 0 | W5: 0 | X5: 0 | Y5: 0 | Z5: 0 | AA5: 0 | AB5: 0 | AC5: 0 | AD5: 0 | AE5: 0
A6: hydro | B6: 0 | C6: 0 | D6: 0 | E6: 0 | F6: 0 | G6: 0 | H6: 0 | I6: 0 | J6: 0 | K6: 0 | L6: 0 | M6: 0 | N6: 0 | O6: 0 | P6: 0 | Q6: 0 | R6: 0 | S6: 0 | T6: 0 | U6: 0 | V6: 0 | W6: 0 | X6: 0 | Y6: 0 | Z6: 0 | AA6: 0 | AB6: 0 | AC6: 0 | AD6: 0 | AE6: 0
A7: onshore wind | B7: 0 | C7: 0 | D7: 0 | E7: 0 | F7: 0 | G7: 0 | H7: 0 | I7: 0 | J7: 0 | K7: 0 | L7: 0 | M7: 0 | N7: 0 | O7: 0 | P7: 0 | Q7: 0 | R7: 0 | S7: 0 | T7: 0 | U7: 0 | V7: 0 | W7: 0 | X7: 0 | Y7: 0 | Z7: 0 | AA7: 0 | AB7: 0 | AC7: 0 | AD7: 0 | AE7: 0
A8: solar PV | B8: =calcs!B25 -> 0 | C8: =calcs!C25 -> 0 | D8: =calcs!D25 -> 0 | E8: =calcs!E25 -> 0 | F8: =calcs!F25 -> 2.0387129 | G8: =calcs!G25 -> 2.0387129 | H8: =calcs!H25 -> 2.0387129 | I8: =calcs!I25 -> 2.0387129 | ... AE8: =calcs!AE25 -> 0
A9: solar thermal | B9: 0 | C9: 0 | D9: 0 | E9: 0 | F9: 0 | G9: 0 | H9: 0 | I9: 0 | J9: 0 | K9: 0 | L9: 0 | M9: 0 | N9: 0 | O9: 0 | P9: 0 | Q9: 0 | R9: 0 | S9: 0 | T9: 0 | U9: 0 | V9: 0 | W9: 0 | X9: 0 | Y9: 0 | Z9: 0 | AA9: 0 | AB9: 0 | AC9: 0 | AD9: 0 | AE9: 0
A10: biomass | B10: 0 | C10: 0 | D10: 0 | E10: 0 | F10: 0 | G10: 0 | H10: 0 | I10: 0 | J10: 0 | K10: 0 | L10: 0 | M10: 0 | N10: 0 | O10: 0 | P10: 0 | Q10: 0 | R10: 0 | S10: 0 | T10: 0 | U10: 0 | V10: 0 | W10: 0 | X10: 0 | Y10: 0 | Z10: 0 | AA10: 0 | AB10: 0 | AC10: 0 | AD10: 0 | AE10: 0
A11: geothermal | B11: 0 | C11: 0 | D11: 0 | E11: 0 | F11: 0 | G11: 0 | H11: 0 | I11: 0 | J11: 0 | K11: 0 | L11: 0 | M11: 0 | N11: 0 | O11: 0 | P11: 0 | Q11: 0 | R11: 0 | S11: 0 | T11: 0 | U11: 0 | V11: 0 | W11: 0 | X11: 0 | Y11: 0 | Z11: 0 | AA11: 0 | AB11: 0 | AC11: 0 | AD11: 0 | AE11: 0
A12: petroleum | B12: 0 | C12: 0 | D12: 0 | E12: 0 | F12: 0 | G12: 0 | H12: 0 | I12: 0 | J12: 0 | K12: 0 | L12: 0 | M12: 0 | N12: 0 | O12: 0 | P12: 0 | Q12: 0 | R12: 0 | S12: 0 | T12: 0 | U12: 0 | V12: 0 | W12: 0 | X12: 0 | Y12: 0 | Z12: 0 | AA12: 0 | AB12: 0 | AC12: 0 | AD12: 0 | AE12: 0
A13: natural gas peaker | B13: 0 | C13: 0 | D13: 0 | E13: 0 | F13: 0 | G13: 0 | H13: 0 | I13: 0 | J13: 0 | K13: 0 | L13: 0 | M13: 0 | N13: 0 | O13: 0 | P13: 0 | Q13: 0 | R13: 0 | S13: 0 | T13: 0 | U13: 0 | V13: 0 | W13: 0 | X13: 0 | Y13: 0 | Z13: 0 | AA13: 0 | AB13: 0 | AC13: 0 | AD13: 0 | AE13: 0
A14: lignite | B14: 0 | C14: 0 | D14: 0 | E14: 0 | F14: 0 | G14: 0 | H14: 0 | I14: 0 | J14: 0 | K14: 0 | L14: 0 | M14: 0 | N14: 0 | O14: 0 | P14: 0 | Q14: 0 | R14: 0 | S14: 0 | T14: 0 | U14: 0 | V14: 0 | W14: 0 | X14: 0 | Y14: 0 | Z14: 0 | AA14: 0 | AB14: 0 | AC14: 0 | AD14: 0 | AE14: 0
A15: offshore wind | B15: 0 | C15: 0 | D15: 0 | E15: 0 | F15: 0 | G15: 0 | H15: 0 | I15: 0 | J15: 0 | K15: 0 | L15: 0 | M15: 0 | N15: 0 | O15: 0 | P15: 0 | Q15: 0 | R15: 0 | S15: 0 | T15: 0 | U15: 0 | V15: 0 | W15: 0 | X15: 0 | Y15: 0 | Z15: 0 | AA15: 0 | AB15: 0 | AC15: 0 | AD15: 0 | AE15: 0
A16: crude oil | B16: 0 | C16: 0 | D16: 0 | E16: 0 | F16: 0 | G16: 0 | H16: 0 | I16: 0 | J16: 0 | K16: 0 | L16: 0 | M16: 0 | N16: 0 | O16: 0 | P16: 0 | Q16: 0 | R16: 0 | S16: 0 | T16: 0 | U16: 0 | V16: 0 | W16: 0 | X16: 0 | Y16: 0 | Z16: 0 | AA16: 0 | AB16: 0 | AC16: 0 | AD16: 0 | AE16: 0
A17: heavy or residual fuel oil | B17: 0 | C17: 0 | D17: 0 | E17: 0 | F17: 0 | G17: 0 | H17: 0 | I17: 0 | J17: 0 | K17: 0 | L17: 0 | M17: 0 | N17: 0 | O17: 0 | P17: 0 | Q17: 0 | R17: 0 | S17: 0 | T17: 0 | U17: 0 | V17: 0 | W17: 0 | X17: 0 | Y17: 0 | Z17: 0 | AA17: 0 | AB17: 0 | AC17: 0 | AD17: 0 | AE17: 0
A18: municipal solid waste | B18: 0 | C18: 0 | D18: 0 | E18: 0 | F18: 0 | G18: 0 | H18: 0 | I18: 0 | J18: 0 | K18: 0 | L18: 0 | M18: 0 | N18: 0 | O18: 0 | P18: 0 | Q18: 0 | R18: 0 | S18: 0 | T18: 0 | U18: 0 | V18: 0 | W18: 0 | X18: 0 | Y18: 0 | Z18: 0 | AA18: 0 | AB18: 0 | AC18: 0 | AD18: 0 | AE18: 0
A19: hard coal w CCS | B19: 0 | C19: 0 | D19: 0 | E19: 0 | F19: 0 | G19: 0 | H19: 0 | I19: 0 | J19: 0 | K19: 0 | L19: 0 | M19: 0 | N19: 0 | O19: 0 | P19: 0 | Q19: 0 | R19: 0 | S19: 0 | T19: 0 | U19: 0 | V19: 0 | W19: 0 | X19: 0 | Y19: 0 | Z19: 0 | AA19: 0 | AB19: 0 | AC19: 0 | AD19: 0 | AE19: 0
A20: natural gas combined cycle w CCS | B20: 0 | C20: 0 | D20: 0 | E20: 0 | F20: 0 | G20: 0 | H20: 0 | I20: 0 | J20: 0 | K20: 0 | L20: 0 | M20: 0 | N20: 0 | O20: 0 | P20: 0 | Q20: 0 | R20: 0 | S20: 0 | T20: 0 | U20: 0 | V20: 0 | W20: 0 | X20: 0 | Y20: 0 | Z20: 0 | AA20: 0 | AB20: 0 | AC20: 0 | AD20: 0 | AE20: 0
... A25: hydrogen combined cycle | B25: 0 | C25: 0 | D25: 0 | E25: 0 | F25: 0 | G25: 0 | H25: 0 | I25: 0 | J25: 0 | K25: 0 | L25: 0 | M25: 0 | N25: 0 | O25: 0 | P25: 0 | Q25: 0 | R25: 0 | S25: 0 | T25: 0 | U25: 0 | V25: 0 | W25: 0 | X25: 0 | Y25: 0 | Z25: 0 | AA25: 0 | AB25: 0 | AC25: 0 | AD25: 0 | AE25: 0

Sheet CiDESCTY-commercial
A1: MW | B1: 2021 | C1: 2022 | D1: 2023 | E1: 2024 | F1: 2025 | G1: 2026 | H1: 2027 | I1: 2028 | J1: 2029 | K1: 2030 | L1: 2031 | M1: 2032 | N1: 2033 | O1: 2034 | P1: 2035 | Q1: 2036 | R1: 2037 | S1: 2038 | T1: 2039 | U1: 2040 | V1: 2041 | W1: 2042 | X1: 2043 | Y1: 2044 | Z1: 2045 | AA1: 2046 | AB1: 2047 | AC1: 2048 | AD1: 2049 | AE1: 2050
A2: hard coal | B2: 0 | C2: 0 | D2: 0 | E2: 0 | F2: 0 | G2: 0 | H2: 0 | I2: 0 | J2: 0 | K2: 0 | L2: 0 | M2: 0 | N2: 0 | O2: 0 | P2: 0 | Q2: 0 | R2: 0 | S2: 0 | T2: 0 | U2: 0 | V2: 0 | W2: 0 | X2: 0 | Y2: 0 | Z2: 0 | AA2: 0 | AB2: 0 | AC2: 0 | AD2: 0 | AE2: 0
A3: natural gas steam turbine | B3: 0 | C3: 0 | D3: 0 | E3: 0 | F3: 0 | G3: 0 | H3: 0 | I3: 0 | J3: 0 | K3: 0 | L3: 0 | M3: 0 | N3: 0 | O3: 0 | P3: 0 | Q3: 0 | R3: 0 | S3: 0 | T3: 0 | U3: 0 | V3: 0 | W3: 0 | X3: 0 | Y3: 0 | Z3: 0 | AA3: 0 | AB3: 0 | AC3: 0 | AD3: 0 | AE3: 0
A4: natural gas combined cycle | B4: 0 | C4: 0 | D4: 0 | E4: 0 | F4: 0 | G4: 0 | H4: 0 | I4: 0 | J4: 0 | K4: 0 | L4: 0 | M4: 0 | N4: 0 | O4: 0 | P4: 0 | Q4: 0 | R4: 0 | S4: 0 | T4: 0 | U4: 0 | V4: 0 | W4: 0 | X4: 0 | Y4: 0 | Z4: 0 | AA4: 0 | AB4: 0 | AC4: 0 | AD4: 0 | AE4: 0
A5: nuclear | B5: 0 | C5: 0 | D5: 0 | E5: 0 | F5: 0 | G5: 0 | H5: 0 | I5: 0 | J5: 0 | K5: 0 | L5: 0 | M5: 0 | N5: 0 | O5: 0 | P5: 0 | Q5: 0 | R5: 0 | S5: 0 | T5: 0 | U5: 0 | V5: 0 | W5: 0 | X5: 0 | Y5: 0 | Z5: 0 | AA5: 0 | AB5: 0 | AC5: 0 | AD5: 0 | AE5: 0
A6: hydro | B6: 0 | C6: 0 | D6: 0 | E6: 0 | F6: 0 | G6: 0 | H6: 0 | I6: 0 | J6: 0 | K6: 0 | L6: 0 | M6: 0 | N6: 0 | O6: 0 | P6: 0 | Q6: 0 | R6: 0 | S6: 0 | T6: 0 | U6: 0 | V6: 0 | W6: 0 | X6: 0 | Y6: 0 | Z6: 0 | AA6: 0 | AB6: 0 | AC6: 0 | AD6: 0 | AE6: 0
A7: onshore wind | B7: 0 | C7: 0 | D7: 0 | E7: 0 | F7: 0 | G7: 0 | H7: 0 | I7: 0 | J7: 0 | K7: 0 | L7: 0 | M7: 0 | N7: 0 | O7: 0 | P7: 0 | Q7: 0 | R7: 0 | S7: 0 | T7: 0 | U7: 0 | V7: 0 | W7: 0 | X7: 0 | Y7: 0 | Z7: 0 | AA7: 0 | AB7: 0 | AC7: 0 | AD7: 0 | AE7: 0
A8: solar PV | B8: =calcs!B26 -> 0 | C8: =calcs!C26 -> 0 | D8: =calcs!D26 -> 0 | E8: =calcs!E26 -> 0 | F8: =calcs!F26 -> 0 | G8: =calcs!G26 -> 0 | H8: =calcs!H26 -> 0 | I8: =calcs!I26 -> 0 | ... AE8: =calcs!AE26 -> 0
A9: solar thermal | B9: 0 | C9: 0 | D9: 0 | E9: 0 | F9: 0 | G9: 0 | H9: 0 | I9: 0 | J9: 0 | K9: 0 | L9: 0 | M9: 0 | N9: 0 | O9: 0 | P9: 0 | Q9: 0 | R9: 0 | S9: 0 | T9: 0 | U9: 0 | V9: 0 | W9: 0 | X9: 0 | Y9: 0 | Z9: 0 | AA9: 0 | AB9: 0 | AC9: 0 | AD9: 0 | AE9: 0
A10: biomass | B10: 0 | C10: 0 | D10: 0 | E10: 0 | F10: 0 | G10: 0 | H10: 0 | I10: 0 | J10: 0 | K10: 0 | L10: 0 | M10: 0 | N10: 0 | O10: 0 | P10: 0 | Q10: 0 | R10: 0 | S10: 0 | T10: 0 | U10: 0 | V10: 0 | W10: 0 | X10: 0 | Y10: 0 | Z10: 0 | AA10: 0 | AB10: 0 | AC10: 0 | AD10: 0 | AE10: 0
A11: geothermal | B11: 0 | C11: 0 | D11: 0 | E11: 0 | F11: 0 | G11: 0 | H11: 0 | I11: 0 | J11: 0 | K11: 0 | L11: 0 | M11: 0 | N11: 0 | O11: 0 | P11: 0 | Q11: 0 | R11: 0 | S11: 0 | T11: 0 | U11: 0 | V11: 0 | W11: 0 | X11: 0 | Y11: 0 | Z11: 0 | AA11: 0 | AB11: 0 | AC11: 0 | AD11: 0 | AE11: 0
A12: petroleum | B12: 0 | C12: 0 | D12: 0 | E12: 0 | F12: 0 | G12: 0 | H12: 0 | I12: 0 | J12: 0 | K12: 0 | L12: 0 | M12: 0 | N12: 0 | O12: 0 | P12: 0 | Q12: 0 | R12: 0 | S12: 0 | T12: 0 | U12: 0 | V12: 0 | W12: 0 | X12: 0 | Y12: 0 | Z12: 0 | AA12: 0 | AB12: 0 | AC12: 0 | AD12: 0 | AE12: 0
A13: natural gas peaker | B13: 0 | C13: 0 | D13: 0 | E13: 0 | F13: 0 | G13: 0 | H13: 0 | I13: 0 | J13: 0 | K13: 0 | L13: 0 | M13: 0 | N13: 0 | O13: 0 | P13: 0 | Q13: 0 | R13: 0 | S13: 0 | T13: 0 | U13: 0 | V13: 0 | W13: 0 | X13: 0 | Y13: 0 | Z13: 0 | AA13: 0 | AB13: 0 | AC13: 0 | AD13: 0 | AE13: 0
A14: lignite | B14: 0 | C14: 0 | D14: 0 | E14: 0 | F14: 0 | G14: 0 | H14: 0 | I14: 0 | J14: 0 | K14: 0 | L14: 0 | M14: 0 | N14: 0 | O14: 0 | P14: 0 | Q14: 0 | R14: 0 | S14: 0 | T14: 0 | U14: 0 | V14: 0 | W14: 0 | X14: 0 | Y14: 0 | Z14: 0 | AA14: 0 | AB14: 0 | AC14: 0 | AD14: 0 | AE14: 0
A15: offshore wind | B15: 0 | C15: 0 | D15: 0 | E15: 0 | F15: 0 | G15: 0 | H15: 0 | I15: 0 | J15: 0 | K15: 0 | L15: 0 | M15: 0 | N15: 0 | O15: 0 | P15: 0 | Q15: 0 | R15: 0 | S15: 0 | T15: 0 | U15: 0 | V15: 0 | W15: 0 | X15: 0 | Y15: 0 | Z15: 0 | AA15: 0 | AB15: 0 | AC15: 0 | AD15: 0 | AE15: 0
A16: crude oil | B16: 0 | C16: 0 | D16: 0 | E16: 0 | F16: 0 | G16: 0 | H16: 0 | I16: 0 | J16: 0 | K16: 0 | L16: 0 | M16: 0 | N16: 0 | O16: 0 | P16: 0 | Q16: 0 | R16: 0 | S16: 0 | T16: 0 | U16: 0 | V16: 0 | W16: 0 | X16: 0 | Y16: 0 | Z16: 0 | AA16: 0 | AB16: 0 | AC16: 0 | AD16: 0 | AE16: 0
A17: heavy or residual fuel oil | B17: 0 | C17: 0 | D17: 0 | E17: 0 | F17: 0 | G17: 0 | H17: 0 | I17: 0 | J17: 0 | K17: 0 | L17: 0 | M17: 0 | N17: 0 | O17: 0 | P17: 0 | Q17: 0 | R17: 0 | S17: 0 | T17: 0 | U17: 0 | V17: 0 | W17: 0 | X17: 0 | Y17: 0 | Z17: 0 | AA17: 0 | AB17: 0 | AC17: 0 | AD17: 0 | AE17: 0
A18: municipal solid waste | B18: 0 | C18: 0 | D18: 0 | E18: 0 | F18: 0 | G18: 0 | H18: 0 | I18: 0 | J18: 0 | K18: 0 | L18: 0 | M18: 0 | N18: 0 | O18: 0 | P18: 0 | Q18: 0 | R18: 0 | S18: 0 | T18: 0 | U18: 0 | V18: 0 | W18: 0 | X18: 0 | Y18: 0 | Z18: 0 | AA18: 0 | AB18: 0 | AC18: 0 | AD18: 0 | AE18: 0
A19: hard coal w CCS | B19: 0 | C19: 0 | D19: 0 | E19: 0 | F19: 0 | G19: 0 | H19: 0 | I19: 0 | J19: 0 | K19: 0 | L19: 0 | M19: 0 | N19: 0 | O19: 0 | P19: 0 | Q19: 0 | R19: 0 | S19: 0 | T19: 0 | U19: 0 | V19: 0 | W19: 0 | X19: 0 | Y19: 0 | Z19: 0 | AA19: 0 | AB19: 0 | AC19: 0 | AD19: 0 | AE19: 0
A20: natural gas combined cycle w CCS | B20: 0 | C20: 0 | D20: 0 | E20: 0 | F20: 0 | G20: 0 | H20: 0 | I20: 0 | J20: 0 | K20: 0 | L20: 0 | M20: 0 | N20: 0 | O20: 0 | P20: 0 | Q20: 0 | R20: 0 | S20: 0 | T20: 0 | U20: 0 | V20: 0 | W20: 0 | X20: 0 | Y20: 0 | Z20: 0 | AA20: 0 | AB20: 0 | AC20: 0 | AD20: 0 | AE20: 0
... A25: hydrogen combined cycle | B25: 0 | C25: 0 | D25: 0 | E25: 0 | F25: 0 | G25: 0 | H25: 0 | I25: 0 | J25: 0 | K25: 0 | L25: 0 | M25: 0 | N25: 0 | O25: 0 | P25: 0 | Q25: 0 | R25: 0 | S25: 0 | T25: 0 | U25: 0 | V25: 0 | W25: 0 | X25: 0 | Y25: 0 | Z25: 0 | AA25: 0 | AB25: 0 | AC25: 0 | AD25: 0 | AE25: 0
