Workbook

Sheet About
A1: BPCiObIC BAU Percent Change in Output by ISIC Code | B1: Nebraska | C1: 44810
A3: Source: | B3: Future Year Projected Changes in Output by ISIC Code
B4: U.S. EIA
B5: 2021
B6: Annual Energy Outlook 2021
B7: https://www.eia.gov/outlooks/aeo/tables_ref.php
B8: Table 23: Industrial Sector Macroeconomic Indicators
B10: U.S. Bureau of Labor Statistics
B11: 2020
B12: Industry Output and Employment
B13: https://www.bls.gov/emp/tables/industry-employment-and-output.htm
B14: Table 2.7: Output and Employment by Industry
B16: GDP Projection
B17: OECD
B18: 2018
B19: Quarterly National Accounts
B20: https://data.oecd.org/gdp/gdp-long-term-forecast.htm
B21: Real GDP long-term forecast
A23: Notes
A25: We need a set of scaling factors to convert the I/O variables that contain static data (for one historical year)
A26: to future time series data.
A28: We base these scaling factors on the projected change in output for each ISIC code, which is readily
A29: available disaggregated by ISIC code. It is crucial for these projections to be disaggregated by ISIC code,
A30: because we need to know how industries grow or shrink relative to one-another, not just how they
A31: grow or shrink overall to fit GDP growth.
A33: For the U.S., we use projections from the BLS and EIA AEO. The BLS has growth rates for all ISIC codes,
A34: but only out to 2029. The EIA has projections for only certain ISIC codes, but out to 2050.
A35: Our static I/O data largely comes from the OECD database and is for year 2015.
A37: We use EIA and BLS to find growth rates out to 2050 (see the "Growth Rates" tab). We smooth
A38: the transition around 2020 to avoid discontinuities.
... A60: output currency year in web-app/OCCF). Therefore, we use these conversion factors:
A62: 1.052913 | B62: 2012 dollars per 2010 dollar
A63: =10^6 -> 1000000 | B63: dollars per million dollars

Sheet BLS Table 2.7
A1: Table 2.7 Employment and Output by Industry
A2: Industry | B2: 2017 NAICS | C2: Employment | J2: Output
C3: Thousands of Jobs | F3: Change | H3: Compound Annual Rate of Change | J3: Billions of Chained 2012 Dollars | M3: Compound Annual Rate of Change
C4: 2009 | D4: 2019 | E4: 2029 | F4: 2009 - 2019 | G4: 2019 - 2029 | H4: 2009 - 2019 | I4: 2019 - 2029 | J4: 2009 | K4: 2019 | L4: 2029 | M4: 2009 - 2019 | N4: 2019 - 2029 | O4: Assigned ISIC Code
A5: Total(1)(2) | C5: 143036.4 | D5: 162795.6 | E5: 168834.7 | F5: 19759.2 | G5: 6039.1 | H5: 1.3 | I5: 0.4 | J5: 27293.3 | K5: 34049.9 | L5: 40867.6 | M5: 2.2 | N5: 1.8
A7: Nonagriculture wage and salary | B7: NA | C7: 132029.2 | D7: 151709.7 | E7: 158115.6 | F7: 19680.5 | G7: 6405.9 | H7: 1.4 | I7: 0.4 | J7: 26836.2 | K7: 33487.1 | L7: 40193.3 | M7: 2.2 | N7: 1.8
A8: Mining | B8: 21 | C8: 643.3 | D8: 684.6 | E8: 777.8 | F8: 41.3 | G8: 93.2 | H8: 0.6 | I8: 1.3 | J8: 485.8 | K8: 635.3 | L8: 835.5 | M8: 2.7 | N8: 2.8
A9: Oil and gas extraction | B9: 211 | C9: 159.8 | D9: 150.1 | E9: 129.7 | F9: -9.7 | G9: -20.4 | H9: -0.6 | I9: -1.4 | J9: 278.2 | K9: 474.3 | L9: 659.6 | M9: 5.5 | N9: 3.4 | O9: ISIC 06
A10: Mining, except oil and gas | B10: 212 | C10: 208.3 | D10: 191.4 | E10: 193.9 | F10: -16.9 | G10: 2.5 | H10: -0.8 | I10: 0.1 | J10: 124.6 | K10: 108.1 | L10: 114.2 | M10: -1.4 | N10: 0.6
A11: Coal mining | B11: 2121 | C11: 81.5 | D11: 51.9 | E11: 43.6 | F11: -29.6 | G11: -8.3 | H11: -4.4 | I11: -1.7 | J11: 50.9 | K11: 44.8 | L11: 43.8 | M11: -1.3 | N11: -0.2 | O11: ISIC 05
A12: Metal ore mining | B12: 2122 | C12: 34.8 | D12: 41.8 | E12: 48.6 | F12: 7 | G12: 6.8 | H12: 1.8 | I12: 1.5 | J12: 40.9 | K12: 36.2 | L12: 38 | M12: -1.2 | N12: 0.5 | O12: ISIC 07T08
A13: Nonmetallic mineral mining and quarrying | B13: 2123 | C13: 92 | D13: 97.7 | E13: 101.7 | F13: 5.7 | G13: 4 | H13: 0.6 | I13: 0.4 | J13: 33.4 | K13: 27.3 | L13: 32.2 | M13: -2 | N13: 1.6 | O13: ISIC 07T08
A14: Support activities for mining | B14: 213 | C14: 275.2 | D14: 343.1 | E14: 454.2 | F14: 67.9 | G14: 111.1 | H14: 2.2 | I14: 2.8 | J14: 83.5 | K14: 82.3 | L14: 109 | M14: -0.1 | N14: 2.9 | O14: ISIC 09
A15: Utilities | B15: 22 | C15: 560.1 | D15: 549 | E15: 506.7 | F15: -11.1 | G15: -42.3 | H15: -0.2 | I15: -0.8 | J15: 443.6 | K15: 458.6 | L15: 534.5 | M15: 0.3 | N15: 1.5
A16: Electric power generation, transmission and distribution | B16: 2211 | C16: 404.1 | D16: 385.5 | E16: 352 | F16: -18.6 | G16: -33.5 | H16: -0.5 | I16: -0.9 | J16: 340.5 | K16: 357 | L16: 422.3 | M16: 0.5 | N16: 1.7 | O16: ISIC 351
A17: Natural gas distribution | B17: 2212 | C17: 108.7 | D17: 110.3 | E17: 99 | F17: 1.6 | G17: -11.3 | H17: 0.1 | I17: -1.1 | J17: 88.7 | K17: 90.8 | L17: 98.8 | M17: 0.2 | N17: 0.8 | O17: ISIC 352T353
A18: Water, sewage and other systems | B18: 2213 | C18: 47.3 | D18: 53.2 | E18: 55.6 | F18: 5.9 | G18: 2.4 | H18: 1.2 | I18: 0.4 | J18: 13 | K18: 11.4 | L18: 12.8 | M18: -1.3 | N18: 1.1 | O18: ISIC 36T39
A19: Construction | B19: 23 | C19: 6016.5 | D19: 7492.2 | E19: 7792.4 | F19: 1475.7 | G19: 300.2 | H19: 2.2 | I19: 0.4 | J19: 1161.5 | K19: 1418.9 | L19: 1616.3 | M19: 2 | N19: 1.3 | O19: ISIC 41T43
A20: Manufacturing | B20: 31-33 | C20: 11847.9 | D20: 12839.5 | E20: 12394.7 | F20: 991.6 | G20: -444.8 | H20: 0.8 | I20: -0.4 | J20: 5261.6 | K20: 6384.1 | L20: 7434 | M20: 2 | N20: 1.5
A21: Food manufacturing | B21: 311 | C21: 1456.4 | D21: 1643.2 | E21: 1649.6 | F21: 186.8 | G21: 6.4 | H21: 1.2 | I21: 0 | J21: 736 | K21: 825 | L21: 972.1 | M21: 1.1 | N21: 1.7 | O21: ISIC 10T12
A22: Animal food manufacturing | B22: 3111 | C22: 51.8 | D22: 64 | E22: 74.8 | F22: 12.2 | G22: 10.8 | H22: 2.1 | I22: 1.6 | J22: 52.7 | K22: 65.7 | L22: 80.7 | M22: 2.2 | N22: 2.1
A23: Grain and oilseed milling | B23: 3112 | C23: 59.7 | D23: 60.6 | E23: 56.1 | F23: 0.9 | G23: -4.5 | H23: 0.1 | I23: -0.8 | J23: 95 | K23: 142.7 | L23: 178.5 | M23: 4.2 | N23: 2.3
A24: Sugar and confectionery product manufacturing | B24: 3113 | C24: 70.9 | D24: 78.8 | E24: 66.8 | F24: 7.9 | G24: -12 | H24: 1.1 | I24: -1.6 | J24: 33.5 | K24: 37.1 | L24: 38.6 | M24: 1 | N24: 0.4
A25: Fruit and vegetable preserving and specialty food manufacturing | B25: 3114 | C25: 172.3 | D25: 173.3 | E25: 158.7 | F25: 1 | G25: -14.6 | H25: 0.1 | I25: -0.9 | J25: 64.7 | K25: 66.6 | L25: 72.5 | M25: 0.3 | N25: 0.9
A26: Dairy product manufacturing | B26: 3115 | C26: 130.7 | D26: 155.6 | E26: 158.7 | F26: 24.9 | G26: 3.1 | H26: 1.8 | I26: 0.2 | J26: 116.8 | K26: 123.1 | L26: 149.4 | M26: 0.5 | N26: 2
A27: Animal slaughtering and processing | B27: 3116 | C27: 497.2 | D27: 531.4 | E27: 545.4 | F27: 34.2 | G27: 14 | H27: 0.7 | I27: 0.3 | J27: 213.2 | K27: 219.9 | L27: 257.9 | M27: 0.3 | N27: 1.6
A28: Seafood product preparation and packaging | B28: 3117 | C28: 38.1 | D28: 35.3 | E28: 29.3 | F28: -2.8 | G28: -6 | H28: -0.8 | I28: -1.8 | J28: 11.6 | K28: 10.9 | L28: 13 | M28: -0.6 | N28: 1.8
A29: Bakeries and tortilla manufacturing | B29: 3118 | C29: 273 | D29: 315.8 | E29: 303.1 | F29: 42.8 | G29: -12.7 | H29: 1.5 | I29: -0.4 | J29: 60.7 | K29: 66.3 | L29: 74.8 | M29: 0.9 | N29: 1.2
A30: Other food manufacturing | B30: 3119 | C30: 162.7 | D30: 228.4 | E30: 256.7 | F30: 65.7 | G30: 28.3 | H30: 3.5 | I30: 1.2 | J30: 88.4 | K30: 96.8 | L30: 115 | M30: 0.9 | N30: 1.7
A31: Beverage and tobacco product | B31: 312 | C31: 187.4 | D31: 285.8 | E31: 296.1 | F31: 98.4 | G31: 10.3 | H31: 4.3 | I31: 0.4 | J31: 167.3 | K31: 168.2 | L31: 181.3 | M31: 0.1 | N31: 0.8 | O31: ISIC 10T12
A32: Beverage manufacturing | B32: 3121 | C32: 168.7 | D32: 275 | E32: 289.4 | F32: 106.3 | G32: 14.4 | H32: 5 | I32: 0.5 | J32: 103.9 | K32: 121.8 | L32: 148.2 | M32: 1.6 | N32: 2
A33: Tobacco manufacturing | B33: 3122 | C33: 18.7 | D33: 11.3 | E33: 6.7 | F33: -7.4 | G33: -4.7 | H33: -4.9 | I33: -5.2 | J33: 63.7 | K33: 47.3 | L33: 38.3 | M33: -2.9 | N33: -2.1
A34: Textile mills and textile product mills | B34: 313,314 | C34: 250.1 | D34: 222 | E34: 198.3 | F34: -28.1 | G34: -23.7 | H34: -1.2 | I34: -1.1 | J34: 51.3 | K34: 52.8 | L34: 50.3 | M34: 0.3 | N34: -0.5 | O34: ISIC 13T15
A35: Apparel, leather and allied product manufacturing | B35: 315, 316 | C35: 196.5 | D35: 137.7 | E35: 94.2 | F35: -58.8 | G35: -43.5 | H35: -3.5 | I35: -3.7 | J35: 25.6 | K35: 19.1 | L35: 20.1 | M35: -2.8 | N35: 0.5 | O35: ISIC 13T15
A36: Wood product manufacturing | B36: 321 | C36: 360.2 | D36: 408.8 | E36: 382.3 | F36: 48.6 | G36: -26.5 | H36: 1.3 | I36: -0.7 | J36: 74.2 | K36: 94.1 | L36: 108.3 | M36: 2.4 | N36: 1.4 | O36: ISIC 16
A37: Sawmills and wood preservation | B37: 3211 | C37: 83.2 | D37: 92.3 | E37: 85.3 | F37: 9.1 | G37: -7 | H37: 1 | I37: -0.8 | J37: 21.4 | K37: 26 | L37: 30.5 | M37: 2 | N37: 1.6
A38: Veneer, plywood, and engineered wood product manufacturing | B38: 3212 | C38: 68.3 | D38: 82.1 | E38: 87 | F38: 13.8 | G38: 4.9 | H38: 1.9 | I38: 0.6 | J38: 17.6 | K38: 20.4 | L38: 23.8 | M38: 1.5 | N38: 1.6
A39: Other wood product manufacturing | B39: 3219 | C39: 208.7 | D39: 234.4 | E39: 210 | F39: 25.7 | G39: -24.4 | H39: 1.2 | I39: -1.1 | J39: 35.4 | K39: 47.9 | L39: 54.2 | M39: 3.1 | N39: 1.3
A40: Paper manufacturing | B40: 322 | C40: 407 | D40: 365.3 | E40: 340 | F40: -41.7 | G40: -25.3 | H40: -1.1 | I40: -0.7 | J40: 172.6 | K40: 176.6 | L40: 183 | M40: 0.2 | N40: 0.4 | O40: ISIC 17T18
A41: Pulp, paper, and paperboard mills | B41: 3221 | C41: 116.9 | D41: 96.4 | E41: 92.3 | F41: -20.5 | G41: -4.1 | H41: -1.9 | I41: -0.4 | J41: 79.4 | K41: 81.1 | L41: 84.4 | M41: 0.2 | N41: 0.4
A42: Converted paper product manufacturing | B42: 3222 | C42: 290.1 | D42: 268.9 | E42: 247.8 | F42: -21.2 | G42: -21.1 | H42: -0.8 | I42: -0.8 | J42: 93.2 | K42: 95.5 | L42: 98.6 | M42: 0.2 | N42: 0.3
A43: Printing and related support activities | B43: 323 | C43: 521.9 | D43: 424.6 | E43: 342.3 | F43: -97.3 | G43: -82.3 | H43: -2 | I43: -2.1 | J43: 86.1 | K43: 83.7 | L43: 89.9 | M43: -0.3 | N43: 0.7 | O43: ISIC 17T18
A44: Petroleum and coal products manufacturing | B44: 324 | C44: 115.3 | D44: 114.5 | E44: 109.1 | F44: -0.8 | G44: -5.4 | H44: -0.1 | I44: -0.5 | J44: 841 | K44: 899.8 | L44: 1132 | M44: 0.7 | N44: 2.3 | O44: ISIC 19
A45: Chemical manufacturing | B45: 325 | C45: 804.1 | D45: 849.9 | E45: 877 | F45: 45.8 | G45: 27.1 | H45: 0.6 | I45: 0.3 | J45: 743.8 | K45: 863.8 | L45: 1034.3 | M45: 1.5 | N45: 1.8
A46: Basic chemical manufacturing | B46: 3251 | C46: 145.3 | D46: 153 | E46: 160 | F46: 7.7 | G46: 7 | H46: 0.5 | I46: 0.4 | J46: 255.7 | K46: 331.5 | L46: 409.4 | M46: 2.6 | N46: 2.1 | O46: ISIC 20
A47: Resin, synthetic rubber, and artificial synthetic fibers and filaments manufacturing | B47: 3252 | C47: 92 | D47: 95.4 | E47: 94.2 | F47: 3.4 | G47: -1.2 | H47: 0.4 | I47: -0.1 | J47: 102.8 | K47: 116 | L47: 138.7 | M47: 1.2 | N47: 1.8 | O47: ISIC 20
A48: Pesticide, fertilizer, and other agricultural chemical manufacturing | B48: 3253 | C48: 36.5 | D48: 36.6 | E48: 34.7 | F48: 0.1 | G48: -1.9 | H48: 0 | I48: -0.5 | J48: 33.6 | K48: 53.6 | L48: 60.4 | M48: 4.8 | N48: 1.2 | O48: ISIC 20
A49: Pharmaceutical and medicine manufacturing | B49: 3254 | C49: 284.4 | D49: 305.9 | E49: 322.3 | F49: 21.5 | G49: 16.4 | H49: 0.7 | I49: 0.5 | J49: 201.4 | K49: 193.8 | L49: 232.3 | M49: -0.4 | N49: 1.8 | O49: ISIC 21
A50: Paint, coating, and adhesive manufacturing | B50: 3255 | C50: 57.3 | D50: 65.4 | E50: 69.4 | F50: 8.1 | G50: 4 | H50: 1.3 | I50: 0.6 | J50: 33.6 | K50: 38 | L50: 40.5 | M50: 1.2 | N50: 0.6 | O50: ISIC 20
A51: Soap, cleaning compound, and toilet preparation manufacturing | B51: 3256 | C51: 102.7 | D51: 110.2 | E51: 117 | F51: 7.5 | G51: 6.8 | H51: 0.7 | I51: 0.6 | J51: 75.3 | K51: 88.5 | L51: 110.8 | M51: 1.6 | N51: 2.3 | O51: ISIC 20
A52: Other chemical product and preparation manufacturing | B52: 3259 | C52: 85.9 | D52: 83.4 | E52: 79.3 | F52: -2.5 | G52: -4.1 | H52: -0.3 | I52: -0.5 | J52: 41.8 | K52: 47.3 | L52: 49.9 | M52: 1.2 | N52: 0.5 | O52: ISIC 20
A53: Plastics and rubber products manufacturing | B53: 326 | C53: 624.9 | D53: 737 | E53: 682.8 | F53: 112.1 | G53: -54.2 | H53: 1.7 | I53: -0.8 | J53: 188.9 | K53: 225.7 | L53: 259 | M53: 1.8 | N53: 1.4 | O53: ISIC 22
A54: Plastics product manufacturing | B54: 3261 | C54: 502.1 | D54: 599.1 | E54: 549.3 | F54: 97 | G54: -49.8 | H54: 1.8 | I54: -0.9 | J54: 150.4 | K54: 177.3 | L54: 203.1 | M54: 1.7 | N54: 1.4
A55: Rubber product manufacturing | B55: 3262 | C55: 122.8 | D55: 137.9 | E55: 133.5 | F55: 15.1 | G55: -4.4 | H55: 1.2 | I55: -0.3 | J55: 38.5 | K55: 48.5 | L55: 55.9 | M55: 2.4 | N55: 1.4
A56: Nonmetallic mineral product manufacturing | B56: 327 | C56: 394.3 | D56: 421.6 | E56: 347.9 | F56: 27.3 | G56: -73.7 | H56: 0.7 | I56: -1.9 | J56: 94 | K56: 120.6 | L56: 140.6 | M56: 2.5 | N56: 1.5
A57: Clay product and refractory manufacturing | B57: 3271 | C57: 43.6 | D57: 38.6 | E57: 29.2 | F57: -5 | G57: -9.4 | H57: -1.2 | I57: -2.8 | J57: 7.7 | K57: 10 | L57: 10.3 | M57: 2.6 | N57: 0.3 | O57: ISIC 239
A58: Glass and glass product manufacturing | B58: 3272 | C58: 83.8 | D58: 86.2 | E58: 79.3 | F58: 2.4 | G58: -6.9 | H58: 0.3 | I58: -0.8 | J58: 18.7 | K58: 28.3 | L58: 33.7 | M58: 4.3 | N58: 1.8 | O58: ISIC 231
A59: Cement and concrete product manufacturing | B59: 3273 | C59: 184.9 | D59: 199 | E59: 141.9 | F59: 14.1 | G59: -57.1 | H59: 0.7 | I59: -3.3 | J59: 42.5 | K59: 48.8 | L59: 57.3 | M59: 1.4 | N59: 1.6 | O59: ISIC 239
A60: Lime, gypsum and other nonmetallic mineral product manufacturing | B60: 3274, 3279 | C60: 82 | D60: 97.8 | E60: 97.5 | F60: 15.8 | G60: -0.3 | H60: 1.8 | I60: 0 | J60: 25 | K60: 33.6 | L60: 39.5 | M60: 3 | N60: 1.6 | O60: ISIC 239
A61: Primary metal manufacturing | B61: 331 | C61: 362.1 | D61: 385.1 | E61: 368.8 | F61: 23 | G61: -16.3 | H61: 0.6 | I61: -0.4 | J61: 203.4 | K61: 249.1 | L61: 269 | M61: 2 | N61: 0.8
A62: Iron and steel mills and ferroalloy manufacturing | B62: 3311 | C62: 85.3 | D62: 86.4 | E62: 79.3 | F62: 1.1 | G62: -7.1 | H62: 0.1 | I62: -0.8 | J62: 85.5 | K62: 102 | L62: 107.8 | M62: 1.8 | N62: 0.6 | O62: ISIC 241
A63: Steel product manufacturing from purchased steel | B63: 3312 | C63: 49.8 | D63: 57.6 | E63: 57.8 | F63: 7.8 | G63: 0.2 | H63: 1.5 | I63: 0 | J63: 17.9 | K63: 22.2 | L63: 25.2 | M63: 2.2 | N63: 1.3
A64: Alumina and aluminum production and processing | B64: 3313 | C64: 55.8 | D64: 59.8 | E64: 53.1 | F64: 4 | G64: -6.7 | H64: 0.7 | I64: -1.2 | J64: 29.4 | K64: 32 | L64: 29.3 | M64: 0.8 | N64: -0.9 | O64: ISIC 242
A65: Nonferrous metal (except aluminum) production and processing | B65: 3314 | C65: 58.2 | D65: 62 | E65: 59.5 | F65: 3.8 | G65: -2.5 | H65: 0.6 | I65: -0.4 | J65: 48 | K65: 61.8 | L65: 73.8 | M65: 2.6 | N65: 1.8 | O65: ISIC 242
A66: Foundries | B66: 3315 | C66: 113 | D66: 119.3 | E66: 119 | F66: 6.3 | G66: -0.3 | H66: 0.5 | I66: 0 | J66: 22.6 | K66: 31.2 | L66: 32.5 | M66: 3.3 | N66: 0.4
A67: Fabricated metal product manufacturing | B67: 332 | C67: 1311.8 | D67: 1491.6 | E67: 1446.2 | F67: 179.8 | G67: -45.4 | H67: 1.3 | I67: -0.3 | J67: 296.7 | K67: 385.7 | L67: 430.6 | M67: 2.7 | N67: 1.1 | O67: ISIC 25
A68: Forging and stamping | B68: 3321 | C68: 89 | D68: 101.1 | E68: 96.2 | F68: 12.1 | G68: -4.9 | H68: 1.3 | I68: -0.5 | J68: 28.4 | K68: 41.7 | L68: 46.3 | M68: 3.9 | N68: 1.1
A69: Cutlery and handtool manufacturing | B69: 3322 | C69: 42.1 | D69: 36.4 | E69: 34.5 | F69: -5.7 | G69: -1.9 | H69: -1.4 | I69: -0.5 | J69: 9.2 | K69: 11.1 | L69: 11.2 | M69: 1.9 | N69: 0.1
A70: Architectural and structural metals manufacturing | B70: 3323 | C70: 344.7 | D70: 400.5 | E70: 403.6 | F70: 55.8 | G70: 3.1 | H70: 1.5 | I70: 0.1 | J70: 74 | K70: 84.1 | L70: 96.4 | M70: 1.3 | N70: 1.4
A71: Boiler, tank, and shipping container manufacturing | B71: 3324 | C71: 88.6 | D71: 96.2 | E71: 95.2 | F71: 7.6 | G71: -1 | H71: 0.8 | I71: -0.1 | J71: 26.9 | K71: 39.3 | L71: 44 | M71: 3.9 | N71: 1.1
A72: Hardware manufacturing | B72: 3325 | C72: 24.3 | D72: 25.5 | E72: 23.9 | F72: 1.2 | G72: -1.6 | H72: 0.5 | I72: -0.7 | J72: 7.6 | K72: 7.8 | L72: 8.3 | M72: 0.2 | N72: 0.5
A73: Spring and wire product manufacturing | B73: 3326 | C73: 42.8 | D73: 43.5 | E73: 41 | F73: 0.7 | G73: -2.5 | H73: 0.2 | I73: -0.6 | J73: 7.4 | K73: 9.9 | L73: 10.4 | M73: 2.9 | N73: 0.5
A74: Machine shops; turned product; and screw, nut, and bolt manufacturing | B74: 3327 | C74: 309.1 | D74: 364.8 | E74: 377.6 | F74: 55.7 | G74: 12.8 | H74: 1.7 | I74: 0.3 | J74: 54.2 | K74: 78.5 | L74: 87.4 | M74: 3.8 | N74: 1.1
A75: Coating, engraving, heat treating, and allied activities | B75: 3328 | C75: 121 | D75: 142 | E75: 136.8 | F75: 21 | G75: -5.2 | H75: 1.6 | I75: -0.4 | J75: 23.3 | K75: 30.6 | L75: 32 | M75: 2.8 | N75: 0.4
A76: Other fabricated metal product manufacturing | B76: 3329 | C76: 250.2 | D76: 281.6 | E76: 237.4 | F76: 31.4 | G76: -44.2 | H76: 1.2 | I76: -1.7 | J76: 66 | K76: 83.2 | L76: 94.9 | M76: 2.3 | N76: 1.3
A77: Machinery manufacturing | B77: 333 | C77: 1028.7 | D77: 1126.1 | E77: 1112.3 | F77: 97.4 | G77: -13.8 | H77: 0.9 | I77: -0.1 | J77: 300 | K77: 385.3 | L77: 445.9 | M77: 2.5 | N77: 1.5 | O77: ISIC 28
A78: Agriculture, construction, and mining machinery manufacturing | B78: 3331 | C78: 213.7 | D78: 221 | E78: 218.7 | F78: 7.3 | G78: -2.3 | H78: 0.3 | I78: -0.1 | J78: 76.6 | K78: 109.9 | L78: 130.4 | M78: 3.7 | N78: 1.7
A79: Industrial machinery manufacturing | B79: 3332 | C79: 101.7 | D79: 118 | E79: 109.3 | F79: 16.3 | G79: -8.7 | H79: 1.5 | I79: -0.8 | J79: 29.6 | K79: 32.1 | L79: 37.5 | M79: 0.8 | N79: 1.6
A80: Commercial and service industry machinery manufacturing, including digital camera manufacturing | B80: 3333 | C80: 96 | D80: 94.4 | E80: 94.2 | F80: -1.6 | G80: -0.2 | H80: -0.2 | I80: 0 | J80: 22.3 | K80: 26.1 | L80: 30.5 | M80: 1.6 | N80: 1.6
A81: Ventilation, heating, air-conditioning, and commercial refrigeration equipment manufacturing | B81: 3334 | C81: 128.5 | D81: 137.8 | E81: 134.2 | F81: 9.3 | G81: -3.6 | H81: 0.7 | I81: -0.3 | J81: 34.7 | K81: 44.7 | L81: 50.1 | M81: 2.6 | N81: 1.2
A82: Metalworking machinery manufacturing | B82: 3335 | C82: 157.6 | D82: 179.7 | E82: 178.1 | F82: 22.1 | G82: -1.6 | H82: 1.3 | I82: -0.1 | J82: 23.7 | K82: 29.3 | L82: 31.4 | M82: 2.1 | N82: 0.7
A83: Engine, turbine, and power transmission equipment manufacturing | B83: 3336 | C83: 94.6 | D83: 99.6 | E83: 100.2 | F83: 5 | G83: 0.6 | H83: 0.5 | I83: 0.1 | J83: 36.9 | K83: 53.8 | L83: 62.4 | M83: 3.9 | N83: 1.5
A84: Other general purpose machinery manufacturing | B84: 3339 | C84: 236.6 | D84: 275.6 | E84: 277.7 | F84: 39 | G84: 2.1 | H84: 1.5 | I84: 0.1 | J84: 76.2 | K84: 89.7 | L84: 103.8 | M84: 1.6 | N84: 1.5
A85: Computer and electronic product manufacturing | B85: 334 | C85: 1136.9 | D85: 1080.5 | E85: 1062.1 | F85: -56.4 | G85: -18.4 | H85: -0.5 | I85: -0.2 | J85: 335.7 | K85: 404.1 | L85: 474.3 | M85: 1.9 | N85: 1.6 | O85: ISIC 26
A86: Computer and peripheral equipment manufacturing, excluding digital camera manufacturing | B86: 3341 | C86: 166.4 | D86: 163 | E86: 168.6 | F86: -3.4 | G86: 5.6 | H86: -0.2 | I86: 0.3 | J86: 44.5 | K86: 56 | L86: 72.9 | M86: 2.3 | N86: 2.7
A87: Communications equipment manufacturing | B87: 3342 | C87: 120.5 | D87: 83.5 | E87: 58 | F87: -37 | G87: -25.5 | H87: -3.6 | I87: -3.6 | J87: 57.7 | K87: 64.8 | L87: 81.5 | M87: 1.2 | N87: 2.3
A88: Audio and video equipment manufacturing | B88: 3343 | C88: 22.6 | D88: 20 | E88: 17.9 | F88: -2.6 | G88: -2.2 | H88: -1.2 | I88: -1.1 | J88: 7.7 | K88: 3.3 | L88: 3.8 | M88: -8 | N88: 1.4
A89: Semiconductor and other electronic component manufacturing | B89: 3344 | C89: 378.1 | D89: 377 | E89: 373.9 | F89: -1.1 | G89: -3.1 | H89: 0 | I89: -0.1 | J89: 91 | K89: 127.4 | L89: 129 | M89: 3.4 | N89: 0.1
A90: Navigational, measuring, electromedical, and control instruments manufacturing | B90: 3345 | C90: 421.6 | D90: 424.1 | E90: 431.4 | F90: 2.5 | G90: 7.3 | H90: 0.1 | I90: 0.2 | J90: 130.6 | K90: 151.7 | L90: 188.1 | M90: 1.5 | N90: 2.2
A91: Manufacturing and reproducing magnetic and optical media | B91: 3346 | C91: 27.7 | D91: 12.9 | E91: 12.4 | F91: -14.8 | G91: -0.5 | H91: -7.4 | I91: -0.4 | J91: 4 | K91: 4 | L91: 4.9 | M91: -0.2 | N91: 2.1
A92: Electrical equipment, appliance, and component manufacturing | B92: 335 | C92: 373.6 | D92: 405.1 | E92: 391.7 | F92: 31.5 | G92: -13.4 | H92: 0.8 | I92: -0.3 | J92: 113.9 | K92: 143 | L92: 158.4 | M92: 2.3 | N92: 1 | O92: ISIC 27
A93: Electric lighting equipment manufacturing | B93: 3351 | C93: 48.4 | D93: 46 | E93: 30.8 | F93: -2.4 | G93: -15.2 | H93: -0.5 | I93: -3.9 | J93: 11.8 | K93: 17.6 | L93: 17.8 | M93: 4 | N93: 0.2
A94: Household appliance manufacturing | B94: 3352 | C94: 59.7 | D94: 62.1 | E94: 60.5 | F94: 2.4 | G94: -1.6 | H94: 0.4 | I94: -0.3 | J94: 21 | K94: 23 | L94: 29 | M94: 0.9 | N94: 2.3
A95: Electrical equipment manufacturing | B95: 3353 | C95: 144.6 | D95: 146.9 | E95: 141.7 | F95: 2.3 | G95: -5.2 | H95: 0.2 | I95: -0.4 | J95: 35.5 | K95: 42.8 | L95: 48.8 | M95: 1.9 | N95: 1.3
A96: Other electrical equipment and component manufacturing | B96: 3359 | C96: 120.9 | D96: 150.1 | E96: 158.7 | F96: 29.2 | G96: 8.6 | H96: 2.2 | I96: 0.6 | J96: 45.6 | K96: 59.6 | L96: 62.8 | M96: 2.7 | N96: 0.5
A97: Transportation equipment manufacturing | B97: 336 | C97: 1348 | D97: 1734.2 | E97: 1715.1 | F97: 386.2 | G97: -19.1 | H97: 2.6 | I97: -0.1 | J97: 624.7 | K97: 1043.4 | L97: 1250.1 | M97: 5.3 | N97: 1.8
A98: Motor vehicle manufacturing | B98: 3361 | C98: 146.4 | D98: 237.2 | E98: 248.9 | F98: 90.8 | G98: 11.7 | H98: 4.9 | I98: 0.5 | J98: 178.6 | K98: 354.7 | L98: 452 | M98: 7.1 | N98: 2.5 | O98: ISIC 29
A99: Motor vehicle body and trailer manufacturing | B99: 3362 | C99: 104.1 | D99: 165.7 | E99: 155.4 | F99: 61.6 | G99: -10.3 | H99: 4.8 | I99: -0.6 | J99: 24.3 | K99: 45.1 | L99: 51.2 | M99: 6.4 | N99: 1.3 | O99: ISIC 29
A100: Motor vehicle parts manufacturing | B100: 3363 | C100: 413.7 | D100: 595.6 | E100: 609.9 | F100: 181.9 | G100: 14.3 | H100: 3.7 | I100: 0.2 | J100: 153.1 | K100: 324.5 | L100: 360 | M100: 7.8 | N100: 1 | O100: ISIC 29
A101: Aerospace product and parts manufacturing | B101: 3364 | C101: 492.2 | D101: 534.3 | E101: 530.5 | F101: 42.1 | G101: -3.8 | H101: 0.8 | I101: -0.1 | J101: 200 | K101: 243.6 | L101: 300.1 | M101: 2 | N101: 2.1 | O101: ISIC 30
...

Sheet AEO22 Table 23 Raw
A1: Table 23. Industrial Sector Macroeconomic Indicators
A2: https://www.eia.gov/outlooks/aeo/data/browser/#/?id=34-AEO2022&cases=lowmacro&sid=lowmacro-d011222a.10-114-AEO2022&sourcekey=0
A3: Thu Jul 14 2022 09:36:04 GMT-0400 (Eastern Daylight Time)
A4: Source: U.S. Energy Information Administration
B5: full name | C5: api key | D5: units | E5: 2020 | F5: 2021 | G5: 2022 | H5: 2023 | I5: 2024 | J5: 2025 | K5: 2026 | L5: 2027 | M5: 2028 | N5: 2029 | O5: 2030 | P5: 2031 | Q5: 2032 | R5: 2033 | S5: 2034 | T5: 2035 | U5: 2036 | V5: 2037 | W5: 2038 | X5: 2039 | Y5: 2040 | Z5: 2041 | AA5: 2042 | AB5: 2043 | AC5: 2044 | AD5: 2045 | AE5: 2046 | AF5: 2047 | AG5: 2048 | AH5: 2049 | AI5: 2050 | AJ5: Growth (2021-2050)
A6: Pinned Series
A7: Gross Domestic Product (billion 2012 dollars) | B7: Industrial Macroeconomic: Gross Domestic Product: Low economic growth | C7: 34-AEO2022.2.lowmacro-d011222a | D7: billion 2012 $ | F7: 19287.709 | G7: 19760.287 | H7: 20221.789 | I7: 20729.912 | J7: 21174.707 | K7: 21588.189 | L7: 21943.693 | M7: 22341.447 | N7: 22750.484 | O7: 23184.713 | P7: 23604.686 | Q7: 24072.311 | R7: 24531.643 | S7: 24923.117 | T7: 25304.564 | U7: 25681.664 | V7: 26080.943 | W7: 26491.984 | X7: 26940.375 | Y7: 27407.311 | Z7: 27842.832 | AA7: 28292.699 | AB7: 28753.758 | AC7: 29223.881 | AD7: 29725.133 | AE7: 30268.092 | AF7: 30800.547 | AG7: 31310.893 | AH7: 31858.811 | AI7: 32479.828 | AJ7: 0.018
A8: Nonfarm Employment (millions) | B8: Industrial Macroeconomic: Employment, Nonfarm: Low economic growth | C8: 34-AEO2022.4.lowmacro-d011222a | D8: millions | F8: 147.7354 | G8: 148.57752 | H8: 151.11475 | I8: 152.88181 | J8: 153.79976 | K8: 154.22972 | L8: 154.40425 | M8: 154.76437 | N8: 155.22359 | O8: 155.96846 | P8: 156.832 | Q8: 157.90752 | R8: 158.97392 | S8: 159.59203 | T8: 160.03293 | U8: 160.57657 | V8: 161.2149 | W8: 161.87415 | X8: 162.66341 | Y8: 163.58928 | Z8: 164.25658 | AA8: 164.99643 | AB8: 165.65443 | AC8: 166.30429 | AD8: 167.18918 | AE8: 168.24129 | AF8: 169.3114 | AG8: 170.22873 | AH8: 171.10382 | AI8: 172.19258 | AJ8: 0.005
A9: Value of Shipments (billion 2012 dollars) | C9: 34-AEO2022.6.
A10: Nonmanufacturing Sector | C10: 34-AEO2022.8.
A11: Agriculture/Forestry/Fishing/Hunting | B11: Industrial Macroeconomic: Nonmanufacturing: Agriculture/Forestry/Fishing/Hunting: Low economic growth | C11: 34-AEO2022.9.lowmacro-d011222a | D11: billion 2012 $ | F11: 545.77948 | G11: 551.13959 | H11: 558.31287 | I11: 562.69605 | J11: 566.57074 | K11: 570.89679 | L11: 574.01483 | M11: 575.9624 | N11: 577.76355 | O11: 580.1933 | P11: 582.15271 | Q11: 584.11523 | R11: 586.77783 | S11: 588.97095 | T11: 590.37793 | U11: 592.02594 | V11: 593.7182 | W11: 595.4386 | X11: 597.58563 | Y11: 599.5246 | Z11: 601.00348 | AA11: 602.93469 | AB11: 605.20435 | AC11: 606.87677 | AD11: 608.2262 | AE11: 609.61218 | AF11: 610.96179 | AG11: 613.48285 | AH11: 616.40076 | AI11: 619.95856 | AJ11: 0.004
A12: Mining | B12: Industrial Macroeconomic: Nonmanufacturing: Mining: Low economic growth | C12: 34-AEO2022.10.lowmacro-d011222a | D12: billion 2012 $ | F12: 688.52893 | G12: 684.08637 | H12: 694.49341 | I12: 699.258 | J12: 707.49762 | K12: 709.31628 | L12: 706.40289 | M12: 714.3717 | N12: 716.31879 | O12: 716.49072 | P12: 716.28943 | Q12: 717.49902 | R12: 719.57141 | S12: 714.41589 | T12: 711.59711 | U12: 710.25049 | V12: 708.04541 | W12: 708.72888 | X12: 711.70679 | Y12: 715.08569 | Z12: 715.07507 | AA12: 714.95477 | AB12: 716.31177 | AC12: 718.23499 | AD12: 723.43109 | AE12: 730.20544 | AF12: 733.34979 | AG12: 732.5788 | AH12: 733.87647 | AI12: 740.8158 | AJ12: 0.003
A13: Construction | B13: Industrial Macroeconomic: Nonmanufacturing: Construction: Low economic growth | C13: 34-AEO2022.14.lowmacro-d011222a | D13: billion 2012 $ | F13: 1448.7993 | G13: 1344.485 | H13: 1310.302 | I13: 1321.8097 | J13: 1327.167 | K13: 1326.1383 | L13: 1323.1837 | M13: 1333.3877 | N13: 1346.314 | O13: 1355.6226 | P13: 1366.4568 | Q13: 1408.8607 | R13: 1446.3237 | S13: 1453.333 | T13: 1458.3185 | U13: 1465.8523 | V13: 1487.8778 | W13: 1517.0828 | X13: 1549.0847 | Y13: 1575.9659 | Z13: 1597.8958 | AA13: 1619.077 | AB13: 1638.0723 | AC13: 1654.094 | AD13: 1668.0818 | AE13: 1686.9323 | AF13: 1705.474 | AG13: 1723.6689 | AH13: 1747.0677 | AI13: 1773.0322 | AJ13: 0.007
A14: Manufacturing Sector | C14: 34-AEO2022.16.
A15: Food Products | B15: Industrial Macroeconomic: Manufacturing: Food Products: Low economic growth | C15: 34-AEO2022.17.lowmacro-d011222a | D15: billion 2012 $ | F15: 951.64435 | G15: 968.1377 | H15: 969.99872 | I15: 974.52918 | J15: 980.4978 | K15: 986.57391 | L15: 993.19183 | M15: 999.98218 | N15: 1005.9415 | O15: 1011.705 | P15: 1017.6683 | Q15: 1023.1825 | R15: 1027.4513 | S15: 1031.0057 | T15: 1034.582 | U15: 1038.2365 | V15: 1041.2788 | W15: 1044.4017 | X15: 1048.0537 | Y15: 1051.4875 | Z15: 1054.3187 | AA15: 1057.787 | AB15: 1061.2743 | AC15: 1064.614 | AD15: 1067.8418 | AE15: 1070.3273 | AF15: 1072.7795 | AG15: 1076.1705 | AH15: 1080.1558 | AI15: 1085.246 | AJ15: 0.005
A16: Beverages and Tobacco Products | B16: Industrial Macroeconomic: Manufacturing: Beverages and Tobacco Products: Low economic growth | C16: 34-AEO2022.22.lowmacro-d011222a | D16: billion 2012 $ | F16: 150.72591 | G16: 146.54585 | H16: 143.67477 | I16: 141.76296 | J16: 140.0777 | K16: 138.97025 | L16: 138.3801 | M16: 138.23795 | N16: 138.09813 | O16: 138.0123 | P16: 137.9388 | Q16: 138.4285 | R16: 138.21021 | S16: 137.88588 | T16: 137.82194 | U16: 137.79297 | V16: 137.77362 | W16: 137.74858 | X16: 137.72784 | Y16: 137.70062 | Z16: 137.56975 | AA16: 137.47768 | AB16: 137.70128 | AC16: 138.13934 | AD16: 138.44804 | AE16: 138.82553 | AF16: 139.34398 | AG16: 140.1508 | AH16: 141.08917 | AI16: 142.09233 | AJ16: -0.002
A17: Textile Mills and Products | B17: Industrial Macroeconomic: Manufacturing: Textile Mills and Products: Low economic growth | C17: 34-AEO2022.23.lowmacro-d011222a | D17: billion 2012 $ | F17: 66.721695 | G17: 67.566856 | H17: 68.538239 | I17: 68.599648 | J17: 68.280685 | K17: 67.760956 | L17: 67.162628 | M17: 66.83532 | N17: 66.431587 | O17: 66.230736 | P17: 66.14399 | Q17: 65.868149 | R17: 65.687248 | S17: 65.428848 | T17: 65.043457 | U17: 64.738548 | V17: 64.548325 | W17: 64.244316 | X17: 64.002434 | Y17: 63.834743 | Z17: 63.52803 | AA17: 63.220856 | AB17: 63.055897 | AC17: 62.821331 | AD17: 62.599751 | AE17: 62.48616 | AF17: 62.27063 | AG17: 61.878735 | AH17: 61.477104 | AI17: 61.008438 | AJ17: -0.003
A18: Wood Products | B18: Industrial Macroeconomic: Manufacturing: Wood Products: Low economic growth | C18: 34-AEO2022.24.lowmacro-d011222a | D18: billion 2012 $ | F18: 109.86588 | G18: 103.38457 | H18: 97.434769 | I18: 97.533112 | J18: 98.415634 | K18: 94.94783 | L18: 90.944565 | M18: 87.395416 | N18: 85.54142 | O18: 85.198097 | P18: 83.265373 | Q18: 82.290382 | R18: 81.322891 | S18: 80.92173 | T18: 80.755692 | U18: 81.03405 | V18: 80.751335 | W18: 80.406364 | X18: 80.710457 | Y18: 81.227318 | Z18: 82.065094 | AA18: 83.27713 | AB18: 84.180367 | AC18: 83.959122 | AD18: 83.839531 | AE18: 84.499367 | AF18: 85.330498 | AG18: 86.038773 | AH18: 87.018608 | AI18: 89.788933 | AJ18: -0.007
A19: Furniture and Related Products | B19: Industrial Macroeconomic: Manufacturing: Furniture and Related Products: Low economic growth | C19: 34-AEO2022.25.lowmacro-d011222a | D19: billion 2012 $ | F19: 73.106606 | G19: 74.492615 | H19: 74.920853 | I19: 74.970245 | J19: 75.073692 | K19: 74.8134 | L19: 73.955078 | M19: 73.365143 | N19: 72.822044 | O19: 73.29007 | P19: 73.36235 | Q19: 73.803444 | R19: 74.245209 | S19: 74.740074 | T19: 75.565613 | U19: 76.517937 | V19: 77.588066 | W19: 78.300179 | X19: 79.465652 | Y19: 80.69249 | Z19: 81.847878 | AA19: 83.49836 | AB19: 85.137604 | AC19: 85.927277 | AD19: 86.475052 | AE19: 88.442543 | AF19: 90.415634 | AG19: 91.291969 | AH19: 92.91996 | AI19: 95.786667 | AJ19: 0.009
A20: Paper Products | B20: Industrial Macroeconomic: Manufacturing: Paper Products: Low economic growth | C20: 34-AEO2022.26.lowmacro-d011222a | D20: billion 2012 $ | F20: 172.22682 | G20: 173.27202 | H20: 172.6449 | I20: 171.37058 | J20: 169.47244 | K20: 167.81551 | L20: 166.21905 | M20: 164.84427 | N20: 163.43594 | O20: 161.91228 | P20: 160.28799 | Q20: 158.89955 | R20: 157.27025 | S20: 155.54358 | T20: 154.1387 | U20: 152.74083 | V20: 151.28488 | W20: 149.95772 | X20: 148.82761 | Y20: 147.4711 | Z20: 146.1517 | AA20: 145.10872 | AB20: 144.08342 | AC20: 142.386 | AD20: 141.10953 | AE20: 140.48241 | AF20: 139.86592 | AG20: 139.51621 | AH20: 137.74025 | AI20: 137.07678 | AJ20: -0.008
A21: Printing | B21: Industrial Macroeconomic: Manufacturing: Printing: Low economic growth | C21: 34-AEO2022.30.lowmacro-d011222a | D21: billion 2012 $ | F21: 82.234703 | G21: 81.187164 | H21: 79.630684 | I21: 77.586235 | J21: 75.565125 | K21: 73.57209 | L21: 71.851616 | M21: 70.612923 | N21: 69.551025 | O21: 68.676834 | P21: 67.632065 | Q21: 67.00843 | R21: 66.476471 | S21: 65.723656 | T21: 64.944397 | U21: 63.884346 | V21: 62.556236 | W21: 61.694462 | X21: 61.072052 | Y21: 61.092018 | Z21: 61.034531 | AA21: 60.722279 | AB21: 61.370449 | AC21: 60.406033 | AD21: 59.911457 | AE21: 58.687168 | AF21: 57.077961 | AG21: 55.920696 | AH21: 55.103806 | AI21: 53.869823 | AJ21: -0.014
A22: Chemical Manufacturing | B22: Industrial Macroeconomic: Manufacturing: Chemical Manufacturing: Low economic growth | C22: 34-AEO2022.31.lowmacro-d011222a | D22: billion 2012 $ | F22: 980.72162 | G22: 940.86902 | H22: 930.38812 | I22: 926.09253 | J22: 934.00262 | K22: 943.36395 | L22: 951.80042 | M22: 959.39624 | N22: 964.21442 | O22: 970.38867 | P22: 979.80133 | Q22: 994.3761 | R22: 1006.7592 | S22: 1016.3872 | T22: 1027.3154 | U22: 1039.3499 | V22: 1052.8604 | W22: 1066.6614 | X22: 1080.9395 | Y22: 1093.8854 | Z22: 1108.3926 | AA22: 1126.677 | AB22: 1146.8215 | AC22: 1162.175 | AD22: 1178.572 | AE22: 1203.0021 | AF22: 1224.2114 | AG22: 1238.2368 | AH22: 1257.2178 | AI22: 1282.0889 | AJ22: 0.009
A23: Bulk Chemicals | B23: Industrial Macroeconomic: Manufacturing: Chemicals: Bulk Chemicals: Low economic growth | C23: 34-AEO2022.32.lowmacro-d011222a | D23: billion 2012 $ | F23: 463.10675 | G23: 455.29825 | H23: 451.30203 | I23: 448.81549 | J23: 456.10266 | K23: 463.94165 | L23: 470.07739 | M23: 475.59738 | N23: 478.43301 | O23: 482.5159 | P23: 488.89401 | Q23: 499.06354 | R23: 506.06686 | S23: 510.52136 | T23: 515.73773 | U23: 521.2262 | V23: 527.0581 | W23: 532.28247 | X23: 537.46704 | Y23: 541.01819 | Z23: 545.26508 | AA23: 550.62842 | AB23: 556.98749 | AC23: 558.42749 | AD23: 560.82269 | AE23: 569.84582 | AF23: 574.25354 | AG23: 571.66547 | AH23: 573.69122 | AI23: 583.27954 | AJ23: 0.008
A24: Inorganic | B24: Industrial Macroeconomic: Manufacturing: Chemicals: Bulk Chemicals: Inorganic: Low economic growth | C24: 34-AEO2022.33.lowmacro-d011222a | D24: billion 2012 $ | F24: 53.850636 | G24: 51.550568 | H24: 49.438751 | I24: 48.350109 | J24: 47.734375 | K24: 47.503693 | L24: 47.458179 | M24: 47.77747 | N24: 47.768639 | O24: 47.684147 | P24: 47.559883 | Q24: 47.722786 | R24: 47.588608 | S24: 47.195621 | T24: 46.945366 | U24: 46.787834 | V24: 46.789524 | W24: 46.814411 | X24: 46.820007 | Y24: 46.556324 | Z24: 46.370941 | AA24: 46.241123 | AB24: 46.037731 | AC24: 45.256706 | AD24: 44.760391 | AE24: 44.776981 | AF24: 44.703194 | AG24: 43.526035 | AH24: 42.594841 | AI24: 42.479103 | AJ24: -0.008
A25: Organic | B25: Industrial Macroeconomic: Manufacturing: Chemicals: Bulk Chemicals: Organic: Low economic growth | C25: 34-AEO2022.34.lowmacro-d011222a | D25: billion 2012 $ | F25: 234.04575 | G25: 225.48904 | H25: 227.23129 | I25: 229.23759 | J25: 233.21202 | K25: 235.84613 | L25: 238.11675 | M25: 240.73488 | N25: 243.95473 | O25: 247.65332 | P25: 251.37535 | Q25: 256.15503 | R25: 259.93643 | S25: 264.31485 | T25: 268.79715 | U25: 273.12537 | V25: 277.17215 | W25: 280.96246 | X25: 284.30344 | Y25: 287.328 | Z25: 291.57227 | AA25: 296.06671 | AB25: 300.46002 | AC25: 301.39941 | AD25: 302.66382 | AE25: 308.00751 | AF25: 310.79541 | AG25: 309.99149 | AH25: 311.87802 | AI25: 317.72769 | AJ25: 0.011
A26: Resin | B26: Synthetic Rubber | C26: and Fibers | D26: Industrial Macroeconomic: Manufacturing: Chemicals: Bulk Chemicals: Resin, Synthetic Rubber, and Fibers: Low economic growth | E26: 34-AEO2022.36.lowmacro-d011222a | F26: 130.70677 | G26: 135.51041 | H26: 131.55824 | I26: 128.28755 | J26: 132.05852 | K26: 137.17943 | L26: 140.60777 | M26: 142.44058 | N26: 141.51822 | O26: 141.52049 | P26: 143.9295 | Q26: 148.53035 | R26: 151.4269 | S26: 151.70508 | T26: 152.396 | U26: 153.5166 | V26: 155.09947 | W26: 156.34813 | X26: 158.01975 | Y26: 158.76155 | Z26: 158.86943 | AA26: 159.73305 | AB26: 161.8185 | AC26: 163.12077 | AD26: 164.79562 | AE26: 168.07678 | AF26: 169.5834 | AG26: 169.12285 | AH26: 170.11667 | AI26: 173.62245 | AJ26: 0.01
A27: Agricultural Chemicals | B27: Industrial Macroeconomic: Manufacturing: Chemicals: Bulk Chemicals: Agricultural Chemicals: Low economic growth | C27: 34-AEO2022.37.lowmacro-d011222a | D27: billion 2012 $ | F27: 44.50359 | G27: 42.748219 | H27: 43.073761 | I27: 42.940258 | J27: 43.097713 | K27: 43.412411 | L27: 43.894714 | M27: 44.644444 | N27: 45.191433 | O27: 45.65794 | P27: 46.029278 | Q27: 46.65538 | R27: 47.114948 | S27: 47.305813 | T27: 47.59919 | U27: 47.796402 | V27: 47.996956 | W27: 48.157459 | X27: 48.323879 | Y27: 48.372288 | Z27: 48.45245 | AA27: 48.587543 | AB27: 48.671253 | AC27: 48.650597 | AD27: 48.602818 | AE27: 48.984562 | AF27: 49.171539 | AG27: 49.025089 | AH27: 49.101685 | AI27: 49.450348 | AJ27: 0.004
A28: Other Chemical Products | B28: Industrial Macroeconomic: Manufacturing: Chemicals: Other Chemical Products: Low economic growth | C28: 34-AEO2022.38.lowmacro-d011222a | D28: billion 2012 $ | F28: 517.61487 | G28: 485.57077 | H28: 479.08609 | I28: 477.27707 | J28: 477.89996 | K28: 479.4223 | L28: 481.72305 | M28: 483.79889 | N28: 485.7814 | O28: 487.87274 | P28: 490.90732 | Q28: 495.31259 | R28: 500.69232 | S28: 505.86581 | T28: 511.57764 | U28: 518.12372 | V28: 525.80219 | W28: 534.37884 | X28: 543.47247 | Y28: 552.86719 | Z28: 563.12744 | AA28: 576.04864 | AB28: 589.83411 | AC28: 603.74756 | AD28: 617.74927 | AE28: 633.15625 | AF28: 649.95789 | AG28: 666.57135 | AH28: 683.52649 | AI28: 698.80933 | AJ28: 0.01
A29: Petroleum and Coal Products | B29: Industrial Macroeconomic: Manufacturing: Petroleum and Coal Products: Low economic growth | C29: 34-AEO2022.43.lowmacro-d011222a | D29: billion 2012 $ | F29: 789.06366 | G29: 885.51178 | H29: 899.4964 | I29: 897.32391 | J29: 897.97327 | K29: 896.10211 | L29: 892.39954 | M29: 890.51331 | N29: 887.01245 | O29: 884.10364 | P29: 883.01489 | Q29: 884.73651 | R29: 884.38123 | S29: 882.0946 | T29: 879.74872 | U29: 878.12824 | V29: 877.94244 | W29: 877.26892 | X29: 878.56305 | Y29: 878.48267 | Z29: 879.24432 | AA29: 881.4317 | AB29: 883.83002 | AC29: 884.55798 | AD29: 886.77826 | AE29: 890.43878 | AF29: 892.92889 | AG29: 893.51227 | AH29: 896.77118 | AI29: 904.23969 | AJ29: 0.005
A30: Petroleum Refineries | B30: Industrial Macroeconomic: Manufacturing: Petroleum and Coal: Petroleum Refineries: Low economic growth | C30: 34-AEO2022.44.lowmacro-d011222a | D30: billion 2012 $ | F30: 746.87048 | G30: 840.716 | H30: 850.76227 | I30: 846.17731 | J30: 846.14966 | K30: 844.26404 | L30: 840.59943 | M30: 838.8761 | N30: 835.64575 | O30: 832.79443 | P30: 831.82013 | Q30: 833.64276 | R30: 833.2926 | S30: 831.01508 | T30: 828.73273 | U30: 827.11176 | V30: 826.83716 | W30: 826.18012 | X30: 827.33057 | Y30: 827.06683 | Z30: 827.62585 | AA30: 829.53912 | AB30: 831.72736 | AC30: 832.18103 | AD30: 834.06146 | AE30: 837.30823 | AF30: 839.42822 | AG30: 839.74255 | AH30: 842.51312 | AI30: 849.40979 | AJ30: 0.004
A31: Other Petroleum and Coal Products | B31: Industrial Macroeconomic: Manufacturing: Petroleum and Coal: Other Petroleum & Coal Products: Low economic growth | C31: 34-AEO2022.45.lowmacro-d011222a | D31: billion 2012 $ | F31: 42.193161 | G31: 44.795792 | H31: 48.734158 | I31: 51.146606 | J31: 51.823608 | K31: 51.838081 | L31: 51.800133 | M31: 51.637184 | N31: 51.366695 | O31: 51.309204 | P31: 51.194752 | Q31: 51.093731 | R31: 51.088634 | S31: 51.079502 | T31: 51.015999 | U31: 51.016506 | V31: 51.105297 | W31: 51.088779 | X31: 51.232498 | Y31: 51.415825 | Z31: 51.618454 | AA31: 51.89257 | AB31: 52.102638 | AC31: 52.376976 | AD31: 52.716824 | AE31: 53.130543 | AF31: 53.500679 | AG31: 53.769714 | AH31: 54.258045 | AI31: 54.829876 | AJ31: 0.009
A32: Plastics and Rubber Products | B32: Industrial Macroeconomic: Manufacturing: Plastics and Rubber Products: Low economic growth | C32: 34-AEO2022.46.lowmacro-d011222a | D32: billion 2012 $ | F32: 245.4554 | G32: 241.79295 | H32: 238.33037 | I32: 239.35245 | J32: 241.29742 | K32: 243.38844 | L32: 246.60761 | M32: 251.6187 | N32: 255.54027 | O32: 259.35934 | P32: 262.99316 | Q32: 267.15747 | R32: 270.87466 | S32: 273.07782 | T32: 276.69217 | U32: 280.75842 | V32: 285.36069 | W32: 289.78723 | X32: 294.53464 | Y32: 299.19794 | Z32: 303.74289 | AA32: 308.89786 | AB32: 315.15469 | AC32: 320.66641 | AD32: 326.10001 | AE32: 333.03391 | AF32: 339.61481 | AG32: 345.44083 | AH32: 351.487 | AI32: 359.67404 | AJ32: 0.013
A33: Stone | B33: Clay | C33: and Glass Products | D33: Industrial Macroeconomic: Manufacturing: Stone, Clay, and Glass Products: Low economic growth | E33: 34-AEO2022.47.lowmacro-d011222a | F33: 113.22774 | G33: 109.10921 | H33: 106.69244 | I33: 107.43405 | J33: 108.52844 | K33: 109.18559 | L33: 109.47917 | M33: 109.89218 | N33: 110.35785 | O33: 111.35317 | P33: 112.26262 | Q33: 113.35408 | R33: 114.38032 | S33: 114.70245 | T33: 115.58392 | U33: 116.3244 | V33: 117.12651 | W33: 117.76143 | X33: 118.411 | Y33: 119.15473 | Z33: 120.05633 | AA33: 120.6676 | AB33: 120.67708 | AC33: 121.01808 | AD33: 121.5524 | AE33: 122.32906 | AF33: 123.00944 | AG33: 122.92292 | AH33: 122.63182 | AI33: 122.74751 | AJ33: 0.003
A34: Glass and Glass Products | B34: Industrial Macroeconomic: Manufacturing: Stone, Clay, and Glass: Glass and Glass Products: Low economic growth | C34: 34-AEO2022.48.lowmacro-d011222a | D34: billion 2012 $ | F34: 23.465088 | G34: 21.78306 | H34: 21.384214 | I34: 20.878117 | J34: 20.782543 | K34: 20.692644 | L34: 20.512907 | M34: 20.323284 | N34: 20.166574 | O34: 20.228386 | P34: 20.307383 | Q34: 20.425203 | R34: 20.49914 | S34: 20.438978 | T34: 20.404791 | U34: 20.316797 | V34: 20.171747 | W34: 20.004017 | X34: 19.919577 | Y34: 19.699514 | Z34: 19.535419 | AA34: 19.386906 | AB34: 19.26335 | AC34: 19.142691 | AD34: 18.977442 | AE34: 18.848768 | AF34: 18.691172 | AG34: 18.550406 | AH34: 18.279713 | AI34: 18.123037 | AJ34: -0.009
A35: Cement and Lime | B35: Industrial Macroeconomic: Manufacturing: Stone, Clay, and Glass: Cement and Lime: Low economic growth | C35: 34-AEO2022.50.lowmacro-d011222a | D35: billion 2012 $ | F35: 13.972248 | G35: 14.70841 | H35: 14.789883 | I35: 15.090622 | J35: 15.311079 | K35: 15.412535 | L35: 15.460963 | M35: 15.52693 | N35: 15.640759 | O35: 15.860228 | P35: 16.10014 | Q35: 16.290489 | R35: 16.472929 | S35: 16.664034 | T35: 16.89053 | U35: 17.055897 | V35: 17.196074 | W35: 17.328506 | X35: 17.456821 | Y35: 17.659683 | Z35: 17.887959 | AA35: 18.065277 | AB35: 18.146942 | AC35: 18.263258 | AD35: 18.386185 | AE35: 18.506489 | AF35: 18.638 | AG35: 18.651054 | AH35: 18.658253 | AI35: 18.717762 | AJ35: 0.01
A36: Other Nonmetallic Mineral Products | B36: Industrial Macroeconomic: Manufacturing: Stone, Clay, and Glass: Other Nonmetallic Mineral Products: Low economic growth | C36: 34-AEO2022.53.lowmacro-d011222a | D36: billion 2012 $ | F36: 75.790398 | G36: 72.617737 | H36: 70.518349 | I36: 71.465309 | J36: 72.434814 | K36: 73.080406 | L36: 73.505302 | M36: 74.041969 | N36: 74.550514 | O36: 75.264557 | P36: 75.855095 | Q36: 76.63839 | R36: 77.408257 | S36: 77.599434 | T36: 78.288597 | U36: 78.951706 | V36: 79.75869 | W36: 80.428902 | X36: 81.034607 | Y36: 81.795532 | Z36: 82.63295 | AA36: 83.215416 | AB36: 83.266785 | AC36: 83.612137 | AD36: 84.188766 | AE36: 84.973801 | AF36: 85.680267 | AG36: 85.721458 | AH36: 85.693855 | AI36: 85.906715 | AJ36: 0.004
A37: Primary Metals Industry | B37: Industrial Macroeconomic: Manufacturing: Primary Metals Industry: Low economic growth | C37: 34-AEO2022.54.lowmacro-d011222a | D37: billion 2012 $ | F37: 240.15085 | G37: 248.90256 | H37: 250.07703 | I37: 249.02979 | J37: 250.30414 | K37: 250.60803 | L37: 250.12616 | M37: 250.00717 | N37: 249.85892 | O37: 249.90987 | P37: 249.19882 | Q37: 249.03748 | R37: 248.40512 | S37: 247.97603 | T37: 248.2272 | U37: 248.2901 | V37: 248.27737 | W37: 248.48131 | X37: 248.10503 | Y37: 247.7168 | Z37: 248.85091 | AA37: 250.90131 | AB37: 253.09219 | AC37: 253.60751 | AD37: 254.59634 | AE37: 257.39395 | AF37: 259.41773 | AG37: 258.65225 | AH37: 258.38315 | AI37: 260.98474 | AJ37: 0.003
A38: Iron and Steel Mills and Products | B38: Industrial Macroeconomic: Manufacturing: Primary Metals: Iron and Steel Mills and Products: Low economic growth | C38: 34-AEO2022.55.lowmacro-d011222a | D38: billion 2012 $ | F38: 125.35865 | G38: 127.9127 | H38: 128.28152 | I38: 127.14848 | J38: 128.20995 | K38: 127.60918 | L38: 126.0716 | M38: 124.35245 | N38: 123.02968 | O38: 122.10035 | P38: 120.69582 | Q38: 119.79025 | R38: 118.34252 | S38: 117.34465 | T38: 116.88985 | U38: 116.50053 | V38: 115.87187 | W38: 115.07552 | X38: 113.55775 | Y38: 112.11298 | Z38: 112.0481 | AA38: 112.7039 | AB38: 113.54688 | AC38: 112.8486 | AD38: 112.08395 | AE38: 112.8539 | AF38: 112.86078 | AG38: 110.48788 | AH38: 108.78362 | AI38: 109.414 | AJ38: -0.005
A39: Alumina and Aluminum Products | B39: Industrial Macroeconomic: Manufacturing: Primary Metals: Alumina and Aluminum Products: Low economic growth | C39: 34-AEO2022.56.lowmacro-d011222a | D39: billion 2012 $ | F39: 37.984837 | G39: 40.76638 | H39: 41.336983 | I39: 41.340252 | J39: 41.685944 | K39: 42.266392 | L39: 42.752811 | M39: 43.178772 | N39: 43.57325 | O39: 43.938221 | P39: 44.238689 | Q39: 44.402592 | R39: 44.571877 | S39: 44.748257 | T39: 44.868229 | U39: 44.736099 | V39: 44.609898 | W39: 44.769489 | X39: 44.712196 | Y39: 44.451584 | Z39: 44.670883 | AA39: 45.104656 | AB39: 45.442837 | AC39: 45.543003 | AD39: 45.942951 | AE39: 46.439526 | AF39: 46.926342 | AG39: 47.142418 | AH39: 47.268768 | AI39: 47.882832 | AJ39: 0.008
A40: Other Primary Metal Products | B40: Industrial Macroeconomic: Manufacturing: Primary Metals: Other Primary Metal Products: Low economic growth | C40: 34-AEO2022.57.lowmacro-d011222a | D40: billion 2012 $ | F40: 76.807365 | G40: 80.223488 | H40: 80.458534 | I40: 80.541054 | J40: 80.408257 | K40: 80.732468 | L40: 81.301743 | M40: 82.475945 | N40: 83.255989 | O40: 83.871292 | P40: 84.26432 | Q40: 84.844643 | R40: 85.49073 | S40: 85.883118 | T40: 86.469139 | U40: 87.053467 | V40: 87.795616 | W40: 88.636292 | X40: 89.835083 | Y40: 91.152229 | Z40: 92.131912 | AA40: 93.092735 | AB40: 94.102486 | AC40: 95.215919 | AD40: 96.569435 | AE40: 98.100525 | AF40: 99.630608 | AG40: 101.02195 | AH40: 102.33075 | AI40: 103.68793 | AJ40: 0.01
A41: Fabricated Metal Products | B41: Industrial Macroeconomic: Manufacturing: Fabricated Metal Products: Low economic growth | C41: 34-AEO2022.58.lowmacro-d011222a | D41: billion 2012 $ | F41: 356.37753 | G41: 359.29523 | H41: 363.27826 | I41: 368.16574 | J41: 371.49912 | K41: 372.5903 | L41: 372.03076 | M41: 371.24576 | N41: 370.73941 | O41: 372.00726 | P41: 373.46173 | Q41: 376.92716 | R41: 379.46411 | S41: 381.31366 | T41: 384.96924 | U41: 389.30478 | V41: 394.42783 | W41: 398.19241 | X41: 402.32666 | Y41: 404.35208 | Z41: 404.87933 | AA41: 408.22418 | AB41: 412.78311 | AC41: 414.81549 | AD41: 416.70447 | AE41: 421.12729 | AF41: 424.59088 | AG41: 422.18838 | AH41: 420.16357 | AI41: 423.55368 | AJ41: 0.006
A42: Machinery | B42: Industrial Macroeconomic: Manufacturing: Machinery: Low economic growth | C42: 34-AEO2022.59.lowmacro-d011222a | D42: billion 2012 $ | F42: 388.79587 | G42: 398.37433 | H42: 399.22537 | I42: 401.57873 | J42: 405.31845 | K42: 408.47577 | L42: 413.05301 | M42: 419.55804 | N42: 425.84226 | O42: 432.07843 | P42: 438.23566 | Q42: 445.50433 | R42: 452.63754 | S42: 458.25269 | T42: 465.47064 | U42: 473.26666 | V42: 480.79089 | W42: 486.65778 | X42: 492.95572 | Y42: 499.28601 | Z42: 504.48224 | AA42: 510.45432 | AB42: 517.14227 | AC42: 522.06903 | AD42: 526.67352 | AE42: 535.09979 | AF42: 542.12152 | AG42: 547.38361 | AH42: 553.39325 | AI42: 562.37976 | AJ42: 0.013
A43: Computers and Electronics | B43: Industrial Macroeconomic: Manufacturing: Computers and Electronics: Low economic growth | C43: 34-AEO2022.60.lowmacro-d011222a | D43: billion 2012 $ | F43: 481.07022 | G43: 505.31369 | H43: 525.62903 | I43: 533.49408 | J43: 539.71503 | K43: 545.90918 | L43: 553.06506 | M43: 565.90131 | N43: 575.21942 | O43: 582.54346 | P43: 590.87946 | Q43: 600.48511 | R43: 610.7312 | S43: 619.27539 | T43: 629.14563 | U43: 639.70923 | V43: 652.65076 | W43: 667.27393 | X43: 682.90515 | Y43: 699.01855 | Z43: 714.75574 | AA43: 731.39124 | AB43: 748.01068 | AC43: 765.94458 | AD43: 784.43158 | AE43: 803.51324 | AF43: 823.01654 | AG43: 845.07056 | AH43: 869.23822 | AI43: 891.82745 | AJ43: 0.022
A44: Transportation Equipment | B44: Industrial Macroeconomic: Manufacturing: Transportation Equipment: Low economic growth | C44: 34-AEO2022.61.lowmacro-d011222a | D44: billion 2012 $ | F44: 1097.1733 | G44: 1186.0754 | H44: 1256.5553 | I44: 1230.3678 | J44: 1211.1823 | K44: 1197.546 | L44: 1182.4027 | M44: 1180.8767 | N44: 1171.392 | O44: 1167.7052 | P44: 1169.613 | Q44: 1178.7113 | R44: 1188.4805 | S44: 1195.6718 | T44: 1206.9403 | U44: 1219.6143 | V44: 1230.877 | W44: 1242.949 | X44: 1256.4797 | Y44: 1272.7285 | Z44: 1292.1147 | AA44: 1311.7543 | AB44: 1334.0293 | AC44: 1351.8857 | AD44: 1374.7927 | AE44: 1404.347 | AF44: 1429.564 | AG44: 1443.489 | AH44: 1457.2767 | AI44: 1477.3979 | AJ44: 0.01
A45: Electrical Equipment | B45: Industrial Macroeconomic: Manufacturing: Electrical Equipment: Low economic growth | C45: 34-AEO2022.62.lowmacro-d011222a | D45: billion 2012 $ | F45: 133.00749 | G45: 137.61655 | H45: 140.91475 | I45: 142.85202 | J45: 143.6158 | K45: 144.11873 | L45: 144.58192 | M45: 145.72432 | N45: 146.6942 | O45: 147.99382 | P45: 147.95579 | Q45: 149.27063 | R45: 151.78803 | S45: 154.34442 | T45: 157.2585 | U45: 160.44098 | V45: 164.25591 | W45: 168.6109 | X45: 173.6132 | Y45: 178.56233 | Z45: 183.50467 | AA45: 188.88182 | AB45: 194.57617 | AC45: 200.2644 | AD45: 206.51587 | AE45: 213.24478 | AF45: 219.98364 | AG45: 227.37213 | AH45: 235.17171 | AI45: 242.98387 | AJ45: 0.021
... A47: Total Industrial Value of Shipments | B47: Industrial Macroeconomic: Total Industrial Value of Shipments: Low economic growth | C47: 34-AEO2022.65.lowmacro-d011222a | D47: billion 2012 $ | F47: 9275.0264 | G47: 9366.1943 | H47: 9440.3613 | I47: 9447.7051 | J47: 9475.5957 | K47: 9489.0049 | L47: 9491.3828 | M47: 9543.9258 | N47: 9576.7686 | O47: 9616.2188 | P47: 9663.5879 | Q47: 9768.1211 | R47: 9863.7695 | S47: 9907.1172 | T47: 9963.7617 | U47: 10030.242 | V47: 10114.481 | W47: 10208.514 | X47: 10316.464 | Y47: 10417.968 | Z47: 10513.542 | AA47: 10622.887 | AB47: 10740.371 | AC47: 10833.379 | AD47: 10935.759 | AE47: 11074.145 | AF47: 11196.312 | AG47: 11286.252 | AH47: 11395.392 | AI47: 11547.006 | AJ47: 0.008

Sheet AEO22 Table 23
C1: ref2021.d113020a | D1: 2020 | E1: 2021 | F1: 2022 | G1: 2023 | H1: 2024 | I1: 2025 | J1: 2026 | K1: 2027 | L1: 2028 | M1: 2029 | N1: 2030 | O1: 2031 | P1: 2032 | Q1: 2033 | R1: 2034 | S1: 2035 | T1: 2036 | U1: 2037 | V1: 2038 | W1: 2039 | X1: 2040 | Y1: 2041 | Z1: 2042 | AA1: 2043 | AB1: 2044 | AC1: 2045 | AD1: 2046 | AE1: 2047 | AF1: 2048 | AG1: 2049 | AH1: 2050
D3: Report | E3: Annual Energy Outlook 2021
D4: Scenario | E4: ref2021 | H4: Reference case
D5: Datekey | E5: d113020a
D6: Release Date | F6: January 2021
A10: ISM000 | C10: 23. Industrial Sector Macroeconomic Indicators | AI10: Compound
AI11: Growth
AI12: 2020-2050
B13: Assigned ISIC Code | C13: Indicators | D13: 2020 | E13: 2021 | F13: 2022 | G13: 2023 | H13: 2024 | I13: 2025 | J13: 2026 | K13: 2027 | L13: 2028 | M13: 2029 | N13: 2030 | O13: 2031 | P13: 2032 | Q13: 2033 | R13: 2034 | S13: 2035 | T13: 2036 | U13: 2037 | V13: 2038 | W13: 2039 | X13: 2040 | Y13: 2041 | Z13: 2042 | AA13: 2043 | AB13: 2044 | AC13: 2045 | AD13: 2046 | AE13: 2047 | AF13: 2048 | AG13: 2049 | AH13: 2050 | AI13: (percent)
A15: ISM000:ba_GDP(billionm_ | C15: Gross Domestic Product (billion 2012 dollars) | D15: 18171.387 | E15: ='AEO22 Table 23 Raw'!F7 -> 19287.709 | F15: ='AEO22 Table 23 Raw'!G7 -> 19760.287 | G15: ='AEO22 Table 23 Raw'!H7 -> 20221.789 | H15: ='AEO22 Table 23 Raw'!I7 -> 20729.912 | I15: ='AEO22 Table 23 Raw'!J7 -> 21174.707 | J15: ='AEO22 Table 23 Raw'!K7 -> 21588.189 | K15: ='AEO22 Table 23 Raw'!L7 -> 21943.693 | L15: ='AEO22 Table 23 Raw'!M7 -> 22341.447 | ... AI15: ='AEO22 Table 23 Raw'!AJ7 -> 0.018
A17: ISM000:ca_NonfarmEmploy | C17: Nonfarm Employment (millions) | D17: 141.52545 | E17: ='AEO22 Table 23 Raw'!F8 -> 147.7354 | F17: ='AEO22 Table 23 Raw'!G8 -> 148.57752 | G17: ='AEO22 Table 23 Raw'!H8 -> 151.11475 | H17: ='AEO22 Table 23 Raw'!I8 -> 152.88181 | I17: ='AEO22 Table 23 Raw'!J8 -> 153.79976 | J17: ='AEO22 Table 23 Raw'!K8 -> 154.22972 | K17: ='AEO22 Table 23 Raw'!L8 -> 154.40425 | L17: ='AEO22 Table 23 Raw'!M8 -> 154.76437 | ... AI17: ='AEO22 Table 23 Raw'!AJ8 -> 0.005
C19: Value of Shipments (billion 2012 dollars)
C21: Nonmanufacturing Sector
A22: ISM000:ea_Agricultural | B22: ISIC 01T03 | C22: Agriculture/Forestry/Fishing/Hunting | D22: 498.04193 | E22: ='AEO22 Table 23 Raw'!F11 -> 545.77948 | F22: ='AEO22 Table 23 Raw'!G11 -> 551.13959 | G22: ='AEO22 Table 23 Raw'!H11 -> 558.31287 | H22: ='AEO22 Table 23 Raw'!I11 -> 562.69605 | I22: ='AEO22 Table 23 Raw'!J11 -> 566.57074 | J22: ='AEO22 Table 23 Raw'!K11 -> 570.89679 | K22: ='AEO22 Table 23 Raw'!L11 -> 574.01483 | L22: ='AEO22 Table 23 Raw'!M11 -> 575.9624 | ... AI22: ='AEO22 Table 23 Raw'!AJ11 -> 0.004
A23: ISM000:ea_Mining | B23: ISIC 05, ISIC 06, ISIC 07T08 | C23: Mining | D23: 717.90631 | E23: ='AEO22 Table 23 Raw'!F12 -> 688.52893 | F23: ='AEO22 Table 23 Raw'!G12 -> 684.08637 | G23: ='AEO22 Table 23 Raw'!H12 -> 694.49341 | H23: ='AEO22 Table 23 Raw'!I12 -> 699.258 | I23: ='AEO22 Table 23 Raw'!J12 -> 707.49762 | J23: ='AEO22 Table 23 Raw'!K12 -> 709.31628 | K23: ='AEO22 Table 23 Raw'!L12 -> 706.40289 | L23: ='AEO22 Table 23 Raw'!M12 -> 714.3717 | ... AI23: ='AEO22 Table 23 Raw'!AJ12 -> 0.003
A24: ISM000:ea_Construction | B24: ISIC 41T43 | C24: Construction | D24: 1319.283 | E24: ='AEO22 Table 23 Raw'!F13 -> 1448.7993 | F24: ='AEO22 Table 23 Raw'!G13 -> 1344.485 | G24: ='AEO22 Table 23 Raw'!H13 -> 1310.302 | H24: ='AEO22 Table 23 Raw'!I13 -> 1321.8097 | I24: ='AEO22 Table 23 Raw'!J13 -> 1327.167 | J24: ='AEO22 Table 23 Raw'!K13 -> 1326.1383 | K24: ='AEO22 Table 23 Raw'!L13 -> 1323.1837 | L24: ='AEO22 Table 23 Raw'!M13 -> 1333.3877 | ... AI24: ='AEO22 Table 23 Raw'!AJ13 -> 0.007
C26: Manufacturing Sector
A27: ISM000:fa_FoodandKindre | B27: ISIC 10T12 | C27: Food Products | D27: 892.20709 | E27: ='AEO22 Table 23 Raw'!F15 -> 951.64435 | F27: ='AEO22 Table 23 Raw'!G15 -> 968.1377 | G27: ='AEO22 Table 23 Raw'!H15 -> 969.99872 | H27: ='AEO22 Table 23 Raw'!I15 -> 974.52918 | I27: ='AEO22 Table 23 Raw'!J15 -> 980.4978 | J27: ='AEO22 Table 23 Raw'!K15 -> 986.57391 | K27: ='AEO22 Table 23 Raw'!L15 -> 993.19183 | L27: ='AEO22 Table 23 Raw'!M15 -> 999.98218 | ... AI27: ='AEO22 Table 23 Raw'!AJ15 -> 0.005
A28: ISM000:fa_BeveragesandT | B28: ISIC 10T12 | C28: Beverages and Tobacco Products | D28: 150.3951 | E28: ='AEO22 Table 23 Raw'!F16 -> 150.72591 | F28: ='AEO22 Table 23 Raw'!G16 -> 146.54585 | G28: ='AEO22 Table 23 Raw'!H16 -> 143.67477 | H28: ='AEO22 Table 23 Raw'!I16 -> 141.76296 | I28: ='AEO22 Table 23 Raw'!J16 -> 140.0777 | J28: ='AEO22 Table 23 Raw'!K16 -> 138.97025 | K28: ='AEO22 Table 23 Raw'!L16 -> 138.3801 | L28: ='AEO22 Table 23 Raw'!M16 -> 138.23795 | ... AI28: ='AEO22 Table 23 Raw'!AJ16 -> -0.002
A29: ISM000:fa_TextileMillPr | B29: ISIC 13T15 | C29: Textile Mills and Products | D29: 63.119968 | E29: ='AEO22 Table 23 Raw'!F17 -> 66.721695 | F29: ='AEO22 Table 23 Raw'!G17 -> 67.566856 | G29: ='AEO22 Table 23 Raw'!H17 -> 68.538239 | H29: ='AEO22 Table 23 Raw'!I17 -> 68.599648 | I29: ='AEO22 Table 23 Raw'!J17 -> 68.280685 | J29: ='AEO22 Table 23 Raw'!K17 -> 67.760956 | K29: ='AEO22 Table 23 Raw'!L17 -> 67.162628 | L29: ='AEO22 Table 23 Raw'!M17 -> 66.83532 | ... AI29: ='AEO22 Table 23 Raw'!AJ17 -> -0.003
A30: ISM000:fa_LumberandWood | B30: ISIC 16 | C30: Wood Products | D30: 91.311569 | E30: ='AEO22 Table 23 Raw'!F18 -> 109.86588 | F30: ='AEO22 Table 23 Raw'!G18 -> 103.38457 | G30: ='AEO22 Table 23 Raw'!H18 -> 97.434769 | H30: ='AEO22 Table 23 Raw'!I18 -> 97.533112 | I30: ='AEO22 Table 23 Raw'!J18 -> 98.415634 | J30: ='AEO22 Table 23 Raw'!K18 -> 94.94783 | K30: ='AEO22 Table 23 Raw'!L18 -> 90.944565 | L30: ='AEO22 Table 23 Raw'!M18 -> 87.395416 | ... AI30: ='AEO22 Table 23 Raw'!AJ18 -> -0.007
A31: ISM000:fa_FurnitureandF | B31: ISIC 31T33 | C31: Furniture and Related Products | D31: 63.518311 | E31: ='AEO22 Table 23 Raw'!F19 -> 73.106606 | F31: ='AEO22 Table 23 Raw'!G19 -> 74.492615 | G31: ='AEO22 Table 23 Raw'!H19 -> 74.920853 | H31: ='AEO22 Table 23 Raw'!I19 -> 74.970245 | I31: ='AEO22 Table 23 Raw'!J19 -> 75.073692 | J31: ='AEO22 Table 23 Raw'!K19 -> 74.8134 | K31: ='AEO22 Table 23 Raw'!L19 -> 73.955078 | L31: ='AEO22 Table 23 Raw'!M19 -> 73.365143 | ... AI31: ='AEO22 Table 23 Raw'!AJ19 -> 0.009
A32: ISM000:fa_PaperandAllie | B32: ISIC 17T18 | C32: Paper Products | D32: 168.2229 | E32: ='AEO22 Table 23 Raw'!F20 -> 172.22682 | F32: ='AEO22 Table 23 Raw'!G20 -> 173.27202 | G32: ='AEO22 Table 23 Raw'!H20 -> 172.6449 | H32: ='AEO22 Table 23 Raw'!I20 -> 171.37058 | I32: ='AEO22 Table 23 Raw'!J20 -> 169.47244 | J32: ='AEO22 Table 23 Raw'!K20 -> 167.81551 | K32: ='AEO22 Table 23 Raw'!L20 -> 166.21905 | L32: ='AEO22 Table 23 Raw'!M20 -> 164.84427 | ... AI32: ='AEO22 Table 23 Raw'!AJ20 -> -0.008
A33: ISM000:fa_PrintingandPu | B33: ISIC 17T18 | C33: Printing | D33: 62.247051 | E33: ='AEO22 Table 23 Raw'!F21 -> 82.234703 | F33: ='AEO22 Table 23 Raw'!G21 -> 81.187164 | G33: ='AEO22 Table 23 Raw'!H21 -> 79.630684 | H33: ='AEO22 Table 23 Raw'!I21 -> 77.586235 | I33: ='AEO22 Table 23 Raw'!J21 -> 75.565125 | J33: ='AEO22 Table 23 Raw'!K21 -> 73.57209 | K33: ='AEO22 Table 23 Raw'!L21 -> 71.851616 | L33: ='AEO22 Table 23 Raw'!M21 -> 70.612923 | ... AI33: ='AEO22 Table 23 Raw'!AJ21 -> -0.014
A34: ISM000:fa_ChemicalandAl | B34: ISIC 20 | C34: Chemical Manufacturing | D34: 801.99793 | E34: ='AEO22 Table 23 Raw'!F22 -> 980.72162 | F34: ='AEO22 Table 23 Raw'!G22 -> 940.86902 | G34: ='AEO22 Table 23 Raw'!H22 -> 930.38812 | H34: ='AEO22 Table 23 Raw'!I22 -> 926.09253 | I34: ='AEO22 Table 23 Raw'!J22 -> 934.00262 | J34: ='AEO22 Table 23 Raw'!K22 -> 943.36395 | K34: ='AEO22 Table 23 Raw'!L22 -> 951.80042 | L34: ='AEO22 Table 23 Raw'!M22 -> 959.39624 | ... AI34: ='AEO22 Table 23 Raw'!AJ22 -> 0.009
A35: ISM000:fa_BulkChemicals | C35: Bulk Chemicals | D35: 425.08127 | E35: ='AEO22 Table 23 Raw'!F23 -> 463.10675 | F35: ='AEO22 Table 23 Raw'!G23 -> 455.29825 | G35: ='AEO22 Table 23 Raw'!H23 -> 451.30203 | H35: ='AEO22 Table 23 Raw'!I23 -> 448.81549 | I35: ='AEO22 Table 23 Raw'!J23 -> 456.10266 | J35: ='AEO22 Table 23 Raw'!K23 -> 463.94165 | K35: ='AEO22 Table 23 Raw'!L23 -> 470.07739 | L35: ='AEO22 Table 23 Raw'!M23 -> 475.59738 | ... AI35: ='AEO22 Table 23 Raw'!AJ23 -> 0.008
A36: ISM000:fa_Inorganic | C36: Inorganic | D36: 41.68821 | E36: ='AEO22 Table 23 Raw'!F24 -> 53.850636 | F36: ='AEO22 Table 23 Raw'!G24 -> 51.550568 | G36: ='AEO22 Table 23 Raw'!H24 -> 49.438751 | H36: ='AEO22 Table 23 Raw'!I24 -> 48.350109 | I36: ='AEO22 Table 23 Raw'!J24 -> 47.734375 | J36: ='AEO22 Table 23 Raw'!K24 -> 47.503693 | K36: ='AEO22 Table 23 Raw'!L24 -> 47.458179 | L36: ='AEO22 Table 23 Raw'!M24 -> 47.77747 | ... AI36: ='AEO22 Table 23 Raw'!AJ24 -> -0.008
A37: ISM000:fa_Organic | C37: Organic | D37: 225.51531 | E37: ='AEO22 Table 23 Raw'!F25 -> 234.04575 | F37: ='AEO22 Table 23 Raw'!G25 -> 225.48904 | G37: ='AEO22 Table 23 Raw'!H25 -> 227.23129 | H37: ='AEO22 Table 23 Raw'!I25 -> 229.23759 | I37: ='AEO22 Table 23 Raw'!J25 -> 233.21202 | J37: ='AEO22 Table 23 Raw'!K25 -> 235.84613 | K37: ='AEO22 Table 23 Raw'!L25 -> 238.11675 | L37: ='AEO22 Table 23 Raw'!M25 -> 240.73488 | ... AI37: ='AEO22 Table 23 Raw'!AJ25 -> 0.011
A38: ISM000:fa_Resins | C38: Resin, Synthetic Rubber, and Fibers | D38: 105.9968 | E38: ='AEO22 Table 23 Raw'!F26 -> 130.70677 | F38: ='AEO22 Table 23 Raw'!G26 -> 135.51041 | G38: ='AEO22 Table 23 Raw'!H26 -> 131.55824 | H38: ='AEO22 Table 23 Raw'!I26 -> 128.28755 | I38: ='AEO22 Table 23 Raw'!J26 -> 132.05852 | J38: ='AEO22 Table 23 Raw'!K26 -> 137.17943 | K38: ='AEO22 Table 23 Raw'!L26 -> 140.60777 | L38: ='AEO22 Table 23 Raw'!M26 -> 142.44058 | ... AI38: ='AEO22 Table 23 Raw'!AJ26 -> 0.01
A39: ISM000:fa_AgriculturalC | C39: Agricultural Chemicals | D39: 51.880939 | E39: ='AEO22 Table 23 Raw'!F27 -> 44.50359 | F39: ='AEO22 Table 23 Raw'!G27 -> 42.748219 | G39: ='AEO22 Table 23 Raw'!H27 -> 43.073761 | H39: ='AEO22 Table 23 Raw'!I27 -> 42.940258 | I39: ='AEO22 Table 23 Raw'!J27 -> 43.097713 | J39: ='AEO22 Table 23 Raw'!K27 -> 43.412411 | K39: ='AEO22 Table 23 Raw'!L27 -> 43.894714 | L39: ='AEO22 Table 23 Raw'!M27 -> 44.644444 | ... AI39: ='AEO22 Table 23 Raw'!AJ27 -> 0.004
A40: ISM000:fa_OtherChemical | C40: Other Chemical Products | D40: 376.91669 | E40: ='AEO22 Table 23 Raw'!F28 -> 517.61487 | F40: ='AEO22 Table 23 Raw'!G28 -> 485.57077 | G40: ='AEO22 Table 23 Raw'!H28 -> 479.08609 | H40: ='AEO22 Table 23 Raw'!I28 -> 477.27707 | I40: ='AEO22 Table 23 Raw'!J28 -> 477.89996 | J40: ='AEO22 Table 23 Raw'!K28 -> 479.4223 | K40: ='AEO22 Table 23 Raw'!L28 -> 481.72305 | L40: ='AEO22 Table 23 Raw'!M28 -> 483.79889 | ... AI40: ='AEO22 Table 23 Raw'!AJ28 -> 0.01
A41: ISM000:fa_PetroleumandC | B41: ISIC 19 | C41: Petroleum and Coal Products | D41: 777.24219 | E41: ='AEO22 Table 23 Raw'!F29 -> 789.06366 | F41: ='AEO22 Table 23 Raw'!G29 -> 885.51178 | G41: ='AEO22 Table 23 Raw'!H29 -> 899.4964 | H41: ='AEO22 Table 23 Raw'!I29 -> 897.32391 | I41: ='AEO22 Table 23 Raw'!J29 -> 897.97327 | J41: ='AEO22 Table 23 Raw'!K29 -> 896.10211 | K41: ='AEO22 Table 23 Raw'!L29 -> 892.39954 | L41: ='AEO22 Table 23 Raw'!M29 -> 890.51331 | ... AI41: ='AEO22 Table 23 Raw'!AJ29 -> 0.005
A42: ISM000:fa_PetroleumRefi | C42: Petroleum Refineries | D42: 735.55859 | E42: ='AEO22 Table 23 Raw'!F30 -> 746.87048 | F42: ='AEO22 Table 23 Raw'!G30 -> 840.716 | G42: ='AEO22 Table 23 Raw'!H30 -> 850.76227 | H42: ='AEO22 Table 23 Raw'!I30 -> 846.17731 | I42: ='AEO22 Table 23 Raw'!J30 -> 846.14966 | J42: ='AEO22 Table 23 Raw'!K30 -> 844.26404 | K42: ='AEO22 Table 23 Raw'!L30 -> 840.59943 | L42: ='AEO22 Table 23 Raw'!M30 -> 838.8761 | ... AI42: ='AEO22 Table 23 Raw'!AJ30 -> 0.004
A43: ISM000:fa_OtherPetroleu | C43: Other Petroleum and Coal Products | D43: 41.68362 | E43: ='AEO22 Table 23 Raw'!F31 -> 42.193161 | F43: ='AEO22 Table 23 Raw'!G31 -> 44.795792 | G43: ='AEO22 Table 23 Raw'!H31 -> 48.734158 | H43: ='AEO22 Table 23 Raw'!I31 -> 51.146606 | I43: ='AEO22 Table 23 Raw'!J31 -> 51.823608 | J43: ='AEO22 Table 23 Raw'!K31 -> 51.838081 | K43: ='AEO22 Table 23 Raw'!L31 -> 51.800133 | L43: ='AEO22 Table 23 Raw'!M31 -> 51.637184 | ... AI43: ='AEO22 Table 23 Raw'!AJ31 -> 0.009
A44: ISM000:fa_RubberandMisc | B44: ISIC 22 | C44: Plastics and Rubber Products | D44: 204.0638 | E44: ='AEO22 Table 23 Raw'!F32 -> 245.4554 | F44: ='AEO22 Table 23 Raw'!G32 -> 241.79295 | G44: ='AEO22 Table 23 Raw'!H32 -> 238.33037 | H44: ='AEO22 Table 23 Raw'!I32 -> 239.35245 | I44: ='AEO22 Table 23 Raw'!J32 -> 241.29742 | J44: ='AEO22 Table 23 Raw'!K32 -> 243.38844 | K44: ='AEO22 Table 23 Raw'!L32 -> 246.60761 | L44: ='AEO22 Table 23 Raw'!M32 -> 251.6187 | ... AI44: ='AEO22 Table 23 Raw'!AJ32 -> 0.013
A45: ISM000:fa_Stone,Clay,an | C45: Stone, Clay, and Glass Products | D45: 109.90946 | E45: ='AEO22 Table 23 Raw'!F33 -> 113.22774 | F45: ='AEO22 Table 23 Raw'!G33 -> 109.10921 | G45: ='AEO22 Table 23 Raw'!H33 -> 106.69244 | H45: ='AEO22 Table 23 Raw'!I33 -> 107.43405 | I45: ='AEO22 Table 23 Raw'!J33 -> 108.52844 | J45: ='AEO22 Table 23 Raw'!K33 -> 109.18559 | K45: ='AEO22 Table 23 Raw'!L33 -> 109.47917 | L45: ='AEO22 Table 23 Raw'!M33 -> 109.89218 | ... AI45: ='AEO22 Table 23 Raw'!AJ33 -> 0.003
A46: ISM000:fa_GlassandGlass | B46: ISIC 231 | C46: Glass and Glass Products | D46: 21.00304 | E46: ='AEO22 Table 23 Raw'!F34 -> 23.465088 | F46: ='AEO22 Table 23 Raw'!G34 -> 21.78306 | G46: ='AEO22 Table 23 Raw'!H34 -> 21.384214 | H46: ='AEO22 Table 23 Raw'!I34 -> 20.878117 | I46: ='AEO22 Table 23 Raw'!J34 -> 20.782543 | J46: ='AEO22 Table 23 Raw'!K34 -> 20.692644 | K46: ='AEO22 Table 23 Raw'!L34 -> 20.512907 | L46: ='AEO22 Table 23 Raw'!M34 -> 20.323284 | ... AI46: ='AEO22 Table 23 Raw'!AJ34 -> -0.009
A47: ISM000:fa_CementandHydr | B47: ISIC 239 | C47: Cement and Lime | D47: 14.143185 | E47: ='AEO22 Table 23 Raw'!F35 -> 13.972248 | F47: ='AEO22 Table 23 Raw'!G35 -> 14.70841 | G47: ='AEO22 Table 23 Raw'!H35 -> 14.789883 | H47: ='AEO22 Table 23 Raw'!I35 -> 15.090622 | I47: ='AEO22 Table 23 Raw'!J35 -> 15.311079 | J47: ='AEO22 Table 23 Raw'!K35 -> 15.412535 | K47: ='AEO22 Table 23 Raw'!L35 -> 15.460963 | L47: ='AEO22 Table 23 Raw'!M35 -> 15.52693 | ... AI47: ='AEO22 Table 23 Raw'!AJ35 -> 0.01
A48: ISM000:fa_OtherStone,Cl | B48: ISIC 239 | C48: Other Nonmetallic Mineral Products | D48: 74.763237 | E48: ='AEO22 Table 23 Raw'!F36 -> 75.790398 | F48: ='AEO22 Table 23 Raw'!G36 -> 72.617737 | G48: ='AEO22 Table 23 Raw'!H36 -> 70.518349 | H48: ='AEO22 Table 23 Raw'!I36 -> 71.465309 | I48: ='AEO22 Table 23 Raw'!J36 -> 72.434814 | J48: ='AEO22 Table 23 Raw'!K36 -> 73.080406 | K48: ='AEO22 Table 23 Raw'!L36 -> 73.505302 | L48: ='AEO22 Table 23 Raw'!M36 -> 74.041969 | ... AI48: ='AEO22 Table 23 Raw'!AJ36 -> 0.004
A49: ISM000:ga_PrimaryMetals | C49: Primary Metals Industry | D49: 221.20732 | E49: ='AEO22 Table 23 Raw'!F37 -> 240.15085 | F49: ='AEO22 Table 23 Raw'!G37 -> 248.90256 | G49: ='AEO22 Table 23 Raw'!H37 -> 250.07703 | H49: ='AEO22 Table 23 Raw'!I37 -> 249.02979 | I49: ='AEO22 Table 23 Raw'!J37 -> 250.30414 | J49: ='AEO22 Table 23 Raw'!K37 -> 250.60803 | K49: ='AEO22 Table 23 Raw'!L37 -> 250.12616 | L49: ='AEO22 Table 23 Raw'!M37 -> 250.00717 | ... AI49: ='AEO22 Table 23 Raw'!AJ37 -> 0.003
A50: ISM000:ga_BlastFurnacea | B50: ISIC 241 | C50: Iron and Steel Mills and Products | D50: 108.4389 | E50: ='AEO22 Table 23 Raw'!F38 -> 125.35865 | F50: ='AEO22 Table 23 Raw'!G38 -> 127.9127 | G50: ='AEO22 Table 23 Raw'!H38 -> 128.28152 | H50: ='AEO22 Table 23 Raw'!I38 -> 127.14848 | I50: ='AEO22 Table 23 Raw'!J38 -> 128.20995 | J50: ='AEO22 Table 23 Raw'!K38 -> 127.60918 | K50: ='AEO22 Table 23 Raw'!L38 -> 126.0716 | L50: ='AEO22 Table 23 Raw'!M38 -> 124.35245 | ... AI50: ='AEO22 Table 23 Raw'!AJ38 -> -0.005
A51: ISM000:ga_Aluminum | B51: ISIC 242 | C51: Alumina and Aluminum Products | D51: 34.496738 | E51: ='AEO22 Table 23 Raw'!F39 -> 37.984837 | F51: ='AEO22 Table 23 Raw'!G39 -> 40.76638 | G51: ='AEO22 Table 23 Raw'!H39 -> 41.336983 | H51: ='AEO22 Table 23 Raw'!I39 -> 41.340252 | I51: ='AEO22 Table 23 Raw'!J39 -> 41.685944 | J51: ='AEO22 Table 23 Raw'!K39 -> 42.266392 | K51: ='AEO22 Table 23 Raw'!L39 -> 42.752811 | L51: ='AEO22 Table 23 Raw'!M39 -> 43.178772 | ... AI51: ='AEO22 Table 23 Raw'!AJ39 -> 0.008
A52: ISM000:ga_OtherPrimaryM | B52: ISIC 242 | C52: Other Primary Metal Products | D52: 78.271683 | E52: ='AEO22 Table 23 Raw'!F40 -> 76.807365 | F52: ='AEO22 Table 23 Raw'!G40 -> 80.223488 | G52: ='AEO22 Table 23 Raw'!H40 -> 80.458534 | H52: ='AEO22 Table 23 Raw'!I40 -> 80.541054 | I52: ='AEO22 Table 23 Raw'!J40 -> 80.408257 | J52: ='AEO22 Table 23 Raw'!K40 -> 80.732468 | K52: ='AEO22 Table 23 Raw'!L40 -> 81.301743 | L52: ='AEO22 Table 23 Raw'!M40 -> 82.475945 | ... AI52: ='AEO22 Table 23 Raw'!AJ40 -> 0.01
A53: ISM000:ga_FabricatedMet | B53: ISIC 25 | C53: Fabricated Metal Products | D53: 371.87851 | E53: ='AEO22 Table 23 Raw'!F41 -> 356.37753 | F53: ='AEO22 Table 23 Raw'!G41 -> 359.29523 | G53: ='AEO22 Table 23 Raw'!H41 -> 363.27826 | H53: ='AEO22 Table 23 Raw'!I41 -> 368.16574 | I53: ='AEO22 Table 23 Raw'!J41 -> 371.49912 | J53: ='AEO22 Table 23 Raw'!K41 -> 372.5903 | K53: ='AEO22 Table 23 Raw'!L41 -> 372.03076 | L53: ='AEO22 Table 23 Raw'!M41 -> 371.24576 | ... AI53: ='AEO22 Table 23 Raw'!AJ41 -> 0.006
A54: ISM000:ga_IndustrialMac | B54: ISIC 28 | C54: Machinery | D54: 327.14691 | E54: ='AEO22 Table 23 Raw'!F42 -> 388.79587 | F54: ='AEO22 Table 23 Raw'!G42 -> 398.37433 | G54: ='AEO22 Table 23 Raw'!H42 -> 399.22537 | H54: ='AEO22 Table 23 Raw'!I42 -> 401.57873 | I54: ='AEO22 Table 23 Raw'!J42 -> 405.31845 | J54: ='AEO22 Table 23 Raw'!K42 -> 408.47577 | K54: ='AEO22 Table 23 Raw'!L42 -> 413.05301 | L54: ='AEO22 Table 23 Raw'!M42 -> 419.55804 | ... AI54: ='AEO22 Table 23 Raw'!AJ42 -> 0.013
A55: ISM000:ga_Electronicand | B55: ISIC 26 | C55: Computers and Electronics | D55: 352.31 | E55: ='AEO22 Table 23 Raw'!F43 -> 481.07022 | F55: ='AEO22 Table 23 Raw'!G43 -> 505.31369 | G55: ='AEO22 Table 23 Raw'!H43 -> 525.62903 | H55: ='AEO22 Table 23 Raw'!I43 -> 533.49408 | I55: ='AEO22 Table 23 Raw'!J43 -> 539.71503 | J55: ='AEO22 Table 23 Raw'!K43 -> 545.90918 | K55: ='AEO22 Table 23 Raw'!L43 -> 553.06506 | L55: ='AEO22 Table 23 Raw'!M43 -> 565.90131 | ... AI55: ='AEO22 Table 23 Raw'!AJ43 -> 0.022
A56: ISM000:ga_Transportatio | B56: ISIC 29, ISIC 30 | C56: Transportation Equipment | D56: 703.6698 | E56: ='AEO22 Table 23 Raw'!F44 -> 1097.1733 | F56: ='AEO22 Table 23 Raw'!G44 -> 1186.0754 | G56: ='AEO22 Table 23 Raw'!H44 -> 1256.5553 | H56: ='AEO22 Table 23 Raw'!I44 -> 1230.3678 | I56: ='AEO22 Table 23 Raw'!J44 -> 1211.1823 | J56: ='AEO22 Table 23 Raw'!K44 -> 1197.546 | K56: ='AEO22 Table 23 Raw'!L44 -> 1182.4027 | L56: ='AEO22 Table 23 Raw'!M44 -> 1180.8767 | ... AI56: ='AEO22 Table 23 Raw'!AJ44 -> 0.01
A57: ISM000:ga_Instrumentsan | B57: ISIC 27 | C57: Electrical Equipment | D57: 121.1327 | E57: ='AEO22 Table 23 Raw'!F45 -> 133.00749 | F57: ='AEO22 Table 23 Raw'!G45 -> 137.61655 | G57: ='AEO22 Table 23 Raw'!H45 -> 140.91475 | H57: ='AEO22 Table 23 Raw'!I45 -> 142.85202 | I57: ='AEO22 Table 23 Raw'!J45 -> 143.6158 | J57: ='AEO22 Table 23 Raw'!K45 -> 144.11873 | K57: ='AEO22 Table 23 Raw'!L45 -> 144.58192 | L57: ='AEO22 Table 23 Raw'!M45 -> 145.72432 | ... AI57: ='AEO22 Table 23 Raw'!AJ45 -> 0.021
A58: ISM000:ga_Miscellaneous | B58: ISIC 31T33 | C58: Miscellaneous Manufacturing | D58: 150.84331 | E58: ='AEO22 Table 23 Raw'!F46 -> 160.34868 | F58: ='AEO22 Table 23 Raw'!G46 -> 159.03638 | G58: ='AEO22 Table 23 Raw'!H46 -> 159.82165 | H58: ='AEO22 Table 23 Raw'!I46 -> 161.89937 | I58: ='AEO22 Table 23 Raw'!J46 -> 163.54092 | J58: ='AEO22 Table 23 Raw'!K46 -> 166.9111 | K58: ='AEO22 Table 23 Raw'!L46 -> 170.5298 | L58: ='AEO22 Table 23 Raw'!M46 -> 174.19583 | ... AI58: ='AEO22 Table 23 Raw'!AJ46 -> 0.011
A60: ISM000:ha_TotalIndustri | C60: Total Industrial Value of Shipments | D60: 8167.6558 | E60: ='AEO22 Table 23 Raw'!F47 -> 9275.0264 | F60: ='AEO22 Table 23 Raw'!G47 -> 9366.1943 | G60: ='AEO22 Table 23 Raw'!H47 -> 9440.3613 | H60: ='AEO22 Table 23 Raw'!I47 -> 9447.7051 | I60: ='AEO22 Table 23 Raw'!J47 -> 9475.5957 | J60: ='AEO22 Table 23 Raw'!K47 -> 9489.0049 | K60: ='AEO22 Table 23 Raw'!L47 -> 9491.3828 | L60: ='AEO22 Table 23 Raw'!M47 -> 9543.9258 | ... AI60: ='AEO22 Table 23 Raw'!AJ47 -> 0.008
C62: Note: Totals may not equal sum of components due to independent rounding.
C63: Sources: 2020: IHS Markit, Macroeconomic model, May 2019.
C64: Projections: U.S. Energy Information Administration, AEO2021 National Energy Modeling System run ref2021.d113020a.

Sheet Growth Rates
A1: BLS Data | F1: EIA AEO Data
B2: Compound Growth Rate (output-weighted average of components of each ISIC code)
B3: 2009-2019 | C3: 2019-2029 | G3: 2020-2050
A4: ISIC 01T03 | B4: {=SUMPRODUCT(--('BLS Table 2.7'!$O:$O=$A4),'BLS Table 2.7'!K:K,'BLS Table 2.7'!M:M)/SUMIFS('BLS Table 2.7'!K:K,'BLS Table 2.7'!$O:$O,$A4)/100} -> 0.022 | C4: {=SUMPRODUCT(--('BLS Table 2.7'!$O:$O=$A4),'BLS Table 2.7'!L:L,'BLS Table 2.7'!N:N)/SUMIFS('BLS Table 2.7'!L:L,'BLS Table 2.7'!$O:$O,$A4)/100} -> 0.018 | F4: ISIC 01T03 | G4: =IFERROR(INDEX('AEO22 Table 23'!$AI$22:$AI$58,MATCH($F4,'AEO22 Table 23'!$B$22:$B$58,0)),"") -> 0.004
A5: ISIC 05 | B5: {=SUMPRODUCT(--('BLS Table 2.7'!$O:$O=$A5),'BLS Table 2.7'!K:K,'BLS Table 2.7'!M:M)/SUMIFS('BLS Table 2.7'!K:K,'BLS Table 2.7'!$O:$O,$A5)/100} -> -0.013 | C5: {=SUMPRODUCT(--('BLS Table 2.7'!$O:$O=$A5),'BLS Table 2.7'!L:L,'BLS Table 2.7'!N:N)/SUMIFS('BLS Table 2.7'!L:L,'BLS Table 2.7'!$O:$O,$A5)/100} -> -0.002 | F5: ISIC 05 | G5: =IFERROR(INDEX('AEO22 Table 23'!$AI$22:$AI$58,MATCH($F5,'AEO22 Table 23'!$B$22:$B$58,0)),"")
A6: ISIC 06 | B6: {=SUMPRODUCT(--('BLS Table 2.7'!$O:$O=$A6),'BLS Table 2.7'!K:K,'BLS Table 2.7'!M:M)/SUMIFS('BLS Table 2.7'!K:K,'BLS Table 2.7'!$O:$O,$A6)/100} -> 0.055 | C6: {=SUMPRODUCT(--('BLS Table 2.7'!$O:$O=$A6),'BLS Table 2.7'!L:L,'BLS Table 2.7'!N:N)/SUMIFS('BLS Table 2.7'!L:L,'BLS Table 2.7'!$O:$O,$A6)/100} -> 0.034 | F6: ISIC 06 | G6: =IFERROR(INDEX('AEO22 Table 23'!$AI$22:$AI$58,MATCH($F6,'AEO22 Table 23'!$B$22:$B$58,0)),"")
A7: ISIC 07T08 | B7: {=SUMPRODUCT(--('BLS Table 2.7'!$O:$O=$A7),'BLS Table 2.7'!K:K,'BLS Table 2.7'!M:M)/SUMIFS('BLS Table 2.7'!K:K,'BLS Table 2.7'!$O:$O,$A7)/100} -> -0.01543937 | C7: {=SUMPRODUCT(--('BLS Table 2.7'!$O:$O=$A7),'BLS Table 2.7'!L:L,'BLS Table 2.7'!N:N)/SUMIFS('BLS Table 2.7'!L:L,'BLS Table 2.7'!$O:$O,$A7)/100} -> 0.010045584 | F7: ISIC 07T08 | G7: =IFERROR(INDEX('AEO22 Table 23'!$AI$22:$AI$58,MATCH($F7,'AEO22 Table 23'!$B$22:$B$58,0)),"")
A8: ISIC 09 | B8: {=SUMPRODUCT(--('BLS Table 2.7'!$O:$O=$A8),'BLS Table 2.7'!K:K,'BLS Table 2.7'!M:M)/SUMIFS('BLS Table 2.7'!K:K,'BLS Table 2.7'!$O:$O,$A8)/100} -> -0.001 | C8: {=SUMPRODUCT(--('BLS Table 2.7'!$O:$O=$A8),'BLS Table 2.7'!L:L,'BLS Table 2.7'!N:N)/SUMIFS('BLS Table 2.7'!L:L,'BLS Table 2.7'!$O:$O,$A8)/100} -> 0.029 | F8: ISIC 09 | G8: =IFERROR(INDEX('AEO22 Table 23'!$AI$22:$AI$58,MATCH($F8,'AEO22 Table 23'!$B$22:$B$58,0)),"")
A9: ISIC 10T12 | B9: {=SUMPRODUCT(--('BLS Table 2.7'!$O:$O=$A9),'BLS Table 2.7'!K:K,'BLS Table 2.7'!M:M)/SUMIFS('BLS Table 2.7'!K:K,'BLS Table 2.7'!$O:$O,$A9)/100} -> 0.0093064841 | C9: {=SUMPRODUCT(--('BLS Table 2.7'!$O:$O=$A9),'BLS Table 2.7'!L:L,'BLS Table 2.7'!N:N)/SUMIFS('BLS Table 2.7'!L:L,'BLS Table 2.7'!$O:$O,$A9)/100} -> 0.015585313 | F9: ISIC 10T12 | G9: =IFERROR(INDEX('AEO22 Table 23'!$AI$22:$AI$58,MATCH($F9,'AEO22 Table 23'!$B$22:$B$58,0)),"") -> 0.005
A10: ISIC 13T15 | B10: {=SUMPRODUCT(--('BLS Table 2.7'!$O:$O=$A10),'BLS Table 2.7'!K:K,'BLS Table 2.7'!M:M)/SUMIFS('BLS Table 2.7'!K:K,'BLS Table 2.7'!$O:$O,$A10)/100} -> -0.0052350487 | C10: {=SUMPRODUCT(--('BLS Table 2.7'!$O:$O=$A10),'BLS Table 2.7'!L:L,'BLS Table 2.7'!N:N)/SUMIFS('BLS Table 2.7'!L:L,'BLS Table 2.7'!$O:$O,$A10)/100} -> -0.0021448864 | F10: ISIC 13T15 | G10: =IFERROR(INDEX('AEO22 Table 23'!$AI$22:$AI$58,MATCH($F10,'AEO22 Table 23'!$B$22:$B$58,0)),"") -> -0.003
A11: ISIC 16 | B11: {=SUMPRODUCT(--('BLS Table 2.7'!$O:$O=$A11),'BLS Table 2.7'!K:K,'BLS Table 2.7'!M:M)/SUMIFS('BLS Table 2.7'!K:K,'BLS Table 2.7'!$O:$O,$A11)/100} -> 0.024 | C11: {=SUMPRODUCT(--('BLS Table 2.7'!$O:$O=$A11),'BLS Table 2.7'!L:L,'BLS Table 2.7'!N:N)/SUMIFS('BLS Table 2.7'!L:L,'BLS Table 2.7'!$O:$O,$A11)/100} -> 0.014 | F11: ISIC 16 | G11: =IFERROR(INDEX('AEO22 Table 23'!$AI$22:$AI$58,MATCH($F11,'AEO22 Table 23'!$B$22:$B$58,0)),"") -> -0.007
A12: ISIC 17T18 | B12: {=SUMPRODUCT(--('BLS Table 2.7'!$O:$O=$A12),'BLS Table 2.7'!K:K,'BLS Table 2.7'!M:M)/SUMIFS('BLS Table 2.7'!K:K,'BLS Table 2.7'!$O:$O,$A12)/100} -> 0.00039223972 | C12: {=SUMPRODUCT(--('BLS Table 2.7'!$O:$O=$A12),'BLS Table 2.7'!L:L,'BLS Table 2.7'!N:N)/SUMIFS('BLS Table 2.7'!L:L,'BLS Table 2.7'!$O:$O,$A12)/100} -> 0.0049882741 | F12: ISIC 17T18 | G12: =IFERROR(INDEX('AEO22 Table 23'!$AI$22:$AI$58,MATCH($F12,'AEO22 Table 23'!$B$22:$B$58,0)),"") -> -0.008
A13: ISIC 19 | B13: {=SUMPRODUCT(--('BLS Table 2.7'!$O:$O=$A13),'BLS Table 2.7'!K:K,'BLS Table 2.7'!M:M)/SUMIFS('BLS Table 2.7'!K:K,'BLS Table 2.7'!$O:$O,$A13)/100} -> 0.007 | C13: {=SUMPRODUCT(--('BLS Table 2.7'!$O:$O=$A13),'BLS Table 2.7'!L:L,'BLS Table 2.7'!N:N)/SUMIFS('BLS Table 2.7'!L:L,'BLS Table 2.7'!$O:$O,$A13)/100} -> 0.023 | F13: ISIC 19 | G13: =IFERROR(INDEX('AEO22 Table 23'!$AI$22:$AI$58,MATCH($F13,'AEO22 Table 23'!$B$22:$B$58,0)),"") -> 0.005
A14: ISIC 20 | B14: {=SUMPRODUCT(--('BLS Table 2.7'!$O:$O=$A14),'BLS Table 2.7'!K:K,'BLS Table 2.7'!M:M)/SUMIFS('BLS Table 2.7'!K:K,'BLS Table 2.7'!$O:$O,$A14)/100} -> 0.022260187 | C14: {=SUMPRODUCT(--('BLS Table 2.7'!$O:$O=$A14),'BLS Table 2.7'!L:L,'BLS Table 2.7'!N:N)/SUMIFS('BLS Table 2.7'!L:L,'BLS Table 2.7'!$O:$O,$A14)/100} -> 0.018352106 | F14: ISIC 20 | G14: =IFERROR(INDEX('AEO22 Table 23'!$AI$22:$AI$58,MATCH($F14,'AEO22 Table 23'!$B$22:$B$58,0)),"") -> 0.009
A15: ISIC 21 | B15: {=SUMPRODUCT(--('BLS Table 2.7'!$O:$O=$A15),'BLS Table 2.7'!K:K,'BLS Table 2.7'!M:M)/SUMIFS('BLS Table 2.7'!K:K,'BLS Table 2.7'!$O:$O,$A15)/100} -> -0.004 | C15: {=SUMPRODUCT(--('BLS Table 2.7'!$O:$O=$A15),'BLS Table 2.7'!L:L,'BLS Table 2.7'!N:N)/SUMIFS('BLS Table 2.7'!L:L,'BLS Table 2.7'!$O:$O,$A15)/100} -> 0.018 | F15: ISIC 21 | G15: =IFERROR(INDEX('AEO22 Table 23'!$AI$22:$AI$58,MATCH($F15,'AEO22 Table 23'!$B$22:$B$58,0)),"")
... A24: ISIC 28 | B24: {=SUMPRODUCT(--('BLS Table 2.7'!$O:$O=$A24),'BLS Table 2.7'!K:K,'BLS Table 2.7'!M:M)/SUMIFS('BLS Table 2.7'!K:K,'BLS Table 2.7'!$O:$O,$A24)/100} -> 0.025 | C24: {=SUMPRODUCT(--('BLS Table 2.7'!$O:$O=$A24),'BLS Table 2.7'!L:L,'BLS Table 2.7'!N:N)/SUMIFS('BLS Table 2.7'!L:L,'BLS Table 2.7'!$O:$O,$A24)/100} -> 0.015 | F24: ISIC 28 | G24: =IFERROR(INDEX('AEO22 Table 23'!$AI$22:$AI$58,MATCH($F24,'AEO22 Table 23'!$B$22:$B$58,0)),"") -> 0.013
A25: ISIC 29 | B25: {=SUMPRODUCT(--('BLS Table 2.7'!$O:$O=$A25),'BLS Table 2.7'!K:K,'BLS Table 2.7'!M:M)/SUMIFS('BLS Table 2.7'!K:K,'BLS Table 2.7'!$O:$O,$A25)/100} -> 0.073700262 | C25: {=SUMPRODUCT(--('BLS Table 2.7'!$O:$O=$A25),'BLS Table 2.7'!L:L,'BLS Table 2.7'!N:N)/SUMIFS('BLS Table 2.7'!L:L,'BLS Table 2.7'!$O:$O,$A25)/100} -> 0.018032437 | F25: ISIC 29 | G25: ='AEO22 Table 23'!$AI$56 -> 0.01
A26: ISIC 30 | B26: {=SUMPRODUCT(--('BLS Table 2.7'!$O:$O=$A26),'BLS Table 2.7'!K:K,'BLS Table 2.7'!M:M)/SUMIFS('BLS Table 2.7'!K:K,'BLS Table 2.7'!$O:$O,$A26)/100} -> 0.017897004 | C26: {=SUMPRODUCT(--('BLS Table 2.7'!$O:$O=$A26),'BLS Table 2.7'!L:L,'BLS Table 2.7'!N:N)/SUMIFS('BLS Table 2.7'!L:L,'BLS Table 2.7'!$O:$O,$A26)/100} -> 0.019602007 | F26: ISIC 30 | G26: ='AEO22 Table 23'!$AI$56 -> 0.01
A27: ISIC 31T33 | B27: {=SUMPRODUCT(--('BLS Table 2.7'!$O:$O=$A27),'BLS Table 2.7'!K:K,'BLS Table 2.7'!M:M)/SUMIFS('BLS Table 2.7'!K:K,'BLS Table 2.7'!$O:$O,$A27)/100} -> 0.0061778414 | C27: {=SUMPRODUCT(--('BLS Table 2.7'!$O:$O=$A27),'BLS Table 2.7'!L:L,'BLS Table 2.7'!N:N)/SUMIFS('BLS Table 2.7'!L:L,'BLS Table 2.7'!$O:$O,$A27)/100} -> 0.014107993 | F27: ISIC 31T33 | G27: =IFERROR(INDEX('AEO22 Table 23'!$AI$22:$AI$58,MATCH($F27,'AEO22 Table 23'!$B$22:$B$58,0)),"") -> 0.009
A28: ISIC 351 | B28: {=SUMPRODUCT(--('BLS Table 2.7'!$O:$O=$A28),'BLS Table 2.7'!K:K,'BLS Table 2.7'!M:M)/SUMIFS('BLS Table 2.7'!K:K,'BLS Table 2.7'!$O:$O,$A28)/100} -> 0.005 | C28: {=SUMPRODUCT(--('BLS Table 2.7'!$O:$O=$A28),'BLS Table 2.7'!L:L,'BLS Table 2.7'!N:N)/SUMIFS('BLS Table 2.7'!L:L,'BLS Table 2.7'!$O:$O,$A28)/100} -> 0.017 | F28: ISIC 351 | G28: =IFERROR(INDEX('AEO22 Table 23'!$AI$22:$AI$58,MATCH($F28,'AEO22 Table 23'!$B$22:$B$58,0)),"")
A29: ISIC 352T353 | B29: {=SUMPRODUCT(--('BLS Table 2.7'!$O:$O=$A29),'BLS Table 2.7'!K:K,'BLS Table 2.7'!M:M)/SUMIFS('BLS Table 2.7'!K:K,'BLS Table 2.7'!$O:$O,$A29)/100} -> 0.002 | C29: {=SUMPRODUCT(--('BLS Table 2.7'!$O:$O=$A29),'BLS Table 2.7'!L:L,'BLS Table 2.7'!N:N)/SUMIFS('BLS Table 2.7'!L:L,'BLS Table 2.7'!$O:$O,$A29)/100} -> 0.008 | F29: ISIC 352T353 | G29: =IFERROR(INDEX('AEO22 Table 23'!$AI$22:$AI$58,MATCH($F29,'AEO22 Table 23'!$B$22:$B$58,0)),"")
A30: ISIC 36T39 | B30: {=SUMPRODUCT(--('BLS Table 2.7'!$O:$O=$A30),'BLS Table 2.7'!K:K,'BLS Table 2.7'!M:M)/SUMIFS('BLS Table 2.7'!K:K,'BLS Table 2.7'!$O:$O,$A30)/100} -> 0.014653409 | C30: {=SUMPRODUCT(--('BLS Table 2.7'!$O:$O=$A30),'BLS Table 2.7'!L:L,'BLS Table 2.7'!N:N)/SUMIFS('BLS Table 2.7'!L:L,'BLS Table 2.7'!$O:$O,$A30)/100} -> 0.016380645 | F30: ISIC 36T39 | G30: =IFERROR(INDEX('AEO22 Table 23'!$AI$22:$AI$58,MATCH($F30,'AEO22 Table 23'!$B$22:$B$58,0)),"")
A31: ISIC 41T43 | B31: {=SUMPRODUCT(--('BLS Table 2.7'!$O:$O=$A31),'BLS Table 2.7'!K:K,'BLS Table 2.7'!M:M)/SUMIFS('BLS Table 2.7'!K:K,'BLS Table 2.7'!$O:$O,$A31)/100} -> 0.02 | C31: {=SUMPRODUCT(--('BLS Table 2.7'!$O:$O=$A31),'BLS Table 2.7'!L:L,'BLS Table 2.7'!N:N)/SUMIFS('BLS Table 2.7'!L:L,'BLS Table 2.7'!$O:$O,$A31)/100} -> 0.013 | F31: ISIC 41T43 | G31: =IFERROR(INDEX('AEO22 Table 23'!$AI$22:$AI$58,MATCH($F31,'AEO22 Table 23'!$B$22:$B$58,0)),"") -> 0.007
A32: ISIC 45T47 | B32: {=SUMPRODUCT(--('BLS Table 2.7'!$O:$O=$A32),'BLS Table 2.7'!K:K,'BLS Table 2.7'!M:M)/SUMIFS('BLS Table 2.7'!K:K,'BLS Table 2.7'!$O:$O,$A32)/100} -> 0.041035167 | C32: {=SUMPRODUCT(--('BLS Table 2.7'!$O:$O=$A32),'BLS Table 2.7'!L:L,'BLS Table 2.7'!N:N)/SUMIFS('BLS Table 2.7'!L:L,'BLS Table 2.7'!$O:$O,$A32)/100} -> 0.025021213 | F32: ISIC 45T47 | G32: =IFERROR(INDEX('AEO22 Table 23'!$AI$22:$AI$58,MATCH($F32,'AEO22 Table 23'!$B$22:$B$58,0)),"")
A33: ISIC 49T53 | B33: {=SUMPRODUCT(--('BLS Table 2.7'!$O:$O=$A33),'BLS Table 2.7'!K:K,'BLS Table 2.7'!M:M)/SUMIFS('BLS Table 2.7'!K:K,'BLS Table 2.7'!$O:$O,$A33)/100} -> 0.018 | C33: {=SUMPRODUCT(--('BLS Table 2.7'!$O:$O=$A33),'BLS Table 2.7'!L:L,'BLS Table 2.7'!N:N)/SUMIFS('BLS Table 2.7'!L:L,'BLS Table 2.7'!$O:$O,$A33)/100} -> 0.016 | F33: ISIC 49T53 | G33: =IFERROR(INDEX('AEO22 Table 23'!$AI$22:$AI$58,MATCH($F33,'AEO22 Table 23'!$B$22:$B$58,0)),"")
A34: ISIC 55T56 | B34: {=SUMPRODUCT(--('BLS Table 2.7'!$O:$O=$A34),'BLS Table 2.7'!K:K,'BLS Table 2.7'!M:M)/SUMIFS('BLS Table 2.7'!K:K,'BLS Table 2.7'!$O:$O,$A34)/100} -> 0.031 | C34: {=SUMPRODUCT(--('BLS Table 2.7'!$O:$O=$A34),'BLS Table 2.7'!L:L,'BLS Table 2.7'!N:N)/SUMIFS('BLS Table 2.7'!L:L,'BLS Table 2.7'!$O:$O,$A34)/100} -> 0.021 | F34: ISIC 55T56 | G34: =IFERROR(INDEX('AEO22 Table 23'!$AI$22:$AI$58,MATCH($F34,'AEO22 Table 23'!$B$22:$B$58,0)),"")
A35: ISIC 58T60 | B35: {=SUMPRODUCT(--('BLS Table 2.7'!$O:$O=$A35),'BLS Table 2.7'!K:K,'BLS Table 2.7'!M:M)/SUMIFS('BLS Table 2.7'!K:K,'BLS Table 2.7'!$O:$O,$A35)/100} -> 0.022434706 | C35: {=SUMPRODUCT(--('BLS Table 2.7'!$O:$O=$A35),'BLS Table 2.7'!L:L,'BLS Table 2.7'!N:N)/SUMIFS('BLS Table 2.7'!L:L,'BLS Table 2.7'!$O:$O,$A35)/100} -> 0.026399864 | F35: ISIC 58T60 | G35: =IFERROR(INDEX('AEO22 Table 23'!$AI$22:$AI$58,MATCH($F35,'AEO22 Table 23'!$B$22:$B$58,0)),"")
A36: ISIC 61 | B36: {=SUMPRODUCT(--('BLS Table 2.7'!$O:$O=$A36),'BLS Table 2.7'!K:K,'BLS Table 2.7'!M:M)/SUMIFS('BLS Table 2.7'!K:K,'BLS Table 2.7'!$O:$O,$A36)/100} -> 0.037 | C36: {=SUMPRODUCT(--('BLS Table 2.7'!$O:$O=$A36),'BLS Table 2.7'!L:L,'BLS Table 2.7'!N:N)/SUMIFS('BLS Table 2.7'!L:L,'BLS Table 2.7'!$O:$O,$A36)/100} -> 0.02 | F36: ISIC 61 | G36: =IFERROR(INDEX('AEO22 Table 23'!$AI$22:$AI$58,MATCH($F36,'AEO22 Table 23'!$B$22:$B$58,0)),"")
A37: ISIC 62T63 | B37: {=SUMPRODUCT(--('BLS Table 2.7'!$O:$O=$A37),'BLS Table 2.7'!K:K,'BLS Table 2.7'!M:M)/SUMIFS('BLS Table 2.7'!K:K,'BLS Table 2.7'!$O:$O,$A37)/100} -> 0.13241388 | C37: {=SUMPRODUCT(--('BLS Table 2.7'!$O:$O=$A37),'BLS Table 2.7'!L:L,'BLS Table 2.7'!N:N)/SUMIFS('BLS Table 2.7'!L:L,'BLS Table 2.7'!$O:$O,$A37)/100} -> 0.037309863 | F37: ISIC 62T63 | G37: =IFERROR(INDEX('AEO22 Table 23'!$AI$22:$AI$58,MATCH($F37,'AEO22 Table 23'!$B$22:$B$58,0)),"")
A38: ISIC 64T66 | B38: {=SUMPRODUCT(--('BLS Table 2.7'!$O:$O=$A38),'BLS Table 2.7'!K:K,'BLS Table 2.7'!M:M)/SUMIFS('BLS Table 2.7'!K:K,'BLS Table 2.7'!$O:$O,$A38)/100} -> 0.011 | C38: {=SUMPRODUCT(--('BLS Table 2.7'!$O:$O=$A38),'BLS Table 2.7'!L:L,'BLS Table 2.7'!N:N)/SUMIFS('BLS Table 2.7'!L:L,'BLS Table 2.7'!$O:$O,$A38)/100} -> 0.014 | F38: ISIC 64T66 | G38: =IFERROR(INDEX('AEO22 Table 23'!$AI$22:$AI$58,MATCH($F38,'AEO22 Table 23'!$B$22:$B$58,0)),"")
... A45: ISIC 97T98 | B45: {=SUMPRODUCT(--('BLS Table 2.7'!$O:$O=$A45),'BLS Table 2.7'!K:K,'BLS Table 2.7'!M:M)/SUMIFS('BLS Table 2.7'!K:K,'BLS Table 2.7'!$O:$O,$A45)/100} -> 0.008 | C45: {=SUMPRODUCT(--('BLS Table 2.7'!$O:$O=$A45),'BLS Table 2.7'!L:L,'BLS Table 2.7'!N:N)/SUMIFS('BLS Table 2.7'!L:L,'BLS Table 2.7'!$O:$O,$A45)/100} -> 0.017 | F45: ISIC 97T98 | G45: =IFERROR(INDEX('AEO22 Table 23'!$AI$22:$AI$58,MATCH($F45,'AEO22 Table 23'!$B$22:$B$58,0)),"")
A48: Chosen Rates by Year
A49: For years 2015-2019, we use BLS data, because AEO data starts with 2020.
A50: For years 2026-2050, we use EIA AEO data for ISIC codes for which data are available and BLS data for other ISIC codes.
A51: For years 2021-2025, we smooth the transition between the two regimes above, to avoid sudden discontinuities.
A52: Note that since EIA AEO doesn't disaggregate "Mining," we use BLS data for mining, as the trends are quite different for different types of mining.
B54: 2015 | C54: 2016 | D54: 2017 | E54: 2018 | F54: 2019 | G54: 2020 | H54: 2021 | I54: 2022 | J54: 2023 | K54: 2024 | L54: 2025 | M54: 2026 | N54: 2027 | O54: 2028 | P54: 2029 | Q54: 2030 | R54: 2031 | S54: 2032 | T54: 2033 | U54: 2034 | V54: 2035 | W54: 2036 | X54: 2037 | Y54: 2038 | Z54: 2039 | AA54: 2040 | AB54: 2041 | AC54: 2042 | AD54: 2043 | AE54: 2044 | AF54: 2045 | AG54: 2046 | AH54: 2047 | AI54: 2048 | AJ54: 2049 | AK54: 2050
A55: ISIC 01T03 | B55: =$B4 -> 0.022 | C55: =$B4 -> 0.022 | D55: =$B4 -> 0.022 | E55: =$B4 -> 0.022 | F55: =$B4 -> 0.022 | G55: =$F55+($M55-$F55)*(G$54-$F$54)/($M$54-$F$54) -> 0.019428571 | H55: =$F55+($M55-$F55)*(H$54-$F$54)/($M$54-$F$54) -> 0.016857143 | I55: =$F55+($M55-$F55)*(I$54-$F$54)/($M$54-$F$54) -> 0.014285714 | J55: =$F55+($M55-$F55)*(J$54-$F$54)/($M$54-$F$54) -> 0.011714286 | K55: =$F55+($M55-$F55)*(K$54-$F$54)/($M$54-$F$54) -> 0.0091428571 | L55: =$F55+($M55-$F55)*(L$54-$F$54)/($M$54-$F$54) -> 0.0065714286 | M55: =IF($G4="",$C4,$G4) -> 0.004 | N55: =IF($G4="",$C4,$G4) -> 0.004 | O55: =IF($G4="",$C4,$G4) -> 0.004 | P55: =IF($G4="",$C4,$G4) -> 0.004 | Q55: =IF($G4="",$C4,$G4) -> 0.004 | R55: =IF($G4="",$C4,$G4) -> 0.004 | S55: =IF($G4="",$C4,$G4) -> 0.004 | T55: =IF($G4="",$C4,$G4) -> 0.004 | ... AK55: =IF($G4="",$C4,$G4) -> 0.004
A56: ISIC 05 | B56: =$B5 -> -0.013 | C56: =$B5 -> -0.013 | D56: =$B5 -> -0.013 | E56: =$B5 -> -0.013 | F56: =$B5 -> -0.013 | G56: =$F56+($M56-$F56)*(G$54-$F$54)/($M$54-$F$54) -> -0.011428571 | H56: =$F56+($M56-$F56)*(H$54-$F$54)/($M$54-$F$54) -> -0.0098571429 | I56: =$F56+($M56-$F56)*(I$54-$F$54)/($M$54-$F$54) -> -0.0082857143 | J56: =$F56+($M56-$F56)*(J$54-$F$54)/($M$54-$F$54) -> -0.0067142857 | K56: =$F56+($M56-$F56)*(K$54-$F$54)/($M$54-$F$54) -> -0.0051428571 | L56: =$F56+($M56-$F56)*(L$54-$F$54)/($M$54-$F$54) -> -0.0035714286 | M56: =IF($G5="",$C5,$G5) -> -0.002 | N56: =IF($G5="",$C5,$G5) -> -0.002 | O56: =IF($G5="",$C5,$G5) -> -0.002 | P56: =IF($G5="",$C5,$G5) -> -0.002 | Q56: =IF($G5="",$C5,$G5) -> -0.002 | R56: =IF($G5="",$C5,$G5) -> -0.002 | S56: =IF($G5="",$C5,$G5) -> -0.002 | T56: =IF($G5="",$C5,$G5) -> -0.002 | ... AK56: =IF($G5="",$C5,$G5) -> -0.002
A57: ISIC 06 | B57: =$B6 -> 0.055 | C57: =$B6 -> 0.055 | D57: =$B6 -> 0.055 | E57: =$B6 -> 0.055 | F57: =$B6 -> 0.055 | G57: =$F57+($M57-$F57)*(G$54-$F$54)/($M$54-$F$54) -> 0.052 | H57: =$F57+($M57-$F57)*(H$54-$F$54)/($M$54-$F$54) -> 0.049 | I57: =$F57+($M57-$F57)*(I$54-$F$54)/($M$54-$F$54) -> 0.046 | J57: =$F57+($M57-$F57)*(J$54-$F$54)/($M$54-$F$54) -> 0.043 | K57: =$F57+($M57-$F57)*(K$54-$F$54)/($M$54-$F$54) -> 0.04 | L57: =$F57+($M57-$F57)*(L$54-$F$54)/($M$54-$F$54) -> 0.037 | M57: =IF($G6="",$C6,$G6) -> 0.034 | N57: =IF($G6="",$C6,$G6) -> 0.034 | O57: =IF($G6="",$C6,$G6) -> 0.034 | P57: =IF($G6="",$C6,$G6) -> 0.034 | Q57: =IF($G6="",$C6,$G6) -> 0.034 | R57: =IF($G6="",$C6,$G6) -> 0.034 | S57: =IF($G6="",$C6,$G6) -> 0.034 | T57: =IF($G6="",$C6,$G6) -> 0.034 | ... AK57: =IF($G6="",$C6,$G6) -> 0.034
A58: ISIC 07T08 | B58: =$B7 -> -0.01543937 | C58: =$B7 -> -0.01543937 | D58: =$B7 -> -0.01543937 | E58: =$B7 -> -0.01543937 | F58: =$B7 -> -0.01543937 | G58: =$F58+($M58-$F58)*(G$54-$F$54)/($M$54-$F$54) -> -0.011798662 | H58: =$F58+($M58-$F58)*(H$54-$F$54)/($M$54-$F$54) -> -0.0081579546 | I58: =$F58+($M58-$F58)*(I$54-$F$54)/($M$54-$F$54) -> -0.0045172469 | J58: =$F58+($M58-$F58)*(J$54-$F$54)/($M$54-$F$54) -> -0.00087653915 | K58: =$F58+($M58-$F58)*(K$54-$F$54)/($M$54-$F$54) -> 0.0027641686 | L58: =$F58+($M58-$F58)*(L$54-$F$54)/($M$54-$F$54) -> 0.0064048763 | M58: =IF($G7="",$C7,$G7) -> 0.010045584 | N58: =IF($G7="",$C7,$G7) -> 0.010045584 | O58: =IF($G7="",$C7,$G7) -> 0.010045584 | P58: =IF($G7="",$C7,$G7) -> 0.010045584 | Q58: =IF($G7="",$C7,$G7) -> 0.010045584 | R58: =IF($G7="",$C7,$G7) -> 0.010045584 | S58: =IF($G7="",$C7,$G7) -> 0.010045584 | T58: =IF($G7="",$C7,$G7) -> 0.010045584 | ... AK58: =IF($G7="",$C7,$G7) -> 0.010045584
A59: ISIC 09 | B59: =$B8 -> -0.001 | C59: =$B8 -> -0.001 | D59: =$B8 -> -0.001 | E59: =$B8 -> -0.001 | F59: =$B8 -> -0.001 | G59: =$F59+($M59-$F59)*(G$54-$F$54)/($M$54-$F$54) -> 0.0032857143 | H59: =$F59+($M59-$F59)*(H$54-$F$54)/($M$54-$F$54) -> 0.0075714286 | I59: =$F59+($M59-$F59)*(I$54-$F$54)/($M$54-$F$54) -> 0.011857143 | J59: =$F59+($M59-$F59)*(J$54-$F$54)/($M$54-$F$54) -> 0.016142857 | K59: =$F59+($M59-$F59)*(K$54-$F$54)/($M$54-$F$54) -> 0.020428571 | L59: =$F59+($M59-$F59)*(L$54-$F$54)/($M$54-$F$54) -> 0.024714286 | M59: =IF($G8="",$C8,$G8) -> 0.029 | N59: =IF($G8="",$C8,$G8) -> 0.029 | O59: =IF($G8="",$C8,$G8) -> 0.029 | P59: =IF($G8="",$C8,$G8) -> 0.029 | Q59: =IF($G8="",$C8,$G8) -> 0.029 | R59: =IF($G8="",$C8,$G8) -> 0.029 | S59: =IF($G8="",$C8,$G8) -> 0.029 | T59: =IF($G8="",$C8,$G8) -> 0.029 | ... AK59: =IF($G8="",$C8,$G8) -> 0.029
A60: ISIC 10T12 | B60: =$B9 -> 0.0093064841 | C60: =$B9 -> 0.0093064841 | D60: =$B9 -> 0.0093064841 | E60: =$B9 -> 0.0093064841 | F60: =$B9 -> 0.0093064841 | G60: =$F60+($M60-$F60)*(G$54-$F$54)/($M$54-$F$54) -> 0.0086912721 | H60: =$F60+($M60-$F60)*(H$54-$F$54)/($M$54-$F$54) -> 0.0080760601 | I60: =$F60+($M60-$F60)*(I$54-$F$54)/($M$54-$F$54) -> 0.0074608481 | J60: =$F60+($M60-$F60)*(J$54-$F$54)/($M$54-$F$54) -> 0.006845636 | K60: =$F60+($M60-$F60)*(K$54-$F$54)/($M$54-$F$54) -> 0.006230424 | L60: =$F60+($M60-$F60)*(L$54-$F$54)/($M$54-$F$54) -> 0.005615212 | M60: =IF($G9="",$C9,$G9) -> 0.005 | N60: =IF($G9="",$C9,$G9) -> 0.005 | O60: =IF($G9="",$C9,$G9) -> 0.005 | P60: =IF($G9="",$C9,$G9) -> 0.005 | Q60: =IF($G9="",$C9,$G9) -> 0.005 | R60: =IF($G9="",$C9,$G9) -> 0.005 | S60: =IF($G9="",$C9,$G9) -> 0.005 | T60: =IF($G9="",$C9,$G9) -> 0.005 | ... AK60: =IF($G9="",$C9,$G9) -> 0.005
A61: ISIC 13T15 | B61: =$B10 -> -0.0052350487 | C61: =$B10 -> -0.0052350487 | D61: =$B10 -> -0.0052350487 | E61: =$B10 -> -0.0052350487 | F61: =$B10 -> -0.0052350487 | G61: =$F61+($M61-$F61)*(G$54-$F$54)/($M$54-$F$54) -> -0.004915756 | H61: =$F61+($M61-$F61)*(H$54-$F$54)/($M$54-$F$54) -> -0.0045964633 | I61: =$F61+($M61-$F61)*(I$54-$F$54)/($M$54-$F$54) -> -0.0042771707 | J61: =$F61+($M61-$F61)*(J$54-$F$54)/($M$54-$F$54) -> -0.003957878 | K61: =$F61+($M61-$F61)*(K$54-$F$54)/($M$54-$F$54) -> -0.0036385853 | L61: =$F61+($M61-$F61)*(L$54-$F$54)/($M$54-$F$54) -> -0.0033192927 | M61: =IF($G10="",$C10,$G10) -> -0.003 | N61: =IF($G10="",$C10,$G10) -> -0.003 | O61: =IF($G10="",$C10,$G10) -> -0.003 | P61: =IF($G10="",$C10,$G10) -> -0.003 | Q61: =IF($G10="",$C10,$G10) -> -0.003 | R61: =IF($G10="",$C10,$G10) -> -0.003 | S61: =IF($G10="",$C10,$G10) -> -0.003 | T61: =IF($G10="",$C10,$G10) -> -0.003 | ... AK61: =IF($G10="",$C10,$G10) -> -0.003
A62: ISIC 16 | B62: =$B11 -> 0.024 | C62: =$B11 -> 0.024 | D62: =$B11 -> 0.024 | E62: =$B11 -> 0.024 | F62: =$B11 -> 0.024 | G62: =$F62+($M62-$F62)*(G$54-$F$54)/($M$54-$F$54) -> 0.019571429 | H62: =$F62+($M62-$F62)*(H$54-$F$54)/($M$54-$F$54) -> 0.015142857 | I62: =$F62+($M62-$F62)*(I$54-$F$54)/($M$54-$F$54) -> 0.010714286 | J62: =$F62+($M62-$F62)*(J$54-$F$54)/($M$54-$F$54) -> 0.0062857143 | K62: =$F62+($M62-$F62)*(K$54-$F$54)/($M$54-$F$54) -> 0.0018571429 | L62: =$F62+($M62-$F62)*(L$54-$F$54)/($M$54-$F$54) -> -0.0025714286 | M62: =IF($G11="",$C11,$G11) -> -0.007 | N62: =IF($G11="",$C11,$G11) -> -0.007 | O62: =IF($G11="",$C11,$G11) -> -0.007 | P62: =IF($G11="",$C11,$G11) -> -0.007 | Q62: =IF($G11="",$C11,$G11) -> -0.007 | R62: =IF($G11="",$C11,$G11) -> -0.007 | S62: =IF($G11="",$C11,$G11) -> -0.007 | T62: =IF($G11="",$C11,$G11) -> -0.007 | ... AK62: =IF($G11="",$C11,$G11) -> -0.007
A63: ISIC 17T18 | B63: =$B12 -> 0.00039223972 | C63: =$B12 -> 0.00039223972 | D63: =$B12 -> 0.00039223972 | E63: =$B12 -> 0.00039223972 | F63: =$B12 -> 0.00039223972 | G63: =$F63+($M63-$F63)*(G$54-$F$54)/($M$54-$F$54) -> -0.00080665167 | H63: =$F63+($M63-$F63)*(H$54-$F$54)/($M$54-$F$54) -> -0.0020055431 | I63: =$F63+($M63-$F63)*(I$54-$F$54)/($M$54-$F$54) -> -0.0032044344 | J63: =$F63+($M63-$F63)*(J$54-$F$54)/($M$54-$F$54) -> -0.0044033258 | K63: =$F63+($M63-$F63)*(K$54-$F$54)/($M$54-$F$54) -> -0.0056022172 | L63: =$F63+($M63-$F63)*(L$54-$F$54)/($M$54-$F$54) -> -0.0068011086 | M63: =IF($G12="",$C12,$G12) -> -0.008 | N63: =IF($G12="",$C12,$G12) -> -0.008 | O63: =IF($G12="",$C12,$G12) -> -0.008 | P63: =IF($G12="",$C12,$G12) -> -0.008 | Q63: =IF($G12="",$C12,$G12) -> -0.008 | R63: =IF($G12="",$C12,$G12) -> -0.008 | S63: =IF($G12="",$C12,$G12) -> -0.008 | T63: =IF($G12="",$C12,$G12) -> -0.008 | ... AK63: =IF($G12="",$C12,$G12) -> -0.008
A64: ISIC 19 | B64: =$B13 -> 0.007 | C64: =$B13 -> 0.007 | D64: =$B13 -> 0.007 | E64: =$B13 -> 0.007 | F64: =$B13 -> 0.007 | G64: =$F64+($M64-$F64)*(G$54-$F$54)/($M$54-$F$54) -> 0.0067142857 | H64: =$F64+($M64-$F64)*(H$54-$F$54)/($M$54-$F$54) -> 0.0064285714 | I64: =$F64+($M64-$F64)*(I$54-$F$54)/($M$54-$F$54) -> 0.0061428571 | J64: =$F64+($M64-$F64)*(J$54-$F$54)/($M$54-$F$54) -> 0.0058571429 | K64: =$F64+($M64-$F64)*(K$54-$F$54)/($M$54-$F$54) -> 0.0055714286 | L64: =$F64+($M64-$F64)*(L$54-$F$54)/($M$54-$F$54) -> 0.0052857143 | M64: =IF($G13="",$C13,$G13) -> 0.005 | N64: =IF($G13="",$C13,$G13) -> 0.005 | O64: =IF($G13="",$C13,$G13) -> 0.005 | P64: =IF($G13="",$C13,$G13) -> 0.005 | Q64: =IF($G13="",$C13,$G13) -> 0.005 | R64: =IF($G13="",$C13,$G13) -> 0.005 | S64: =IF($G13="",$C13,$G13) -> 0.005 | T64: =IF($G13="",$C13,$G13) -> 0.005 | ... AK64: =IF($G13="",$C13,$G13) -> 0.005
A65: ISIC 20 | B65: =$B14 -> 0.022260187 | C65: =$B14 -> 0.022260187 | D65: =$B14 -> 0.022260187 | E65: =$B14 -> 0.022260187 | F65: =$B14 -> 0.022260187 | G65: =$F65+($M65-$F65)*(G$54-$F$54)/($M$54-$F$54) -> 0.020365874 | H65: =$F65+($M65-$F65)*(H$54-$F$54)/($M$54-$F$54) -> 0.018471562 | I65: =$F65+($M65-$F65)*(I$54-$F$54)/($M$54-$F$54) -> 0.01657725 | J65: =$F65+($M65-$F65)*(J$54-$F$54)/($M$54-$F$54) -> 0.014682937 | K65: =$F65+($M65-$F65)*(K$54-$F$54)/($M$54-$F$54) -> 0.012788625 | L65: =$F65+($M65-$F65)*(L$54-$F$54)/($M$54-$F$54) -> 0.010894312 | M65: =IF($G14="",$C14,$G14) -> 0.009 | N65: =IF($G14="",$C14,$G14) -> 0.009 | O65: =IF($G14="",$C14,$G14) -> 0.009 | P65: =IF($G14="",$C14,$G14) -> 0.009 | Q65: =IF($G14="",$C14,$G14) -> 0.009 | R65: =IF($G14="",$C14,$G14) -> 0.009 | S65: =IF($G14="",$C14,$G14) -> 0.009 | T65: =IF($G14="",$C14,$G14) -> 0.009 | ... AK65: =IF($G14="",$C14,$G14) -> 0.009
A66: ISIC 21 | B66: =$B15 -> -0.004 | C66: =$B15 -> -0.004 | D66: =$B15 -> -0.004 | E66: =$B15 -> -0.004 | F66: =$B15 -> -0.004 | G66: =$F66+($M66-$F66)*(G$54-$F$54)/($M$54-$F$54) -> -0.00085714286 | H66: =$F66+($M66-$F66)*(H$54-$F$54)/($M$54-$F$54) -> 0.0022857143 | I66: =$F66+($M66-$F66)*(I$54-$F$54)/($M$54-$F$54) -> 0.0054285714 | J66: =$F66+($M66-$F66)*(J$54-$F$54)/($M$54-$F$54) -> 0.0085714286 | K66: =$F66+($M66-$F66)*(K$54-$F$54)/($M$54-$F$54) -> 0.011714286 | L66: =$F66+($M66-$F66)*(L$54-$F$54)/($M$54-$F$54) -> 0.014857143 | M66: =IF($G15="",$C15,$G15) -> 0.018 | N66: =IF($G15="",$C15,$G15) -> 0.018 | O66: =IF($G15="",$C15,$G15) -> 0.018 | P66: =IF($G15="",$C15,$G15) -> 0.018 | Q66: =IF($G15="",$C15,$G15) -> 0.018 | R66: =IF($G15="",$C15,$G15) -> 0.018 | S66: =IF($G15="",$C15,$G15) -> 0.018 | T66: =IF($G15="",$C15,$G15) -> 0.018 | ... AK66: =IF($G15="",$C15,$G15) -> 0.018
... A96: ISIC 97T98 | B96: =$B45 -> 0.008 | C96: =$B45 -> 0.008 | D96: =$B45 -> 0.008 | E96: =$B45 -> 0.008 | F96: =$B45 -> 0.008 | G96: =$F96+($M96-$F96)*(G$54-$F$54)/($M$54-$F$54) -> 0.0092857143 | H96: =$F96+($M96-$F96)*(H$54-$F$54)/($M$54-$F$54) -> 0.010571429 | I96: =$F96+($M96-$F96)*(I$54-$F$54)/($M$54-$F$54) -> 0.011857143 | J96: =$F96+($M96-$F96)*(J$54-$F$54)/($M$54-$F$54) -> 0.013142857 | K96: =$F96+($M96-$F96)*(K$54-$F$54)/($M$54-$F$54) -> 0.014428571 | L96: =$F96+($M96-$F96)*(L$54-$F$54)/($M$54-$F$54) -> 0.015714286 | M96: =IF($G45="",$C45,$G45) -> 0.017 | N96: =IF($G45="",$C45,$G45) -> 0.017 | O96: =IF($G45="",$C45,$G45) -> 0.017 | P96: =IF($G45="",$C45,$G45) -> 0.017 | Q96: =IF($G45="",$C45,$G45) -> 0.017 | R96: =IF($G45="",$C45,$G45) -> 0.017 | S96: =IF($G45="",$C45,$G45) -> 0.017 | T96: =IF($G45="",$C45,$G45) -> 0.017 | ... AK96: =IF($G45="",$C45,$G45) -> 0.017
A99: Change Relative to IO Input Data Year
B100: 2015 | C100: 2016 | D100: 2017 | E100: 2018 | F100: 2019 | G100: 2020 | H100: 2021 | I100: 2022 | J100: 2023 | K100: 2024 | L100: 2025 | M100: 2026 | N100: 2027 | O100: 2028 | P100: 2029 | Q100: 2030 | R100: 2031 | S100: 2032 | T100: 2033 | U100: 2034 | V100: 2035 | W100: 2036 | X100: 2037 | Y100: 2038 | Z100: 2039 | AA100: 2040 | AB100: 2041 | AC100: 2042 | AD100: 2043 | AE100: 2044 | AF100: 2045 | AG100: 2046 | AH100: 2047 | AI100: 2048 | AJ100: 2049 | AK100: 2050
A101: ISIC 01T03 | B101: 0 | C101: =(B101+1)*(1+B55)-1 -> 0.022 | D101: =(C101+1)*(1+C55)-1 -> 0.044484 | E101: =(D101+1)*(1+D55)-1 -> 0.067462648 | F101: =(E101+1)*(1+E55)-1 -> 0.090946826 | G101: =(F101+1)*(1+F55)-1 -> 0.11494766 | H101: =(G101+1)*(1+G55)-1 -> 0.1366095 | I101: =(H101+1)*(1+H55)-1 -> 0.15576949 | J101: =(I101+1)*(1+I55)-1 -> 0.17228048 | ... AK101: =(AJ101+1)*(1+AJ55)-1 -> 0.32585421
A102: ISIC 05 | B102: 0 | C102: =(B102+1)*(1+B56)-1 -> -0.013 | D102: =(C102+1)*(1+C56)-1 -> -0.025831 | E102: =(D102+1)*(1+D56)-1 -> -0.038495197 | F102: =(E102+1)*(1+E56)-1 -> -0.050994759 | G102: =(F102+1)*(1+F56)-1 -> -0.063331828 | H102: =(G102+1)*(1+G56)-1 -> -0.074036607 | I102: =(H102+1)*(1+H56)-1 -> -0.08316396 | J102: =(I102+1)*(1+I56)-1 -> -0.090760602 | ... AK102: =(AJ102+1)*(1+AJ56)-1 -> -0.14671852
A103: ISIC 06 | B103: 0 | C103: =(B103+1)*(1+B57)-1 -> 0.055 | D103: =(C103+1)*(1+C57)-1 -> 0.113025 | E103: =(D103+1)*(1+D57)-1 -> 0.17424137 | F103: =(E103+1)*(1+E57)-1 -> 0.23882465 | G103: =(F103+1)*(1+F57)-1 -> 0.30696001 | H103: =(G103+1)*(1+G57)-1 -> 0.37492193 | I103: =(H103+1)*(1+H57)-1 -> 0.4422931 | J103: =(I103+1)*(1+I57)-1 -> 0.50863858 | ... AK103: =(AJ103+1)*(1+AJ57)-1 -> 2.7859471
A104: ISIC 07T08 | B104: 0 | C104: =(B104+1)*(1+B58)-1 -> -0.01543937 | D104: =(C104+1)*(1+C58)-1 -> -0.030640366 | E104: =(D104+1)*(1+D58)-1 -> -0.045606668 | F104: =(E104+1)*(1+E58)-1 -> -0.0603419 | G104: =(F104+1)*(1+F58)-1 -> -0.074849629 | H104: =(G104+1)*(1+G58)-1 -> -0.085765166 | I104: =(H104+1)*(1+H58)-1 -> -0.093223452 | J104: =(I104+1)*(1+I58)-1 -> -0.097319586 | ... AK104: =(AJ104+1)*(1+AJ58)-1 -> 0.1569327
A105: ISIC 09 | B105: 0 | C105: =(B105+1)*(1+B59)-1 -> -0.001 | D105: =(C105+1)*(1+C59)-1 -> -0.001999 | E105: =(D105+1)*(1+D59)-1 -> -0.002997001 | F105: =(E105+1)*(1+E59)-1 -> -0.003994004 | G105: =(F105+1)*(1+F59)-1 -> -0.00499001 | H105: =(G105+1)*(1+G59)-1 -> -0.0017206915 | I105: =(H105+1)*(1+H59)-1 -> 0.005837709 | J105: =(I105+1)*(1+I59)-1 -> 0.01776407 | ... AK105: =(AJ105+1)*(1+AJ59)-1 -> 1.1476143
A106: ISIC 10T12 | B106: 0 | C106: =(B106+1)*(1+B60)-1 -> 0.0093064841 | D106: =(C106+1)*(1+C60)-1 -> 0.018699579 | E106: =(D106+1)*(1+D60)-1 -> 0.02818009 | F106: =(E106+1)*(1+E60)-1 -> 0.037748832 | G106: =(F106+1)*(1+F60)-1 -> 0.047406625 | H106: =(G106+1)*(1+G60)-1 -> 0.056509921 | I106: =(H106+1)*(1+H60)-1 -> 0.065042358 | J106: =(I106+1)*(1+I60)-1 -> 0.072988478 | ... AK106: =(AJ106+1)*(1+AJ60)-1 -> 0.2321759
A107: ISIC 13T15 | B107: 0 | C107: =(B107+1)*(1+B61)-1 -> -0.0052350487 | D107: =(C107+1)*(1+C61)-1 -> -0.010442692 | E107: =(D107+1)*(1+D61)-1 -> -0.015623072 | F107: =(E107+1)*(1+E61)-1 -> -0.020776333 | G107: =(F107+1)*(1+F61)-1 -> -0.025902617 | H107: =(G107+1)*(1+G61)-1 -> -0.030691042 | I107: =(H107+1)*(1+H61)-1 -> -0.035146435 | J107: =(I107+1)*(1+I61)-1 -> -0.039273279 | ... AK107: =(AJ107+1)*(1+AJ61)-1 -> -0.11583295
A108: ISIC 16 | B108: 0 | C108: =(B108+1)*(1+B62)-1 -> 0.024 | D108: =(C108+1)*(1+C62)-1 -> 0.048576 | E108: =(D108+1)*(1+D62)-1 -> 0.073741824 | F108: =(E108+1)*(1+E62)-1 -> 0.099511628 | G108: =(F108+1)*(1+F62)-1 -> 0.12589991 | H108: =(G108+1)*(1+G62)-1 -> 0.14793538 | I108: =(H108+1)*(1+H62)-1 -> 0.1653184 | J108: =(I108+1)*(1+I62)-1 -> 0.17780395 | ... AK108: =(AJ108+1)*(1+AJ62)-1 -> 0.00060779489
A109: ISIC 17T18 | B109: 0 | C109: =(B109+1)*(1+B63)-1 -> 0.00039223972 | D109: =(C109+1)*(1+C63)-1 -> 0.0007846333 | E109: =(D109+1)*(1+D63)-1 -> 0.0011771808 | F109: =(E109+1)*(1+E63)-1 -> 0.0015698822 | G109: =(F109+1)*(1+F63)-1 -> 0.0019627377 | H109: =(G109+1)*(1+G63)-1 -> 0.0011545028 | I109: =(H109+1)*(1+H63)-1 -> -0.00085335563 | J109: =(I109+1)*(1+I63)-1 -> -0.0040550556 | ... AK109: =(AJ109+1)*(1+AJ63)-1 -> -0.19240193
A110: ISIC 19 | B110: 0 | C110: =(B110+1)*(1+B64)-1 -> 0.007 | D110: =(C110+1)*(1+C64)-1 -> 0.014049 | E110: =(D110+1)*(1+D64)-1 -> 0.021147343 | F110: =(E110+1)*(1+E64)-1 -> 0.028295374 | G110: =(F110+1)*(1+F64)-1 -> 0.035493442 | H110: =(G110+1)*(1+G64)-1 -> 0.042446041 | I110: =(H110+1)*(1+H64)-1 -> 0.04914748 | J110: =(I110+1)*(1+I64)-1 -> 0.055592243 | ... AK110: =(AJ110+1)*(1+AJ64)-1 -> 0.20981903
A111: ISIC 20 | B111: 0 | C111: =(B111+1)*(1+B65)-1 -> 0.022260187 | D111: =(C111+1)*(1+C65)-1 -> 0.045015889 | E111: =(D111+1)*(1+D65)-1 -> 0.068278138 | F111: =(E111+1)*(1+E65)-1 -> 0.092058209 | G111: =(F111+1)*(1+F65)-1 -> 0.11636763 | H111: =(G111+1)*(1+G65)-1 -> 0.13910343 | I111: =(H111+1)*(1+H65)-1 -> 0.16014445 | J111: =(I111+1)*(1+I65)-1 -> 0.17937645 | ... AK111: =(AJ111+1)*(1+AJ65)-1 -> 0.5191315
A112: ISIC 21 | B112: 0 | C112: =(B112+1)*(1+B66)-1 -> -0.004 | D112: =(C112+1)*(1+C66)-1 -> -0.007984 | E112: =(D112+1)*(1+D66)-1 -> -0.011952064 | F112: =(E112+1)*(1+E66)-1 -> -0.015904256 | G112: =(F112+1)*(1+F66)-1 -> -0.019840639 | H112: =(G112+1)*(1+G66)-1 -> -0.020680775 | I112: =(H112+1)*(1+H66)-1 -> -0.018442331 | J112: =(I112+1)*(1+I66)-1 -> -0.013113875 | ... AK112: =(AJ112+1)*(1+AJ66)-1 -> 0.568134
... A142: ISIC 97T98 | B142: 0 | C142: =(B142+1)*(1+B96)-1 -> 0.008 | D142: =(C142+1)*(1+C96)-1 -> 0.016064 | E142: =(D142+1)*(1+D96)-1 -> 0.024192512 | F142: =(E142+1)*(1+E96)-1 -> 0.032386052 | G142: =(F142+1)*(1+F96)-1 -> 0.040645141 | H142: =(G142+1)*(1+G96)-1 -> 0.050308274 | I142: =(H142+1)*(1+H96)-1 -> 0.061411533 | J142: =(I142+1)*(1+I96)-1 -> 0.073996841 | ... AK142: =(AJ142+1)*(1+AJ96)-1 -> 0.68023333

Sheet Data from BVAbIC
A1: Unit: USD | B1: ISIC 01T03 | C1: ISIC 05 | D1: ISIC 06 | E1: ISIC 07T08 | F1: ISIC 09 | G1: ISIC 10T12 | H1: ISIC 13T15 | I1: ISIC 16 | J1: ISIC 17T18 | K1: ISIC 19 | L1: ISIC 20 | M1: ISIC 21 | N1: ISIC 22 | O1: ISIC 231 | P1: ISIC 239 | Q1: ISIC 241 | R1: ISIC 242 | S1: ISIC 25 | T1: ISIC 26 | U1: ISIC 27 | V1: ISIC 28 | W1: ISIC 29 | X1: ISIC 30 | Y1: ISIC 31T33 | Z1: ISIC 351 | AA1: ISIC 352T353 | AB1: ISIC 36T39 | AC1: ISIC 41T43 | AD1: ISIC 45T47 | AE1: ISIC 49T53 | AF1: ISIC 55T56 | AG1: ISIC 58T60 | AH1: ISIC 61 | AI1: ISIC 62T63 | AJ1: ISIC 64T66 | AK1: ISIC 68 | AL1: ISIC 69T82 | AM1: ISIC 84 | AN1: ISIC 85 | AO1: ISIC 86T88 | AP1: ISIC 90T96 | AQ1: ISIC 97T98
A2: Value Added | B2: 1.8780808e+11 | C2: 2.3194952e+10 | D2: 1.9423318e+11 | E2: 3.9890017e+10 | F2: 5.0276705e+10 | G2: 2.4066632e+11 | H2: 2.6767287e+10 | I2: 2.8192508e+10 | J2: 9.3611547e+10 | K2: 1.5350774e+11 | L2: 2.3920865e+11 | M2: 1.2500051e+11 | N2: 7.7354067e+10 | O2: 1.0821227e+10 | P2: 3.897414e+10 | Q2: 3.0145257e+10 | R2: 2.3754994e+10 | S2: 1.4218405e+11 | T2: 2.6978944e+11 | U2: 5.4554596e+10 | V2: 1.4259961e+11 | W2: 1.5549209e+11 | X2: 1.2994747e+11 | Y2: 1.0959528e+11 | Z2: 2.0275489e+11 | AA2: 4.2222754e+10 | AB2: 5.1188122e+10 | AC2: 7.1674077e+11 | AD2: 1.7870469e+12 | AE2: 5.5998435e+11 | AF2: 4.6967495e+11 | AG2: 4.214779e+11 | AH2: 2.7242106e+11 | AI2: 3.6244761e+11 | AJ2: 1.2888796e+12 | AK2: 2.1082272e+12 | AL2: 1.9729881e+12 | AM2: 1.5021391e+12 | AN2: 9.3719429e+11 | AO2: 1.2439765e+12 | AP2: 4.5298669e+11 | AQ2: 2.0682998e+10

Sheet OECD GDP Data
A1: LOCATION | B1: INDICATOR | C1: SUBJECT | D1: MEASURE | E1: FREQUENCY | F1: TIME | G1: Value | I1: Value (2012 USD)
A2: USA | B2: GDPLTFORECAST | C2: TOT | D2: MLN_USD | E2: A | F2: 2014 | G2: 16208167 | I2: =G2*About!$A$62*About!$A$63 -> 1.706579e+13
A3: USA | B3: GDPLTFORECAST | C3: TOT | D3: MLN_USD | E3: A | F3: 2015 | G3: 16671978 | I3: =G3*About!$A$62*About!$A$63 -> 1.7554143e+13
A4: USA | B4: GDPLTFORECAST | C4: TOT | D4: MLN_USD | E4: A | F4: 2016 | G4: 16919603 | I4: =G4*About!$A$62*About!$A$63 -> 1.7814871e+13
A5: USA | B5: GDPLTFORECAST | C5: TOT | D5: MLN_USD | E5: A | F5: 2017 | G5: 17304243 | I5: =G5*About!$A$62*About!$A$63 -> 1.8219863e+13
A6: USA | B6: GDPLTFORECAST | C6: TOT | D6: MLN_USD | E6: A | F6: 2018 | G6: 17798639 | I6: =G6*About!$A$62*About!$A$63 -> 1.8740418e+13
A7: USA | B7: GDPLTFORECAST | C7: TOT | D7: MLN_USD | E7: A | F7: 2019 | G7: 18292646 | I7: =G7*About!$A$62*About!$A$63 -> 1.9260565e+13
A8: USA | B8: GDPLTFORECAST | C8: TOT | D8: MLN_USD | E8: A | F8: 2020 | G8: 18587190 | I8: =G8*About!$A$62*About!$A$63 -> 1.9570694e+13
A9: USA | B9: GDPLTFORECAST | C9: TOT | D9: MLN_USD | E9: A | F9: 2021 | G9: 18849540 | I9: =G9*About!$A$62*About!$A$63 -> 1.9846926e+13
A10: USA | B10: GDPLTFORECAST | C10: TOT | D10: MLN_USD | E10: A | F10: 2022 | G10: 19124900 | I10: =G10*About!$A$62*About!$A$63 -> 2.0136856e+13
A11: USA | B11: GDPLTFORECAST | C11: TOT | D11: MLN_USD | E11: A | F11: 2023 | G11: 19422190 | I11: =G11*About!$A$62*About!$A$63 -> 2.0449877e+13
A12: USA | B12: GDPLTFORECAST | C12: TOT | D12: MLN_USD | E12: A | F12: 2024 | G12: 19740540 | I12: =G12*About!$A$62*About!$A$63 -> 2.0785071e+13
A13: USA | B13: GDPLTFORECAST | C13: TOT | D13: MLN_USD | E13: A | F13: 2025 | G13: 20075600 | I13: =G13*About!$A$62*About!$A$63 -> 2.113786e+13
... A48: USA | B48: GDPLTFORECAST | C48: TOT | D48: MLN_USD | E48: A | F48: 2060 | G48: 38974320 | I48: =G48*About!$A$62*About!$A$63 -> 4.1036569e+13

Sheet Rescale to Fit GDP Proj
A1: Now that we have growth rates by ISIC code, we rescale all growth rates together such that BAU Value Added
A2: (summed across ISIC codes) reflects the BAU GDP projection in the final year of the model run.
B4: 2015 Value Added | C4: Unscaled Cng by 2050 | D4: Unscaled 2050 Value Added | F4: Scaled Cng by 2050 | G4: Scaled 2050 Value Added
A5: ISIC 01T03 | B5: {=TRANSPOSE('Data from BVAbIC'!B2:AQ2)} -> 1.8780808e+11 | C5: ='Growth Rates'!AK101 -> 0.32585421 | D5: =$B5*(1+C5) -> 2.4900613e+11 | F5: =C5*$D$54 -> 0.27231715 | G5: =$B5*(1+F5) -> 2.3895144e+11
A6: ISIC 05 | B6: 2.3194952e+10 | C6: ='Growth Rates'!AK102 -> -0.14671852 | D6: =$B6*(1+C6) -> 1.9791823e+10 | F6: =C6*$D$54 -> -0.12261302 | G6: =$B6*(1+F6) -> 2.0350949e+10
A7: ISIC 06 | B7: 1.9423318e+11 | C7: ='Growth Rates'!AK103 -> 2.7859471 | D7: =$B7*(1+C7) -> 7.3535656e+11 | F7: =C7*$D$54 -> 2.3282228 | G7: =$B7*(1+F7) -> 6.464513e+11
A8: ISIC 07T08 | B8: 3.9890017e+10 | C8: ='Growth Rates'!AK104 -> 0.1569327 | D8: =$B8*(1+C8) -> 4.6150065e+10 | F8: =C8*$D$54 -> 0.13114904 | G8: =$B8*(1+F8) -> 4.5121554e+10
A9: ISIC 09 | B9: 5.0276705e+10 | C9: ='Growth Rates'!AK105 -> 1.1476143 | D9: =$B9*(1+C9) -> 1.0797497e+11 | F9: =C9*$D$54 -> 0.95906402 | G9: =$B9*(1+F9) -> 9.8495283e+10
A10: ISIC 10T12 | B10: 2.4066632e+11 | C10: ='Growth Rates'!AK106 -> 0.2321759 | D10: =$B10*(1+C10) -> 2.9654324e+11 | F10: =C10*$D$54 -> 0.19402996 | G10: =$B10*(1+F10) -> 2.873628e+11
A11: ISIC 13T15 | B11: 2.6767287e+10 | C11: ='Growth Rates'!AK107 -> -0.11583295 | D11: =$B11*(1+C11) -> 2.3666753e+10 | F11: =C11*$D$54 -> -0.096801876 | G11: =$B11*(1+F11) -> 2.4176164e+10
A12: ISIC 16 | B12: 2.8192508e+10 | C12: ='Growth Rates'!AK108 -> 0.00060779489 | D12: =$B12*(1+C12) -> 2.8209644e+10 | F12: =C12*$D$54 -> 0.00050793566 | G12: =$B12*(1+F12) -> 2.8206828e+10
A13: ISIC 17T18 | B13: 9.3611547e+10 | C13: ='Growth Rates'!AK109 -> -0.19240193 | D13: =$B13*(1+C13) -> 7.5600505e+10 | F13: =C13*$D$54 -> -0.16079076 | G13: =$B13*(1+F13) -> 7.8559675e+10
A14: ISIC 19 | B14: 1.5350774e+11 | C14: ='Growth Rates'!AK110 -> 0.20981903 | D14: =$B14*(1+C14) -> 1.8571659e+11 | F14: =C14*$D$54 -> 0.17534627 | G14: =$B14*(1+F14) -> 1.8042475e+11
A15: ISIC 20 | B15: 2.3920865e+11 | C15: ='Growth Rates'!AK111 -> 0.5191315 | D15: =$B15*(1+C15) -> 3.6338939e+11 | F15: =C15*$D$54 -> 0.43383945 | G15: =$B15*(1+F15) -> 3.4298679e+11
A16: ISIC 21 | B16: 1.2500051e+11 | C16: ='Growth Rates'!AK112 -> 0.568134 | D16: =$B16*(1+C16) -> 1.9601756e+11 | F16: =C16*$D$54 -> 0.47479096 | G16: =$B16*(1+F16) -> 1.8434963e+11
A17: ISIC 22 | B17: 7.7354067e+10 | C17: ='Growth Rates'!AK113 -> 0.63471958 | D17: =$B17*(1+C17) -> 1.2645221e+11 | F17: =C17*$D$54 -> 0.53043669 | G17: =$B17*(1+F17) -> 1.183855e+11
... A46: ISIC 97T98 | B46: 2.0682998e+10 | C46: ='Growth Rates'!AK142 -> 0.68023333 | D46: =$B46*(1+C46) -> 3.4752263e+10 | F46: =C46*$D$54 -> 0.56847264 | G46: =$B46*(1+F46) -> 3.2440717e+10
A48: Total | B48: =SUM(B5:B46) -> 1.7000603e+13 | D48: =SUM(D5:D46) -> 3.5692529e+13 | G48: =SUM(G5:G46) -> 3.2621491e+13
A50: Unscaled Percent Growth of GDP | D50: =(D48-B48)/B48 -> 1.099486
A52: Percent Growth of GDP from Input Data | D52: =('OECD GDP Data'!I38-'OECD GDP Data'!I3)/'OECD GDP Data'!I3 -> 0.9188431
A54: Scaling Factor to Fit GDP Projection | D54: =D52/D50 -> 0.83570242
A56: Scaled Percent Growth of GDP (double check) | D56: =(G48-B48)/B48 -> 0.9188431
A58: Scaled Change Relative to IO Input Data Year
B59: 2015 | C59: 2016 | D59: 2017 | E59: 2018 | F59: 2019 | G59: 2020 | H59: 2021 | I59: 2022 | J59: 2023 | K59: 2024 | L59: 2025 | M59: 2026 | N59: 2027 | O59: 2028 | P59: 2029 | Q59: 2030 | R59: 2031 | S59: 2032 | T59: 2033 | U59: 2034 | V59: 2035 | W59: 2036 | X59: 2037 | Y59: 2038 | Z59: 2039 | AA59: 2040 | AB59: 2041 | AC59: 2042 | AD59: 2043 | AE59: 2044 | AF59: 2045 | AG59: 2046 | AH59: 2047 | AI59: 2048 | AJ59: 2049 | AK59: 2050
A60: ISIC 01T03 | B60: ='Growth Rates'!B101*$D$54 -> 0 | C60: ='Growth Rates'!C101*$D$54 -> 0.018385453 | D60: ='Growth Rates'!D101*$D$54 -> 0.037175387 | E60: ='Growth Rates'!E101*$D$54 -> 0.056378699 | F60: ='Growth Rates'!F101*$D$54 -> 0.076004483 | G60: ='Growth Rates'!G101*$D$54 -> 0.096062035 | H60: ='Growth Rates'!H101*$D$54 -> 0.11416489 | I60: ='Growth Rates'!I101*$D$54 -> 0.13017694 | ... AK60: ='Growth Rates'!AK101*$D$54 -> 0.27231715
A61: ISIC 05 | B61: ='Growth Rates'!B102*$D$54 -> 0 | C61: ='Growth Rates'!C102*$D$54 -> -0.010864132 | D61: ='Growth Rates'!D102*$D$54 -> -0.021587029 | E61: ='Growth Rates'!E102*$D$54 -> -0.032170529 | F61: ='Growth Rates'!F102*$D$54 -> -0.042616444 | G61: ='Growth Rates'!G102*$D$54 -> -0.052926562 | H61: ='Growth Rates'!H102*$D$54 -> -0.061872572 | I61: ='Growth Rates'!I102*$D$54 -> -0.069500323 | ... AK61: ='Growth Rates'!AK102*$D$54 -> -0.12261302
A62: ISIC 06 | B62: ='Growth Rates'!B103*$D$54 -> 0 | C62: ='Growth Rates'!C103*$D$54 -> 0.045963633 | D62: ='Growth Rates'!D103*$D$54 -> 0.094455267 | E62: ='Growth Rates'!E103*$D$54 -> 0.14561394 | F62: ='Growth Rates'!F103*$D$54 -> 0.19958634 | G62: ='Growth Rates'!G103*$D$54 -> 0.25652722 | H62: ='Growth Rates'!H103*$D$54 -> 0.31332316 | I62: ='Growth Rates'!I103*$D$54 -> 0.36962542 | ... AK62: ='Growth Rates'!AK103*$D$54 -> 2.3282228
A63: ISIC 07T08 | B63: ='Growth Rates'!B104*$D$54 -> 0 | C63: ='Growth Rates'!C104*$D$54 -> -0.012902719 | D63: ='Growth Rates'!D104*$D$54 -> -0.025606228 | E63: ='Growth Rates'!E104*$D$54 -> -0.038113603 | F63: ='Growth Rates'!F104*$D$54 -> -0.050427872 | G63: ='Growth Rates'!G104*$D$54 -> -0.062552017 | H63: ='Growth Rates'!H104*$D$54 -> -0.071674157 | I63: ='Growth Rates'!I104*$D$54 -> -0.077907065 | ... AK63: ='Growth Rates'!AK104*$D$54 -> 0.13114904
A64: ISIC 09 | B64: ='Growth Rates'!B105*$D$54 -> 0 | C64: ='Growth Rates'!C105*$D$54 -> -0.00083570242 | D64: ='Growth Rates'!D105*$D$54 -> -0.0016705691 | E64: ='Growth Rates'!E105*$D$54 -> -0.002504601 | F64: ='Growth Rates'!F105*$D$54 -> -0.0033377988 | G64: ='Growth Rates'!G105*$D$54 -> -0.0041701635 | H64: ='Growth Rates'!H105*$D$54 -> -0.001437986 | I64: ='Growth Rates'!I105*$D$54 -> 0.0048785876 | ... AK64: ='Growth Rates'!AK105*$D$54 -> 0.95906402
A65: ISIC 10T12 | B65: ='Growth Rates'!B106*$D$54 -> 0 | C65: ='Growth Rates'!C106*$D$54 -> 0.0077774513 | D65: ='Growth Rates'!D106*$D$54 -> 0.015627283 | E65: ='Growth Rates'!E106*$D$54 -> 0.02355017 | F65: ='Growth Rates'!F106*$D$54 -> 0.03154679 | G65: ='Growth Rates'!G106*$D$54 -> 0.039617831 | H65: ='Growth Rates'!H106*$D$54 -> 0.047225478 | I65: ='Growth Rates'!I106*$D$54 -> 0.054356057 | ... AK65: ='Growth Rates'!AK106*$D$54 -> 0.19402996
A66: ISIC 13T15 | B66: ='Growth Rates'!B107*$D$54 -> 0 | C66: ='Growth Rates'!C107*$D$54 -> -0.0043749429 | D66: ='Growth Rates'!D107*$D$54 -> -0.0087269827 | E66: ='Growth Rates'!E107*$D$54 -> -0.013056239 | F66: ='Growth Rates'!F107*$D$54 -> -0.017362832 | G66: ='Growth Rates'!G107*$D$54 -> -0.02164688 | H66: ='Growth Rates'!H107*$D$54 -> -0.025648578 | I66: ='Growth Rates'!I107*$D$54 -> -0.029371961 | ... AK66: ='Growth Rates'!AK107*$D$54 -> -0.096801876
A67: ISIC 16 | B67: ='Growth Rates'!B108*$D$54 -> 0 | C67: ='Growth Rates'!C108*$D$54 -> 0.020056858 | D67: ='Growth Rates'!D108*$D$54 -> 0.040595081 | E67: ='Growth Rates'!E108*$D$54 -> 0.061626221 | F67: ='Growth Rates'!F108*$D$54 -> 0.083162109 | G67: ='Growth Rates'!G108*$D$54 -> 0.10521486 | H67: ='Growth Rates'!H108*$D$54 -> 0.12362995 | I67: ='Growth Rates'!I108*$D$54 -> 0.13815699 | ... AK67: ='Growth Rates'!AK108*$D$54 -> 0.00050793566
A68: ISIC 17T18 | B68: ='Growth Rates'!B109*$D$54 -> 0 | C68: ='Growth Rates'!C109*$D$54 -> 0.00032779569 | D68: ='Growth Rates'!D109*$D$54 -> 0.00065571995 | E68: ='Growth Rates'!E109*$D$54 -> 0.00098377284 | F68: ='Growth Rates'!F109*$D$54 -> 0.0013119544 | G68: ='Growth Rates'!G109*$D$54 -> 0.0016402647 | H68: ='Growth Rates'!H109*$D$54 -> 0.00096482081 | I68: ='Growth Rates'!I109*$D$54 -> -0.00071315137 | ... AK68: ='Growth Rates'!AK109*$D$54 -> -0.16079076
A69: ISIC 19 | B69: ='Growth Rates'!B110*$D$54 -> 0 | C69: ='Growth Rates'!C110*$D$54 -> 0.005849917 | D69: ='Growth Rates'!D110*$D$54 -> 0.011740783 | E69: ='Growth Rates'!E110*$D$54 -> 0.017672886 | F69: ='Growth Rates'!F110*$D$54 -> 0.023646513 | G69: ='Growth Rates'!G110*$D$54 -> 0.029661956 | H69: ='Growth Rates'!H110*$D$54 -> 0.035472259 | I69: ='Growth Rates'!I110*$D$54 -> 0.041072668 | ... AK69: ='Growth Rates'!AK110*$D$54 -> 0.17534627
A70: ISIC 20 | B70: ='Growth Rates'!B111*$D$54 -> 0 | C70: ='Growth Rates'!C111*$D$54 -> 0.018602892 | D70: ='Growth Rates'!D111*$D$54 -> 0.037619888 | E70: ='Growth Rates'!E111*$D$54 -> 0.057060206 | F70: ='Growth Rates'!F111*$D$54 -> 0.076933268 | G70: ='Growth Rates'!G111*$D$54 -> 0.097248709 | H70: ='Growth Rates'!H111*$D$54 -> 0.11624907 | I70: ='Growth Rates'!I111*$D$54 -> 0.13383311 | ... AK70: ='Growth Rates'!AK111*$D$54 -> 0.43383945
A71: ISIC 21 | B71: ='Growth Rates'!B112*$D$54 -> 0 | C71: ='Growth Rates'!C112*$D$54 -> -0.0033428097 | D71: ='Growth Rates'!D112*$D$54 -> -0.0066722482 | E71: ='Growth Rates'!E112*$D$54 -> -0.0099883689 | F71: ='Growth Rates'!F112*$D$54 -> -0.013291225 | G71: ='Growth Rates'!G112*$D$54 -> -0.01658087 | H71: ='Growth Rates'!H112*$D$54 -> -0.017282974 | I71: ='Growth Rates'!I112*$D$54 -> -0.015412301 | ... AK71: ='Growth Rates'!AK112*$D$54 -> 0.47479096
... A101: ISIC 97T98 | B101: ='Growth Rates'!B142*$D$54 -> 0 | C101: ='Growth Rates'!C142*$D$54 -> 0.0066856194 | D101: ='Growth Rates'!D142*$D$54 -> 0.013424724 | E101: ='Growth Rates'!E142*$D$54 -> 0.020217741 | F101: ='Growth Rates'!F142*$D$54 -> 0.027065102 | G101: ='Growth Rates'!G142*$D$54 -> 0.033967242 | H101: ='Growth Rates'!H142*$D$54 -> 0.042042747 | I101: ='Growth Rates'!I142*$D$54 -> 0.051321767 | ... AK101: ='Growth Rates'!AK142*$D$54 -> 0.56847264

Sheet BPCiObIC
A1: Unit: dimensionless (% change) | B1: 2020 | C1: 2021 | D1: 2022 | E1: 2023 | F1: 2024 | G1: 2025 | H1: 2026 | I1: 2027 | J1: 2028 | K1: 2029 | L1: 2030 | M1: 2031 | N1: 2032 | O1: 2033 | P1: 2034 | Q1: 2035 | R1: 2036 | S1: 2037 | T1: 2038 | U1: 2039 | V1: 2040 | W1: 2041 | X1: 2042 | Y1: 2043 | Z1: 2044 | AA1: 2045 | AB1: 2046 | AC1: 2047 | AD1: 2048 | AE1: 2049 | AF1: 2050
A2: ISIC 01T03 | B2: ='Rescale to Fit GDP Proj'!G60 -> 0.096062035 | C2: ='Rescale to Fit GDP Proj'!H60 -> 0.11416489 | D2: ='Rescale to Fit GDP Proj'!I60 -> 0.13017694 | E2: ='Rescale to Fit GDP Proj'!J60 -> 0.14397521 | F2: ='Rescale to Fit GDP Proj'!K60 -> 0.15545144 | G2: ='Rescale to Fit GDP Proj'!L60 -> 0.16451342 | H2: ='Rescale to Fit GDP Proj'!M60 -> 0.17108626 | I2: ='Rescale to Fit GDP Proj'!N60 -> 0.17511342 | ... AF2: ='Rescale to Fit GDP Proj'!AK60 -> 0.27231715
A3: ISIC 05 | B3: ='Rescale to Fit GDP Proj'!G61 -> -0.052926562 | C3: ='Rescale to Fit GDP Proj'!H61 -> -0.061872572 | D3: ='Rescale to Fit GDP Proj'!I61 -> -0.069500323 | E3: ='Rescale to Fit GDP Proj'!J61 -> -0.075848855 | F3: ='Rescale to Fit GDP Proj'!K61 -> -0.080950729 | G3: ='Rescale to Fit GDP Proj'!L61 -> -0.084832309 | H3: ='Rescale to Fit GDP Proj'!M61 -> -0.087513988 | I3: ='Rescale to Fit GDP Proj'!N61 -> -0.089010365 | ... AF3: ='Rescale to Fit GDP Proj'!AK61 -> -0.12261302
A4: ISIC 06 | B4: ='Rescale to Fit GDP Proj'!G62 -> 0.25652722 | C4: ='Rescale to Fit GDP Proj'!H62 -> 0.31332316 | D4: ='Rescale to Fit GDP Proj'!I62 -> 0.36962542 | E4: ='Rescale to Fit GDP Proj'!J62 -> 0.4250705 | F4: ='Rescale to Fit GDP Proj'!K62 -> 0.47928373 | G4: ='Rescale to Fit GDP Proj'!L62 -> 0.53188318 | H4: ='Rescale to Fit GDP Proj'!M62 -> 0.58248385 | I4: ='Rescale to Fit GDP Proj'!N62 -> 0.63070218 | ... AF4: ='Rescale to Fit GDP Proj'!AK62 -> 2.3282228
A5: ISIC 07T08 | B5: ='Rescale to Fit GDP Proj'!G63 -> -0.062552017 | C5: ='Rescale to Fit GDP Proj'!H63 -> -0.071674157 | D5: ='Rescale to Fit GDP Proj'!I63 -> -0.077907065 | E5: ='Rescale to Fit GDP Proj'!J63 -> -0.081330214 | F5: ='Rescale to Fit GDP Proj'!K63 -> -0.081991451 | G5: ='Rescale to Fit GDP Proj'!L63 -> -0.079908066 | H5: ='Rescale to Fit GDP Proj'!M63 -> -0.075067297 | I5: ='Rescale to Fit GDP Proj'!N63 -> -0.067426273 | ... AF5: ='Rescale to Fit GDP Proj'!AK63 -> 0.13114904
A6: ISIC 09 | B6: ='Rescale to Fit GDP Proj'!G64 -> -0.0041701635 | C6: ='Rescale to Fit GDP Proj'!H64 -> -0.001437986 | D6: ='Rescale to Fit GDP Proj'!I64 -> 0.0048785876 | E6: ='Rescale to Fit GDP Proj'!J64 -> 0.014845477 | F6: ='Rescale to Fit GDP Proj'!K64 -> 0.02857575 | G6: ='Rescale to Fit GDP Proj'!L64 -> 0.046231718 | H6: ='Rescale to Fit GDP Proj'!M64 -> 0.068028091 | I6: ='Rescale to Fit GDP Proj'!N64 -> 0.094236276 | ... AF6: ='Rescale to Fit GDP Proj'!AK64 -> 0.95906402
A7: ISIC 10T12 | B7: ='Rescale to Fit GDP Proj'!G65 -> 0.039617831 | C7: ='Rescale to Fit GDP Proj'!H65 -> 0.047225478 | D7: ='Rescale to Fit GDP Proj'!I65 -> 0.054356057 | E7: ='Rescale to Fit GDP Proj'!J65 -> 0.060996648 | F7: ='Rescale to Fit GDP Proj'!K65 -> 0.067135123 | G7: ='Rescale to Fit GDP Proj'!L65 -> 0.072760184 | H7: ='Rescale to Fit GDP Proj'!M65 -> 0.077861394 | I7: ='Rescale to Fit GDP Proj'!N65 -> 0.082429213 | ... AF7: ='Rescale to Fit GDP Proj'!AK65 -> 0.19402996
A8: ISIC 13T15 | B8: ='Rescale to Fit GDP Proj'!G66 -> -0.02164688 | C8: ='Rescale to Fit GDP Proj'!H66 -> -0.025648578 | D8: ='Rescale to Fit GDP Proj'!I66 -> -0.029371961 | E8: ='Rescale to Fit GDP Proj'!J66 -> -0.032820774 | F8: ='Rescale to Fit GDP Proj'!K66 -> -0.035998482 | G8: ='Rescale to Fit GDP Proj'!L66 -> -0.038908273 | H8: ='Rescale to Fit GDP Proj'!M66 -> -0.041553066 | I8: ='Rescale to Fit GDP Proj'!N66 -> -0.043935514 | ... AF8: ='Rescale to Fit GDP Proj'!AK66 -> -0.096801876
A9: ISIC 16 | B9: ='Rescale to Fit GDP Proj'!G67 -> 0.10521486 | C9: ='Rescale to Fit GDP Proj'!H67 -> 0.12362995 | D9: ='Rescale to Fit GDP Proj'!I67 -> 0.13815699 | E9: ='Rescale to Fit GDP Proj'!J67 -> 0.14859119 | F9: ='Rescale to Fit GDP Proj'!K67 -> 0.15477818 | G9: ='Rescale to Fit GDP Proj'!L67 -> 0.15661765 | H9: ='Rescale to Fit GDP Proj'!M67 -> 0.15406597 | I9: ='Rescale to Fit GDP Proj'!N67 -> 0.14713759 | ... AF9: ='Rescale to Fit GDP Proj'!AK67 -> 0.00050793566
A10: ISIC 17T18 | B10: ='Rescale to Fit GDP Proj'!G68 -> 0.0016402647 | C10: ='Rescale to Fit GDP Proj'!H68 -> 0.00096482081 | D10: ='Rescale to Fit GDP Proj'!I68 -> -0.00071315137 | E10: ='Rescale to Fit GDP Proj'!J68 -> -0.0033888198 | F10: ='Rescale to Fit GDP Proj'!K68 -> -0.0070537678 | G10: ='Rescale to Fit GDP Proj'!L68 -> -0.011696038 | H10: ='Rescale to Fit GDP Proj'!M68 -> -0.017300194 | I10: ='Rescale to Fit GDP Proj'!N68 -> -0.023847412 | ... AF10: ='Rescale to Fit GDP Proj'!AK68 -> -0.16079076
A11: ISIC 19 | B11: ='Rescale to Fit GDP Proj'!G69 -> 0.029661956 | C11: ='Rescale to Fit GDP Proj'!H69 -> 0.035472259 | D11: ='Rescale to Fit GDP Proj'!I69 -> 0.041072668 | E11: ='Rescale to Fit GDP Proj'!J69 -> 0.046458572 | F11: ='Rescale to Fit GDP Proj'!K69 -> 0.051625515 | G11: ='Rescale to Fit GDP Proj'!L69 -> 0.056569199 | H11: ='Rescale to Fit GDP Proj'!M69 -> 0.061285492 | I11: ='Rescale to Fit GDP Proj'!N69 -> 0.065770432 | ... AF11: ='Rescale to Fit GDP Proj'!AK69 -> 0.17534627
A12: ISIC 20 | B12: ='Rescale to Fit GDP Proj'!G70 -> 0.097248709 | C12: ='Rescale to Fit GDP Proj'!H70 -> 0.11624907 | D12: ='Rescale to Fit GDP Proj'!I70 -> 0.13383311 | E12: ='Rescale to Fit GDP Proj'!J70 -> 0.14990534 | F12: ='Rescale to Fit GDP Proj'!K70 -> 0.16437696 | G12: ='Rescale to Fit GDP Proj'!L70 -> 0.1771666 | H12: ='Rescale to Fit GDP Proj'!M70 -> 0.18820111 | I12: ='Rescale to Fit GDP Proj'!N70 -> 0.19741624 | ... AF12: ='Rescale to Fit GDP Proj'!AK70 -> 0.43383945
A13: ISIC 21 | B13: ='Rescale to Fit GDP Proj'!G71 -> -0.01658087 | C13: ='Rescale to Fit GDP Proj'!H71 -> -0.017282974 | D13: ='Rescale to Fit GDP Proj'!I71 -> -0.015412301 | E13: ='Rescale to Fit GDP Proj'!J71 -> -0.010959298 | F13: ='Rescale to Fit GDP Proj'!K71 -> -0.0038900707 | G13: ='Rescale to Fit GDP Proj'!L71 -> 0.0058540169 | H13: ='Rescale to Fit GDP Proj'!M71 -> 0.018357141 | I13: ='Rescale to Fit GDP Proj'!N71 -> 0.033730213 | ... AF13: ='Rescale to Fit GDP Proj'!AK71 -> 0.47479096
... A43: ISIC 97T98 | B43: ='Rescale to Fit GDP Proj'!G101 -> 0.033967242 | C43: ='Rescale to Fit GDP Proj'!H101 -> 0.042042747 | D43: ='Rescale to Fit GDP Proj'!I101 -> 0.051321767 | E43: ='Rescale to Fit GDP Proj'!J101 -> 0.061839339 | F43: ='Rescale to Fit GDP Proj'!K101 -> 0.073635603 | G43: ='Rescale to Fit GDP Proj'!L101 -> 0.086756051 | H43: ='Rescale to Fit GDP Proj'!M101 -> 0.10125183 | I43: ='Rescale to Fit GDP Proj'!N101 -> 0.11718005 | ... AF43: ='Rescale to Fit GDP Proj'!AK101 -> 0.56847264
